Workbook

Sheet NOTES
C1: Revenue Forecast | D1: Gross Profit Forecast | E1: Total Cost Forecast | F1: Net Profit Forecast
C3: Revenue in the best case grows strongly month-on-month due to high client acquisition, good conversion rates, and stable pricing. The business benefits from strong market demand and effective outreach. Each month shows improvement, indicating scalability and growing brand trust. This level of growth suggests that marketing, referrals, and partnerships are working efficiently. The revenue trend reflects a business that is gaining traction quickly and capturing market share. | D3: Gross profit in the best case remains high because revenue increases faster than direct costs. Service delivery is efficient and pricing is well-structured, leading to strong margins. The company benefits from economies of scale as more clients are served without proportional cost increases. This shows good operational efficiency and a strong business model. Healthy gross profit gives room for marketing and team expansion while still maintaining profitability. | E3: Total costs rise gradually as the company invests in salaries, marketing, and operations to support growth. However, these increases are planned and supported by rising revenue. Fixed costs are well managed and variable costs scale efficiently. Spending aligns with expansion goals rather than wasteful expenditure. The company is investing to grow, not just to sustain. This balanced cost structure ensures that higher spending leads to higher returns. Overall, costs are controlled and strategic. | F3: Net profit becomes positive early and improves steadily. Revenue growth outpaces cost increases, leading to strong profitability. This indicates financial health and sustainability. Positive net profit allows reinvestment, reserves, and business expansion. It also improves investor confidence. The company is not only growing but doing so profitably. This scenario reflects ideal execution, strong demand, and efficient cost control.
B8: Best
C17: Revenue grows at a steady and realistic pace. Client acquisition and conversions are consistent but not aggressive. Growth reflects achievable assumptions under normal conditions. The business gains clients gradually and builds trust over time. This scenario assumes stable performance without viral growth. Revenue increases show positive momentum but require patience. It represents a practical and believable growth path. | D17: Gross profit is stable with reasonable margins. Direct costs are covered comfortably, but margins are not very high. Pricing and cost structure are balanced. The company operates efficiently but without major economies of scale yet. Gross profit supports operations but leaves limited buffer for large expansions. It reflects a sustainable but cautious model. | E17: Total costs are controlled and predictable. Salaries, admin, and marketing are kept within planned limits. Fixed costs form a significant portion, but spending is disciplined. The company avoids overspending and focuses on efficiency. Cost growth aligns with revenue growth. This shows financial discipline and realistic budgeting. | F17: Net profit is low or slightly negative in early months but improves over time. As revenue scales, profitability gradually appears. This reflects a normal startup journey. The business moves toward break-even steadily. It is sustainable but requires patience. Profitability is achievable with consistent execution.
B23: Base
C31: Revenue grows slowly due to lower traffic, weaker conversions, or slower client onboarding. Demand exists but scaling is limited. Marketing may not perform as expected. Client acquisition is inconsistent. Revenue increases are small and gradual. This scenario reflects conservative outcomes and market uncertainty. | D31: Gross profit is thin because direct costs consume a larger share of revenue. Margins are tight, leaving little buffer. Service delivery costs weigh heavily on income. The business model still works but with limited efficiency. Profitability at the gross level is present but weak. | E31: Total costs remain relatively high since many expenses are fixed. Even if revenue slows, salaries and admin costs continue. This creates pressure on finances. Limited flexibility in reducing costs affects sustainability. The company must manage cash carefully in this scenario. | F31: Net profit stays negative for longer. Slow revenue growth and steady costs delay profitability. The business may need external funding or cost reductions. This scenario highlights risk and the importance of contingency planning. Long-term survival depends on improving growth or reducing expenses.
B36: Worst

Sheet ABOUT CH
B1: About Codes Health
B7: Codes Health is a next-generation digital health company focused on transforming how healthcare services are delivered, managed, and experienced. The company operates at the intersection of healthcare and technology, building scalable digital infrastructure that enhances accessibility, improves operational efficiency, and supports data-driven decision-making. By integrating smart digital tools into healthcare systems, Codes Health aims to simplify patient care workflows and enable more responsive, efficient service delivery. The company is positioned as an early-stage growth startup operating in the rapidly expanding digital health sector. Based on benchmarking against comparable startups and available industry performance indicators, we estimated that Codes Health generated approximately $300,000 in revenue in 2025. This estimate serves as the foundation for our forward-looking financial projections and reflects a realistic early traction phase typical of emerging health technology firms. For modeling purposes, Codes Health is assumed to have secured approximately $500,000 in seed-level funding, consistent with capital raised by startups at a similar development stage. This funding is projected to support platform development, infrastructure scaling, talent acquisition, and early market expansion. The assumed funding structure reflects a common startup growth trajectory where early investment enables rapid product refinement and customer acquisition. Our financial model is constructed using best-case, base-case, and worst-case scenarios to capture uncertainty inherent in startup growth. Revenue assumptions are driven by user adoption rates, pricing benchmarks, and scalable service expansion. Cost assumptions incorporate a blend of fixed operational infrastructure and variable expenses that increase with growth. This structured scenario approach allows for realistic performance evaluation under multiple market conditions. Codes Health is modeled as a high-potential digital health venture positioned to benefit from increasing global demand for technology-enabled healthcare solutions. While the financial figures used in this model are hypothetical and created strictly for analytical and educational purposes, the modeling framework follows industry-standard startup financial planning practices. The exercise demonstrates how structured assumptions, funding strategy, and operational scaling interact to shape the financial trajectory of an early-stage health technology company. Through this model, Codes Health represents a practical simulation of how innovation-driven healthcare startups can scale responsibly while balancing growth, cost discipline, and long-term sustainability.
D28: For Providers | P28: For Lawyers
B31: Trusted Investor Backing | D31: Pin - Point Past Providers | P31: Missing Record Review | AB31: Practices
AB34: Personal Injury
D36: When Codes Health refers to “pinpointing past providers,” it means accurately identifying every healthcare professional or institution that has previously treated a patient. In legal and administrative cases, missing even one provider can result in incomplete medical histories, delayed documentation, or weakened case outcomes. Codes Health uses structured data collection and verification processes to map a patient’s treatment journey and ensure no relevant provider is overlooked. This creates a complete healthcare timeline, allowing records to be requested efficiently and confidently. By eliminating uncertainty, the platform improves accuracy, reduces delays, and ensures decisions are based on full medical visibility. | P36: Missing record review refers to the process of identifying gaps or incomplete sections within a patient’s medical documentation. In healthcare and legal workflows, incomplete records can lead to delays, compliance issues, or incorrect decisions. Codes Health uses structured verification tools to systematically scan collected documentation and flag missing reports, treatment periods, or provider entries. This proactive review ensures that medical histories are complete before analysis or case preparation begins. By detecting issues early, the platform prevents last-minute complications and strengthens documentation reliability. The result is a more accurate, organized, and dependable medical record system that supports confident decision-making.
J47: Gather Medical Records | V47: Automated Follow Ups
J52: Gathering medical records refers to the secure collection and consolidation of patient documentation from multiple healthcare providers into a single organized system. Traditionally, this process is slow and fragmented, requiring manual coordination across hospitals, clinics, and administrative offices. Codes Health streamlines record retrieval through automated request workflows and standardized digital processing. The platform ensures documents are collected efficiently, verified for accuracy, and formatted for easy review. By centralizing records, Codes Health reduces administrative delays and eliminates inconsistencies. This creates a reliable medical archive that supports legal review, insurance processing, and healthcare decision-making with speed, clarity, and confidence. | V52: Automated follow-ups refer to the system-driven tracking and management of outstanding record requests and documentation tasks without manual intervention. In traditional workflows, staff must repeatedly contact providers to check request status, which is time-consuming and prone to delays. Codes Health replaces this process with automated reminders and progress monitoring that continuously follow up until records are received. This ensures no request is forgotten or stalled. By maintaining consistent communication in the background, the platform accelerates turnaround times and reduces administrative workload. Automated follow-ups create a dependable workflow where documentation moves forward efficiently without requiring constant human oversight.
AB57: Mass Torts
D65: Codes Health delivers healthcare providers a modern digital framework that streamlines medical record management, external documentation requests, and compliance workflows. Hospitals, clinics, and healthcare organizations operate under increasing administrative pressure as record-sharing demands grow alongside regulatory complexity. Providers must maintain accuracy, protect patient privacy, and respond efficiently to legal and insurance requests — all while prioritizing patient care. Codes Health acts as a digital extension of provider infrastructure, reducing administrative strain and improving operational clarity. The platform enables providers to structure patient records into standardized digital formats that are easy to retrieve, verify, and transfer. This eliminates the inefficiencies of fragmented record systems and manual document handling. Automated request intake ensures that incoming legal or administrative inquiries are processed through consistent workflows rather than ad hoc staff intervention. This reduces human error and ensures documentation integrity. One of the most significant benefits for providers is time savings. Administrative staff traditionally spend extensive hours locating files, verifying patient authorization, and coordinating document delivery. Codes Health automates large portions of this workflow, allowing healthcare teams to redirect energy toward clinical responsibilities. Faster processing also improves external relationships with legal professionals, insurers, and regulatory bodies by delivering predictable response timelines. Compliance and security are central pillars of the platform. Healthcare providers operate in a heavily regulated environment where improper data handling can result in severe legal and financial consequences. Codes Health incorporates secure encryption, access controls, and audit tracking to ensure every document exchange meets privacy standards. By embedding compliance into daily operations, the platform reduces institutional risk and strengthens patient trust. Workflow transparency is another core advantage. Providers gain visibility into request status, outstanding documentation, and follow-up requirements through centralized dashboards. This tracking system prevents lost records and communication breakdowns while enabling proactive issue resolution. Missing or incomplete documentation can be identified early, minimizing downstream complications. Codes Health also supports scalability. Whether serving small clinics or large hospital networks, the platform adapts to growing record volumes without sacrificing performance. This scalability allows providers to modernize infrastructure without disruptive operational transitions. As healthcare systems increasingly digitize, Codes Health becomes a long-term administrative partner capable of evolving alongside institutional needs. By modernizing record management and documentation workflows, Codes Health improves productivity, reduces operational friction, and strengthens compliance. Providers benefit from faster information exchange, lower administrative burden, and enhanced data security. The result is a more efficient healthcare environment where organizations can maintain regulatory excellence while focusing on their primary mission: delivering high-quality patient care. | Q65: Codes Health provides legal professionals with a comprehensive, technology-driven infrastructure designed to simplify the management of medical documentation — one of the most complex and resource-intensive components of healthcare-related legal cases. Attorneys handling personal injury litigation, malpractice claims, insurance disputes, disability cases, and workers’ compensation matters rely heavily on complete and accurate medical records. However, retrieving, verifying, organizing, and interpreting these records is traditionally slow, fragmented, and prone to administrative bottlenecks. Codes Health transforms this process into a structured digital workflow that prioritizes speed, clarity, and reliability. The platform enables legal teams to systematically identify all relevant healthcare providers connected to a case. Through automated provider discovery tools, lawyers can ensure that no critical medical source is overlooked. Once providers are identified, Codes Health centralizes record requests and manages the retrieval process through secure, standardized channels. Instead of navigating multiple hospital systems, fax requests, or inconsistent documentation formats, attorneys receive organized digital files that are uniform, searchable, and immediately usable. A key advantage of Codes Health is its missing-record review framework. Legal cases can be weakened by incomplete documentation, and gaps in medical history often go unnoticed until late stages of litigation. Codes Health uses structured validation systems to flag missing reports, incomplete treatment timelines, and documentation inconsistencies. This proactive review reduces legal risk and strengthens case preparation by ensuring attorneys work with complete medical narratives. Automation plays a critical role in improving operational efficiency. Automated follow-up mechanisms track outstanding record requests and continuously prompt providers without manual intervention. Legal staff no longer need to dedicate hours to repetitive communication and status monitoring. Instead, they can focus on case analysis, client interaction, and legal strategy. This shift reduces overhead costs and accelerates case timelines. Beyond administrative efficiency, Codes Health enhances legal insight. The platform organizes records into chronological medical timelines that allow lawyers to interpret treatment progression, causation patterns, and expert evidence more clearly. Consolidated reporting tools transform raw medical data into structured summaries, making it easier to communicate complex healthcare information to judges, juries, insurers, and clients. Security and compliance are foundational to the system. Codes Health is designed around privacy-first architecture, ensuring sensitive patient information is handled according to regulatory standards. Secure encryption, audit trails, and controlled access protocols protect both legal firms and their clients from data exposure risks. Ultimately, Codes Health functions as a strategic infrastructure partner for legal professionals. It converts medical documentation from a logistical obstacle into an operational advantage. By combining automation, verification, and structured data organization, the platform enables lawyers to operate faster, more accurately, and with greater confidence. In high-stakes legal environments where precision and time are critical, Codes Health empowers legal teams to deliver stronger advocacy and better client outcomes.
AB79: Medical Malpractice
AB101: Workers Compensation
B108: Codes Health is supported by investors known for backing high-growth technology companies. Pathlight Ventures focuses on early-stage startups driving innovation in healthcare and enterprise software. General Catalyst is a global venture capital firm recognized for scaling transformative companies across technology and healthcare. Haystack invests in ambitious founders building category-defining startups. Y Combinator, one of the world’s most influential startup accelerators, has launched thousands of successful companies through its mentorship-driven model. Night Capital backs emerging ventures with strong growth potential, providing strategic capital and operational guidance. Together, these investors reflect strong confidence in Codes Health’s long-term vision. Beyond capital, these investors bring deep industry expertise, operational mentorship, and access to global startup networks. Their involvement signals strong validation of Codes Health’s business model and growth potential. With support from firms experienced in scaling technology-driven healthcare platforms, the company is positioned to accelerate product development, expand market reach, and strengthen strategic partnerships. This investor ecosystem enhances credibility, attracts top talent, and provides long-term stability — key factors that support sustainable growth in a competitive digital health landscape.
AB123: Insurance Litigation
D130: Benefit of Using Codes - Health
D133: Codes Health delivers a streamlined solution that simplifies the complex process of managing medical records and coordinating healthcare documentation. One of its primary benefits is efficiency. By digitizing and organizing healthcare information, the platform significantly reduces the time spent locating providers, retrieving records, and verifying documentation. This enables both healthcare professionals and legal teams to focus on decision-making rather than administrative work. Accuracy and completeness are another major advantage. Codes Health helps identify missing or incomplete records through structured review systems, ensuring that critical healthcare information is not overlooked. This reduces errors, improves case preparation, and strengthens compliance standards. Automated follow-up systems further enhance reliability by ensuring that outstanding requests and updates are tracked without manual intervention. The platform also improves collaboration between medical providers and legal professionals. By acting as a secure bridge between healthcare and legal ecosystems, Codes Health supports smoother communication and faster case processing. Secure data handling and privacy-focused infrastructure protect sensitive information, building trust among users and maintaining regulatory integrity. From a scalability perspective, Codes Health is designed to grow with its users. Whether serving small clinics, large healthcare networks, or legal firms handling complex cases, the platform adapts to increasing data volume without sacrificing performance. This flexibility positions it as a long-term infrastructure partner rather than a short-term tool. Overall, Codes Health enhances productivity, reduces administrative friction, strengthens compliance, and enables faster access to critical medical information — delivering measurable value across healthcare and legal workflows.
B146: Done for educational purposes

Sheet REVENUE ASSUMPTION
B1: CH (Codes Health) | D1: Revenue Assumption
D4: 45741 | E4: =EDATE(D$4,1) -> 45772 | F4: =EDATE(E$4,1) -> 45802 | G4: =EDATE(F$4,1) -> 45833 | H4: =EDATE(G$4,1) -> 45863 | I4: =EDATE(H$4,1) -> 45894 | J4: =EDATE(I$4,1) -> 45925 | K4: =EDATE(J$4,1) -> 45955 | L4: =EDATE(K$4,1) -> 45986 | ... AB4: =EDATE(AA$4,1) -> 46471
B6: Assumptions | C6: Unit | D6: Month 1 | E6: Month 2 | F6: Month 3 | G6: Month 4 | H6: Month 5 | I6: Month 6 | J6: Month 7 | K6: Month 8 | L6: Month 9 | M6: Month 10 | N6: Month 11 | O6: Month 12 | P6: Month 13 | Q6: Month 14 | R6: Month 15 | S6: Month 16 | T6: Month 17 | U6: Month 18 | V6: Month 19 | W6: Month 20 | X6: Month 21 | Y6: Month 22 | Z6: Month 23 | AA6: Month 24 | AB6: Month 25
B8: Revenue Assumption | D8: Best Case
B11: Client Assumption
B13: Opening Active Clients | C13: No. | D13: 7 | E13: =D$18 -> 13.979 | F13: =E$18 -> 27.937063 | G13: =F$18 -> 48.853252 | H13: =G$18 -> 76.706692 | I13: =H$18 -> 111.47657 | J13: =I$18 -> 153.14214 | K13: =J$18 -> 201.68272 | L13: =K$18 -> 257.07767 | ... AB13: =AA$18 -> 2045.3033
B14: New Client Added | C14: No. | D14: 7 | E14: =D$14+7 -> 14 | F14: =E$14+7 -> 21 | G14: =F$14+7 -> 28 | H14: =G$14+7 -> 35 | I14: =H$14+7 -> 42 | J14: =I$14+7 -> 49 | K14: =J$14+7 -> 56 | L14: =K$14+7 -> 63 | ... AB14: =AA$14+7 -> 175
B15: Client Chrun Rate | C15: % | D15: 0.003 | E15: 0.003 | F15: 0.003 | G15: 0.003 | H15: 0.003 | I15: 0.003 | J15: 0.003 | K15: 0.003 | L15: 0.003 | M15: 0.003 | N15: 0.003 | O15: 0.003 | P15: 0.004 | Q15: 0.004 | R15: 0.004 | S15: 0.004 | T15: 0.004 | U15: 0.004 | V15: 0.004 | W15: 0.004 | X15: 0.004 | Y15: 0.004 | Z15: 0.004 | AA15: 0.004 | AB15: 0.004
B16: Client Lost (Churn) | C16: No. | D16: =D$13*D$15 -> 0.021 | E16: =E$13*E$15 -> 0.041937 | F16: =F$13*F$15 -> 0.083811189 | G16: =G$13*G$15 -> 0.14655976 | H16: =H$13*H$15 -> 0.23012008 | I16: =I$13*I$15 -> 0.33442972 | J16: =J$13*J$15 -> 0.45942643 | K16: =K$13*K$15 -> 0.60504815 | ... AB16: =AB$13*AB$15 -> 8.1812131
B18: Closing Active Clients | C18: No. | D18: =D13+D14-D16 -> 13.979 | E18: =E13+E14-E16 -> 27.937063 | F18: =F13+F14-F16 -> 48.853252 | G18: =G13+G14-G16 -> 76.706692 | H18: =H13+H14-H16 -> 111.47657 | I18: =I13+I14-I16 -> 153.14214 | J18: =J13+J14-J16 -> 201.68272 | K18: =K13+K14-K16 -> 257.07767 | ... AB18: =AB13+AB14-AB16 -> 2212.1221
B20: Pricing Assumptions
B22: Avg. Monthly Subscription Fee | C22: $ | D22: 500 | E22: 500 | F22: 500 | G22: 500 | H22: 500 | I22: 500 | J22: 500 | K22: 500 | L22: 500 | M22: 500 | N22: 500 | O22: 500 | P22: 500 | Q22: 500 | R22: 500 | S22: 500 | T22: 500 | U22: 500 | V22: 500 | W22: 500 | X22: 500 | Y22: 500 | Z22: 500 | AA22: 500 | AB22: 500
B23: Per Record / Usage Fee | C23: $ | D23: 1 | E23: 1 | F23: 1 | G23: 1 | H23: 1 | I23: 1 | J23: 1 | K23: 1 | L23: 1 | M23: 1 | N23: 1 | O23: 1 | P23: 1 | Q23: 1 | R23: 1 | S23: 1 | T23: 2 | U23: 2 | V23: 2 | W23: 2 | X23: 2 | Y23: 2 | Z23: 2 | AA23: 2 | AB23: 2
B25: Average Revenue per Client | D25: =SUM(D22:D23) -> 501 | E25: =SUM(E22:E23) -> 501 | F25: =SUM(F22:F23) -> 501 | G25: =SUM(G22:G23) -> 501 | H25: =SUM(H22:H23) -> 501 | I25: =SUM(I22:I23) -> 501 | J25: =SUM(J22:J23) -> 501 | K25: =SUM(K22:K23) -> 501 | ... AB25: =SUM(AB22:AB23) -> 502
B27: Revenue Calculation
B29: Active Paying Clients | C29: No. | D29: =D$18 -> 13.979 | E29: =E$18 -> 27.937063 | F29: =F$18 -> 48.853252 | G29: =G$18 -> 76.706692 | H29: =H$18 -> 111.47657 | I29: =I$18 -> 153.14214 | J29: =J$18 -> 201.68272 | K29: =K$18 -> 257.07767 | ... AB29: =AB$18 -> 2212.1221
B30: ARPU | C30: $ | D30: =D$25 -> 501 | E30: =E$25 -> 501 | F30: =F$25 -> 501 | G30: =G$25 -> 501 | H30: =H$25 -> 501 | I30: =I$25 -> 501 | J30: =J$25 -> 501 | K30: =K$25 -> 501 | ... AB30: =AB$25 -> 502
B32: Total Revenue | C32: $ | D32: =D29*D30 -> 7003.479 | E32: =E29*E30 -> 13996.469 | F32: =F29*F30 -> 24475.479 | G32: =G29*G30 -> 38430.053 | H32: =H29*H30 -> 55849.763 | I32: =I29*I30 -> 76724.213 | J32: =J29*J30 -> 101043.04 | K32: =K29*K30 -> 128795.91 | ... AB32: =AB29*AB30 -> 1110485.3
B34: Revenue Assumption | D34: Base Case
B37: Client Assumption
B39: Opening Active Clients | C39: No. | D39: 5 | E39: =D$44 -> 9.96 | F39: =E$44 -> 19.88032 | G39: =F$44 -> 34.721277 | H39: =G$44 -> 54.443507 | I39: =H$44 -> 79.007959 | J39: =I$44 -> 108.3759 | K39: =J$44 -> 142.50889 | L39: =K$44 -> 181.36882 | ... AB39: =AA$44 -> 1406.7387
B40: New Client Added | C40: No. | D40: 5 | E40: =D$40+5 -> 10 | F40: =E$40+5 -> 15 | G40: =F$40+5 -> 20 | H40: =G$40+5 -> 25 | I40: =H$40+5 -> 30 | J40: =I$40+5 -> 35 | K40: =J$40+5 -> 40 | L40: =K$40+5 -> 45 | ... AB40: =AA$40+5 -> 125
B41: Client Chrun Rate | C41: % | D41: 0.008 | E41: 0.008 | F41: 0.008 | G41: 0.008 | H41: 0.008 | I41: 0.008 | J41: 0.008 | K41: 0.008 | L41: 0.008 | M41: 0.008 | N41: 0.008 | O41: 0.008 | P41: 0.009 | Q41: 0.009 | R41: 0.009 | S41: 0.009 | T41: 0.009 | U41: 0.009 | V41: 0.009 | W41: 0.009 | X41: 0.009 | Y41: 0.009 | Z41: 0.009 | AA41: 0.009 | AB41: 0.009
B42: Client Lost (Churn) | C42: No. | D42: =D$41*D$39 -> 0.04 | E42: =E$41*E$39 -> 0.07968 | F42: =F$41*F$39 -> 0.15904256 | G42: =G$41*G$39 -> 0.27777022 | H42: =H$41*H$39 -> 0.43554806 | I42: =I$41*I$39 -> 0.63206367 | J42: =J$41*J$39 -> 0.86700716 | K42: =K$41*K$39 -> 1.1400711 | ... AB42: =AB$41*AB$39 -> 12.660648
B44: Closing Active Clients | C44: No. | D44: =D39+D40-D42 -> 9.96 | E44: =E39+E40-E42 -> 19.88032 | F44: =F39+F40-F42 -> 34.721277 | G44: =G39+G40-G42 -> 54.443507 | H44: =H39+H40-H42 -> 79.007959 | I44: =I39+I40-I42 -> 108.3759 | J44: =J39+J40-J42 -> 142.50889 | K44: =K39+K40-K42 -> 181.36882 | ... AB44: =AB39+AB40-AB42 -> 1519.078
B46: Pricing Assumptions
B48: Avg. Monthly Subscription Fee | C48: $ | D48: 250 | E48: 250 | F48: 250 | G48: 250 | H48: 250 | I48: 250 | J48: 250 | K48: 250 | L48: 250 | M48: 250 | N48: 250 | O48: 250 | P48: 250 | Q48: 250 | R48: 250 | S48: 250 | T48: 250 | U48: 250 | V48: 250 | W48: 250 | X48: 250 | Y48: 250 | Z48: 250 | AA48: 250 | AB48: 250
B49: Per Record / Usage Fee | C49: $ | D49: 0.5 | E49: 0.5 | F49: 0.5 | G49: 0.5 | H49: 0.5 | I49: 0.5 | J49: 0.5 | K49: 0.5 | L49: 0.5 | M49: 0.5 | N49: 0.5 | O49: 0.5 | P49: 0.5 | Q49: 0.5 | R49: 0.5 | S49: 0.5 | T49: 1 | U49: 1 | V49: 1 | W49: 1 | X49: 1 | Y49: 1 | Z49: 1 | AA49: 1 | AB49: 1
B51: Average Revenue per Client | D51: =D$48+D$49 -> 250.5 | E51: =E$48+E$49 -> 250.5 | F51: =F$48+F$49 -> 250.5 | G51: =G$48+G$49 -> 250.5 | H51: =H$48+H$49 -> 250.5 | I51: =I$48+I$49 -> 250.5 | J51: =J$48+J$49 -> 250.5 | K51: =K$48+K$49 -> 250.5 | ... AB51: =AB$48+AB$49 -> 251
B53: Revenue Calculation
B55: Active Paying Clients | C55: No. | D55: =D$44 -> 9.96 | E55: =E$44 -> 19.88032 | F55: =F$44 -> 34.721277 | G55: =G$44 -> 54.443507 | H55: =H$44 -> 79.007959 | I55: =I$44 -> 108.3759 | J55: =J$44 -> 142.50889 | K55: =K$44 -> 181.36882 | ... AB55: =AB$44 -> 1519.078
B56: ARPU | C56: $ | D56: =D$51 -> 250.5 | E56: =E$51 -> 250.5 | F56: =F$51 -> 250.5 | G56: =G$51 -> 250.5 | H56: =H$51 -> 250.5 | I56: =I$51 -> 250.5 | J56: =J$51 -> 250.5 | K56: =K$51 -> 250.5 | ... AB56: =AB$51 -> 251
B58: Total Revenue | C58: $ | D58: =D$55*D$56 -> 2494.98 | E58: =E$55*E$56 -> 4980.0202 | F58: =F$55*F$56 -> 8697.68 | G58: =G$55*G$56 -> 13638.099 | H58: =H$55*H$56 -> 19791.494 | I58: =I$55*I$56 -> 27148.162 | J58: =J$55*J$56 -> 35698.477 | K58: =K$55*K$56 -> 45432.889 | ... AB58: =AB$55*AB$56 -> 381288.59
B60: Revenue Assumption | D60: Worst Case
B63: Client Assumption
B65: Opening Active Clients | C65: No. | D65: 3 | E65: =D$70 -> 5.946 | F65: =E$70 -> 11.838972 | G65: =F$70 -> 20.625871 | H65: =G$70 -> 32.254605 | I65: =H$70 -> 46.674022 | J65: =I$70 -> 63.83389 | K65: =J$70 -> 83.68488 | L65: =K$70 -> 106.17855 | ... AB65: =AA$70 -> 784.1105
B66: New Client Added | C66: No. | D66: 3 | E66: =D$66+3 -> 6 | F66: =E$66+3 -> 9 | G66: =F$66+3 -> 12 | H66: =G$66+3 -> 15 | I66: =H$66+3 -> 18 | J66: =I$66+3 -> 21 | K66: =J$66+3 -> 24 | L66: =K$66+3 -> 27 | ... AB66: =AA$66+3 -> 75
B67: Client Chrun Rate | C67: % | D67: 0.018 | E67: 0.018 | F67: 0.018 | G67: 0.018 | H67: 0.018 | I67: 0.018 | J67: 0.018 | K67: 0.018 | L67: 0.018 | M67: 0.018 | N67: 0.018 | O67: 0.018 | P67: 0.019 | Q67: 0.019 | R67: 0.019 | S67: 0.019 | T67: 0.019 | U67: 0.019 | V67: 0.019 | W67: 0.019 | X67: 0.019 | Y67: 0.019 | Z67: 0.019 | AA67: 0.019 | AB67: 0.019
B68: Client Lost (Churn) | C68: No. | D68: =D$65*D$67 -> 0.054 | E68: =E$65*E$67 -> 0.107028 | F68: =F$65*F$67 -> 0.2131015 | G68: =G$65*G$67 -> 0.37126567 | H68: =H$65*H$67 -> 0.58058289 | I68: =I$65*I$67 -> 0.8401324 | J68: =J$65*J$67 -> 1.14901 | K68: =K$65*K$67 -> 1.5063278 | ... AB68: =AB$65*AB$67 -> 14.898099
B70: Closing Active Clients | C70: No. | D70: =D65+D66-D68 -> 5.946 | E70: =E65+E66-E68 -> 11.838972 | F70: =F65+F66-F68 -> 20.625871 | G70: =G65+G66-G68 -> 32.254605 | H70: =H65+H66-H68 -> 46.674022 | I70: =I65+I66-I68 -> 63.83389 | J70: =J65+J66-J68 -> 83.68488 | K70: =K65+K66-K68 -> 106.17855 | ... AB70: =AB65+AB66-AB68 -> 844.2124
B72: Pricing Assumptions
B74: Avg. Monthly Subscription Fee | C74: $ | D74: 150 | E74: 150 | F74: 150 | G74: 150 | H74: 150 | I74: 150 | J74: 150 | K74: 150 | L74: 150 | M74: 150 | N74: 150 | O74: 150 | P74: 150 | Q74: 150 | R74: 150 | S74: 150 | T74: 150 | U74: 150 | V74: 150 | W74: 150 | X74: 150 | Y74: 150 | Z74: 150 | AA74: 150 | AB74: 150
B75: Per Record / Usage Fee | C75: $ | D75: 0.25 | E75: 0.25 | F75: 0.25 | G75: 0.25 | H75: 0.25 | I75: 0.25 | J75: 0.25 | K75: 0.25 | L75: 0.25 | M75: 0.25 | N75: 0.25 | O75: 0.25 | P75: 0.25 | Q75: 0.25 | R75: 0.25 | S75: 0.25 | T75: 0.5 | U75: 0.5 | V75: 0.5 | W75: 0.5 | X75: 0.5 | Y75: 0.5 | Z75: 0.5 | AA75: 0.5 | AB75: 0.5
B77: Average Revenue per Client | D77: =SUM(D74:D75) -> 150.25 | E77: =SUM(E74:E75) -> 150.25 | F77: =SUM(F74:F75) -> 150.25 | G77: =SUM(G74:G75) -> 150.25 | H77: =SUM(H74:H75) -> 150.25 | I77: =SUM(I74:I75) -> 150.25 | J77: =SUM(J74:J75) -> 150.25 | K77: =SUM(K74:K75) -> 150.25 | ... AB77: =SUM(AB74:AB75) -> 150.5
B79: Revenue Calculation
B81: Active Paying Clients | C81: No. | D81: =D$70 -> 5.946 | E81: =E$70 -> 11.838972 | F81: =F$70 -> 20.625871 | G81: =G$70 -> 32.254605 | H81: =H$70 -> 46.674022 | I81: =I$70 -> 63.83389 | J81: =J$70 -> 83.68488 | K81: =K$70 -> 106.17855 | ... AB81: =AB$70 -> 844.2124
B82: ARPU | C82: $ | D82: =D$77 -> 150.25 | E82: =E$77 -> 150.25 | F82: =F$77 -> 150.25 | G82: =G$77 -> 150.25 | H82: =H$77 -> 150.25 | I82: =I$77 -> 150.25 | J82: =J$77 -> 150.25 | K82: =K$77 -> 150.25 | ... AB82: =AB$77 -> 150.5
B84: Total Revenue | C84: $ | D84: =D$81*D$82 -> 893.3865 | E84: =E$81*E$82 -> 1778.8055 | F84: =F$81*F$82 -> 3099.037 | G84: =G$81*G$82 -> 4846.2544 | H84: =H$81*H$82 -> 7012.7718 | I84: =I$81*I$82 -> 9591.0419 | J84: =J$81*J$82 -> 12573.653 | K84: =K$81*K$82 -> 15953.327 | ... AB84: =AB$81*AB$82 -> 127053.97
D86: Active Clients for Each Month (Best Case)
B89: In the best-case scenario, the number of active clients increases steadily each month, driven by strong client acquisition and minimal churn. Opening active clients grow consistently as new clients are added at a faster pace, while churn remains low due to high product value and strong client retention. As a result, closing active clients show a clear upward trend throughout the forecast period. This reflects successful market adoption and improving brand credibility over time.
C106: Active Clients for Each Month (Base Case)
B109: In the base-case scenario, active clients grow gradually over the forecast period, reflecting stable client onboarding and moderate churn. Each month begins with a growing base of opening active clients, supported by consistent new client additions. Churn remains controlled and predictable, allowing closing active clients to increase steadily. Overall, this trend represents realistic and sustainable growth under normal operating conditions.
C126: Active Clients for Each Month (Worst Case)
B129: In the worst-case scenario, growth in active clients is slower due to limited client additions and higher churn. While new clients continue to be onboarded each month, client losses partially offset this growth. As a result, closing active clients increase at a modest pace, indicating challenges in retention and slower market traction under unfavorable conditions.
B146: Done for educational purposes

Sheet COST ASSUMPTION
B1: CH (Codes Health) | D1: Cost Assumption
D4: 45741 | E4: =EDATE(D$4,1) -> 45772 | F4: =EDATE(E$4,1) -> 45802 | G4: =EDATE(F$4,1) -> 45833 | H4: =EDATE(G$4,1) -> 45863 | I4: =EDATE(H$4,1) -> 45894 | J4: =EDATE(I$4,1) -> 45925 | K4: =EDATE(J$4,1) -> 45955 | L4: =EDATE(K$4,1) -> 45986 | ... AB4: =EDATE(AA$4,1) -> 46471
B6: Assumptions | C6: Unit | D6: Month 1 | E6: Month 2 | F6: Month 3 | G6: Month 4 | H6: Month 5 | I6: Month 6 | J6: Month 7 | K6: Month 8 | L6: Month 9 | M6: Month 10 | N6: Month 11 | O6: Month 12 | P6: Month 13 | Q6: Month 14 | R6: Month 15 | S6: Month 16 | T6: Month 17 | U6: Month 18 | V6: Month 19 | W6: Month 20 | X6: Month 21 | Y6: Month 22 | Z6: Month 23 | AA6: Month 24 | AB6: Month 25
B8: Cost Assumption | D8: Best Case
B11: Variable Cost Assumptions
B13: Active Paying Clients | C13: $/Client | D13: ='REVENUE ASSUMPTION'!D$18 -> 13.979 | E13: ='REVENUE ASSUMPTION'!E$18 -> 27.937063 | F13: ='REVENUE ASSUMPTION'!F$18 -> 48.853252 | G13: ='REVENUE ASSUMPTION'!G$18 -> 76.706692 | H13: ='REVENUE ASSUMPTION'!H$18 -> 111.47657 | I13: ='REVENUE ASSUMPTION'!I$18 -> 153.14214 | J13: ='REVENUE ASSUMPTION'!J$18 -> 201.68272 | K13: ='REVENUE ASSUMPTION'!K$18 -> 257.07767 | ... AB13: ='REVENUE ASSUMPTION'!AB$18 -> 2212.1221
B14: AI & Cloud Cost per Client | C14: $/Client | D14: 0.15 | E14: 0.15 | F14: 0.15 | G14: 0.15 | H14: 0.15 | I14: 0.15 | J14: 0.15 | K14: 0.15 | L14: 0.15 | M14: 0.15 | N14: 0.15 | O14: 0.15 | P14: 0.15 | Q14: 0.15 | R14: 0.15 | S14: 0.15 | T14: 0.15 | U14: 0.15 | V14: 0.15 | W14: 0.15 | X14: 0.15 | Y14: 0.1 | Z14: 0.1 | AA14: 0.1 | AB14: 0.1
B15: Medical Record Retrieval Cost | C15: $/Client | D15: 25 | E15: 25 | F15: 25 | G15: 25 | H15: 25 | I15: 25 | J15: 25 | K15: 25 | L15: 25 | M15: 25 | N15: 25 | O15: 25 | P15: 25 | Q15: 25 | R15: 25 | S15: 25 | T15: 25 | U15: 25 | V15: 25 | W15: 25 | X15: 25 | Y15: 20 | Z15: 20 | AA15: 20 | AB15: 20
B16: Customer Support Cost | C16: $/Client | D16: 2 | E16: 2 | F16: 2 | G16: 2 | H16: 2 | I16: 2 | J16: 2 | K16: 2 | L16: 2 | M16: 2 | N16: 2 | O16: 2 | P16: 2 | Q16: 2 | R16: 2 | S16: 2 | T16: 2 | U16: 2 | V16: 2 | W16: 2 | X16: 2 | Y16: 2 | Z16: 2 | AA16: 2 | AB16: 2
B18: Total Variable Cost per Client | D18: =SUM(D14:D16) -> 27.15 | E18: =SUM(E14:E16) -> 27.15 | F18: =SUM(F14:F16) -> 27.15 | G18: =SUM(G14:G16) -> 27.15 | H18: =SUM(H14:H16) -> 27.15 | I18: =SUM(I14:I16) -> 27.15 | J18: =SUM(J14:J16) -> 27.15 | K18: =SUM(K14:K16) -> 27.15 | ... AB18: =SUM(AB14:AB16) -> 22.1
B20: Total Variable Cost | D20: =D$18*D$13 -> 379.52985 | E20: =E$18*E$13 -> 758.49126 | F20: =F$18*F$13 -> 1326.3658 | G20: =G$18*G$13 -> 2082.5867 | H20: =H$18*H$13 -> 3026.5889 | I20: =I$18*I$13 -> 4157.8092 | J20: =J$18*J$13 -> 5475.6857 | K20: =K$18*K$13 -> 6979.6587 | ... AB20: =AB$18*AB$13 -> 48887.898
B22: Fixed Cost Assumptions
B24: Salaries & Wages | C24: $ | D24: =800000/12 -> 66666.667 | E24: =800000/12 -> 66666.667 | F24: =800000/12 -> 66666.667 | G24: =800000/12 -> 66666.667 | H24: =800000/12 -> 66666.667 | I24: =800000/12 -> 66666.667 | J24: =800000/12 -> 66666.667 | K24: =800000/12 -> 66666.667 | ... P24: =800000/12 -> 66666.667 | Q24: 70000 | R24: 70000 | S24: 70000 | T24: 70000 | U24: 70000 | V24: 70000 | W24: 70000 | X24: 70000 | Y24: 70000 | Z24: 70000 | AA24: 70000 | AB24: 70000
B25: Cloud Infrastructure | C25: $ | D25: =24000/12 -> 2000 | E25: =24000/12 -> 2000 | F25: =24000/12 -> 2000 | G25: =24000/12 -> 2000 | H25: =24000/12 -> 2000 | I25: =24000/12 -> 2000 | J25: =24000/12 -> 2000 | K25: =24000/12 -> 2000 | ... P25: =24000/12 -> 2000 | Q25: 3000 | R25: 3000 | S25: 3000 | T25: 3000 | U25: 3000 | V25: 3000 | W25: 3000 | X25: 3000 | Y25: 3000 | Z25: 3000 | AA25: 3000 | AB25: 3000
B26: Legal & Compliance | C26: $ | D26: =40000/12 -> 3333.3333 | E26: =40000/12 -> 3333.3333 | F26: =40000/12 -> 3333.3333 | G26: =40000/12 -> 3333.3333 | H26: =40000/12 -> 3333.3333 | I26: =40000/12 -> 3333.3333 | J26: =40000/12 -> 3333.3333 | K26: =40000/12 -> 3333.3333 | ... P26: =40000/12 -> 3333.3333 | Q26: 4333 | R26: 4333 | S26: 4333 | T26: 4333 | U26: 4333 | V26: 4333 | W26: 4333 | X26: 4333 | Y26: 4333 | Z26: 4333 | AA26: 4333 | AB26: 4333
B27: Office, Tools & Admin | C27: $ | D27: =10000/12 -> 833.33333 | E27: =10000/12 -> 833.33333 | F27: =10000/12 -> 833.33333 | G27: =10000/12 -> 833.33333 | H27: =10000/12 -> 833.33333 | I27: =10000/12 -> 833.33333 | J27: =10000/12 -> 833.33333 | K27: =10000/12 -> 833.33333 | ... P27: =10000/12 -> 833.33333 | Q27: 933 | R27: 933 | S27: 933 | T27: 933 | U27: 933 | V27: 933 | W27: 933 | X27: 933 | Y27: 933 | Z27: 933 | AA27: 933 | AB27: 933
B29: Total Fixed Cost | D29: =SUM(D24:D27) -> 72833.333 | E29: =SUM(E24:E27) -> 72833.333 | F29: =SUM(F24:F27) -> 72833.333 | G29: =SUM(G24:G27) -> 72833.333 | H29: =SUM(H24:H27) -> 72833.333 | I29: =SUM(I24:I27) -> 72833.333 | J29: =SUM(J24:J27) -> 72833.333 | K29: =SUM(K24:K27) -> 72833.333 | ... AB29: =SUM(AB24:AB27) -> 78266
B31: Cost Assumption | D31: Base Case
B34: Variable Cost Assumptions
B36: Active Paying Clients | C36: $/Client | D36: ='REVENUE ASSUMPTION'!D$44 -> 9.96 | E36: ='REVENUE ASSUMPTION'!E$44 -> 19.88032 | F36: ='REVENUE ASSUMPTION'!F$44 -> 34.721277 | G36: ='REVENUE ASSUMPTION'!G$44 -> 54.443507 | H36: ='REVENUE ASSUMPTION'!H$44 -> 79.007959 | I36: ='REVENUE ASSUMPTION'!I$44 -> 108.3759 | J36: ='REVENUE ASSUMPTION'!J$44 -> 142.50889 | K36: ='REVENUE ASSUMPTION'!K$44 -> 181.36882 | ... AB36: ='REVENUE ASSUMPTION'!AB$44 -> 1519.078
B37: AI & Cloud Cost per Client | C37: $/Client | D37: 0.8 | E37: 0.8 | F37: 0.8 | G37: 0.8 | H37: 0.8 | I37: 0.8 | J37: 0.8 | K37: 0.8 | L37: 0.8 | M37: 0.8 | N37: 0.8 | O37: 0.8 | P37: 0.8 | Q37: 0.8 | R37: 0.8 | S37: 0.8 | T37: 0.8 | U37: 0.8 | V37: 0.8 | W37: 0.8 | X37: 0.8 | Y37: 0.75 | Z37: 0.75 | AA37: 0.75 | AB37: 0.75
B38: Medical Record Retrieval Cost | C38: $/Client | D38: 35 | E38: 35 | F38: 35 | G38: 35 | H38: 35 | I38: 35 | J38: 35 | K38: 35 | L38: 35 | M38: 35 | N38: 35 | O38: 35 | P38: 35 | Q38: 35 | R38: 35 | S38: 35 | T38: 35 | U38: 35 | V38: 35 | W38: 35 | X38: 35 | Y38: 30 | Z38: 30 | AA38: 30 | AB38: 30
B39: Customer Support Cost | C39: $/Client | D39: 5 | E39: 5 | F39: 5 | G39: 5 | H39: 5 | I39: 5 | J39: 5 | K39: 5 | L39: 5 | M39: 5 | N39: 5 | O39: 5 | P39: 5 | Q39: 5 | R39: 5 | S39: 5 | T39: 5 | U39: 5 | V39: 5 | W39: 5 | X39: 5 | Y39: 5 | Z39: 5 | AA39: 5 | AB39: 5
B41: Total Variable Cost per Client | D41: =SUM(D37:D39) -> 40.8 | E41: =SUM(E37:E39) -> 40.8 | F41: =SUM(F37:F39) -> 40.8 | G41: =SUM(G37:G39) -> 40.8 | H41: =SUM(H37:H39) -> 40.8 | I41: =SUM(I37:I39) -> 40.8 | J41: =SUM(J37:J39) -> 40.8 | K41: =SUM(K37:K39) -> 40.8 | ... AB41: =SUM(AB37:AB39) -> 35.75
B43: Total Variable Cost | D43: =D$41*D$36 -> 406.368 | E43: =E$41*E$36 -> 811.11706 | F43: =F$41*F$36 -> 1416.6281 | G43: =G$41*G$36 -> 2221.2951 | H43: =H$41*H$36 -> 3223.5247 | I43: =I$41*I$36 -> 4421.7365 | J43: =J$41*J$36 -> 5814.3626 | K43: =K$41*K$36 -> 7399.8477 | ... AB43: =AB$41*AB$36 -> 54307.04
B45: Fixed Cost Assumptions
B47: Salaries & Wages | C47: $ | D47: =1300000/12 -> 108333.33 | E47: =1300000/12 -> 108333.33 | F47: =1300000/12 -> 108333.33 | G47: =1300000/12 -> 108333.33 | H47: =1300000/12 -> 108333.33 | I47: =1300000/12 -> 108333.33 | J47: =1300000/12 -> 108333.33 | K47: =1300000/12 -> 108333.33 | ... P47: =1300000/12 -> 108333.33 | Q47: 110000 | R47: 110000 | S47: 110000 | T47: 110000 | U47: 110000 | V47: 110000 | W47: 110000 | X47: 110000 | Y47: 110000 | Z47: 110000 | AA47: 110000 | AB47: 110000
B48: Cloud Infrastructure | C48: $ | D48: =60000/12 -> 5000 | E48: =60000/12 -> 5000 | F48: =60000/12 -> 5000 | G48: =60000/12 -> 5000 | H48: =60000/12 -> 5000 | I48: =60000/12 -> 5000 | J48: =60000/12 -> 5000 | K48: =60000/12 -> 5000 | ... P48: =60000/12 -> 5000 | Q48: 6000 | R48: 6000 | S48: 6000 | T48: 6000 | U48: 6000 | V48: 6000 | W48: 6000 | X48: 6000 | Y48: 6000 | Z48: 6000 | AA48: 6000 | AB48: 6000
B49: Legal & Compliance | C49: $ | D49: =80000/12 -> 6666.6667 | E49: =80000/12 -> 6666.6667 | F49: =80000/12 -> 6666.6667 | G49: =80000/12 -> 6666.6667 | H49: =80000/12 -> 6666.6667 | I49: =80000/12 -> 6666.6667 | J49: =80000/12 -> 6666.6667 | K49: =80000/12 -> 6666.6667 | ... P49: =80000/12 -> 6666.6667 | Q49: 7667 | R49: 7667 | S49: 7667 | T49: 7667 | U49: 7667 | V49: 7667 | W49: 7667 | X49: 7667 | Y49: 7667 | Z49: 7667 | AA49: 7667 | AB49: 7667
B50: Office, Tools & Admin | C50: $ | D50: =25000/12 -> 2083.3333 | E50: =25000/12 -> 2083.3333 | F50: =25000/12 -> 2083.3333 | G50: =25000/12 -> 2083.3333 | H50: =25000/12 -> 2083.3333 | I50: =25000/12 -> 2083.3333 | J50: =25000/12 -> 2083.3333 | K50: =25000/12 -> 2083.3333 | ... P50: =25000/12 -> 2083.3333 | Q50: 3083 | R50: 3083 | S50: 3083 | T50: 3083 | U50: 3083 | V50: 3083 | W50: 3083 | X50: 3083 | Y50: 3083 | Z50: 3083 | AA50: 3083 | AB50: 3083
B52: Total Fixed Cost | D52: =SUM(D47:D50) -> 122083.33 | E52: =SUM(E47:E50) -> 122083.33 | F52: =SUM(F47:F50) -> 122083.33 | G52: =SUM(G47:G50) -> 122083.33 | H52: =SUM(H47:H50) -> 122083.33 | I52: =SUM(I47:I50) -> 122083.33 | J52: =SUM(J47:J50) -> 122083.33 | K52: =SUM(K47:K50) -> 122083.33 | ... AB52: =SUM(AB47:AB50) -> 126750
B54: Cost Assumption | D54: Worst Case
B57: Variable Cost Assumptions
B59: Active Paying Clients | C59: $/Client | D59: ='REVENUE ASSUMPTION'!D$70 -> 5.946 | E59: ='REVENUE ASSUMPTION'!E$70 -> 11.838972 | F59: ='REVENUE ASSUMPTION'!F$70 -> 20.625871 | G59: ='REVENUE ASSUMPTION'!G$70 -> 32.254605 | H59: ='REVENUE ASSUMPTION'!H$70 -> 46.674022 | I59: ='REVENUE ASSUMPTION'!I$70 -> 63.83389 | J59: ='REVENUE ASSUMPTION'!J$70 -> 83.68488 | K59: ='REVENUE ASSUMPTION'!K$70 -> 106.17855 | ... AB59: ='REVENUE ASSUMPTION'!AB$70 -> 844.2124
B60: AI & Cloud Cost per Client | C60: $/Client | D60: 2.5 | E60: 2.5 | F60: 2.5 | G60: 2.5 | H60: 2.5 | I60: 2.5 | J60: 2.5 | K60: 2.5 | L60: 2.5 | M60: 2.5 | N60: 2.5 | O60: 2.5 | P60: 2.5 | Q60: 2.5 | R60: 2.5 | S60: 2.5 | T60: 2.5 | U60: 2.5 | V60: 2.5 | W60: 2.5 | X60: 2.5 | Y60: 3 | Z60: 3 | AA60: 3 | AB60: 3
B61: Medical Record Retrieval Cost | C61: $/Client | D61: 45 | E61: 45 | F61: 45 | G61: 45 | H61: 45 | I61: 45 | J61: 45 | K61: 45 | L61: 45 | M61: 45 | N61: 45 | O61: 45 | P61: 45 | Q61: 45 | R61: 45 | S61: 45 | T61: 45 | U61: 45 | V61: 45 | W61: 45 | X61: 45 | Y61: 50 | Z61: 50 | AA61: 50 | AB61: 50
B62: Customer Support Cost | C62: $/Client | D62: 12 | E62: 12 | F62: 12 | G62: 12 | H62: 12 | I62: 12 | J62: 12 | K62: 12 | L62: 12 | M62: 12 | N62: 12 | O62: 12 | P62: 12 | Q62: 12 | R62: 12 | S62: 12 | T62: 12 | U62: 12 | V62: 12 | W62: 12 | X62: 12 | Y62: 12 | Z62: 12 | AA62: 12 | AB62: 12
B64: Total Variable Cost per Client | D64: =SUM(D60:D62) -> 59.5 | E64: =SUM(E60:E62) -> 59.5 | F64: =SUM(F60:F62) -> 59.5 | G64: =SUM(G60:G62) -> 59.5 | H64: =SUM(H60:H62) -> 59.5 | I64: =SUM(I60:I62) -> 59.5 | J64: =SUM(J60:J62) -> 59.5 | K64: =SUM(K60:K62) -> 59.5 | ... AB64: =SUM(AB60:AB62) -> 65
B66: Total Variable Cost | D66: =D$64*D$59 -> 353.787 | E66: =E$64*E$59 -> 704.41883 | F66: =F$64*F$59 -> 1227.2393 | G66: =G$64*G$59 -> 1919.149 | H66: =H$64*H$59 -> 2777.1043 | I66: =I$64*I$59 -> 3798.1164 | J66: =J$64*J$59 -> 4979.2503 | K66: =K$64*K$59 -> 6317.6238 | ... AB66: =AB$64*AB$59 -> 54873.806
B68: Fixed Cost Assumptions
B70: Salaries & Wages | C70: $ | D70: =1800000/12 -> 150000 | E70: =1800000/12 -> 150000 | F70: =1800000/12 -> 150000 | G70: =1800000/12 -> 150000 | H70: =1800000/12 -> 150000 | I70: =1800000/12 -> 150000 | J70: =1800000/12 -> 150000 | K70: =1800000/12 -> 150000 | ... AB70: =1800000/12 -> 150000
B71: Cloud Infrastructure | C71: $ | D71: =120000/12 -> 10000 | E71: =120000/12 -> 10000 | F71: =120000/12 -> 10000 | G71: =120000/12 -> 10000 | H71: =120000/12 -> 10000 | I71: =120000/12 -> 10000 | J71: =120000/12 -> 10000 | K71: =120000/12 -> 10000 | ... AB71: =120000/12 -> 10000
B72: Legal & Compliance | C72: $ | D72: =150000/12 -> 12500 | E72: =150000/12 -> 12500 | F72: =150000/12 -> 12500 | G72: =150000/12 -> 12500 | H72: =150000/12 -> 12500 | I72: =150000/12 -> 12500 | J72: =150000/12 -> 12500 | K72: =150000/12 -> 12500 | ... AB72: =150000/12 -> 12500
B73: Office, Tools & Admin | C73: $ | D73: =50000/12 -> 4166.6667 | E73: =50000/12 -> 4166.6667 | F73: =50000/12 -> 4166.6667 | G73: =50000/12 -> 4166.6667 | H73: =50000/12 -> 4166.6667 | I73: =50000/12 -> 4166.6667 | J73: =50000/12 -> 4166.6667 | K73: =50000/12 -> 4166.6667 | ... AB73: =50000/12 -> 4166.6667
B75: Total Fixed Cost | D75: =SUM(D70:D73) -> 176666.67 | E75: =SUM(E70:E73) -> 176666.67 | F75: =SUM(F70:F73) -> 176666.67 | G75: =SUM(G70:G73) -> 176666.67 | H75: =SUM(H70:H73) -> 176666.67 | I75: =SUM(I70:I73) -> 176666.67 | J75: =SUM(J70:J73) -> 176666.67 | K75: =SUM(K70:K73) -> 176666.67 | ... AB75: =SUM(AB70:AB73) -> 176666.67
D77: Variable / Fixed Cost (Best Case)
B80: Variable Cost: Variable costs rise gradually with higher client usage but remain efficient due to scale benefits and optimized AI and cloud usage. Fixed Cost: Fixed costs stay largely stable with only planned increases in salaries and tools, improving operating leverage.
D95: Variable / Fixed Cost (Base Case)
B98: Variable Cost: Variable costs increase steadily in proportion to moderate growth in users, AI usage, and customer support activity. Fixed Cost: Fixed costs grow in a controlled and predictable manner to support normal business operations.
D113: Variable / Fixed Cost (Worst Case)
B116: Variable Cost: Variable costs remain relatively high per client due to lower utilization and weaker economies of scale. Fixed Cost: Fixed costs remain mostly inflexible despite slower growth, putting pressure on overall profitability.
B131: Done for educational purposes
B133: The cost assumptions for Codes Health have been developed to realistically reflect the operational structure of a growing health-tech platform while maintaining clarity and transparency in financial modeling. Costs are classified into variable costs and fixed costs to clearly show how expenses behave with changes in scale, usage, and growth across different scenarios. Variable costs primarily include AI API usage, cloud infrastructure, customer support, and other usage-linked operational expenses. These costs are assumed to move in line with platform activity, such as the number of active clients and system usage. In the best-case scenario, variable costs grow at a controlled rate due to higher utilization efficiency and economies of scale. In the base case, variable costs increase steadily, reflecting normal operational efficiency and balanced growth. In the worst-case scenario, variable costs remain relatively high per client because of lower utilization levels and limited scale benefits, placing pressure on margins. Fixed costs consist of salaries, software subscriptions, compliance expenses, administrative costs, and other overheads that do not vary directly with short-term changes in revenue. These costs are assumed to be largely stable over time, with planned and gradual increases to support business continuity and compliance requirements. In the best and base cases, fixed costs grow in a predictable and disciplined manner, allowing the business to benefit from operating leverage as revenue expands. In the worst case, fixed costs remain relatively inflexible despite slower growth, highlighting the downside risk to profitability. Overall, the cost assumptions aim to capture realistic cost behavior under different operating conditions, enabling a structured comparison between best, base, and worst-case outcomes and supporting informed financial analysis for Codes Health.

Sheet INCOME STATEMENT
B1: CH (Codes Health) | D1: Income Statement
D4: 45741 | E4: =EDATE(D$4,1) -> 45772 | F4: =EDATE(E$4,1) -> 45802 | G4: =EDATE(F$4,1) -> 45833 | H4: =EDATE(G$4,1) -> 45863 | I4: =EDATE(H$4,1) -> 45894 | J4: =EDATE(I$4,1) -> 45925 | K4: =EDATE(J$4,1) -> 45955 | L4: =EDATE(K$4,1) -> 45986 | ... AB4: =EDATE(AA$4,1) -> 46471
B6: Assumptions | C6: Unit | D6: Month 1 | E6: Month 2 | F6: Month 3 | G6: Month 4 | H6: Month 5 | I6: Month 6 | J6: Month 7 | K6: Month 8 | L6: Month 9 | M6: Month 10 | N6: Month 11 | O6: Month 12 | P6: Month 13 | Q6: Month 14 | R6: Month 15 | S6: Month 16 | T6: Month 17 | U6: Month 18 | V6: Month 19 | W6: Month 20 | X6: Month 21 | Y6: Month 22 | Z6: Month 23 | AA6: Month 24 | AB6: Month 25
B8: Income Statement | D8: Choose scenario is used for Income Statement for better visualisation | P8: 2
B11: Revenue
B13: Subscription Revenue | C13: $ | D13: =CHOOSE($P$8,'REVENUE ASSUMPTION'!D$22*'REVENUE ASSUMPTION'!D$18,'REVENUE ASSUMPTION'!D$48*'REVENUE ASSUMPTION'!D$44,'REVENUE ASSUMPTION'!D$74*'REVENUE ASSUMPTION'!D$70) -> 2490 | E13: =CHOOSE($P$8,'REVENUE ASSUMPTION'!E$22*'REVENUE ASSUMPTION'!E$18,'REVENUE ASSUMPTION'!E$48*'REVENUE ASSUMPTION'!E$44,'REVENUE ASSUMPTION'!E$74*'REVENUE ASSUMPTION'!E$70) -> 4970.08 | F13: =CHOOSE($P$8,'REVENUE ASSUMPTION'!F$22*'REVENUE ASSUMPTION'!F$18,'REVENUE ASSUMPTION'!F$48*'REVENUE ASSUMPTION'!F$44,'REVENUE ASSUMPTION'!F$74*'REVENUE ASSUMPTION'!F$70) -> 8680.3194 | G13: =CHOOSE($P$8,'REVENUE ASSUMPTION'!G$22*'REVENUE ASSUMPTION'!G$18,'REVENUE ASSUMPTION'!G$48*'REVENUE ASSUMPTION'!G$44,'REVENUE ASSUMPTION'!G$74*'REVENUE ASSUMPTION'!G$70) -> 13610.877 | H13: =CHOOSE($P$8,'REVENUE ASSUMPTION'!H$22*'REVENUE ASSUMPTION'!H$18,'REVENUE ASSUMPTION'!H$48*'REVENUE ASSUMPTION'!H$44,'REVENUE ASSUMPTION'!H$74*'REVENUE ASSUMPTION'!H$70) -> 19751.99 | I13: =CHOOSE($P$8,'REVENUE ASSUMPTION'!I$22*'REVENUE ASSUMPTION'!I$18,'REVENUE ASSUMPTION'!I$48*'REVENUE ASSUMPTION'!I$44,'REVENUE ASSUMPTION'!I$74*'REVENUE ASSUMPTION'!I$70) -> 27093.974 | J13: =CHOOSE($P$8,'REVENUE ASSUMPTION'!J$22*'REVENUE ASSUMPTION'!J$18,'REVENUE ASSUMPTION'!J$48*'REVENUE ASSUMPTION'!J$44,'REVENUE ASSUMPTION'!J$74*'REVENUE ASSUMPTION'!J$70) -> 35627.222 | K13: =CHOOSE($P$8,'REVENUE ASSUMPTION'!K$22*'REVENUE ASSUMPTION'!K$18,'REVENUE ASSUMPTION'!K$48*'REVENUE ASSUMPTION'!K$44,'REVENUE ASSUMPTION'!K$74*'REVENUE ASSUMPTION'!K$70) -> 45342.204 | ... AB13: =CHOOSE($P$8,'REVENUE ASSUMPTION'!AB$22*'REVENUE ASSUMPTION'!AB$18,'REVENUE ASSUMPTION'!AB$48*'REVENUE ASSUMPTION'!AB$44,'REVENUE ASSUMPTION'!AB$74*'REVENUE ASSUMPTION'!AB$70) -> 379769.51
B14: Usage Based Revenue | C14: $ | D14: =CHOOSE($P$8,'REVENUE ASSUMPTION'!D$23*'REVENUE ASSUMPTION'!D$18,'REVENUE ASSUMPTION'!D$49*'REVENUE ASSUMPTION'!D$44,'REVENUE ASSUMPTION'!D$75*'REVENUE ASSUMPTION'!D$70) -> 4.98 | E14: =CHOOSE($P$8,'REVENUE ASSUMPTION'!E$23*'REVENUE ASSUMPTION'!E$18,'REVENUE ASSUMPTION'!E$49*'REVENUE ASSUMPTION'!E$44,'REVENUE ASSUMPTION'!E$75*'REVENUE ASSUMPTION'!E$70) -> 9.94016 | F14: =CHOOSE($P$8,'REVENUE ASSUMPTION'!F$23*'REVENUE ASSUMPTION'!F$18,'REVENUE ASSUMPTION'!F$49*'REVENUE ASSUMPTION'!F$44,'REVENUE ASSUMPTION'!F$75*'REVENUE ASSUMPTION'!F$70) -> 17.360639 | G14: =CHOOSE($P$8,'REVENUE ASSUMPTION'!G$23*'REVENUE ASSUMPTION'!G$18,'REVENUE ASSUMPTION'!G$49*'REVENUE ASSUMPTION'!G$44,'REVENUE ASSUMPTION'!G$75*'REVENUE ASSUMPTION'!G$70) -> 27.221754 | H14: =CHOOSE($P$8,'REVENUE ASSUMPTION'!H$23*'REVENUE ASSUMPTION'!H$18,'REVENUE ASSUMPTION'!H$49*'REVENUE ASSUMPTION'!H$44,'REVENUE ASSUMPTION'!H$75*'REVENUE ASSUMPTION'!H$70) -> 39.50398 | I14: =CHOOSE($P$8,'REVENUE ASSUMPTION'!I$23*'REVENUE ASSUMPTION'!I$18,'REVENUE ASSUMPTION'!I$49*'REVENUE ASSUMPTION'!I$44,'REVENUE ASSUMPTION'!I$75*'REVENUE ASSUMPTION'!I$70) -> 54.187948 | J14: =CHOOSE($P$8,'REVENUE ASSUMPTION'!J$23*'REVENUE ASSUMPTION'!J$18,'REVENUE ASSUMPTION'!J$49*'REVENUE ASSUMPTION'!J$44,'REVENUE ASSUMPTION'!J$75*'REVENUE ASSUMPTION'!J$70) -> 71.254444 | K14: =CHOOSE($P$8,'REVENUE ASSUMPTION'!K$23*'REVENUE ASSUMPTION'!K$18,'REVENUE ASSUMPTION'!K$49*'REVENUE ASSUMPTION'!K$44,'REVENUE ASSUMPTION'!K$75*'REVENUE ASSUMPTION'!K$70) -> 90.684409 | ... AB14: =CHOOSE($P$8,'REVENUE ASSUMPTION'!AB$23*'REVENUE ASSUMPTION'!AB$18,'REVENUE ASSUMPTION'!AB$49*'REVENUE ASSUMPTION'!AB$44,'REVENUE ASSUMPTION'!AB$75*'REVENUE ASSUMPTION'!AB$70) -> 1519.078
B16: Total Revenue | C16: $ | D16: =SUM(D13:D14) -> 2494.98 | E16: =SUM(E13:E14) -> 4980.0202 | F16: =SUM(F13:F14) -> 8697.68 | G16: =SUM(G13:G14) -> 13638.099 | H16: =SUM(H13:H14) -> 19791.494 | I16: =SUM(I13:I14) -> 27148.162 | J16: =SUM(J13:J14) -> 35698.477 | K16: =SUM(K13:K14) -> 45432.889 | ... AB16: =SUM(AB13:AB14) -> 381288.59
B18: COGS
B20: AI & Cloud Usage | C20: $ | D20: =CHOOSE($P$8,'COST ASSUMPTION'!D$14*'COST ASSUMPTION'!D$13,'COST ASSUMPTION'!D$37*'COST ASSUMPTION'!D$36,'COST ASSUMPTION'!D$60*'COST ASSUMPTION'!D$59) -> 7.968 | E20: =CHOOSE($P$8,'COST ASSUMPTION'!E$14*'COST ASSUMPTION'!E$13,'COST ASSUMPTION'!E$37*'COST ASSUMPTION'!E$36,'COST ASSUMPTION'!E$60*'COST ASSUMPTION'!E$59) -> 15.904256 | F20: =CHOOSE($P$8,'COST ASSUMPTION'!F$14*'COST ASSUMPTION'!F$13,'COST ASSUMPTION'!F$37*'COST ASSUMPTION'!F$36,'COST ASSUMPTION'!F$60*'COST ASSUMPTION'!F$59) -> 27.777022 | G20: =CHOOSE($P$8,'COST ASSUMPTION'!G$14*'COST ASSUMPTION'!G$13,'COST ASSUMPTION'!G$37*'COST ASSUMPTION'!G$36,'COST ASSUMPTION'!G$60*'COST ASSUMPTION'!G$59) -> 43.554806 | H20: =CHOOSE($P$8,'COST ASSUMPTION'!H$14*'COST ASSUMPTION'!H$13,'COST ASSUMPTION'!H$37*'COST ASSUMPTION'!H$36,'COST ASSUMPTION'!H$60*'COST ASSUMPTION'!H$59) -> 63.206367 | I20: =CHOOSE($P$8,'COST ASSUMPTION'!I$14*'COST ASSUMPTION'!I$13,'COST ASSUMPTION'!I$37*'COST ASSUMPTION'!I$36,'COST ASSUMPTION'!I$60*'COST ASSUMPTION'!I$59) -> 86.700716 | J20: =CHOOSE($P$8,'COST ASSUMPTION'!J$14*'COST ASSUMPTION'!J$13,'COST ASSUMPTION'!J$37*'COST ASSUMPTION'!J$36,'COST ASSUMPTION'!J$60*'COST ASSUMPTION'!J$59) -> 114.00711 | K20: =CHOOSE($P$8,'COST ASSUMPTION'!K$14*'COST ASSUMPTION'!K$13,'COST ASSUMPTION'!K$37*'COST ASSUMPTION'!K$36,'COST ASSUMPTION'!K$60*'COST ASSUMPTION'!K$59) -> 145.09505 | ... AB20: =CHOOSE($P$8,'COST ASSUMPTION'!AB$14*'COST ASSUMPTION'!AB$13,'COST ASSUMPTION'!AB$37*'COST ASSUMPTION'!AB$36,'COST ASSUMPTION'!AB$60*'COST ASSUMPTION'!AB$59) -> 1139.3085
B21: Medical Record Retrieval | C21: $ | D21: =CHOOSE($P$8,'COST ASSUMPTION'!D$15*'COST ASSUMPTION'!D$13,'COST ASSUMPTION'!D$38*'COST ASSUMPTION'!D$36,'COST ASSUMPTION'!D$61*'COST ASSUMPTION'!D$59) -> 348.6 | E21: =CHOOSE($P$8,'COST ASSUMPTION'!E$15*'COST ASSUMPTION'!E$13,'COST ASSUMPTION'!E$38*'COST ASSUMPTION'!E$36,'COST ASSUMPTION'!E$61*'COST ASSUMPTION'!E$59) -> 695.8112 | F21: =CHOOSE($P$8,'COST ASSUMPTION'!F$15*'COST ASSUMPTION'!F$13,'COST ASSUMPTION'!F$38*'COST ASSUMPTION'!F$36,'COST ASSUMPTION'!F$61*'COST ASSUMPTION'!F$59) -> 1215.2447 | G21: =CHOOSE($P$8,'COST ASSUMPTION'!G$15*'COST ASSUMPTION'!G$13,'COST ASSUMPTION'!G$38*'COST ASSUMPTION'!G$36,'COST ASSUMPTION'!G$61*'COST ASSUMPTION'!G$59) -> 1905.5228 | H21: =CHOOSE($P$8,'COST ASSUMPTION'!H$15*'COST ASSUMPTION'!H$13,'COST ASSUMPTION'!H$38*'COST ASSUMPTION'!H$36,'COST ASSUMPTION'!H$61*'COST ASSUMPTION'!H$59) -> 2765.2786 | I21: =CHOOSE($P$8,'COST ASSUMPTION'!I$15*'COST ASSUMPTION'!I$13,'COST ASSUMPTION'!I$38*'COST ASSUMPTION'!I$36,'COST ASSUMPTION'!I$61*'COST ASSUMPTION'!I$59) -> 3793.1563 | J21: =CHOOSE($P$8,'COST ASSUMPTION'!J$15*'COST ASSUMPTION'!J$13,'COST ASSUMPTION'!J$38*'COST ASSUMPTION'!J$36,'COST ASSUMPTION'!J$61*'COST ASSUMPTION'!J$59) -> 4987.8111 | K21: =CHOOSE($P$8,'COST ASSUMPTION'!K$15*'COST ASSUMPTION'!K$13,'COST ASSUMPTION'!K$38*'COST ASSUMPTION'!K$36,'COST ASSUMPTION'!K$61*'COST ASSUMPTION'!K$59) -> 6347.9086 | ... AB21: =CHOOSE($P$8,'COST ASSUMPTION'!AB$15*'COST ASSUMPTION'!AB$13,'COST ASSUMPTION'!AB$38*'COST ASSUMPTION'!AB$36,'COST ASSUMPTION'!AB$61*'COST ASSUMPTION'!AB$59) -> 45572.341
B23: Total COGS | C23: $ | D23: =SUM(D20:D21) -> 356.568 | E23: =SUM(E20:E21) -> 711.71546 | F23: =SUM(F20:F21) -> 1243.0217 | G23: =SUM(G20:G21) -> 1949.0776 | H23: =SUM(H20:H21) -> 2828.4849 | I23: =SUM(I20:I21) -> 3879.8571 | J23: =SUM(J20:J21) -> 5101.8182 | K23: =SUM(K20:K21) -> 6493.0037 | ... AB23: =SUM(AB20:AB21) -> 46711.65
B25: Gross Profit | C25: $ | D25: =D16-D23 -> 2138.412 | E25: =E16-E23 -> 4268.3047 | F25: =F16-F23 -> 7454.6583 | G25: =G16-G23 -> 11689.021 | H25: =H16-H23 -> 16963.009 | I25: =I16-I23 -> 23268.305 | J25: =J16-J23 -> 30596.658 | K25: =K16-K23 -> 38939.885 | ... AB25: =AB16-AB23 -> 334576.94
B26: Gross Profit Margin % | C26: % | D26: =D$25/D16 -> 0.85708583 | E26: =E$25/E16 -> 0.85708583 | F26: =F$25/F16 -> 0.85708583 | G26: =G$25/G16 -> 0.85708583 | H26: =H$25/H16 -> 0.85708583 | I26: =I$25/I16 -> 0.85708583 | J26: =J$25/J16 -> 0.85708583 | K26: =K$25/K16 -> 0.85708583 | ... AB26: =AB$25/AB16 -> 0.87749004
B28: OpEx
B30: Variable Cost
B32: Customer Support Cost | C32: $ | D32: =CHOOSE($P$8,'COST ASSUMPTION'!D$16*'COST ASSUMPTION'!D$13,'COST ASSUMPTION'!D$39*'COST ASSUMPTION'!D$36,'COST ASSUMPTION'!D$62*'COST ASSUMPTION'!D$59) -> 49.8 | E32: =CHOOSE($P$8,'COST ASSUMPTION'!E$16*'COST ASSUMPTION'!E$13,'COST ASSUMPTION'!E$39*'COST ASSUMPTION'!E$36,'COST ASSUMPTION'!E$62*'COST ASSUMPTION'!E$59) -> 99.4016 | F32: =CHOOSE($P$8,'COST ASSUMPTION'!F$16*'COST ASSUMPTION'!F$13,'COST ASSUMPTION'!F$39*'COST ASSUMPTION'!F$36,'COST ASSUMPTION'!F$62*'COST ASSUMPTION'!F$59) -> 173.60639 | G32: =CHOOSE($P$8,'COST ASSUMPTION'!G$16*'COST ASSUMPTION'!G$13,'COST ASSUMPTION'!G$39*'COST ASSUMPTION'!G$36,'COST ASSUMPTION'!G$62*'COST ASSUMPTION'!G$59) -> 272.21754 | H32: =CHOOSE($P$8,'COST ASSUMPTION'!H$16*'COST ASSUMPTION'!H$13,'COST ASSUMPTION'!H$39*'COST ASSUMPTION'!H$36,'COST ASSUMPTION'!H$62*'COST ASSUMPTION'!H$59) -> 395.0398 | I32: =CHOOSE($P$8,'COST ASSUMPTION'!I$16*'COST ASSUMPTION'!I$13,'COST ASSUMPTION'!I$39*'COST ASSUMPTION'!I$36,'COST ASSUMPTION'!I$62*'COST ASSUMPTION'!I$59) -> 541.87948 | J32: =CHOOSE($P$8,'COST ASSUMPTION'!J$16*'COST ASSUMPTION'!J$13,'COST ASSUMPTION'!J$39*'COST ASSUMPTION'!J$36,'COST ASSUMPTION'!J$62*'COST ASSUMPTION'!J$59) -> 712.54444 | K32: =CHOOSE($P$8,'COST ASSUMPTION'!K$16*'COST ASSUMPTION'!K$13,'COST ASSUMPTION'!K$39*'COST ASSUMPTION'!K$36,'COST ASSUMPTION'!K$62*'COST ASSUMPTION'!K$59) -> 906.84409 | ... AB32: =CHOOSE($P$8,'COST ASSUMPTION'!AB$16*'COST ASSUMPTION'!AB$13,'COST ASSUMPTION'!AB$39*'COST ASSUMPTION'!AB$36,'COST ASSUMPTION'!AB$62*'COST ASSUMPTION'!AB$59) -> 7595.3902
B34: Total Variable Cost | C34: $ | D34: =D$32 -> 49.8 | E34: =E$32 -> 99.4016 | F34: =F$32 -> 173.60639 | G34: =G$32 -> 272.21754 | H34: =H$32 -> 395.0398 | I34: =I$32 -> 541.87948 | J34: =J$32 -> 712.54444 | K34: =K$32 -> 906.84409 | ... AB34: =AB$32 -> 7595.3902
B36: Contribution Margin | C36: $ | D36: =D25-D34 -> 2088.612 | E36: =E25-E34 -> 4168.9031 | F36: =F25-F34 -> 7281.0519 | G36: =G25-G34 -> 11416.803 | H36: =H25-H34 -> 16567.969 | I36: =I25-I34 -> 22726.425 | J36: =J25-J34 -> 29884.114 | K36: =K25-K34 -> 38033.041 | ... AB36: =AB25-AB34 -> 326981.55
B37: Contribution Margin % | C37: % | D37: =D36/D16 -> 0.83712575 | E37: =E36/E16 -> 0.83712575 | F37: =F36/F16 -> 0.83712575 | G37: =G36/G16 -> 0.83712575 | H37: =H36/H16 -> 0.83712575 | I37: =I36/I16 -> 0.83712575 | J37: =J36/J16 -> 0.83712575 | K37: =K36/K16 -> 0.83712575 | ... AB37: =AB36/AB16 -> 0.85756972
B39: Fixed Cost
B41: Salaries & Wages | C41: $ | D41: =CHOOSE($P$8,'COST ASSUMPTION'!D24,'COST ASSUMPTION'!D47,'COST ASSUMPTION'!D70) -> 108333.33 | E41: =CHOOSE($P$8,'COST ASSUMPTION'!E24,'COST ASSUMPTION'!E47,'COST ASSUMPTION'!E70) -> 108333.33 | F41: =CHOOSE($P$8,'COST ASSUMPTION'!F24,'COST ASSUMPTION'!F47,'COST ASSUMPTION'!F70) -> 108333.33 | G41: =CHOOSE($P$8,'COST ASSUMPTION'!G24,'COST ASSUMPTION'!G47,'COST ASSUMPTION'!G70) -> 108333.33 | H41: =CHOOSE($P$8,'COST ASSUMPTION'!H24,'COST ASSUMPTION'!H47,'COST ASSUMPTION'!H70) -> 108333.33 | I41: =CHOOSE($P$8,'COST ASSUMPTION'!I24,'COST ASSUMPTION'!I47,'COST ASSUMPTION'!I70) -> 108333.33 | J41: =CHOOSE($P$8,'COST ASSUMPTION'!J24,'COST ASSUMPTION'!J47,'COST ASSUMPTION'!J70) -> 108333.33 | K41: =CHOOSE($P$8,'COST ASSUMPTION'!K24,'COST ASSUMPTION'!K47,'COST ASSUMPTION'!K70) -> 108333.33 | ... AB41: =CHOOSE($P$8,'COST ASSUMPTION'!AB24,'COST ASSUMPTION'!AB47,'COST ASSUMPTION'!AB70) -> 110000
B42: Cloud Infrastructure | C42: $ | D42: =CHOOSE($P$8,'COST ASSUMPTION'!D25,'COST ASSUMPTION'!D48,'COST ASSUMPTION'!D71) -> 5000 | E42: =CHOOSE($P$8,'COST ASSUMPTION'!E25,'COST ASSUMPTION'!E48,'COST ASSUMPTION'!E71) -> 5000 | F42: =CHOOSE($P$8,'COST ASSUMPTION'!F25,'COST ASSUMPTION'!F48,'COST ASSUMPTION'!F71) -> 5000 | G42: =CHOOSE($P$8,'COST ASSUMPTION'!G25,'COST ASSUMPTION'!G48,'COST ASSUMPTION'!G71) -> 5000 | H42: =CHOOSE($P$8,'COST ASSUMPTION'!H25,'COST ASSUMPTION'!H48,'COST ASSUMPTION'!H71) -> 5000 | I42: =CHOOSE($P$8,'COST ASSUMPTION'!I25,'COST ASSUMPTION'!I48,'COST ASSUMPTION'!I71) -> 5000 | J42: =CHOOSE($P$8,'COST ASSUMPTION'!J25,'COST ASSUMPTION'!J48,'COST ASSUMPTION'!J71) -> 5000 | K42: =CHOOSE($P$8,'COST ASSUMPTION'!K25,'COST ASSUMPTION'!K48,'COST ASSUMPTION'!K71) -> 5000 | ... AB42: =CHOOSE($P$8,'COST ASSUMPTION'!AB25,'COST ASSUMPTION'!AB48,'COST ASSUMPTION'!AB71) -> 6000
B43: Legal & Compliance | C43: $ | D43: =CHOOSE($P$8,'COST ASSUMPTION'!D26,'COST ASSUMPTION'!D49,'COST ASSUMPTION'!D72) -> 6666.6667 | E43: =CHOOSE($P$8,'COST ASSUMPTION'!E26,'COST ASSUMPTION'!E49,'COST ASSUMPTION'!E72) -> 6666.6667 | F43: =CHOOSE($P$8,'COST ASSUMPTION'!F26,'COST ASSUMPTION'!F49,'COST ASSUMPTION'!F72) -> 6666.6667 | G43: =CHOOSE($P$8,'COST ASSUMPTION'!G26,'COST ASSUMPTION'!G49,'COST ASSUMPTION'!G72) -> 6666.6667 | H43: =CHOOSE($P$8,'COST ASSUMPTION'!H26,'COST ASSUMPTION'!H49,'COST ASSUMPTION'!H72) -> 6666.6667 | I43: =CHOOSE($P$8,'COST ASSUMPTION'!I26,'COST ASSUMPTION'!I49,'COST ASSUMPTION'!I72) -> 6666.6667 | J43: =CHOOSE($P$8,'COST ASSUMPTION'!J26,'COST ASSUMPTION'!J49,'COST ASSUMPTION'!J72) -> 6666.6667 | K43: =CHOOSE($P$8,'COST ASSUMPTION'!K26,'COST ASSUMPTION'!K49,'COST ASSUMPTION'!K72) -> 6666.6667 | ... AB43: =CHOOSE($P$8,'COST ASSUMPTION'!AB26,'COST ASSUMPTION'!AB49,'COST ASSUMPTION'!AB72) -> 7667
B44: Office, Tools & Admin | C44: $ | D44: =CHOOSE($P$8,'COST ASSUMPTION'!D27,'COST ASSUMPTION'!D50,'COST ASSUMPTION'!D73) -> 2083.3333 | E44: =CHOOSE($P$8,'COST ASSUMPTION'!E27,'COST ASSUMPTION'!E50,'COST ASSUMPTION'!E73) -> 2083.3333 | F44: =CHOOSE($P$8,'COST ASSUMPTION'!F27,'COST ASSUMPTION'!F50,'COST ASSUMPTION'!F73) -> 2083.3333 | G44: =CHOOSE($P$8,'COST ASSUMPTION'!G27,'COST ASSUMPTION'!G50,'COST ASSUMPTION'!G73) -> 2083.3333 | H44: =CHOOSE($P$8,'COST ASSUMPTION'!H27,'COST ASSUMPTION'!H50,'COST ASSUMPTION'!H73) -> 2083.3333 | I44: =CHOOSE($P$8,'COST ASSUMPTION'!I27,'COST ASSUMPTION'!I50,'COST ASSUMPTION'!I73) -> 2083.3333 | J44: =CHOOSE($P$8,'COST ASSUMPTION'!J27,'COST ASSUMPTION'!J50,'COST ASSUMPTION'!J73) -> 2083.3333 | K44: =CHOOSE($P$8,'COST ASSUMPTION'!K27,'COST ASSUMPTION'!K50,'COST ASSUMPTION'!K73) -> 2083.3333 | ... AB44: =CHOOSE($P$8,'COST ASSUMPTION'!AB27,'COST ASSUMPTION'!AB50,'COST ASSUMPTION'!AB73) -> 3083
B46: Total Fixed Cost | C46: $ | D46: =SUM(D41:D44) -> 122083.33 | E46: =SUM(E41:E44) -> 122083.33 | F46: =SUM(F41:F44) -> 122083.33 | G46: =SUM(G41:G44) -> 122083.33 | H46: =SUM(H41:H44) -> 122083.33 | I46: =SUM(I41:I44) -> 122083.33 | J46: =SUM(J41:J44) -> 122083.33 | K46: =SUM(K41:K44) -> 122083.33 | ... AB46: =SUM(AB41:AB44) -> 126750
B48: Total OpEx | C48: $ | D48: =D46+D34 -> 122133.13 | E48: =E46+E34 -> 122182.73 | F48: =F46+F34 -> 122256.94 | G48: =G46+G34 -> 122355.55 | H48: =H46+H34 -> 122478.37 | I48: =I46+I34 -> 122625.21 | J48: =J46+J34 -> 122795.88 | K48: =K46+K34 -> 122990.18 | ... AB48: =AB46+AB34 -> 134345.39
B50: Total Cost | C50: $ | D50: =D48+D23 -> 122489.7 | E50: =E48+E23 -> 122894.45 | F50: =F48+F23 -> 123499.96 | G50: =G48+G23 -> 124304.63 | H50: =H48+H23 -> 125306.86 | I50: =I48+I23 -> 126505.07 | J50: =J48+J23 -> 127897.7 | K50: =K48+K23 -> 129483.18 | ... AB50: =AB48+AB23 -> 181057.04
B52: EBT | C52: $ | D52: =D36-D46 -> -119994.72 | E52: =E36-E46 -> -117914.43 | F52: =F36-F46 -> -114802.28 | G52: =G36-G46 -> -110666.53 | H52: =H36-H46 -> -105515.36 | I52: =I36-I46 -> -99356.908 | J52: =J36-J46 -> -92199.219 | K52: =K36-K46 -> -84050.292 | ... AB52: =AB36-AB46 -> 200231.55
B54: Tax | C54: % | D54: 0.21 | E54: 0.21 | F54: 0.21 | G54: 0.21 | H54: 0.21 | I54: 0.21 | J54: 0.21 | K54: 0.21 | L54: 0.21 | M54: 0.21 | N54: 0.21 | O54: 0.21 | P54: 0.21 | Q54: 0.21 | R54: 0.21 | S54: 0.21 | T54: 0.21 | U54: 0.21 | V54: 0.21 | W54: 0.21 | X54: 0.21 | Y54: 0.21 | Z54: 0.21 | AA54: 0.21 | AB54: 0.21
B56: Net Profit | C56: $ | D56: =IF(D52>0,D52*D54,"N/A") -> N/A | E56: =IF(E52>0,E52*E54,"N/A") -> N/A | F56: =IF(F52>0,F52*F54,"N/A") -> N/A | G56: =IF(G52>0,G52*G54,"N/A") -> N/A | H56: =IF(H52>0,H52*H54,"N/A") -> N/A | I56: =IF(I52>0,I52*I54,"N/A") -> N/A | J56: =IF(J52>0,J52*J54,"N/A") -> N/A | K56: =IF(K52>0,K52*K54,"N/A") -> N/A | ... AB56: =IF(AB52>0,AB52*AB54,"N/A") -> 42048.625
D58: Revenue Forecast
B61: =CHOOSE($P$8,NOTES!$C$3,NOTES!$C$17,NOTES!$C$31) -> Revenue grows at a steady and realistic pace. Client acquisition and conversions are consistent but not aggressive. Growth reflects achievable assumptions under normal conditions. The business gains clients gradually and builds trust over time. This scenario assumes stable performance without viral growth. Revenue increases show positive momentum but require patience. It represents a practical and believable growth path.
D76: Gross Profit Forecast
B79: =CHOOSE($P$8,NOTES!$D$3,NOTES!$D$17,NOTES!$D$31) -> Gross profit is stable with reasonable margins. Direct costs are covered comfortably, but margins are not very high. Pricing and cost structure are balanced. The company operates efficiently but without major economies of scale yet. Gross profit supports operations but leaves limited buffer for large expansions. It reflects a sustainable but cautious model.
D94: Total Cost Forecast
B97: =CHOOSE($P$8,NOTES!$E$3,NOTES!$E$31) -> Total costs remain relatively high since many expenses are fixed. Even if revenue slows, salaries and admin costs continue. This creates pressure on finances. Limited flexibility in reducing costs affects sustainability. The company must manage cash carefully in this scenario.
D112: Net Profit Forecast
B115: =CHOOSE($P$8,NOTES!$F$3,NOTES!$F$17,NOTES!$F$31) -> Net profit is low or slightly negative in early months but improves over time. As revenue scales, profitability gradually appears. This reflects a normal startup journey. The business moves toward break-even steadily. It is sustainable but requires patience. Profitability is achievable with consistent execution.
B130: Cash Flow Runway | D130: Choose scenario is used for Cash Flow Runway for better visualisation | P130: 2
B133: Starting Cash | C133: $ | D133: 500000 | E133: =IF(D139<0,D139+$D$141,D139) -> 380005.28 | F133: =IF(E139<0,E139+$D$141,E139) -> 262090.85 | G133: =IF(F139<0,F139+$D$141,F139) -> 147288.57 | H133: =IF(G139<0,G139+$D$141,G139) -> 36622.037 | I133: =IF(H139<0,H139+$D$141,H139) -> 431106.67 | J133: =IF(I139<0,I139+$D$141,I139) -> 331749.76 | K133: =IF(J139<0,J139+$D$141,J139) -> 239550.55 | L133: =IF(K139<0,K139+$D$141,K139) -> 155500.25 | ... AB133: =IF(AA139<0,AA139+$D$141,AA139) -> 1160017.1
B134: Revenue | C134: $ | D134: =CHOOSE($P$130,'REVENUE ASSUMPTION'!D$32,'REVENUE ASSUMPTION'!D$58,'REVENUE ASSUMPTION'!D$84) -> 2494.98 | E134: =CHOOSE($P$130,'REVENUE ASSUMPTION'!E$32,'REVENUE ASSUMPTION'!E$58,'REVENUE ASSUMPTION'!E$84) -> 4980.0202 | F134: =CHOOSE($P$130,'REVENUE ASSUMPTION'!F$32,'REVENUE ASSUMPTION'!F$58,'REVENUE ASSUMPTION'!F$84) -> 8697.68 | G134: =CHOOSE($P$130,'REVENUE ASSUMPTION'!G$32,'REVENUE ASSUMPTION'!G$58,'REVENUE ASSUMPTION'!G$84) -> 13638.099 | H134: =CHOOSE($P$130,'REVENUE ASSUMPTION'!H$32,'REVENUE ASSUMPTION'!H$58,'REVENUE ASSUMPTION'!H$84) -> 19791.494 | I134: =CHOOSE($P$130,'REVENUE ASSUMPTION'!I$32,'REVENUE ASSUMPTION'!I$58,'REVENUE ASSUMPTION'!I$84) -> 27148.162 | J134: =CHOOSE($P$130,'REVENUE ASSUMPTION'!J$32,'REVENUE ASSUMPTION'!J$58,'REVENUE ASSUMPTION'!J$84) -> 35698.477 | K134: =CHOOSE($P$130,'REVENUE ASSUMPTION'!K$32,'REVENUE ASSUMPTION'!K$58,'REVENUE ASSUMPTION'!K$84) -> 45432.889 | ... AB134: =CHOOSE($P$130,'REVENUE ASSUMPTION'!AB$32,'REVENUE ASSUMPTION'!AB$58,'REVENUE ASSUMPTION'!AB$84) -> 381288.59
B135: Expenses | C135: $ | D135: =CHOOSE($P$130,'COST ASSUMPTION'!D29+'COST ASSUMPTION'!D20,'COST ASSUMPTION'!D52+'COST ASSUMPTION'!D43,'COST ASSUMPTION'!D66+'COST ASSUMPTION'!D75) -> 122489.7 | E135: =CHOOSE($P$130,'COST ASSUMPTION'!E29+'COST ASSUMPTION'!E20,'COST ASSUMPTION'!E52+'COST ASSUMPTION'!E43,'COST ASSUMPTION'!E66+'COST ASSUMPTION'!E75) -> 122894.45 | F135: =CHOOSE($P$130,'COST ASSUMPTION'!F29+'COST ASSUMPTION'!F20,'COST ASSUMPTION'!F52+'COST ASSUMPTION'!F43,'COST ASSUMPTION'!F66+'COST ASSUMPTION'!F75) -> 123499.96 | G135: =CHOOSE($P$130,'COST ASSUMPTION'!G29+'COST ASSUMPTION'!G20,'COST ASSUMPTION'!G52+'COST ASSUMPTION'!G43,'COST ASSUMPTION'!G66+'COST ASSUMPTION'!G75) -> 124304.63 | H135: =CHOOSE($P$130,'COST ASSUMPTION'!H29+'COST ASSUMPTION'!H20,'COST ASSUMPTION'!H52+'COST ASSUMPTION'!H43,'COST ASSUMPTION'!H66+'COST ASSUMPTION'!H75) -> 125306.86 | I135: =CHOOSE($P$130,'COST ASSUMPTION'!I29+'COST ASSUMPTION'!I20,'COST ASSUMPTION'!I52+'COST ASSUMPTION'!I43,'COST ASSUMPTION'!I66+'COST ASSUMPTION'!I75) -> 126505.07 | J135: =CHOOSE($P$130,'COST ASSUMPTION'!J29+'COST ASSUMPTION'!J20,'COST ASSUMPTION'!J52+'COST ASSUMPTION'!J43,'COST ASSUMPTION'!J66+'COST ASSUMPTION'!J75) -> 127897.7 | K135: =CHOOSE($P$130,'COST ASSUMPTION'!K29+'COST ASSUMPTION'!K20,'COST ASSUMPTION'!K52+'COST ASSUMPTION'!K43,'COST ASSUMPTION'!K66+'COST ASSUMPTION'!K75) -> 129483.18 | ... AB135: =CHOOSE($P$130,'COST ASSUMPTION'!AB29+'COST ASSUMPTION'!AB20,'COST ASSUMPTION'!AB52+'COST ASSUMPTION'!AB43,'COST ASSUMPTION'!AB66+'COST ASSUMPTION'!AB75) -> 181057.04
B137: Net Cash Flow | C137: $ | D137: =D134-D135 -> -119994.72 | E137: =E134-E135 -> -117914.43 | F137: =F134-F135 -> -114802.28 | G137: =G134-G135 -> -110666.53 | H137: =H134-H135 -> -105515.36 | I137: =I134-I135 -> -99356.908 | J137: =J134-J135 -> -92199.219 | K137: =K134-K135 -> -84050.292 | ... AB137: =AB134-AB135 -> 200231.55
B139: Ending Cash | C139: $ | D139: =IF(D137<0,D133+D137,D133+D137) -> 380005.28 | E139: =IF(E137<0,E133+E137,E133+E137) -> 262090.85 | F139: =IF(F137<0,F133+F137,F133+F137) -> 147288.57 | G139: =IF(G137<0,G133+G137,G133+G137) -> 36622.037 | H139: =IF(H137<0,H133+H137,H133+H137) -> -68893.327 | I139: =IF(I137<0,I133+I137,I133+I137) -> 331749.76 | J139: =IF(J137<0,J133+J137,J133+J137) -> 239550.55 | K139: =IF(K137<0,K133+K137,K133+K137) -> 155500.25 | ... AB139: =IF(AB137<0,AB133+AB137,AB133+AB137) -> 1360248.7
B141: Fund Incoming | C141: $ | D141: 500000 | E141: 0 | F141: 0 | G141: 0 | H141: 0 | I141: 0 | J141: 0 | K141: 0 | L141: 0 | M141: 0 | N141: 0 | O141: 0 | P141: 0 | Q141: 0 | R141: 0 | S141: 0 | T141: 0 | U141: 0 | V141: 0 | W141: 0 | X141: 0 | Y141: 0 | Z141: 0 | AA141: 0 | AB141: 0
B142: Month Requiring Funds | D142: =IF(D139<0,"Taken","N/A") -> N/A | E142: =IF(E139<0,"Taken","N/A") -> N/A | F142: =IF(F139<0,"Taken","N/A") -> N/A | G142: =IF(G139<0,"Taken","N/A") -> N/A | H142: =IF(H139<0,"Taken","N/A") -> Taken | I142: =IF(I139<0,"Taken","N/A") -> N/A | J142: =IF(J139<0,"Taken","N/A") -> N/A | K142: =IF(K139<0,"Taken","N/A") -> N/A | ... AB142: =IF(AB139<0,"Taken","N/A") -> N/A
B144: For best case no funding is really needed to run th business, base case scenario requires atleast 1MN $ of funding before being profitable but worse case scenario requires lots of amount in order to carry out their expenses but it is very unlikely
B146: Done for educational purposes

Sheet CONCLUSION
B1: Conclusion
B7: Revenue Logic
B10: The revenue model for Codes Health is structured around four main drivers: new client additions, churn rate, average monthly subscription fee, and usage-based fees. These drivers were selected because they represent how a healthcare records and support platform realistically generates recurring income. In the Best Case, the model assumes strong client acquisition driven by referrals, partnerships, and faster onboarding. New client additions increase steadily over time, leading to a rapid rise in active clients. Churn is assumed to be minimal because satisfied healthcare clients tend to maintain long-term vendor relationships. The subscription fee is assumed at approximately $500 per client per month, reflecting premium pricing or expanded services. Usage fees further increase revenue as higher client activity generates additional billing. This case reflects a scenario where Codes Health achieves strong market acceptance and pricing power. In the Base Case, growth is moderate and realistic. New client additions increase gradually rather than aggressively, reflecting the slower sales cycles typical in healthcare. Churn is present but controlled, acknowledging that some clients may leave due to pricing or operational changes. The average subscription fee of approximately $200 per client per month reflects competitive but sustainable pricing. Usage fees provide incremental revenue but do not dominate total income. This scenario represents steady traction and realistic growth. In the Worst Case, client acquisition is slower, and churn is slightly higher. This reflects potential challenges in onboarding or competition. Pricing is assumed at around $120 per client per month, representing competitive pressure or limited service scope. Usage fees are lower due to reduced client activity. This scenario acknowledges downside risk while still assuming business continuity. Overall, the revenue assumptions across all cases are grounded in healthcare industry realities where trust, compliance, and gradual adoption shape growth.
B25: Cost Logic
B28: The cost model separates variable and fixed costs to reflect how expenses behave in a service-based healthcare startup. Variable Costs Variable costs scale with the number of clients served. Best Case: Variable cost per client is approximately $27, assuming operational efficiency and scale benefits. Base Case: Around $41 per client, reflecting normal service effort. Worst Case: Around $65 per client, assuming higher servicing burden or inefficiencies. This structure ensures that margins remain realistic as the company grows. Fixed Costs Fixed costs are largely driven by salaries and administrative overhead. Monthly salary costs range roughly: $66k–$76k in earlier periods Increasing toward $110k+ as hiring expands These assumptions are supported by real job postings showing salaries of $100k–$200k annually per employee, which equals roughly $8k–$16k monthly per hire. This validates the payroll assumptions and shows that compensation is market-aligned. Administrative, compliance, and infrastructure costs remain stable across scenarios, reflecting the need for secure systems and regulatory adherence in healthcare operations. The Best Case assumes costs grow efficiently with revenue. The Base Case assumes controlled cost growth. The Worst Case assumes fixed costs remain high even if revenue grows slowly, creating pressure on margins.
B63: Income Statement Insight
B66: Gross Profit Gross profit improves steadily as client numbers grow. Since subscription revenue per client significantly exceeds variable cost per client, the model shows strong gross margin potential. The Best Case achieves the highest margins due to higher pricing and lower variable costs. The Base Case maintains stable margins. The Worst Case shows thinner margins but still positive gross profit. Contribution Margin Contribution margins remain positive in all scenarios. This indicates that each additional client contributes toward covering fixed costs after variable costs are paid. This confirms viable unit economics and scalability potential. Net Profit Net profit trends clearly show the impact of fixed costs and operating leverage. In early periods, net profit is limited or negative due to salary and infrastructure commitments. This is typical for startups investing in growth. As revenue scales, fixed costs are absorbed and net profit improves. Best Case: Net profit turns positive earlier and grows strongly as high pricing and strong client growth absorb fixed costs quickly. Base Case: Net profit improves gradually, showing a realistic path to sustainability. Profitability is achieved as revenue catches up with payroll and fixed costs. Worst Case: Net profit remains low or negative for longer because slower revenue growth struggles to absorb fixed costs. This highlights execution risk.
B87: Overall Conclusion
B90: This financial model provides a balanced and realistic evaluation of Codes Health. Revenue assumptions reflect healthcare client behavior and realistic pricing. Cost assumptions are supported by real-world salary benchmarks and operational needs. The income statement shows clear operating leverage and improving margins with scale. Across all cases, the model demonstrates that Codes Health has a scalable business model with positive unit economics. However, success is execution-dependent. If client acquisition and retention keep pace with hiring, profitability is achievable. If payroll expands faster than revenue, financial pressure increases. Overall, Codes Health appears to be a potentially scalable healthcare services business with credible pathways to profitability, but success depends on disciplined growth, hiring control, and strong execution. The model is realistic, analytical, and suitable for investor or academic evaluation.
B98: Done for educational purposes
B100: This financial model has been prepared solely for academic, educational, and analytical purposes. The primary objective of this model is to demonstrate financial modeling techniques, scenario analysis, and structured business evaluation within a learning environment. It is not intended to serve as a precise forecast, valuation, or representation of the actual financial performance of Codes Health or any other entity. The figures, projections, and assumptions used in this model are based on hypothetical scenarios, publicly observable information, and logical estimations designed to illustrate how financial models are constructed and interpreted. The model relies on simplified assumptions to simulate how a healthcare services business might behave financially under different conditions. These assumptions include estimated client growth, churn rates, pricing structures, cost behavior, and hiring patterns. While efforts have been made to keep assumptions realistic and aligned with general industry practices, they do not represent verified internal data from Codes Health. They are conceptual inputs used for learning and analytical demonstration. Real-world financial outcomes are influenced by numerous dynamic factors such as market conditions, competition, regulation, operational execution, macroeconomic trends, and company-specific decisions, all of which extend beyond the scope of this model. Revenue assumptions in this model are constructed using theoretical client acquisition patterns and pricing frameworks common in subscription-based or service-oriented healthcare platforms. These assumptions illustrate how recurring revenue models function but should not be interpreted as actual revenue expectations. Real healthcare businesses often experience variability in client onboarding timelines, compliance approvals, contract negotiations, and service utilization, which can significantly alter financial outcomes. The model simplifies these elements to maintain clarity in learning how revenue flows through a financial structure. Cost assumptions are similarly illustrative. Salary ranges referenced in the model are based on general market observations and publicly available job postings to maintain realism in scenario construction. However, actual compensation structures within any organization may vary based on geography, experience levels, internal policies, and equity-based compensation. Infrastructure, compliance, and administrative cost estimates are also conceptual and may differ materially from real operational costs faced by healthcare companies. The scenario framework — best case, base case, and worst case — is included to teach sensitivity analysis and risk awareness. These scenarios are not predictions but analytical tools that show how outcomes change under different assumptions. In practice, real businesses may experience conditions outside these defined scenarios. The purpose here is to illustrate modeling methodology rather than to define future performance boundaries. This model does not incorporate full due diligence factors such as detailed regulatory compliance analysis, legal liabilities, cybersecurity risks, or detailed capital structure considerations. Healthcare businesses, in particular, operate in highly regulated environments where compliance costs and legal requirements can materially affect financial performance. These complexities are simplified in this model to focus on core financial modeling concepts. The model also does not attempt to capture qualitative factors such as management capability, organizational culture, operational execution quality, technological differentiation, or competitive positioning. These elements play a significant role in determining real-world business success but are difficult to quantify in a simplified academic model. Therefore, the absence of these factors should not be interpreted as a reflection of their importance. All financial projections are inherently uncertain. Even professional financial forecasts prepared by experienced analysts can differ significantly from actual outcomes. This model is created in a learning context where the goal is to understand relationships between financial variables rather than to produce precise predictions. Users of this model should view it as an educational exercise in structured thinking and financial planning. The model is not audited, verified, or endorsed by Codes Health or any external party. Any resemblance between modeled figures and actual company performance is purely coincidental. The company name is used as a case study example to apply financial modeling techniques in a practical context. No confidential or proprietary information has been used in the preparation of this model. This model is intended to help students and learners understand how assumptions drive financial results, how income statements are built, how operating leverage works, and how scenario analysis can support decision-making frameworks. It is a tool for developing analytical skills, not for forming business judgments about any real company. Readers should interpret this model as a demonstration of methodology rather than a representation of reality. Financial models are only as strong as their assumptions, and assumptions are inherently subject to change. Market conditions evolve, technologies advance, regulations shift, and consumer behavior adapts. All of these can influence financial outcomes in ways that simplified models cannot fully capture. In an academic setting, models like this are valuable for illustrating cause-and-effect relationships between revenue growth, cost structure, and profitability. They allow learners to test scenarios, explore sensitivity, and understand financial dynamics. That educational purpose is the foundation of this model. The preparation of this model reflects an attempt to apply logical reasoning, publicly observable benchmarks, and structured financial thinking. However, it does not claim to represent professional financial advice, corporate guidance, or strategic recommendations for any organization. It should be evaluated within the context of a learning exercise. By presenting multiple scenarios and clearly stating assumptions, the model encourages transparency and critical thinking. Users are encouraged to question assumptions, adjust variables, and explore alternative outcomes as part of the learning process. This iterative approach is central to financial modeling education. Ultimately, this model is an academic exercise designed to develop financial literacy, analytical reasoning, and scenario planning skills. It is not a substitute for professional financial analysis, corporate disclosures, or audited financial statements. Any interpretation of the model should remain within its educational intent. But one things to keep in mind that according to our analysis this company needs more funding but one more thing which is true is when this company becomes profitable which may take whole year of 2026 it will not take to much time to touch break - even
