Workbook

Sheet DATA
B2: Metric (₹ Cr) | C2: FY21 | D2: FY22 | E2: FY23 | F2: FY24 | G2: FY25
B3: Revenue from Operations | C3: 471.79 | D3: 624.71 | E3: 696.45 | F3: 810.83 | G3: 1055.5
B4: EBITDA | C4: 214.23 | D4: 296.63 | E4: 313.47 | F4: 382.09 | G4: 502.16
B5: D&A | C5: 97.91 | D5: 36.16 | E5: 43.45 | F5: 48.62 | G5: 59.33
B6: EBIT | C6: 116.32 | D6: 260.46 | E6: 270.02 | F6: 333.47 | G6: 442.83
B7: Interest Expense (Finance Costs) | C7: 51.91 | D7: 52.83 | E7: 10.61 | F7: 8.33 | G7: 4.63
B8: PBT | C8: 64.41 | D8: 207.63 | E8: 259.41 | F8: 325.14 | G8: 438.2
B9: Tax (Current + Deferred) | C9: 131.72 | D9: 54.62 | E9: 63.16 | F9: 79.72 | G9: 112.65
B10: PAT | C10: -67.31 | D10: 153.02 | E10: 196.25 | F10: 245.42 | G10: 325.55
B11: Cash & Cash Equivalents | C11: 14.71 | D11: 30.92 | E11: 57 | F11: 46.64 | G11: 22.78
B12: Total Debt (Borrowings) | C12: 346.13 | D12: 122.51 | E12: 130.07 | F12: 0 | G12: 0
B13: Trade Receivables | C13: 107.87 | D13: 107.06 | E13: 117.64 | F13: 143.5 | G13: 179.67
B14: Trade Payables | C14: 25.05 | D14: 23.94 | E14: 24.69 | F14: 40.16 | G14: 66.94
B15: Inventory | C15: Nil | D15: Nil | E15: Nil | F15: Nil | G15: Nil
B16: Net Working Capital (TR − TP) | C16: 82.82 | D16: 83.13 | E16: 92.95 | F16: 103.34 | G16: 112.73
B17: CFO | C17: 202.38 | D17: 256.27 | E17: 232.02 | F17: 286.34 | G17: 393.31
B18: Capex (PP&E + Intangibles) | C18: 30.32 | D18: 66.76 | E18: 65.59 | F18: 79.67 | G18: 85.66
B19: Free Cash Flow (CFO − Capex) | C19: 172.06 | D19: 189.51 | E19: 166.43 | F19: 206.66 | G19: 307.65
B20: Dividends Paid | C20: 0 | D20: 0 | E20: 0 | F20: 0 | G20: 98.52

Sheet COVER PAGE
B1: Kfin | C1: LBO Model
B6: Leveraged Buyout Model
B8: Kfin Technologies
B16: Entry structuring, capital stack, debt paydown & exit returns
B20: Entry EBITDA Multiple | E20: 29.13x
B22: Holding Period | E22: 5 Years
B24: Exit IRR | E24: 0.2052
B26: MOIC | E26: 2.54x
B28: Sponsor Equity (% of Total Sources) | E28: 0.8178
B31: This model presents a complete leveraged buyout analysis of Kfin Technologies, covering the purchase price buildup, sources and uses of funds, capital structure, debt schedule with cash sweep, and exit returns analysis with IRR and MOIC sensitivity across 5 year holding period.
B35: This leveraged buyout model and all accompanying analysis, projections, and figures relating to KFin Technologies have been prepared solely for educational and illustrative purposes. The assumptions, forecasts, and valuation outputs presented are based on simplified modelling techniques and publicly available information, and do not represent investment recommendations, research coverage, or professional financial advice. Nothing in this document should be interpreted as a solicitation to buy, sell, or hold any security. Readers are strongly encouraged to conduct independent due diligence and consult a qualified, licensed financial advisor before making any investment decisions.
B43: Table of Contents
B45: Assumption (Revenue, Margin, Capital Structure and Return Hurdle Assumption) | G45: 2
B47: Actual Figures ( Historical P&L, Balance Sheet, Cash Flow Statement) | G47: 3
B49: Operating Forecast (Projected Financials and Key Ratios) | G49: 4
B51: Purchase Price Buildup ( Sources and Uses of Funds) | G51: 5
B53: Debt Schedule and Cash Sweep ( Debt Paydown, Interest Paydown Plan) | G53: 6
B55: Exit / Gain Analysis and Sensitivity | G55: 7
B58: Prepared By - Sharwin Wagh

Sheet ASSUMPTIONS
B1: Kfin | C1: Assumptions
B6: Particulars | C6: Year 1 | D6: Year 2 | E6: Year 3 | F6: Year 4 | G6: Year 5
B8: Revenue Forecast Assumption
B9: Rev Growth (%) | C9: =CHOOSE($G$40,$G$36,$G$37,$G$38) -> 0.17300259 | D9: =C9 -> 0.17300259 | E9: =D9 -> 0.17300259 | F9: =E9 -> 0.17300259 | G9: =F9 -> 0.17300259
B11: EBITDA Margin Assumption
B12: EBITDA Margin (%) | C12: =AVERAGE('HISTORICAL DATA'!C48:G48) -> 0.46519863 | D12: =$C$12 -> 0.46519863 | E12: =$C$12 -> 0.46519863 | F12: =$C$12 -> 0.46519863 | G12: =$C$12 -> 0.46519863
B14: D & A Assumption
B15: D & A (% of Rev) | C15: 0.0591 | D15: 0.0591 | E15: 0.0591 | F15: 0.0591 | G15: 0.0591
B17: Capex Assumption
B18: Capex (% of Rev) | C18: 0.0889 | D18: 0.0889 | E18: 0.0889 | F18: 0.0889 | G18: 0.0889
B20: Transaction Assumption
B21: Assumption | C21: Value | E21: Metrics | G21: Value
B23: Entry EBITDA Multiple | C23: =G31 -> 29.133734 | E23: Share Price | G23: 847.95
B24: Exit EBITDA Multiple | C24: =$C$23 -> 29.133734 | E24: Shares Out. | G24: 17.28
B25: Holding Period (Yrs) | C25: 5 | E25: Market Cap. | G25: =G23*G24 -> 14652.576
B26: Tax Rate | C26: 0.25 | E26: Net Debt | G26: ='HISTORICAL DATA'!G28 -> -22.78
B27: Transaction Fees (% of EV) | C27: ='PURCHASE PRICE & SOURCES, USES'!C18 -> 292.14032 | E27: EV | G27: =G25+G26 -> 14629.796
B29: Capital Structure Assumption
B30: Assumption | C30: Value | E30: 2025 EBITDA | G30: ='HISTORICAL DATA'!G10 -> 502.16
E31: EBITDA Mul. | G31: =G27/G30 -> 29.133734
B32: Senior Debt (% of EV) | C32: ='PURCHASE PRICE & SOURCES, USES'!G8/G27 -> 0.17626079
B33: Mezzanine Debt (% of EV) | C33: ='PURCHASE PRICE & SOURCES, USES'!G9/G27 -> 0.0092768839 | E33: 2025 DSO | G33: =('HISTORICAL DATA'!C30/'HISTORICAL DATA'!C8)*365 -> 83.453549
B34: Sponsor Equity (% of EV) | C34: =100%-(C32+C33) -> 0.81446232 | E34: 2025 DPO | G34: =('HISTORICAL DATA'!C32/('HISTORICAL DATA'!C8-'HISTORICAL DATA'!C10))*365 -> 35.499495
B35: Interest Rate (%) | C35: ='PURCHASE PRICE & SOURCES, USES'!C29+'PURCHASE PRICE & SOURCES, USES'!C30 -> 0.23
B36: Mandatory Amortization | C36: 0 | E36: CAGR Rev (Bull) | G36: =_xlfn.RRI(4,'HISTORICAL DATA'!C8,'HISTORICAL DATA'!G8) -> 0.22300259
B37: Cash Sweep (%) | C37: 1 | E37: CAGR Rev (Base) | G37: =G36-5% -> 0.17300259
E38: CAGR Rev (Bear) | G38: =G37-5% -> 0.12300259
B39: Exit Assumption
B40: Assumption | C40: Value | E40: Scenario Change | G40: 2
B42: Exit Year | C42: 2030 | E42: Revenue growth is estimated in 3 cases (bull, base and bear), to get realistic view. Historical data indicates clear trend for ebitda margin, D&A % of Rev and Capex % of Rev hence evaluation by considering cases is not strictly required. It can also be noticed that exit EBITDA Multiple is same as entry EBITDA Multiple, it is taken into consideration since industry average for EBITDA Multiple is around 34x therefore we are well within its limit. Our target IRR is 20% + and MOIC is 3x +, specific assumptions are made because it is industry norm. also by using formula EBITDA / Min interest coverage ratio * Diluted interest rate we can raise max debt upto 2714 crores. Also min interest c.r. is taken as 2x since its what considerd by lenders.
B43: Exit EBITDA Multiple | C43: =C24 -> 29.133734
B45: Return Hurdles
B46: Assumption | C46: Value
B48: Target IRR (%) | C48: 0.2
B49: Target MOIC (x) | C49: 3
B51: Min Interest Coverage Ratio | C51: 2
B53: Diluted Interest Rate | C53: =('PURCHASE PRICE & SOURCES, USES'!C23*'PURCHASE PRICE & SOURCES, USES'!C29)+('PURCHASE PRICE & SOURCES, USES'!C24*'PURCHASE PRICE & SOURCES, USES'!C30) -> 0.0925
B55: Max debt to be raised | C55: =G30/(C51*C53) -> 2714.3784
B58: Prepared By - Sharwin Wagh

Sheet HISTORICAL DATA
B1: Kfin | C1: Actual Figures
B6: Particulars | C6: 2021 | D6: =C6+1 -> 2022 | E6: =D6+1 -> 2023 | F6: =E6+1 -> 2024 | G6: =F6+1 -> 2025
B7: Income Statement Metrics
B8: Revenue | C8: =DATA!C3 -> 471.79 | D8: =DATA!D3 -> 624.71 | E8: =DATA!E3 -> 696.45 | F8: =DATA!F3 -> 810.83 | G8: =DATA!G3 -> 1055.5
B10: EBITDA | C10: =DATA!C4 -> 214.23 | D10: =DATA!D4 -> 296.63 | E10: =DATA!E4 -> 313.47 | F10: =DATA!F4 -> 382.09 | G10: =DATA!G4 -> 502.16
B12: D & A | C12: =DATA!C5 -> 97.91 | D12: =DATA!D5 -> 36.16 | E12: =DATA!E5 -> 43.45 | F12: =DATA!F5 -> 48.62 | G12: =DATA!G5 -> 59.33
B14: EBIT | C14: =DATA!C6 -> 116.32 | D14: =DATA!D6 -> 260.46 | E14: =DATA!E6 -> 270.02 | F14: =DATA!F6 -> 333.47 | G14: =DATA!G6 -> 442.83
B16: Interest Expense | C16: =DATA!C7 -> 51.91 | D16: =DATA!D7 -> 52.83 | E16: =DATA!E7 -> 10.61 | F16: =DATA!F7 -> 8.33 | G16: =DATA!G7 -> 4.63
B18: PBT | C18: =DATA!C8 -> 64.41 | D18: =DATA!D8 -> 207.63 | E18: =DATA!E8 -> 259.41 | F18: =DATA!F8 -> 325.14 | G18: =DATA!G8 -> 438.2
B20: Tax | C20: =DATA!C9 -> 131.72 | D20: =DATA!D9 -> 54.62 | E20: =DATA!E9 -> 63.16 | F20: =DATA!F9 -> 79.72 | G20: =DATA!G9 -> 112.65
B22: PAT | C22: =C18-C20 -> -67.31 | D22: =D18-D20 -> 153.01 | E22: =E18-E20 -> 196.25 | F22: =F18-F20 -> 245.42 | G22: =G18-G20 -> 325.55
B23: Balance Sheet Metrics
B24: Cash | C24: =DATA!C11 -> 14.71 | D24: =DATA!D11 -> 30.92 | E24: =DATA!E11 -> 57 | F24: =DATA!F11 -> 46.64 | G24: =DATA!G11 -> 22.78
B26: Total Debt | C26: =DATA!C12 -> 346.13 | D26: =DATA!D12 -> 122.51 | E26: =DATA!E12 -> 130.07 | F26: =DATA!F12 -> 0 | G26: =DATA!G12 -> 0
B28: Net Debt | C28: =C26-C24 -> 331.42 | D28: =D26-D24 -> 91.59 | E28: =E26-E24 -> 73.07 | F28: =F26-F24 -> -46.64 | G28: =G26-G24 -> -22.78
B30: Trade Receivables | C30: =DATA!C13 -> 107.87 | D30: =DATA!D13 -> 107.06 | E30: =DATA!E13 -> 117.64 | F30: =DATA!F13 -> 143.5 | G30: =DATA!G13 -> 179.67
B32: Trade Payables | C32: =DATA!C14 -> 25.05 | D32: =DATA!D14 -> 23.94 | E32: =DATA!E14 -> 24.69 | F32: =DATA!F14 -> 40.16 | G32: =DATA!G14 -> 66.94
B34: Inventory | C34: =DATA!C15 -> Nil | D34: =DATA!D15 -> Nil | E34: =DATA!E15 -> Nil | F34: =DATA!F15 -> Nil | G34: =DATA!G15 -> Nil
B36: Net Working Capital | C36: =C30-C32 -> 82.82 | D36: =D30-D32 -> 83.12 | E36: =E30-E32 -> 92.95 | F36: =F30-F32 -> 103.34 | G36: =G30-G32 -> 112.73
B37: Cash Flow Statement Metrics
B38: CFO | C38: =DATA!C17 -> 202.38 | D38: =DATA!D17 -> 256.27 | E38: =DATA!E17 -> 232.02 | F38: =DATA!F17 -> 286.34 | G38: =DATA!G17 -> 393.31
B40: Capex | C40: =DATA!C18 -> 30.32 | D40: =DATA!D18 -> 66.76 | E40: =DATA!E18 -> 65.59 | F40: =DATA!F18 -> 79.67 | G40: =DATA!G18 -> 85.66
B42: Free Cash Flow | C42: =C38-C40 -> 172.06 | D42: =D38-D40 -> 189.51 | E42: =E38-E40 -> 166.43 | F42: =F38-F40 -> 206.67 | G42: =G38-G40 -> 307.65
B44: Dividends Paid | C44: =DATA!C20 -> 0 | D44: =DATA!D20 -> 0 | E44: =DATA!E20 -> 0 | F44: =DATA!F20 -> 0 | G44: =DATA!G20 -> 98.52
B45: Key Ratios
B46: Rev Growth % | C46: N/A | D46: =D8/C8-1 -> 0.32412726 | E46: =E8/D8-1 -> 0.11483728 | F46: =F8/E8-1 -> 0.1642329 | G46: =G8/F8-1 -> 0.30175253
B48: EBITDA Margin % | C48: =C10/C8 -> 0.45407915 | D48: =D10/D8 -> 0.47482832 | E48: =E10/E8 -> 0.45009692 | F48: =F10/F8 -> 0.47123318 | G48: =G10/G8 -> 0.47575557
B50: EBIT Margin % | C50: =C14/C8 -> 0.24655037 | D50: =D14/D8 -> 0.41692946 | E50: =E14/E8 -> 0.3877091 | F50: =F14/F8 -> 0.41126993 | G50: =G14/G8 -> 0.41954524
B52: PAT Margin % | C52: =C22/C8 -> -0.14266941 | D52: =D22/D8 -> 0.24492965 | E52: =E22/E8 -> 0.2817862 | F52: =F22/F8 -> 0.3026775 | G52: =G22/G8 -> 0.30843202
B54: Debt / EBITDA | C54: =C26/C10 -> 1.6156934 | D54: =D26/D10 -> 0.4130061 | E54: =E26/E10 -> 0.41493604 | F54: =F26/F10 -> 0 | G54: =G26/G10 -> 0
B56: FCF Conversion % | C56: =C42/C10 -> 0.80315549 | D56: =D42/D10 -> 0.63887672 | E56: =E42/E10 -> 0.530928 | F56: =F42/F10 -> 0.54089351 | G56: =G42/G10 -> 0.61265334
B58: Prepared By - Sharwin Wagh

Sheet OPERATING FORECAST
B1: Kfin | C1: Operating Forecast
B6: Particulars | C6: 2026 | D6: =C6+1 -> 2027 | E6: =D6+1 -> 2028 | F6: =E6+1 -> 2029 | G6: =F6+1 -> 2030
B7: Income Statement Metrics
B8: Revenue | C8: ='HISTORICAL DATA'!$G$8+('HISTORICAL DATA'!$G$8*ASSUMPTIONS!$C$9) -> 1238.1042 | D8: =C$8+(C$8*ASSUMPTIONS!D$9) -> 1452.2995 | E8: =D$8+(D$8*ASSUMPTIONS!E$9) -> 1703.551 | F8: =E$8+(E$8*ASSUMPTIONS!F$9) -> 1998.2698 | G8: =F$8+(F$8*ASSUMPTIONS!G$9) -> 2343.9756
B10: EBITDA | C10: =C$8*ASSUMPTIONS!C$12 -> 575.96439 | D10: =D$8*ASSUMPTIONS!D$12 -> 675.60772 | E10: =E$8*ASSUMPTIONS!E$12 -> 792.4896 | F10: =F$8*ASSUMPTIONS!F$12 -> 929.59236 | G10: =G$8*ASSUMPTIONS!G$12 -> 1090.4142
B12: D & A | C12: =C$8*ASSUMPTIONS!C$15 -> 73.17196 | D12: =D$8*ASSUMPTIONS!D$15 -> 85.830899 | E12: =E$8*ASSUMPTIONS!E$15 -> 100.67987 | F12: =F$8*ASSUMPTIONS!F$15 -> 118.09774 | G12: =G$8*ASSUMPTIONS!G$15 -> 138.52896
B14: EBIT | C14: =C10-C12 -> 502.79243 | D14: =D10-D12 -> 589.77682 | E14: =E10-E12 -> 691.80974 | F14: =F10-F12 -> 811.49461 | G14: =G10-G12 -> 951.88528
B16: Interest Expense | C16: ='DEBT SCHEDULE'!C12 -> 146.84787 | D16: ='DEBT SCHEDULE'!D12 -> 60.2592 | E16: ='DEBT SCHEDULE'!E12 -> 25.015711 | F16: ='DEBT SCHEDULE'!F12 -> 10.553503 | G16: ='DEBT SCHEDULE'!G12 -> 8.4037155
B18: PBT | C18: =C14-C16 -> 355.94456 | D18: =D14-D16 -> 529.51762 | E18: =E14-E16 -> 666.79403 | F18: =F14-F16 -> 800.94111 | G18: =G14-G16 -> 943.48157
B20: Tax | C20: =C18*ASSUMPTIONS!$C$26 -> 88.98614 | D20: =D18*ASSUMPTIONS!$C$26 -> 132.37941 | E20: =E18*ASSUMPTIONS!$C$26 -> 166.69851 | F20: =F18*ASSUMPTIONS!$C$26 -> 200.23528 | G20: =G18*ASSUMPTIONS!$C$26 -> 235.87039
B22: PAT | C22: =C18-C20 -> 266.95842 | D22: =D18-D20 -> 397.13822 | E22: =E18-E20 -> 500.09552 | F22: =F18-F20 -> 600.70583 | G22: =G18-G20 -> 707.61118
B23: Balance Sheet Metrics
B24: Cash | C24: ='HISTORICAL DATA'!$G$24+C38-C40-'DEBT SCHEDULE'!C15 -> 22.78 | D24: =C24+D38-D40-'DEBT SCHEDULE'!D15 -> 22.78 | E24: =D24+E38-E40-'DEBT SCHEDULE'!E15 -> 22.78 | F24: =E24+F38-F40-'DEBT SCHEDULE'!F15 -> 22.78 | G24: =F24+G38-G40-'DEBT SCHEDULE'!G15 -> 22.78
B26: Total Debt | C26: ='DEBT SCHEDULE'!C17 -> 2590.2665 | D26: ='DEBT SCHEDULE'!D17 -> 2274.2391 | E26: ='DEBT SCHEDULE'!E17 -> 1869.2869 | F26: ='DEBT SCHEDULE'!F17 -> 1380.1844 | G26: ='DEBT SCHEDULE'!G17 -> 803.48425
B28: Net Debt | C28: =C26-C24 -> 2567.4865 | D28: =D26-D24 -> 2251.4591 | E28: =E26-E24 -> 1846.5069 | F28: =F26-F24 -> 1357.4044 | G28: =G26-G24 -> 780.70425
B30: Trade Receivables | C30: =C8*(ASSUMPTIONS!$G$33/365) -> 283.07998 | D30: =D8*(ASSUMPTIONS!$G$33/365) -> 332.05355 | E30: =E8*(ASSUMPTIONS!$G$33/365) -> 389.49967 | F30: =F8*(ASSUMPTIONS!$G$33/365) -> 456.88413 | G30: =G8*(ASSUMPTIONS!$G$33/365) -> 535.92626
B32: Trade Payables | C32: =ASSUMPTIONS!$G$34*(('OPERATING FORECAST'!C8-'OPERATING FORECAST'!C10)/365) -> 64.398987 | D32: =ASSUMPTIONS!$G$34*(('OPERATING FORECAST'!D8-'OPERATING FORECAST'!D10)/365) -> 75.540179 | E32: =ASSUMPTIONS!$G$34*(('OPERATING FORECAST'!E8-'OPERATING FORECAST'!E10)/365) -> 88.608825 | F32: =ASSUMPTIONS!$G$34*(('OPERATING FORECAST'!F8-'OPERATING FORECAST'!F10)/365) -> 103.93838 | G32: =ASSUMPTIONS!$G$34*(('OPERATING FORECAST'!G8-'OPERATING FORECAST'!G10)/365) -> 121.91999
B34: Inventory | C34: 0 | D34: 0 | E34: 0 | F34: 0 | G34: 0
B36: Net Working Capital | C36: =C30-C32 -> 218.68099 | D36: =D30-D32 -> 256.51337 | E36: =E30-E32 -> 300.89085 | F36: =F30-F32 -> 352.94574 | G36: =G30-G32 -> 414.00627
B37: Cash Flow Statement Metrics
B38: CFO | C38: =C40+C42 -> 234.17939 | D38: =D40+D42 -> 445.13674 | E38: =E40+E42 -> 556.39791 | F38: =F40+F42 -> 666.74868 | G38: =G40+G42 -> 785.07961
B40: Capex | C40: =C8*ASSUMPTIONS!C18 -> 110.06747 | D40: =D8*ASSUMPTIONS!D18 -> 129.10942 | E40: =E8*ASSUMPTIONS!E18 -> 151.44569 | F40: =F8*ASSUMPTIONS!F18 -> 177.64618 | G40: =G8*ASSUMPTIONS!G18 -> 208.37943
B42: Free Cash Flow | C42: ='DEBT SCHEDULE'!C30 -> 124.11192 | D42: ='DEBT SCHEDULE'!D30 -> 316.02731 | E42: ='DEBT SCHEDULE'!E30 -> 404.95222 | F42: ='DEBT SCHEDULE'!F30 -> 489.1025 | G42: ='DEBT SCHEDULE'!G30 -> 576.70017
B44: Dividends Paid | C44: 0 | D44: 0 | E44: 0 | F44: 0 | G44: 0
B45: Key Ratios
B46: Rev Growth % | C46: =ASSUMPTIONS!C9 -> 0.17300259 | D46: =ASSUMPTIONS!D9 -> 0.17300259 | E46: =ASSUMPTIONS!E9 -> 0.17300259 | F46: =ASSUMPTIONS!F9 -> 0.17300259 | G46: =ASSUMPTIONS!G9 -> 0.17300259
B48: EBITDA Margin % | C48: =ASSUMPTIONS!C12 -> 0.46519863 | D48: =ASSUMPTIONS!D12 -> 0.46519863 | E48: =ASSUMPTIONS!E12 -> 0.46519863 | F48: =ASSUMPTIONS!F12 -> 0.46519863 | G48: =ASSUMPTIONS!G12 -> 0.46519863
B50: EBIT Margin % | C50: =C14/C8 -> 0.40609863 | D50: =D14/D8 -> 0.40609863 | E50: =E14/E8 -> 0.40609863 | F50: =F14/F8 -> 0.40609863 | G50: =G14/G8 -> 0.40609863
B52: PAT Margin % | C52: =C22/C8 -> 0.21561869 | D52: =D22/D8 -> 0.27345477 | E52: =E22/E8 -> 0.29356063 | F52: =F22/F8 -> 0.30061298 | G52: =G22/G8 -> 0.30188504
B54: Debt / EBITDA | C54: =C26/C10 -> 4.4972684 | D54: =D26/D10 -> 3.3662125 | E54: =E26/E10 -> 2.3587526 | F54: =F26/F10 -> 1.4847201 | G54: =G26/G10 -> 0.73686148
B56: FCF Conversion % | C56: =C42/C10 -> 0.21548541 | D56: =D42/D10 -> 0.46776747 | E56: =E42/E10 -> 0.51098742 | F56: =F42/F10 -> 0.52614729 | G56: =G42/G10 -> 0.52888173
B58: Prepared By - Sharwin Wagh

Sheet PURCHASE PRICE & SOURCES, USES
B1: Kfin | C1: Purchase Price Buildup
B6: Particulars | C6: Value | E6: Sources | G6: Amount
B7: Purchase Price Buildup
B8: Share Price | C8: =ASSUMPTIONS!$G$23 -> 847.95 | E8: Senior Debt | G8: =C23*C27 -> 2578.6595
B9: Shares Outstanding | C9: =ASSUMPTIONS!$G$24 -> 17.28 | E9: Mezz Debt | G9: =C24*C27 -> 135.71892
E10: Sponsor Equity | G10: =G12-(G8+G9) -> 12184.778
B11: Market Cap. | C11: =C8*C9 -> 14652.576
B12: Net Debt | C12: ='HISTORICAL DATA'!G28 -> -22.78 | E12: Total Sources | G12: =G19 -> 14899.156
B14: Enterprise Value | C14: =C11+C12 -> 14629.796 | E14: Uses | G14: Amount
B15: Less - Cash Acquired | C15: ='HISTORICAL DATA'!$G$24 -> 22.78
B16: Add - Existing Debt | C16: ='HISTORICAL DATA'!$G$26 -> 0 | E16: Equity Purchase Price | G16: =C17 -> 14607.016
B17: Equity Purchase Price | C17: =C14-C15+C16 -> 14607.016 | E17: Fees | G17: =C18 -> 292.14032
B18: Add - Transaction Fees (%) | C18: =2%*C17 -> 292.14032
E19: Total Uses | G19: =G16+G17 -> 14899.156
B20: Total Purchase Price | C20: =C17+C18 -> 14899.156
B21: Equity Value | C21: =C14-C15+C16 -> 14607.016 | E21: Sources = Uses | G21: =IF(G12=G19,"Fulfilled","Error") -> Fulfilled
B23: Sen. Debt % FCF | C23: 0.95
B24: Mezz Debt % FCF | C24: 0.05 | E24: The Sources and Uses schedule is a critical component of the leveraged buyout model, as it outlines how the acquisition will be financed and where the funds will be deployed. The schedule shows total sources of ₹14,899 crore, which exactly match total uses of ₹14,899 crore, confirming that the transaction is fully funded and financially balanced. This equality between sources and uses is essential in any LBO transaction, as it ensures that all acquisition-related costs are adequately financed without creating a funding gap. The financing structure consists of ₹2,579 crore of senior debt, ₹136 crore of mezzanine debt, and ₹12,185 crore of sponsor equity. Sponsor equity accounts for approximately 81.8% of total funding, while debt contributes the remaining 18.2%. This indicates a relatively conservative leverage profile compared to traditional buyouts, where debt typically forms a larger portion of the capital structure. A higher equity contribution reduces financial risk, lowers interest burden, and provides greater flexibility for management to execute growth initiatives after the acquisition. On the uses side, ₹14,607 crore is allocated toward the equity purchase price of the target company, representing the primary cash outflow of the transaction. The remaining ₹292 crore is reserved for transaction-related expenses, including advisory, legal, financing, and due diligence fees. Overall, the schedule demonstrates a well-structured acquisition financing plan with prudent leverage, strong equity backing, and sufficient funding to cover all transaction requirements.
B25: Sponsor E. % Total Sources | C25: =G10/G12 -> 0.81781664
B27: Total debt to be raised | C27: =ASSUMPTIONS!C55 -> 2714.3784
B29: Sen. Debt Interest | C29: 0.09
B30: Mezz Debt Interest | C30: 0.14
B31: Senior Debt | C31: =C29*G8 -> 232.07935
B32: Mezz Debt | C32: =C30*G9 -> 19.000649
B34: This schedule presents the purchase price buildup and financing assumptions underlying the leveraged buyout transaction. The acquisition is based on a share price of ₹848 and 17 crore shares outstanding, resulting in an implied market capitalization of ₹14,653 crore. After adjusting for net cash of ₹23 crore, the enterprise value is calculated at ₹14,630 crore. The model then derives an equity purchase price of ₹14,607 crore and incorporates transaction fees of ₹292 crore, leading to a total purchase consideration of ₹14,899 crore. To finance the acquisition, the model assumes total debt funding of ₹2,714 crore, comprising 95% senior debt and 5% mezzanine debt. This translates into ₹2,579 crore of senior debt and ₹136 crore of mezzanine debt. The financing structure applies interest rates of 9.0% and 14.0% to senior and mezzanine debt respectively, reflecting their differing risk profiles. Overall, the assumptions indicate disciplined leverage, with sponsor equity remaining the primary source of funding.
B58: Prepared By - Sharwin Wagh

Sheet DEBT SCHEDULE
B1: Kfin | C1: Debt Schedule & Cash Sweep
B6: Debt Schedule
B9: Particulars | C9: 2026 | D9: =C9+1 -> 2027 | E9: =D9+1 -> 2028 | F9: =E9+1 -> 2029 | G9: =F9+1 -> 2030
B11: Opening Debt | C11: ='PURCHASE PRICE & SOURCES, USES'!G8+'PURCHASE PRICE & SOURCES, USES'!G9 -> 2714.3784 | D11: =C$17 -> 2590.2665 | E11: =D$17 -> 2274.2391 | F11: =E$17 -> 1869.2869 | G11: =F$17 -> 1380.1844
B12: Interest Expenses | C12: =C49 -> 146.84787 | D12: =D49 -> 60.2592 | E12: =E49 -> 25.015711 | F12: =F49 -> 10.553503 | G12: =G49 -> 8.4037155
B13: Interest Rate | C13: =C50 -> 0.0541 | D13: =D50 -> 0.023263707 | E13: =E50 -> 0.010999596 | F13: =F50 -> 0.0056457374 | G13: =G50 -> 0.0060888352
B14: FCF Available | C14: =C30 -> 124.11192 | D14: =D30 -> 316.02731 | E14: =E30 -> 404.95222 | F14: =F30 -> 489.1025 | G14: =G30 -> 576.70017
B15: Debt Repayment | C15: =C14*C32 -> 124.11192 | D15: =D14*D32 -> 316.02731 | E15: =E14*E32 -> 404.95222 | F15: =F14*F32 -> 489.1025 | G15: =G14*G32 -> 576.70017
B17: Closing Debt | C17: =C11-C15 -> 2590.2665 | D17: =D11-D15 -> 2274.2391 | E17: =E11-E15 -> 1869.2869 | F17: =F11-F15 -> 1380.1844 | G17: =G11-G15 -> 803.48425
B19: Cash Sweep
B22: Particulars | C22: 2026 | D22: =C22+1 -> 2027 | E22: =D22+1 -> 2028 | F22: =E22+1 -> 2029 | G22: =F22+1 -> 2030
B24: EBITDA | C24: ='OPERATING FORECAST'!C10 -> 575.96439 | D24: ='OPERATING FORECAST'!D10 -> 675.60772 | E24: ='OPERATING FORECAST'!E10 -> 792.4896 | F24: ='OPERATING FORECAST'!F10 -> 929.59236 | G24: ='OPERATING FORECAST'!G10 -> 1090.4142
B25: Less: Taxes | C25: ='OPERATING FORECAST'!C20 -> 88.98614 | D25: ='OPERATING FORECAST'!D20 -> 132.37941 | E25: ='OPERATING FORECAST'!E20 -> 166.69851 | F25: ='OPERATING FORECAST'!F20 -> 200.23528 | G25: ='OPERATING FORECAST'!G20 -> 235.87039
B26: Less: Capex | C26: ='OPERATING FORECAST'!C40 -> 110.06747 | D26: ='OPERATING FORECAST'!D40 -> 129.10942 | E26: ='OPERATING FORECAST'!E40 -> 151.44569 | F26: ='OPERATING FORECAST'!F40 -> 177.64618 | G26: ='OPERATING FORECAST'!G40 -> 208.37943
B27: Less: Increase in NWC | C27: ='OPERATING FORECAST'!C36-'HISTORICAL DATA'!G36 -> 105.95099 | D27: ='OPERATING FORECAST'!D36-'OPERATING FORECAST'!C36 -> 37.832378 | E27: ='OPERATING FORECAST'!E36-'OPERATING FORECAST'!D36 -> 44.377477 | F27: ='OPERATING FORECAST'!F36-'OPERATING FORECAST'!E36 -> 52.054896 | G27: ='OPERATING FORECAST'!G36-'OPERATING FORECAST'!F36 -> 61.060528
B28: Less: Interest | C28: ='OPERATING FORECAST'!C16 -> 146.84787 | D28: ='OPERATING FORECAST'!D16 -> 60.2592 | E28: ='OPERATING FORECAST'!E16 -> 25.015711 | F28: ='OPERATING FORECAST'!F16 -> 10.553503 | G28: ='OPERATING FORECAST'!G16 -> 8.4037155
B30: FCF Available | C30: =C24-C25-C26-C27-C28 -> 124.11192 | D30: =D24-D25-D26-D27-D28 -> 316.02731 | E30: =E24-E25-E26-E27-E28 -> 404.95222 | F30: =F24-F25-F26-F27-F28 -> 489.1025 | G30: =G24-G25-G26-G27-G28 -> 576.70017
B32: Cash Sweep (%) | C32: 1 | D32: 1 | E32: 1 | F32: 1 | G32: 1
B34: Cash Used for Repayment | C34: =C15 -> 124.11192 | D34: =D15 -> 316.02731 | E34: =E15 -> 404.95222 | F34: =F15 -> 489.1025 | G34: =G15 -> 576.70017
B35: Cash Retained | C35: =C30-C34 -> 0 | D35: =D30-D34 -> 0 | E35: =E30-E34 -> 0 | F35: =F30-F34 -> 0 | G35: =G30-G34 -> 0
B37: Cash retained after paying of all debt in 5 years | C37: =C35+D35+E35+F35+G35+'HISTORICAL DATA'!G24 -> 22.78
B40: Interest Payment Plan
B43: Total interest to be paid in next 5 years | C43: ='PURCHASE PRICE & SOURCES, USES'!C31+'PURCHASE PRICE & SOURCES, USES'!C32 -> 251.08
B46: Particulars | C46: 2026 | D46: =C46+1 -> 2027 | E46: =D46+1 -> 2028 | F46: =E46+1 -> 2029 | G46: =F46+1 -> 2030
B48: Interest Remaining | C48: =C43-C49 -> 104.23213 | D48: =C48-D49 -> 43.97293 | E48: =D48-E49 -> 18.957219 | F48: =E48-F49 -> 8.4037155 | G48: =F48-G49 -> 0
B49: Interest Paid | C49: =C43-(C52+C55) -> 146.84787 | D49: =C48-(D52+D55) -> 60.2592 | E49: =D48-(E52+E55) -> 25.015711 | F49: =E48-(F52+F55) -> 10.553503 | G49: =F48-(G52+G55) -> 8.4037155
B50: Interest Rate Paid | C50: =C49/C11 -> 0.0541 | D50: =D49/D11 -> 0.023263707 | E50: =E49/E11 -> 0.010999596 | F50: =F49/F11 -> 0.0056457374 | G50: =G49/G11 -> 0.0060888352
B52: S.D Debt Int. Remaining | C52: ='PURCHASE PRICE & SOURCES, USES'!$C$31-('DEBT SCHEDULE'!C53*'PURCHASE PRICE & SOURCES, USES'!$C$31) -> 92.831741 | D52: =C52-(C52*D53) -> 37.132696 | E52: =D52-(D52*E53) -> 14.853078 | F52: =E52-(E52*F53) -> 5.9412314 | G52: =F52-(F52*G53) -> 0
B53: S.D Debt Interest Paid | C53: 0.6 | D53: 0.6 | E53: 0.6 | F53: 0.6 | G53: 1
B55: M.D Debt Int. Remaining | C55: ='PURCHASE PRICE & SOURCES, USES'!C32-('PURCHASE PRICE & SOURCES, USES'!C32*'DEBT SCHEDULE'!C56) -> 11.400389 | D55: =C55-(C55*D56) -> 6.8402335 | E55: =D55-(D55*E56) -> 4.1041401 | F55: =E55-(E55*F56) -> 2.4624841 | G55: =F55-(F55*G56) -> 0
B56: M.D Debt Interest Paid | C56: 0.4 | D56: 0.4 | E56: 0.4 | F56: 0.4 | G56: 1
B58: Prepared By - Sharwin Wagh

Sheet EXIT, GAIN ANALYSIS & SENSITIVI
B1: Kfin | C1: Exit / Gain Analysis & Sensitivity
B6: Exit Analysis | E6: Returns / Gain Analysis
B9: Item | C9: Value | E9: Item | G9: Value
B10: Exit Analysis
B11: Exit EBITDA | C11: =CHOOSE($C$26,'OPERATING FORECAST'!$C$10,'OPERATING FORECAST'!$D$10,'OPERATING FORECAST'!$E$10,'OPERATING FORECAST'!$F$10,'OPERATING FORECAST'!$G$10) -> 1090.4142 | E11: Entry Equity Investment | G11: ='PURCHASE PRICE & SOURCES, USES'!$G$10 -> 12184.778
B12: Exit EBITDA Multiple | C12: =ASSUMPTIONS!$C$24 -> 29.133734 | E12: Exist Equity Value | G12: =$C$18 -> 30987.135
B13: Enterprise Value | C13: =C11*C12 -> 31767.839 | E13: Money Invested | G13: =G11 -> 12184.778
B14: Total Debt Outstanding | C14: =CHOOSE($C$26,'OPERATING FORECAST'!$C$26,'OPERATING FORECAST'!$D$26,'OPERATING FORECAST'!$E$26,'OPERATING FORECAST'!$F$26,'OPERATING FORECAST'!$G$26) -> 803.48425 | E14: Money Returned | G14: =G12 -> 30987.135
B15: Cash Balance | C15: =CHOOSE($C$26,'OPERATING FORECAST'!$C$24,'OPERATING FORECAST'!$D$24,'OPERATING FORECAST'!$E$24,'OPERATING FORECAST'!$F$24,'OPERATING FORECAST'!$G$24) -> 22.78 | E15: Gain / Profit | G15: =G12-G11 -> 18802.357
B16: Net Debt | C16: =C14-C15 -> 780.70425
E17: IRR | G17: =(C21/G11)^(1/C26)-1 -> 0.20523784
B18: Equity Value | C18: =C13-C16 -> 30987.135
B20: Sponsor Ownership | C20: 1 | E20: MOIC | G20: =C21/G11 -> 2.5431021
B21: Sponsor Equity Proceeds | C21: =C18*C20 -> 30987.135
B23: Sensitivity Analysis
B26: Holding Period | C26: 5
B29: Internal Rate of Return
C30: Number of Holding Period
B31: =$G$17 -> 0.20523784 | C31: 1 | D31: 2 | E31: 3 | F31: 4 | G31: 5
B32: 10 | C32: -0.73802088 | D32: -0.39197676 | E32: -0.20690789 | F32: -0.10157781 | G32: -0.036388258
B33: 15 | C33: -0.50167501 | D33: -0.19568254 | E33: -0.062472315 | F33: 0.0081419252 | G33: 0.050327963
B34: 20 | C34: -0.26532914 | D34: -0.038667128 | E34: 0.047459978 | F34: 0.090548304 | G34: 0.11530677
B35: 25 | C35: -0.028983268 | D35: 0.096081753 | E35: 0.13817518 | F35: 0.15762889 | G35: 0.16793569
B36: 29.13 | C36: 0.16623842 | D36: 0.19598945 | E36: 0.20347445 | F36: 0.20536945 | G36: 0.20520617
B37: 35 | C37: 0.44370847 | D37: 0.32509013 | E37: 0.2856073 | F37: 0.26476198 | G37: 0.25133373
B39: Multiple of Invested Cap.
C40: Number of Holding Period
B41: =$G$20 -> 2.5431021 | C41: 1 | D41: 2 | E41: 3 | F41: 4 | G41: 5
B42: 10 | C42: 0.26197912 | D42: 0.36969226 | E42: 0.49885104 | F42: 0.65151119 | G42: 0.83082665
B43: 15 | C43: 0.49832499 | D43: 0.64692657 | E43: 0.82404761 | F43: 1.0329676 | G43: 1.278276
B44: 20 | C44: 0.73467086 | D44: 0.92416089 | E44: 1.1492442 | F44: 1.414424 | G44: 1.7257254
B45: 25 | C45: 0.97101673 | D45: 1.2013952 | E45: 1.4744408 | F45: 1.7958805 | G45: 2.1731748
B46: 29.13 | C46: 1.1662384 | D46: 1.4303908 | E46: 1.7430531 | F46: 2.1109635 | G46: 2.5427679
B47: 35 | C47: 1.4437085 | D47: 1.7558638 | E47: 2.1248339 | F47: 2.5587933 | G47: 3.0680735
E49: The investment generates progressively stronger returns across all holding periods, with Year 1 delivering modest value creation and Years 2–4 benefiting from continued EBITDA growth and deleveraging. The 5-year exit scenario produces the highest equity value, 2.54x MOIC, 20.52% IRR, and overall sponsor returns, making it the most attractive holding period.
B58: Prepared By - Sharwin Wagh
