Workbook

Sheet DATA SHEET
B1: PROFIT & LOSS
C2: 2014 | D2: =C2+1 -> 2015 | E2: =D2+1 -> 2016 | F2: =E2+1 -> 2017 | G2: =F2+1 -> 2018 | H2: =G2+1 -> 2019 | I2: =H2+1 -> 2020 | J2: =I2+1 -> 2021 | K2: =J2+1 -> 2022 | ... N2: =M2+1 -> 2025
B3: Sales - | C3: 43424 | D3: 46951 | E3: 51244 | F3: 55448 | G3: 54487 | H3: 59019 | I3: 61138 | J3: 61943 | K3: 79093 | L3: 90487 | M3: 89760 | N3: 89088
B4: Sales Growth % | C4: 0.1601 | D4: 0.0812 | E4: 0.0914 | F4: 0.082 | G4: -0.0173 | H4: 0.0832 | I4: 0.0359 | J4: 0.013 | K4: 0.2806 | L4: 0.1409 | M4: -0.008 | N4: -0.0075
B5: Expenses - | C5: 33788 | D5: 36652 | E5: 40448 | F5: 44128 | G5: 44100 | H5: 47406 | I5: 48795 | J5: =SUM(J6:J9) -> 50434 | K5: =SUM(K6:K9) -> 66236 | L5: =SUM(L6:L9) -> 77980 | M5: =SUM(M6:M9) -> 77646 | N5: =SUM(N6:N9) -> 75500
B6: Material Cost % - | C6: 0.07 | D6: 0.07 | E6: 0.06 | F6: 0.05 | G6: 0.03 | H6: 0.02 | I6: 0.02 | J6: 695 | K6: 673 | L6: 649 | M6: 383 | N6: 296
B7: Manufacturing Cost % | C7: 0.13 | D7: 0.12 | E7: 0 | F7: 0 | G7: 0 | H7: 0 | I7: 0 | J7: 8360 | K7: 10858 | L7: 11524 | M7: 10303 | N7: 10014
B8: Employee Cost % | C8: 0.48 | D8: 0.48 | E8: 0.48 | F8: 0.48 | G8: 0.5 | H8: 0.51 | I8: 0.53 | J8: 33237 | K8: 45007 | L8: 53764 | M8: 54930 | N8: 53347
B9: Other Cost % | C9: 0.11 | D9: 0.11 | E9: 0.25 | F9: 0.26 | G9: 0.28 | H9: 0.27 | I9: 0.25 | J9: 8142 | K9: 9698 | L9: 12043 | M9: 12030 | N9: 11843
B10: Operating Profit | C10: 9635 | D10: 10299 | E10: 10796 | F10: 11321 | G10: 10387 | H10: 11613 | I10: 12342 | J10: 14771 | K10: 16684 | L10: 16839 | M10: 16752 | N10: 18021
B11: OPM % | C11: 0.22 | D11: 0.22 | E11: 0.21 | F11: 0.2 | G11: 0.19 | H11: 0.2 | I11: 0.2 | J11: 0.24 | K11: 0.21 | L11: 0.19 | M11: 0.19 | N11: 0.2
B12: Other Income - | C12: 1922 | D12: 2450 | E12: 2752 | F12: 2623 | G12: 2550 | H12: 2614 | I12: 2728 | J12: 2404 | K12: 2067 | L12: 2275 | M12: 2631 | N12: 3909
B13: Exceptional items | C13: 154 | D13: 395 | E13: 265 | F13: 0 | G13: 0 | H13: 0 | I13: 0 | J13: 0 | K13: 0 | L13: 9 | M13: 207 | N13: 61
B14: Other income normal | C14: 1767 | D14: 2055 | E14: 2488 | F14: 2623 | G14: 2550 | H14: 2614 | I14: 2728 | J14: 2404 | K14: 2067 | L14: 2266 | M14: 2424 | N14: 3849
B15: Interest | C15: 383 | D15: 350 | E15: 558 | F15: 594 | G15: 583 | H15: 738 | I15: 733 | J15: 509 | K15: 532 | L15: 1008 | M15: 1255 | N15: 1477
B16: Depreciation | C16: 1060 | D16: 1175 | E16: 1496 | F16: 2310 | G16: 2112 | H16: 1947 | I16: 2086 | J16: 2763 | K16: 3078 | L16: 3340 | M16: 3407 | N16: 2958
B17: Profit before tax | C17: 10114 | D17: 11224 | E17: 11494 | F17: 11039 | G17: 10242 | H17: 11542 | I17: 12252 | J17: 13903 | K17: 15141 | L17: 14766 | M17: 14721 | N17: 17496
... B27: Dividend Payout % | C27: 0.25 | D27: 0.34 | E27: 0.17 | F27: 0.06 | G27: 0.06 | H27: 0.07 | I27: 0.06 | J27: 0.05 | K27: 0.27 | L27: 0.05 | M27: 0.05 | N27: 0.48
B31: BALANCE SHEET
C32: 2014 | D32: =C32+1 -> 2015 | E32: =D32+1 -> 2016 | F32: =E32+1 -> 2017 | G32: =F32+1 -> 2018 | H32: =G32+1 -> 2019 | I32: =H32+1 -> 2020 | J32: =I32+1 -> 2021 | K32: =J32+1 -> 2022 | ... N32: =M32+1 -> 2025
B33: Equity Capital | C33: 493 | D33: 494 | E33: 494 | F33: 486 | G33: 905 | H33: 1207 | I33: 1143 | J33: 1096 | K33: 1096 | L33: 1098 | M33: 1045 | N33: 2094
B34: Reserves | C34: 31636 | D34: 36598 | E34: 45651 | F34: 51184 | G34: 47022 | H34: 55216 | I34: 54179 | J34: 53805 | K34: 64307 | L34: 76570 | M34: 73943 | N34: 80736
B35: Borrowings - | C35: 5159 | D35: 7891 | E35: 12522 | F35: 14241 | G35: 13901 | H35: 9947 | I35: 9724 | J35: 10451 | K35: 17593 | L35: 17467 | M35: 16465 | N35: 19204
B36: Long term Borrowings | C36: 1091 | D36: 1271 | E36: 1736 | F36: 1961 | G36: 4527 | H36: 2837 | I36: 484 | J36: 746 | K36: 5646 | L36: 6127 | M36: 6230 | N36: 6395
B37: Short term Borrowings | C37: 3943 | D37: 6444 | E37: 10265 | F37: 11674 | G37: 7960 | H37: 6808 | I37: 5402 | J37: 6036 | K37: 9523 | L37: 8882 | M37: 7917 | N37: 9786
B38: Lease Liabilities | C38: 0 | D38: 0 | E38: 0 | F38: 0 | G38: 0 | H38: 0 | I38: 1920 | J38: 2118 | K38: 2423 | L38: 2457 | M38: 2318 | N38: 3022
B39: Other Borrowings | C39: 125 | D39: 176 | E39: 521 | F39: 606 | G39: 1415 | H39: 301 | I39: 1918 | J39: 1551 | K39: 0 | L39: 0 | M39: 0 | N39: 0
B40: Other Liabilities - | C40: 12245 | D40: 13367 | E40: 12924 | F40: 12761 | G40: 13563 | H40: 16217 | I40: 15954 | J40: 17213 | K40: 24280 | L40: 21789 | M40: 23611 | N40: 26362
B41: Non Controlling Interest | C41: 139 | D41: 165 | E41: 221 | F41: 239 | G41: 241 | H41: 264 | I41: 188 | J41: 150 | K41: 53 | L41: 60 | M41: 133 | N41: 214
B42: Trade Payables | C42: 5216 | D42: 5849 | E42: 4902 | F42: 4867 | G42: 5120 | H42: 6266 | I42: 5840 | J42: 5417 | K42: 6252 | L42: 5972 | M42: 8857 | N42: 8825
B43: Advance from Customers | C43: 328 | D43: 220 | E43: 238 | F43: 239 | G43: 190 | H43: 136 | I43: 146 | J43: 36 | K43: 63 | L43: 64 | M43: 119 | N43: 79
B44: Other liability items | C44: 6562 | D44: 7134 | E44: 7562 | F44: 7415 | G44: 8012 | H44: 9551 | I44: 9780 | J44: 11610 | K44: 17913 | L44: 15694 | M44: 14501 | N44: 17244
... B66: Total Assets | C66: 49533 | D66: 58350 | E66: 71590 | F66: 78672 | G66: 75391 | H66: 82586 | I66: 81000 | J66: 82566 | K66: 107276 | L66: 116924 | M66: 115064 | N66: 128396
H68: =SUM(J47,J48,J49,J50,J51,J52,J53,J54,J55,J58,J59) -> 56995
B70: CASH FLOW STATEMENT
C71: 2014 | D71: =C71+1 -> 2015 | E71: =D71+1 -> 2016 | F71: =E71+1 -> 2017 | G71: =F71+1 -> 2018 | H71: =G71+1 -> 2019 | I71: =H71+1 -> 2020 | J71: =I71+1 -> 2021 | K71: =J71+1 -> 2022 | ... N71: =M71+1 -> 2025
B72: Cash from Operating Activity - | C72: 6790 | D72: 7840 | E72: 7887 | F72: 9277 | G72: 8423 | H72: 11632 | I72: 10064 | J72: 14755 | K72: 11080 | L72: 13060 | M72: 17622 | N72: 16943
B73: Profit from Operations | C73: 9977 | D73: 10990 | E73: 11180 | F73: 11374 | G73: 11322 | H73: 11430 | I73: 13088 | J73: 14954 | K73: 17297 | L73: 17538 | M73: 17416 | N73: 18533
B74: Receivables | C74: -1566 | D74: -888 | E74: -532 | F74: 335 | G74: -974 | H74: 139 | I74: -333 | J74: 1285 | K74: -4323 | L74: -98 | M74: 782 | N74: 189
B75: Inventory | C75: 97 | D75: -256 | E75: -54 | F75: 148 | G75: 54 | H75: -57 | I75: 208 | J75: 80 | K75: -26 | L75: 16 | M75: 29 | N75: 21
B76: Payables | C76: 0 | D76: 0 | E76: 468 | F76: -523 | G76: 450 | H76: 2084 | I76: -1240 | J76: 570 | K76: 970 | L76: -982 | M76: -44 | N76: 55
B77: Loans Advances | C77: -891 | D77: -363 | E77: 0 | F77: 0 | G77: 0 | H77: 0 | I77: 0 | J77: 0 | K77: 0 | L77: 0 | M77: 0 | N77: 0
B78: Other WC items | C78: 1347 | D78: 783 | E78: -481 | F78: 492 | G78: 381 | H78: 550 | I78: -1021 | J78: 357 | K78: -270 | L78: -391 | M78: 974 | N78: 762
B79: Working Capital Changes | C79: -1013 | D79: -723 | E79: -599 | F79: 451 | G79: -88 | H79: 2716 | I79: -2386 | J79: 2292 | K79: -3649 | L79: -1456 | M79: 1741 | N79: 1027
B80: Direct Taxes | C80: -2173 | D80: -2427 | E80: -2694 | F80: -2548 | G80: -2810 | H80: -2515 | I80: -638 | J80: -2492 | K80: -2569 | L80: -3022 | M80: -1536 | N80: -2618
B81: Cash from Investing Activity - | C81: -284 | D81: -2537 | E81: -13761 | F81: -11770 | G81: 3595 | H81: 5065 | I81: 3593 | J81: 685 | K81: -22321 | L81: -8169 | M81: 1144 | N81: -8044
B82: Fixed assets purchased | C82: -889 | D82: -1285 | E82: -1395 | F82: -2085 | G82: -2187 | H82: -2278 | I82: -2350 | J82: -1958 | K82: -2015 | L82: -1483 | M82: -1051 | N82: -1474
B83: Fixed assets sold | C83: 109 | D83: 143 | E83: 78 | F83: 558 | G83: 117 | H83: 194 | I83: 127 | J83: 75 | K83: 74 | L83: 55 | M83: 402 | N83: 182
... B101: Net Cash Flow | C101: 2936 | D101: 4474 | E101: -6032 | F101: -4767 | G101: -979 | H101: 11760 | I101: -1442 | J101: 2556 | K101: -6583 | L101: -1197 | M101: 509 | N101: 2502
B105: HISTORICAL DATA | C105: WIPRO | E105: NIFTY | G105: TCS | I105: INFOSYS | K105: HCL TECH | M105: LTIMIND TREE | O105: TECH MAHINDRA | Q105: PERSISTENT SYSTEM
B107: Date | C107: Price | D107: % Change | E107: Price | F107: % Change | G107: Price | H107: % Change | I107: Price | J107: % Change | K107: Price | L107: % Change | M107: Price | N107: % Change | O107: Price | P107: % Change | Q107: Price | R107: % Change
B108: 30-03-2025 | C108: 246.3 | D108: =C108/C109-1 -> -0.060819828 | E108: 22904.45 | F108: =E108/E109-1 -> -0.02614443 | G108: 3299.4 | H108: =G108/G109-1 -> -0.085063017 | I108: 1451.65 | J108: =I108/I109-1 -> -0.075764811 | K108: 1422.1 | L108: =K108/K109-1 -> -0.10700157 | M108: 4136.25 | N108: =M108/M109-1 -> -0.079063088 | O108: 1320.95 | P108: =O108/O109-1 -> -0.068605676 | Q108: 4609.95 | R108: =Q108/Q109-1 -> -0.16391748
B109: 23-03-2025 | C109: 262.25 | D109: =C109/C110-1 -> -0.0077563375 | E109: 23519.35 | F109: =E109/E110-1 -> 0.0072354221 | G109: 3606.15 | H109: =G109/G110-1 -> 0.0078393561 | I109: 1570.65 | J109: =I109/I110-1 -> -0.013751531 | K109: 1592.5 | L109: =K109/K110-1 -> 0.016467735 | M109: 4491.35 | N109: =M109/M110-1 -> -0.0063934517 | O109: 1418.25 | P109: =O109/O110-1 -> 0.0063863757 | Q109: 5513.75 | R109: =Q109/Q110-1 -> 0.04515169
B110: 16-03-2025 | C110: 264.3 | D110: =C110/C111-1 -> 0.0011363636 | E110: 23350.4 | F110: =E110/E111-1 -> 0.042558891 | G110: 3578.1 | H110: =G110/G111-1 -> 0.019096851 | I110: 1592.55 | J110: =I110/I111-1 -> 0.0080387379 | K110: 1566.7 | L110: =K110/K111-1 -> 0.020817723 | M110: 4520.25 | N110: =M110/M111-1 -> 0.011909426 | O110: 1409.25 | P110: =O110/O111-1 -> -0.021795717 | Q110: 5275.55 | R110: =Q110/Q111-1 -> 0.029224991
B111: 45903 | C111: 264 | D111: =C111/C112-1 -> -0.073033708 | E111: 22397.2 | F111: =E111/E112-1 -> -0.0068861545 | G111: 3511.05 | H111: =G111/G112-1 -> -0.027733163 | I111: 1579.85 | J111: =I111/I112-1 -> -0.062959668 | K111: 1534.75 | L111: =K111/K112-1 -> -0.014891364 | M111: 4467.05 | N111: =M111/M112-1 -> -0.053981935 | O111: 1440.65 | P111: =O111/O112-1 -> -0.034643348 | Q111: 5125.75 | R111: =Q111/Q112-1 -> -0.028993332
B112: 45691 | C112: 284.8 | D112: =C112/C113-1 -> 0.025751846 | E112: 22552.5 | F112: =E112/E113-1 -> 0.019335855 | G112: 3611.2 | H112: =G112/G113-1 -> 0.036732936 | I112: 1686 | J112: =I112/I113-1 -> -0.001007288 | K112: 1557.95 | L112: =K112/K113-1 -> -0.010856798 | M112: 4721.95 | N112: =M112/M113-1 -> 0.012001843 | O112: 1492.35 | P112: =O112/O113-1 -> 0.0030244984 | Q112: 5278.8 | R112: =Q112/Q113-1 -> -0.0047323667
B113: 23-02-2025 | C113: 277.65 | D113: =C113/C114-1 -> -0.093683695 | E113: 22124.7 | F113: =E113/E114-1 -> -0.029443891 | G113: 3483.25 | H113: =G113/G114-1 -> -0.079965663 | I113: 1687.7 | J113: =I113/I114-1 -> -0.070137741 | K113: 1575.05 | L113: =K113/K114-1 -> -0.073881343 | M113: 4665.95 | N113: =M113/M114-1 -> -0.11938284 | O113: 1487.85 | P113: =O113/O114-1 -> -0.097999394 | Q113: 5303.9 | R113: =Q113/Q114-1 -> -0.071169641
B114: 16-02-2025 | C114: 306.35 | D114: =C114/C115-1 -> -0.005679974 | E114: 22795.9 | F114: =E114/E115-1 -> -0.0058157157 | G114: 3786 | H114: =G114/G115-1 -> -0.037828634 | I114: 1815 | J114: =I114/I115-1 -> -0.022301228 | K114: 1700.7 | L114: =K114/K115-1 -> -0.006165084 | M114: 5298.5 | N114: =M114/M115-1 -> -0.038663909 | O114: 1649.5 | P114: =O114/O115-1 -> -0.0057862697 | Q114: 5710.3 | R114: =Q114/Q115-1 -> 0.026533877
B115: 45902 | C115: 308.1 | D115: =C115/C116-1 -> -0.031132075 | E115: 22929.25 | F115: =E115/E116-1 -> -0.026770006 | G115: 3934.85 | H115: =G115/G116-1 -> -0.023465032 | I115: 1856.4 | J115: =I115/I116-1 -> -0.024820739 | K115: 1711.25 | L115: =K115/K116-1 -> -0.0083446817 | M115: 5511.6 | N115: =M115/M116-1 -> -0.074707048 | O115: 1659.1 | P115: =O115/O116-1 -> -0.019502393 | Q115: 5562.7 | R115: =Q115/Q116-1 -> -0.11055148
B116: 45690 | C116: 318 | D116: =C116/C117-1 -> 0.01955755 | E116: 23559.95 | F116: =E116/E117-1 -> 0.0021928332 | G116: 4029.4 | H116: =G116/G117-1 -> -0.020182862 | I116: 1903.65 | J116: =I116/I117-1 -> 0.01268752 | K116: 1725.65 | L116: =K116/K117-1 -> 0.00011591179 | M116: 5956.6 | N116: =M116/M117-1 -> 0.0071777009 | O116: 1692.1 | P116: =O116/O117-1 -> 0.010540775 | Q116: 6254.1 | R116: =Q116/Q117-1 -> 0.03671717
B117: 26-01-2025 | C117: 311.9 | D117: =C117/C118-1 -> -0.025616995 | E117: 23508.4 | F117: =E117/E118-1 -> 0.018023402 | G117: 4112.4 | H117: =G117/G118-1 -> -0.009621058 | I117: 1879.8 | J117: =I117/I118-1 -> 0.0023194433 | K117: 1725.45 | L117: =K117/K118-1 -> -0.037593775 | M117: 5914.15 | N117: =M117/M118-1 -> -0.014004318 | O117: 1674.45 | P117: =O117/O118-1 -> -0.028205798 | Q117: 6032.6 | R117: =Q117/Q118-1 -> -0.051574918
B118: 19-01-2025 | C118: 320.1 | D118: =C118/C119-1 -> 0.13530768 | E118: 23092.2 | F118: =E118/E119-1 -> -0.0047838229 | G118: 4152.35 | H118: =G118/G119-1 -> 0.0068011541 | I118: 1875.45 | J118: =I118/I119-1 -> 0.033049657 | K118: 1792.85 | L118: =K118/K119-1 -> 0.0022080608 | M118: 5998.15 | N118: =M118/M119-1 -> 0.018309764 | O118: 1723.05 | P118: =O118/O119-1 -> 0.037794375 | Q118: 6360.65 | R118: =Q118/Q119-1 -> 0.06700832
B119: 45992 | C119: 281.95 | D119: =C119/C120-1 -> -0.061886541 | E119: 23203.2 | F119: =E119/E120-1 -> -0.0097432943 | G119: 4124.3 | H119: =G119/G120-1 -> -0.017724449 | I119: 1815.45 | J119: =I119/I120-1 -> -0.077022802 | K119: 1788.9 | L119: =K119/K120-1 -> -0.10034097 | M119: 5890.3 | N119: =M119/M120-1 -> -0.038224153 | O119: 1660.3 | P119: =O119/O120-1 -> -0.026559568 | Q119: 5961.2 | R119: =Q119/Q120-1 -> -0.056719913
B120: 45778 | C120: 300.55 | D120: =C120/C121-1 -> 0.02071659 | E120: 23431.5 | F120: =E120/E121-1 -> -0.02388069 | G120: 4198.72 | H120: =G120/G121-1 -> 0.040427994 | I120: 1966.95 | J120: =I120/I121-1 -> 0.014545455 | K120: 1988.42 | L120: =K120/K121-1 -> 0.024890085 | M120: 6124.4 | N120: =M120/M121-1 -> 0.068196881 | O120: 1705.6 | P120: =O120/O121-1 -> 0.009559324 | Q120: 6319.65 | R120: =Q120/Q121-1 -> -0.01347185
B121: 29-12-2024 | C121: 294.45 | D121: =C121/C122-1 -> -0.047395665 | E121: 24004.75 | F121: =E121/E122-1 -> 0.0080353918 | G121: 4035.57 | H121: =G121/G122-1 -> -0.015594585 | I121: 1938.75 | J121: =I121/I122-1 -> 0.011477762 | K121: 1940.13 | L121: =K121/K122-1 -> 0.028880981 | M121: 5733.4 | N121: =M121/M122-1 -> 0.0097569567 | O121: 1689.45 | P121: =O121/O122-1 -> -0.012969941 | Q121: 6405.95 | R121: =Q121/Q122-1 -> 0.0019316191
B122: 22-12-2024 | C122: 309.1 | D122: =C122/C123-1 -> 0.012778506 | E122: 23813.4 | F122: =E122/E123-1 -> 0.0095771065 | G122: 4099.5 | H122: =G122/G123-1 -> -0.0013057693 | I122: 1916.75 | J122: =I122/I123-1 -> -0.0028093541 | K122: 1885.67 | L122: =K122/K123-1 -> -0.010121001 | M122: 5678 | N122: =M122/M123-1 -> -0.025118898 | O122: 1711.65 | P122: =O122/O123-1 -> 0.015183417 | Q122: 6393.6 | R122: =Q122/Q123-1 -> 0.0039097461
B123: 15-12-2024 | C123: 305.2 | D123: =C123/C124-1 -> -0.015325052 | E123: 23587.5 | F123: =E123/E124-1 -> -0.047673841 | G123: 4104.86 | H123: =G123/G124-1 -> -0.067861117 | I123: 1922.15 | J123: =I123/I124-1 -> -0.038780817 | K123: 1904.95 | L123: =K123/K124-1 -> -0.029181382 | M123: 5824.3 | N123: =M123/M124-1 -> -0.13257229 | O123: 1686.05 | P123: =O123/O124-1 -> -0.061428412 | Q123: 6368.7 | R123: =Q123/Q124-1 -> -0.016819371
B124: 45516 | C124: 309.95 | D124: =C124/C125-1 -> 0.042374306 | E124: 24768.3 | F124: =E124/E125-1 -> 0.0036672637 | G124: 4403.7 | H124: =G124/G125-1 -> 0.0063874764 | I124: 1999.7 | J124: =I124/I125-1 -> 0.040210154 | K124: 1962.21 | L124: =K124/K125-1 -> 0.023979001 | M124: 6714.45 | N124: =M124/M125-1 -> 0.052603113 | O124: 1796.4 | P124: =O124/O125-1 -> 0.0076284496 | Q124: 6477.65 | R124: =Q124/Q125-1 -> 0.049139572
B125: 45303 | C125: 297.35 | D125: =C125/C126-1 -> 0.029177627 | E125: 24677.8 | F125: =E125/E126-1 -> 0.022655411 | G125: 4375.75 | H125: =G125/G126-1 -> 0.040893564 | I125: 1922.4 | J125: =I125/I126-1 -> 0.034744463 | K125: 1916.26 | L125: =K125/K126-1 -> 0.04039395 | M125: 6378.9 | N125: =M125/M126-1 -> 0.033455382 | O125: 1782.8 | P125: =O125/O126-1 -> 0.041172692 | Q125: 6174.25 | R125: =Q125/Q126-1 -> 0.045481869
B126: 24-11-2024 | C126: 288.92 | D126: =C126/C127-1 -> 0.010810622 | E126: 24131.1 | F126: =E126/E127-1 -> 0.0093632685 | G126: 4203.84 | H126: =G126/G127-1 -> 0.0061847774 | I126: 1857.85 | J126: =I126/I127-1 -> -0.023340781 | K126: 1841.86 | L126: =K126/K127-1 -> -0.026521638 | M126: 6172.4 | N126: =M126/M127-1 -> 0.0063094054 | O126: 1712.3 | P126: =O126/O127-1 -> -0.020115025 | Q126: 5905.65 | R126: =Q126/Q127-1 -> 0.018874272
B127: 17-11-2024 | C127: 285.83 | D127: =C127/C128-1 -> 0.0087524263 | E127: 23907.25 | F127: =E127/E128-1 -> 0.015916151 | G127: 4178 | H127: =G127/G128-1 -> 0.023806315 | I127: 1902.25 | J127: =I127/I128-1 -> 0.020219356 | K127: 1892.04 | L127: =K127/K128-1 -> 0.021217339 | M127: 6133.7 | N127: =M127/M128-1 -> 0.023195683 | O127: 1747.45 | P127: =O127/O128-1 -> 0.035525926 | Q127: 5796.25 | R127: =Q127/Q128-1 -> 0.014429977
B128: 45576 | C128: 283.35 | D128: =C128/C129-1 -> -0.0040421793 | E128: 23532.7 | F128: =E128/E129-1 -> -0.025488442 | G128: 4080.85 | H128: =G128/G129-1 -> -0.00026458073 | I128: 1864.55 | J128: =I128/I129-1 -> 0.01890762 | K128: 1852.73 | L128: =K128/K129-1 -> 0.011674448 | M128: 5994.65 | N128: =M128/M129-1 -> 0.011422401 | O128: 1687.5 | P128: =O128/O129-1 -> 0.003657775 | Q128: 5713.8 | R128: =Q128/Q129-1 -> 0.0079559687
B129: 45362 | C129: 284.5 | D129: =C129/C130-1 -> 0.032031052 | E129: 24148.2 | F129: =E129/E130-1 -> -0.0064247758 | G129: 4081.93 | H129: =G129/G130-1 -> 0.04086259 | I129: 1829.95 | J129: =I129/I130-1 -> 0.039242411 | K129: 1831.35 | L129: =K129/K130-1 -> 0.045577555 | M129: 5926.95 | N129: =M129/M130-1 -> 0.034082979 | O129: 1681.35 | P129: =O129/O130-1 -> 0.048451969 | Q129: 5668.7 | R129: =Q129/Q130-1 -> 0.051902023
B130: 27-10-2024 | C130: 275.67 | D130: =C130/C131-1 -> 0.014499687 | E130: 24304.35 | F130: =E130/E131-1 -> 0.0051094257 | G130: 3921.68 | H130: =G130/G131-1 -> -0.018077659 | I130: 1760.85 | J130: =I130/I131-1 -> -0.054348702 | K130: 1751.52 | L130: =K130/K131-1 -> -0.051258023 | M130: 5731.6 | N130: =M130/M131-1 -> -0.02906898 | O130: 1603.65 | P130: =O130/O131-1 -> -0.065717032 | Q130: 5389 | R130: =Q130/Q131-1 -> -0.049709923
B131: 20-10-2024 | C131: 271.73 | D131: =C131/C132-1 -> -0.0094776364 | E131: 24180.8 | F131: =E131/E132-1 -> -0.027088141 | G131: 3993.88 | H131: =G131/G132-1 -> -0.015885766 | I131: 1862.05 | J131: =I131/I132-1 -> -0.009337093 | K131: 1846.15 | L131: =K131/K132-1 -> -0.0028787781 | M131: 5903.2 | N131: =M131/M132-1 -> -0.014770432 | O131: 1716.45 | P131: =O131/O132-1 -> 0.016914509 | Q131: 5670.9 | R131: =Q131/Q132-1 -> 0.029921088
B132: 13-10-2024 | C132: 274.33 | D132: =C132/C133-1 -> 0.038538709 | E132: 24854.05 | F132: =E132/E133-1 -> -0.0044143125 | G132: 4058.35 | H132: =G132/G133-1 -> -0.0063025056 | I132: 1879.6 | J132: =I132/I133-1 -> -0.028680688 | K132: 1851.48 | L132: =K132/K133-1 -> 0.0098118888 | M132: 5991.7 | N132: =M132/M133-1 -> -0.065395924 | O132: 1687.9 | P132: =O132/O133-1 -> 0.024801919 | Q132: 5506.15 | R132: =Q132/Q133-1 -> 0.0066915925
B133: 45453 | C133: 264.15 | D133: =C133/C134-1 -> -0.0098211943 | E133: 24964.25 | F133: =E133/E134-1 -> -0.0020128245 | G133: 4084.09 | H133: =G133/G134-1 -> -0.024235879 | I133: 1935.1 | J133: =I133/I134-1 -> 0.0088366395 | K133: 1833.49 | L133: =K133/K134-1 -> 0.035489792 | M133: 6410.95 | N133: =M133/M134-1 -> 0.048551708 | O133: 1647.05 | P133: =O133/O134-1 -> 0.018930372 | Q133: 5469.55 | R133: =Q133/Q134-1 -> 0.06384572
B134: 29-09-2024 | C134: 266.77 | D134: =C134/C135-1 -> -0.015245478 | E134: 25014.6 | F134: =E134/E135-1 -> -0.044476574 | G134: 4185.53 | H134: =G134/G135-1 -> -0.013100406 | I134: 1918.15 | J134: =I134/I135-1 -> 0.0059787597 | K134: 1770.65 | L134: =K134/K135-1 -> -0.017582698 | M134: 6114.1 | N134: =M134/M135-1 -> -0.0035853392 | O134: 1616.45 | P134: =O134/O135-1 -> 0.0044741339 | Q134: 5141.3 | R134: =Q134/Q135-1 -> -0.05438661
B135: 22-09-2024 | C135: 270.9 | D135: =C135/C136-1 -> 0.0050083472 | E135: 26178.95 | F135: =E135/E136-1 -> 0.015044037 | G135: 4241.09 | H135: =G135/G136-1 -> 0.0055528289 | I135: 1906.75 | J135: =I135/I136-1 -> 0.0005247278 | K135: 1802.34 | L135: =K135/K136-1 -> 0.027466138 | M135: 6136.1 | N135: =M135/M136-1 -> -0.037187554 | O135: 1609.25 | P135: =O135/O136-1 -> -0.0078912487 | Q135: 5437 | R135: =Q135/Q136-1 -> 0.015303312
B136: 15-09-2024 | C136: 269.55 | D136: =C136/C137-1 -> -0.020886306 | E136: 25790.95 | F136: =E136/E137-1 -> 0.017133674 | G136: 4217.67 | H136: =G136/G137-1 -> -0.052558158 | I136: 1905.75 | J136: =I136/I137-1 -> -0.019726352 | K136: 1754.16 | L136: =K136/K137-1 -> -0.029096766 | M136: 6373.1 | N136: =M136/M137-1 -> -0.0067173717 | O136: 1622.05 | P136: =O136/O137-1 -> -0.020530781 | Q136: 5355.05 | R136: =Q136/Q137-1 -> -0.00090486763
B137: 45513 | C137: 275.3 | D137: =C137/C138-1 -> 0.057625816 | E137: 25356.5 | F137: =E137/E138-1 -> 0.020294019 | G137: 4451.64 | H137: =G137/G138-1 -> 0.014776079 | I137: 1944.1 | J137: =I137/I138-1 -> 0.022215212 | K137: 1806.73 | L137: =K137/K138-1 -> 0.03228737 | M137: 6416.2 | N137: =M137/M138-1 -> 0.040678626 | O137: 1656.05 | P137: =O137/O138-1 -> 0.020206376 | Q137: 5359.9 | R137: =Q137/Q138-1 -> 0.03274598
B138: 45300 | C138: 260.3 | D138: =C138/C139-1 -> -0.033060921 | E138: 24852.15 | F138: =E138/E139-1 -> -0.015206511 | G138: 4386.82 | H138: =G138/G139-1 -> -0.021301564 | I138: 1901.85 | J138: =I138/I139-1 -> -0.0215311 | K138: 1750.22 | L138: =K138/K139-1 -> 0.0016252904 | M138: 6165.4 | N138: =M138/M139-1 -> 0.0015188311 | O138: 1623.25 | P138: =O138/O139-1 -> -0.0080965475 | Q138: 5189.95 | R138: =Q138/Q139-1 -> 0.0036937834
B139: 25-08-2024 | C139: 269.2 | D139: =C139/C140-1 -> 0.050741608 | E139: 25235.9 | F139: =E139/E140-1 -> 0.016627624 | G139: 4482.3 | H139: =G139/G140-1 -> 0.020128088 | I139: 1943.7 | J139: =I139/I140-1 -> 0.043821492 | K139: 1747.38 | L139: =K139/K140-1 -> 0.055251255 | M139: 6156.05 | N139: =M139/M140-1 -> 0.09118867 | O139: 1636.5 | P139: =O139/O140-1 -> 0.023836336 | Q139: 5170.85 | R139: =Q139/Q140-1 -> 0.05905786
B140: 18-08-2024 | C140: 256.2 | D140: =C140/C141-1 -> -0.0074768527 | E140: 24823.15 | F140: =E140/E141-1 -> 0.011490904 | G140: 4393.86 | H140: =G140/G141-1 -> 0.010835657 | I140: 1862.1 | J140: =I140/I141-1 -> 0.001694505 | K140: 1655.89 | L140: =K140/K141-1 -> -0.0040777785 | M140: 5641.6 | N140: =M140/M141-1 -> 0.013992361 | O140: 1598.4 | P140: =O140/O141-1 -> 0.0082634202 | Q140: 4882.5 | R140: =Q140/Q141-1 -> 0.00521911
B141: 45604 | C141: 258.13 | D141: =C141/C142-1 -> 0.050803989 | E141: 24541.15 | F141: =E141/E142-1 -> 0.0071262953 | G141: 4346.76 | H141: =G141/G142-1 -> 0.044291755 | I141: 1858.95 | J141: =I141/I142-1 -> 0.049809403 | K141: 1662.67 | L141: =K141/K142-1 -> 0.049248089 | M141: 5563.75 | N141: =M141/M142-1 -> 0.035395595 | O141: 1585.3 | P141: =O141/O142-1 -> 0.052166987 | Q141: 4857.15 | R141: =Q141/Q142-1 -> 0.033645098
B142: 45390 | C142: 245.65 | D142: =C142/C143-1 -> -0.021587605 | E142: 24367.5 | F142: =E142/E143-1 -> -0.014167985 | G142: 4162.4 | H142: =G142/G143-1 -> -0.012678345 | I142: 1770.75 | J142: =I142/I143-1 -> -0.027701515 | K142: 1584.63 | L142: =K142/K143-1 -> -0.012020625 | M142: 5373.55 | N142: =M142/M143-1 -> -0.024746366 | O142: 1506.7 | P142: =O142/O143-1 -> -0.00066326192 | Q142: 4699.05 | R142: =Q142/Q143-1 -> 0.013523569
B143: 28-07-2024 | C143: 251.07 | D143: =C143/C144-1 -> -0.043178354 | E143: 24717.7 | F143: =E143/E144-1 -> -0.0047171616 | G143: 4215.85 | H143: =G143/G144-1 -> -0.023882843 | I143: 1821.2 | J143: =I143/I144-1 -> -0.030709458 | K143: 1603.91 | L143: =K143/K144-1 -> -0.015933688 | M143: 5509.9 | N143: =M143/M144-1 -> -0.048121691 | O143: 1507.7 | P143: =O143/O144-1 -> -0.021704571 | Q143: 4636.35 | R143: =Q143/Q144-1 -> -0.028619617
B144: 21-07-2024 | C144: 262.4 | D144: =C144/C145-1 -> -0.058147882 | E144: 24834.85 | F144: =E144/E145-1 -> 0.012390495 | G144: 4319 | H144: =G144/G145-1 -> 0.019861201 | I144: 1878.9 | J144: =I144/I145-1 -> 0.047937756 | K144: 1629.88 | L144: =K144/K145-1 -> 0.025591332 | M144: 5788.45 | N144: =M144/M145-1 -> 0.0044596764 | O144: 1541.15 | P144: =O144/O145-1 -> 0.033357919 | Q144: 4772.95 | R144: =Q144/Q145-1 -> 0.041344402
B145: 14-07-2024 | C145: 278.6 | D145: =C145/C146-1 -> -0.0052842045 | E145: 24530.9 | F145: =E145/E146-1 -> 0.0011733664 | G145: 4234.89 | H145: =G145/G146-1 -> 0.028310225 | I145: 1792.95 | J145: =I145/I146-1 -> 0.047436834 | K145: 1589.21 | L145: =K145/K146-1 -> 0.022013145 | M145: 5762.75 | N145: =M145/M146-1 -> 0.034113034 | O145: 1491.4 | P145: =O145/O146-1 -> -0.0090694661 | Q145: 4583.45 | R145: =Q145/Q146-1 -> -0.046802537
B146: 45480 | C146: 280.08 | D146: =C146/C147-1 -> 0.046832368 | E146: 24502.15 | F146: =E146/E147-1 -> 0.0073302541 | G146: 4118.3 | H146: =G146/G147-1 -> 0.042911227 | I146: 1711.75 | J146: =I146/I147-1 -> 0.039030016 | K146: 1554.98 | L146: =K146/K147-1 -> 0.026857116 | M146: 5572.65 | N146: =M146/M147-1 -> 0.027841821 | O146: 1505.05 | P146: =O146/O147-1 -> 0.029903856 | Q146: 4808.5 | R146: =Q146/Q147-1 -> 0.0078071784
B147: 30-06-2024 | C147: 267.55 | D147: =C147/C148-1 -> 0.039352032 | E147: 24323.85 | F147: =E147/E148-1 -> 0.013046321 | G147: 3948.85 | H147: =G147/G148-1 -> 0.027572998 | I147: 1647.45 | J147: =I147/I148-1 -> 0.051507899 | K147: 1514.31 | L147: =K147/K148-1 -> 0.040970365 | M147: 5421.7 | N147: =M147/M148-1 -> 0.0068058792 | O147: 1461.35 | P147: =O147/O148-1 -> 0.021673017 | Q147: 4771.25 | R147: =Q147/Q148-1 -> 0.12491011
B148: 23-06-2024 | C148: 257.42 | D148: =C148/C149-1 -> 0.049537245 | E148: 24010.6 | F148: =E148/E149-1 -> 0.021679836 | G148: 3842.89 | H148: =G148/G149-1 -> 0.024508393 | I148: 1566.75 | J148: =I148/I149-1 -> 0.022215698 | K148: 1454.71 | L148: =K148/K149-1 -> 0.0081150381 | M148: 5385.05 | N148: =M148/M149-1 -> 0.050649211 | O148: 1430.35 | P148: =O148/O149-1 -> 0.021824546 | Q148: 4241.45 | R148: =Q148/Q149-1 -> 0.075295669
B149: 16-06-2024 | C149: 245.27 | D149: =C149/C150-1 -> 0.027308901 | E149: 23501.1 | F149: =E149/E150-1 -> 0.0015128529 | G149: 3750.96 | H149: =G149/G150-1 -> -0.0055568517 | I149: 1532.7 | J149: =I149/I150-1 -> 0.029417691 | K149: 1443 | L149: =K149/K150-1 -> 0.01173699 | M149: 5125.45 | N149: =M149/M150-1 -> 0.018459827 | O149: 1399.8 | P149: =O149/O150-1 -> 0.020671552 | Q149: 3944.45 | R149: =Q149/Q150-1 -> 0.045496713
B150: 45541 | C150: 238.75 | D150: =C150/C151-1 -> -0.014529244 | E150: 23465.6 | F150: =E150/E151-1 -> 0.0075332276 | G150: 3771.92 | H150: =G150/G151-1 -> -0.015896787 | I150: 1488.9 | J150: =I150/I151-1 -> -0.029147105 | K150: 1426.26 | L150: =K150/K151-1 -> -0.00031541098 | M150: 5032.55 | N150: =M150/M151-1 -> 0.01112071 | O150: 1371.45 | P150: =O150/O151-1 -> -0.0044642857 | Q150: 3772.8 | R150: =Q150/Q151-1 -> -0.020115577
B151: 45328 | C151: 242.27 | D151: =C151/C152-1 -> 0.1057508 | E151: 23290.15 | F151: =E151/E152-1 -> 0.033707342 | G151: 3832.85 | H151: =G151/G152-1 -> 0.060746952 | I151: 1533.6 | J151: =I151/I152-1 -> 0.090056152 | K151: 1426.71 | L151: =K151/K152-1 -> 0.081111187 | M151: 4977.2 | N151: =M151/M152-1 -> 0.058550799 | O151: 1377.6 | P151: =O151/O152-1 -> 0.12141316 | Q151: 3850.25 | R151: =Q151/Q152-1 -> 0.12894004
B152: 26-05-2024 | C152: 219.1 | D152: =C152/C153-1 -> -0.054870158 | E152: 22530.7 | F152: =E152/E153-1 -> -0.018573775 | G152: 3613.35 | H152: =G152/G153-1 -> -0.046383046 | I152: 1406.9 | J152: =I152/I153-1 -> -0.034312817 | K152: 1319.67 | L152: =K152/K153-1 -> -0.015685836 | M152: 4701.9 | N152: =M152/M153-1 -> -0.028482876 | O152: 1228.45 | P152: =O152/O153-1 -> -0.070588235 | Q152: 3410.5 | R152: =Q152/Q153-1 -> -0.040700945
B153: 19-05-2024 | C153: 231.82 | D153: =C153/C154-1 -> 0.0057266811 | E153: 22957.1 | F153: =E153/E154-1 -> 0.021855151 | G153: 3789.1 | H153: =G153/G154-1 -> 0.004017022 | I153: 1456.89 | J153: =I153/I154-1 -> 0.014399009 | K153: 1340.7 | L153: =K153/K154-1 -> 0.0090010085 | M153: 4839.75 | N153: =M153/M154-1 -> 0.015836534 | O153: 1321.75 | P153: =O153/O154-1 -> 0.012524897 | Q153: 3555.2 | R153: =Q153/Q154-1 -> 0.0042512323
B154: 45631 | C154: 230.5 | D154: =C154/C155-1 -> 0.020227504 | E154: 22466.1 | F154: =E154/E155-1 -> 0.018630527 | G154: 3773.94 | H154: =G154/G155-1 -> -0.015356919 | I154: 1436.21 | J154: =I154/I155-1 -> 0.013614036 | K154: 1328.74 | L154: =K154/K155-1 -> 0.012921276 | M154: 4764.3 | N154: =M154/M155-1 -> 0.033997808 | O154: 1305.4 | P154: =O154/O155-1 -> 0.032426447 | Q154: 3540.15 | R154: =Q154/Q155-1 -> 0.051269488
B155: 45417 | C155: 225.93 | D155: =C155/C156-1 -> -0.012025538 | E155: 22055.2 | F155: =E155/E156-1 -> -0.018715644 | G155: 3832.8 | H155: =G155/G156-1 -> 0.013140052 | I155: 1416.92 | J155: =I155/I156-1 -> 0.0060779914 | K155: 1311.79 | L155: =K155/K156-1 -> -0.0236316 | M155: 4607.65 | N155: =M155/M156-1 -> -0.0095228883 | O155: 1264.4 | P155: =O155/O156-1 -> 0.011155984 | Q155: 3367.5 | R155: =Q155/Q156-1 -> 0.00019305879
B156: 28-04-2024 | C156: 228.68 | D156: =C156/C157-1 -> -0.015583297 | E156: 22475.85 | F156: =E156/E157-1 -> 0.0024933151 | G156: 3783.09 | H156: =G156/G157-1 -> 0.0057691439 | I156: 1408.36 | J156: =I156/I157-1 -> -0.0097522904 | K156: 1343.54 | L156: =K156/K157-1 -> -0.085355227 | M156: 4651.95 | N156: =M156/M157-1 -> -0.028424933 | O156: 1250.45 | P156: =O156/O157-1 -> -0.022130987 | Q156: 3366.85 | R156: =Q156/Q157-1 -> -0.0090067551
...

Sheet STATEMENTS
B3: BALANCE SHEET
B5: Item | C5: FY21 | D5: FY22 | E5: FY23 | F5: FY24 | G5: FY25
B6: ASSETS
B7: Property, Plant & Equipment | C7: 6575 | D7: 7461 | E7: 8234 | F7: 7413 | G7: 7847
B8: Right-of-use Assets | C8: 1642 | D8: 1887 | E8: 1870 | F8: 1796 | G8: 2560
B9: Capital Work-in-progress | C9: 1853 | D9: 1602 | E9: 617 | F9: 723 | G9: 196
B10: Goodwill | C10: 13515 | D10: 24286 | E10: 30349 | F10: 31145 | G10: 32035
B11: Other Intangible Assets | C11: 1309 | D11: 4356 | E11: 4305 | F11: 3275 | G11: 2745
B12: Investments (Non-current) | C12: 1058 | D12: 1911 | E12: 2072 | F12: 2163 | G12: 2646
B13: Trade Receivables (Non-current) | C13: 436 | D13: 476 | E13: 86 | F13: 405 | G13: 30
B14: Other Financial Assets (Non-current) | C14: 609 | D14: 608 | E14: 633 | F14: 555 | G14: 466
B15: Deferred Tax Assets | C15: 166 | D15: 230 | E15: 210 | F15: 182 | G15: 256
B16: Non-current Tax Assets | C16: 1432 | D16: 1026 | E16: 1192 | F16: 904 | G16: 723
B17: Other Non-current Assets | C17: 1671 | D17: 1510 | E17: 1376 | F17: 1058 | G17: 771
B18: Total Non-current Assets | C18: 30414 | D18: 45430 | E18: 51024 | F18: 49724 | G18: 50408
... B29: Total Current Assets | C29: 52319 | D29: 62075 | E29: 66109 | F29: 65063 | G29: 77777
B30: TOTAL ASSETS | C30: 82732 | D30: 1,07,505 | E30: 1,17,133 | F30: 1,14,791 | G30: 1,28,185
B31: EQUITY & LIABILITIES
B32: Share Capital | C32: 1096 | D32: 1096 | E32: 1098 | F32: 1045 | G32: 2094
B33: Other Equity | C33: 53805 | D33: 64307 | E33: 76570 | F33: 73488 | G33: 80270
B34: Equity Attributable | C34: 54901 | D34: 65403 | E34: 77667 | F34: 74533 | G34: 82364
B35: Non-controlling Interest | C35: 150 | D35: 52 | E35: 59 | F35: 134 | G35: 214
B36: TOTAL EQUITY | C36: 55051 | D36: 65455 | E36: 77726 | F36: 74667 | G36: 82578
B37: Borrowings (Non-current) | C37: 746 | D37: 5646 | E37: 6127 | F37: 6230 | G37: 6395
B38: Lease Liabilities (Non-current) | C38: 1351 | D38: 1518 | E38: 1595 | F38: 1396 | G38: 2219
B39: Other Financial Liabilities | C39: 229 | D39: 296 | E39: 265 | F39: 499 | G39: 779
B40: Provisions (Non-current) | C40: 306 | D40: 272 | E40: 295 | F40: 422 | G40: 466
B41: Deferred Tax Liabilities | C41: 461 | D41: 1214 | E41: 1515 | F41: 1747 | G41: 1644
B42: Tax Liabilities (Non-current) | C42: 1107 | D42: 1782 | E42: 2178 | F42: 3709 | G42: 4202
B43: Other Non-current Liabilities | C43: 478 | D43: 485 | E43: 639 | F43: 875 | G43: 1276
... B55: TOTAL LIABILITIES | C55: 27681 | D55: 42050 | E55: 39406 | F55: 40124 | G55: 45607
B56: TOTAL EQUITY + LIABILITIES | C56: 82732 | D56: 1,07,505 | E56: 1,17,133 | F56: 1,14,791 | G56: 1,28,185
B59: PROFIT AND LOSS
B61: Item | C61: FY21 | D61: FY22 | E61: FY23 | F61: FY24 | G61: FY25
B62: INCOME
B63: Revenue from operations | C63: 62243 | D63: 79529 | E63: 90935 | F63: 89794 | G63: 89088
B64: Other income | C64: 2382 | D64: 2061 | E64: 2266 | F64: 2631 | G64: 3884
B65: Total income | C65: =SUM(C63:C64) -> 64625 | D65: =SUM(D63:D64) -> 81590 | E65: =SUM(E63:E64) -> 93201 | F65: =SUM(F63:F64) -> 92425 | G65: =SUM(G63:G64) -> 92972
B66: EXPENSES
B67: Purchases of stock-in-trade | C67: 695 | D67: 674 | E67: 649 | F67: 383 | G67: 297
B68: Change in inventories | C68: 32 | D68: -37 | E68: 15 | F68: 28 | G68: 20
B69: Employee benefits | C69: 33237 | D69: 45007 | E69: 53764 | F69: 54930 | G69: 53348 | I69: Employee Cost | K69: =Table2[[#This Row],[FY25]]+C72 -> 61709 | L69: =Table2[[#This Row],[FY25]]+D72 -> 64207 | M69: =Table2[[#This Row],[FY25]]+E72 -> 64873 | N69: =Table2[[#This Row],[FY25]]+F72 -> 63651 | O69: =Table2[[#This Row],[FY25]]+G72 -> 63363
B70: Finance costs | C70: 509 | D70: 535 | E70: 1077 | F70: 1255 | G70: 1477 | I70: Infrastructure Cost | K70: =C73+C75+C76+C77+C80 -> 4587 | L70: =D73+D75+D76+D77+D80 -> 6045 | M70: =E73+E75+E76+E77+E80 -> 5575 | N70: =F73+F75+F76+F77+F80 -> 5084 | O70: =G73+G75+G76+G77+G80 -> 5063
B71: Depreciation & amortization | C71: 2763 | D71: 3078 | E71: 3340 | F71: 3407 | G71: 2958 | I71: Technology Investment | K71: 0 | L71: =D74+D67+D79 -> 1921 | M71: =E74+E67+E79 -> 2407 | N71: =F74+F67+F79 -> 2285 | O71: =G74+G67+G79 -> 2263
B72: Sub-contracting fees | C72: 8361 | D72: 10859 | E72: 11525 | F72: 10303 | G72: 10015 | I72: Sales & Marketing | K72: =C78 -> 101 | L72: =D78 -> 201 | M72: =E78 -> 295 | N72: =F78 -> 356 | O72: =G78 -> 359
B73: Facility expenses | C73: 2026 | D73: 2569 | E73: 1349 | F73: 1456 | G73: 1607 | I73: D & A | K73: =C71 -> 2763 | L73: =D71 -> 3078 | M73: =E71 -> 3340 | N73: =F71 -> 3407 | O73: =G71 -> 2958
B74: Software license expense | C74: — | D74: 1327 | E74: 1818 | F74: 1838 | G74: 1934
B75: Travel | C75: 526 | D75: 732 | E75: 1445 | F75: 1510 | G75: 1409 | I75: EPS
B76: Communication | C76: 607 | D76: 576 | E76: 591 | F76: 488 | G76: 384
B77: Legal & professional | C77: 556 | D77: 756 | E77: 1329 | F77: 956 | G77: 1127 | I77: ='RELATIVE VALUATION'!B13 -> TCS | K77: 134.19
B78: Marketing & brand | C78: 101 | D78: 201 | E78: 295 | F78: 356 | G78: 359 | I78: ='RELATIVE VALUATION'!B14 -> Infosys | K78: 64.5
B79: Lifetime expected credit loss | C79: 150 | D79: -80 | E79: -60 | F79: 64 | G79: 32 | I79: ='RELATIVE VALUATION'!B15 -> HCL Technologies | K79: 64.16
B80: Other expenses | C80: 872 | D80: 1412 | E80: 861 | F80: 674 | G80: 536 | I80: ='RELATIVE VALUATION'!B16 -> LTIMindtree | K80: 177
B81: Total expenses | C81: 50436 | D81: 66238 | E81: 77982 | F81: 77647 | G81: 75502 | I81: ='RELATIVE VALUATION'!B17 -> Tech Mahindra | K81: 48
B82: OPERATING PROFIT (approx) | C82: 13890 | D82: 15135 | E82: 14771 | F82: 14744 | G82: 17470 | I82: ='RELATIVE VALUATION'!B18 -> Persistent Systems | K82: 90.54
B83: Share of profit/(loss) of associates | C83: 13 | D83: 6 | E83: -6 | F83: -23 | G83: 25
B84: Profit before tax (PBT) | C84: 13903 | D84: 15141 | E84: 14766 | F84: 14721 | G84: 17496
B85: Tax expense | C85: 3035 | D85: 2897 | E85: 3399 | F85: 3609 | G85: 4278
B86: Net profit | C86: 10868 | D86: 12243 | E86: 11367 | F86: 11112 | G86: 13218
B87: Total OCI | C87: 6817 | D87: 11452 | E87: 10738 | F87: 7059 | G87: 4148
B88: Total Comprehensive Income | C88: 11549 | D88: 13389 | E88: 12440 | F88: 11818 | G88: 13633
B89: EPS (Basic ₹) | C89: 19.11 | D89: 22.37 | E89: 20.73 | F89: 10.44 | G89: 12.56
B90: EPS (Diluted ₹) | C90: 19.07 | D90: 22.31 | E90: 20.68 | F90: 10.41 | G90: 12.52
B93: CASH FLOW STATEMENT
B95: Item | C95: FY21 | D95: FY22 | E95: FY23 | F95: FY24 | G95: FY25
B96: OPERATING ACTIVITIES
B97: Profit for the year | C97: 10868 | D97: 12243 | E97: 11367 | F97: 11112 | G97: 13218
B98: Depreciation & amortization | C98: 2763 | D98: 3078 | E98: 3340 | F98: 3407 | G98: 2958
B99: Share-based compensation | C99: 231 | D99: 411 | E99: 397 | F99: 558 | G99: 555
B100: Finance & other income (net) | C100: -1661 | D100: -945 | E100: -811 | F100: -1134 | G100: -2343
B101: Income tax expense | C101: 3035 | D101: 2897 | E101: 3399 | F101: 3609 | G101: 4278
B102: Change in working capital (net) | C102: 2493 | D102: -2089 | E102: -1228 | F102: 1823 | G102: 2527
B103: Cash from operations (before tax) | C103: 17265 | D103: 13648 | E103: 16082 | F103: 19158 | G103: 19560
B104: Taxes paid | C104: -2492 | D104: -2569 | E104: -3022 | F104: -1536 | G104: -2618
B105: Net Operating Cash Flow | C105: 14755 | D105: 11079 | E105: 13060 | F105: 17622 | G105: 16943
B106: INVESTING ACTIVITIES
B107: Capex (PPE purchase) | C107: -1958 | D107: -2015 | E107: -1483 | F107: -1051 | G107: -1474
B108: Investments purchase | C108: -11723 | D108: -1015486 | E108: -80683 | F108: -97507 | G108: -80158
B109: Investments sale | C109: 11891 | D109: 95374 | E109: 74089 | F109: 97860 | G109: 70652
B110: Acquisitions | C110: -987 | D110: -12985 | E110: -4556 | F110: -5291 | G110: -96
B111: Interest received | C111: 1962 | D111: 1227 | E111: 1411 | F111: 2011 | G111: 2621
B112: Dividend received | C112: 0.4 | D112: 0.2 | E112: 0.3 | F112: 0.3 | G112: 0.23
B113: Net Investing Cash Flow | C113: 774 | D113: -22449 | E113: -8406 | F113: 1168 | G113: -8073
B114: FINANCING ACTIVITIES
B115: Proceeds from borrowings | C115: 10342 | D115: 26012 | E115: 16103 | F115: 12050 | G115: 19559
B116: Repayment of borrowings | C116: -9721 | D116: -19181 | E116: -16891 | F116: -13056 | G116: -17763
B117: Lease payments | C117: -866 | D117: -973 | E117: -971 | F117: -1006 | G117: -1047
B118: Interest paid | C118: -333 | D118: -509 | E118: -870 | F118: -1046 | G118: -888
B119: Dividend paid | C119: -546 | D119: -547 | E119: -3281 | F119: -522 | G119: -6275
B120: Buyback of shares | C120: — | D120: — | E120: — | F120: -14517 | G120: —
B121: Net Financing Cash Flow | C121: -1288 | D121: 4659 | E121: -6088 | F121: -18257 | G121: -6396
B122: Net Change in Cash | C122: 2645 | D122: -6711 | E122: -1435 | F122: 533 | G122: 2474
B123: Cash at beginning | C123: 14410 | D123: 16966 | E123: 10383 | F123: 9186 | G123: 9695
B124: FX impact | C124: -89 | D124: 128 | E124: 237 | F124: -24 | G124: 29
B125: Cash at end | C125: 16966 | D125: 10383 | E125: 9186 | F125: 9695 | G125: 12197

Sheet ABOUT
B1: WIPRO | C1: ABOUT WIPRO
C5: Wipro is a leading global information technology, consulting, and business process services company headquartered in Bengaluru, India. Founded in 1945, the company has transformed from a consumer products business into one of the world’s major IT service providers. Wipro delivers innovative solutions in cloud computing, cybersecurity, artificial intelligence, digital transformation, analytics, engineering services, and consulting. The company serves clients across industries including banking, healthcare, retail, manufacturing, telecommunications, and energy. With operations in more than 60 countries and a strong global workforce, Wipro focuses on helping businesses improve efficiency, accelerate digital growth, and enhance customer experiences through technology-driven solutions. The company is recognized for its commitment to sustainability, ethical business practices, innovation, and long-term value creation for stakeholders.
B15: KEY FINANCIAL METRICS | C15: 44276 | D15: =EDATE(C15,12) -> 44641 | E15: =EDATE(D15,12) -> 45006 | F15: =EDATE(E15,12) -> 45372 | G15: =EDATE(F15,12) -> 45737 | J15: SHARE PRICE 2 YEARS
B18: Total Revenue | C18: ='PROFIT & LOSS'!D10 -> 64625 | D18: ='PROFIT & LOSS'!E10 -> 81590 | E18: ='PROFIT & LOSS'!F10 -> 93201 | F18: ='PROFIT & LOSS'!G10 -> 92425 | G18: ='PROFIT & LOSS'!H10 -> 92972
B19: Rev Growth % | C19: ='COMMON SIZE STATEMENT'!K9 -> N/A | D19: ='COMMON SIZE STATEMENT'!L9 -> 0.27771798 | E19: ='COMMON SIZE STATEMENT'!M9 -> 0.14341938 | F19: ='COMMON SIZE STATEMENT'!N9 -> -0.012547424 | G19: ='COMMON SIZE STATEMENT'!O9 -> -0.0078624407
B20: Gross Profit Margins % | C20: ='COMMON SIZE STATEMENT'!D12 -> 0.32572337 | D20: ='COMMON SIZE STATEMENT'!E12 -> 0.283142 | E20: ='COMMON SIZE STATEMENT'!F12 -> 0.28480783 | F20: ='COMMON SIZE STATEMENT'!G12 -> 0.28203443 | G20: ='COMMON SIZE STATEMENT'!H12 -> 0.31076015
B21: EBIT Margins % | C21: ='COMMON SIZE STATEMENT'!D16 -> 0.22745068 | D21: ='COMMON SIZE STATEMENT'!E16 -> 0.17791396 | E21: ='COMMON SIZE STATEMENT'!F16 -> 0.17467624 | F21: ='COMMON SIZE STATEMENT'!G16 -> 0.17345956 | G21: ='COMMON SIZE STATEMENT'!H16 -> 0.20378178
B22: Net Profit Margins % | C22: ='COMMON SIZE STATEMENT'!D20 -> 0.17261122 | D22: ='COMMON SIZE STATEMENT'!E20 -> 0.13584998 | E22: ='COMMON SIZE STATEMENT'!F20 -> 0.126651 | F22: ='COMMON SIZE STATEMENT'!G20 -> 0.12083311 | G22: ='COMMON SIZE STATEMENT'!H20 -> 0.14188143
B23: EPS | C23: ='PROFIT & LOSS'!D42 -> 19.07 | D23: ='PROFIT & LOSS'!E42 -> 22.31 | E23: ='PROFIT & LOSS'!F42 -> 20.68 | F23: ='PROFIT & LOSS'!G42 -> 10.41 | G23: ='PROFIT & LOSS'!H42 -> 12.52
B24: EPS Growth % | C24: N/A | D24: ='PROFIT & LOSS'!E42/'PROFIT & LOSS'!D42-1 -> 0.16990037 | E24: ='PROFIT & LOSS'!F42/'PROFIT & LOSS'!E42-1 -> -0.073061407 | F24: ='PROFIT & LOSS'!G42/'PROFIT & LOSS'!F42-1 -> -0.49661509 | G24: ='PROFIT & LOSS'!H42/'PROFIT & LOSS'!G42-1 -> 0.20268972
B25: DPS | C25: ='PROFIT & LOSS'!D44/'PROFIT & LOSS'!D41 -> 0.5205503 | D25: ='PROFIT & LOSS'!E44/'PROFIT & LOSS'!E41 -> 0.51548335 | E25: ='PROFIT & LOSS'!F44/'PROFIT & LOSS'!F41 -> 5.9774094 | F25: ='PROFIT & LOSS'!G44/'PROFIT & LOSS'!G41 -> 0.95218985 | G25: ='PROFIT & LOSS'!H44/'PROFIT & LOSS'!H41 -> 11.083244
B26: DPS Growth % | C26: N/A | D26: =D25/C25-1 -> -0.0097338297 | E26: =E25/D25-1 -> 10.595737 | F26: =F25/E25-1 -> -0.84070192 | G26: =G25/F25-1 -> 10.639741
B29: KEY FINANCIAL RATIOS | C29: 44276 | D29: =EDATE(C29,12) -> 44641 | E29: =EDATE(D29,12) -> 45006 | F29: =EDATE(E29,12) -> 45372 | G29: =EDATE(F29,12) -> 45737 | J29: SHAREHOLDING PATTERN
B32: P/E | C32: ='RATIO ANALYSIS'!C46 -> 10.015732 | D32: ='RATIO ANALYSIS'!D46 -> 13.265352 | E32: ='RATIO ANALYSIS'!E46 -> 8.8646035 | F32: ='RATIO ANALYSIS'!F46 -> 23.29683 | G32: ='RATIO ANALYSIS'!G46 -> 19.672524
B33: EV/EBITDA | C33: ='RATIO ANALYSIS'!C47 -> 10.949375 | D33: ='RATIO ANALYSIS'!D47 -> 18.143196 | E33: ='RATIO ANALYSIS'!E47 -> 5.4223419 | F33: ='RATIO ANALYSIS'!F47 -> 7.0629605 | G33: ='RATIO ANALYSIS'!G47 -> 6.5408451
B34: Debt to Equity | C34: ='BALANCE SHEET'!D69/'BALANCE SHEET'!D77 -> 0.50284282 | D34: ='BALANCE SHEET'!E69/'BALANCE SHEET'!E77 -> 0.63541364 | E34: ='BALANCE SHEET'!F69/'BALANCE SHEET'!F77 -> 0.50672225 | F34: ='BALANCE SHEET'!G69/'BALANCE SHEET'!G77 -> 0.53738599 | G34: ='BALANCE SHEET'!H69/'BALANCE SHEET'!H77 -> 0.55227785
B35: ROE | C35: ='DUPONT ANALYSIS'!D12 -> N/A | D35: ='DUPONT ANALYSIS'!E12 -> 0.18395765 | E35: ='DUPONT ANALYSIS'!F12 -> 0.16488106 | F35: ='DUPONT ANALYSIS'!G12 -> 0.14656745 | G35: ='DUPONT ANALYSIS'!H12 -> 0.1677764
B36: ROIC | C36: ='INTRINSIC GROWTH'!D64 -> 0.31677514 | D36: ='INTRINSIC GROWTH'!E64 -> 0.23163337 | E36: ='INTRINSIC GROWTH'!F64 -> 0.21503104 | F36: ='INTRINSIC GROWTH'!G64 -> 0.21317448 | G36: ='INTRINSIC GROWTH'!H64 -> 0.22320135
B37: ROA | C37: ='RATIO ANALYSIS'!C21 -> N/A | D37: ='RATIO ANALYSIS'!D21 -> 0.11680955 | E37: ='RATIO ANALYSIS'!E21 -> 0.1053181 | F37: ='RATIO ANALYSIS'!F21 -> 0.096315302 | G37: ='RATIO ANALYSIS'!G21 -> 0.10857863
B40: TOP SHAREHOLDERS | C40: NO. of S. | D40: HOLD | E40: REPRESENTATION | J40: INDEXED NIFTY & WIPRO
B43: ='DATA SHEET'!B356 -> Mr. Azim Hasham Premji (Zash Traders) | C43: ='DATA SHEET'!C356 -> 220.21 Cr | D43: ='DATA SHEET'!D356 -> 0.2103
B44: ='DATA SHEET'!B357 -> Mr. Azim Hasham Premji (Prazim Traders) | C44: ='DATA SHEET'!C357 -> 216.03 Cr | D44: ='DATA SHEET'!D357 -> 0.206
B45: ='DATA SHEET'!B358 -> Mr. Azim Hasham Premji (Hasham Traders) | C45: ='DATA SHEET'!C358 -> 188.68 Cr | D45: ='DATA SHEET'!D358 -> 0.1799
B46: ='DATA SHEET'!B359 -> Azim Premji Trust | C46: ='DATA SHEET'!C359 -> 68.04 Cr | D46: ='DATA SHEET'!D359 -> 0.0649
B47: ='DATA SHEET'!B360 -> Azim H. Premji | C47: ='DATA SHEET'!C360 -> 43.12 Cr | D47: ='DATA SHEET'!D360 -> 0.0411
B48: ='DATA SHEET'!B361 -> LIC ULIP Growth Fund | C48: ='DATA SHEET'!C361 -> 28.02 Cr | D48: ='DATA SHEET'!D361 -> 0.0267
B49: ='DATA SHEET'!B362 -> JP Morgan Chase Bank | C49: ='DATA SHEET'!C362 -> 25.97 Cr | D49: ='DATA SHEET'!D362 -> 0.0248
B50: ='DATA SHEET'!B363 -> Prazim Trading & Investment Co. Pvt Ltd | C50: ='DATA SHEET'!C363 -> 19.37 Cr | D50: ='DATA SHEET'!D363 -> 0.0185
B51: ='DATA SHEET'!B364 -> ICICI Prudential Children’s Fund | C51: ='DATA SHEET'!C364 -> 16.15 Cr | D51: ='DATA SHEET'!D364 -> 0.0154
B54: MANAGERIAL REMUNERATION | C54: DESIGN. | D54: REMUN. | E54: EXP. | F54: X of MEDIAN SALARY | J54: CAPITAL STRUCTURE
B57: Srinivas Pallia | C57: CEO | D57: 53.64 Cr. | E57: 30 + Years | F57: 548x | J57: Current Price | L57: ='PV OF FCFF'!$C$45 -> 246.3
B58: Rishad Premji | C58: Ex. Chairman | D58: 13.7 Cr. | E58: 20 + Years | F58: 140x | J58: N. of Shares (Cr.) | L58: ='PROFIT & LOSS'!$H$41 -> 566.17
B59: Aparna C. Iyer | C59: CFO | D59: 6.4 Cr. | E59: 20 + Years | F59: 65x | J59: Market Cap (Cr.) | L59: =L57*L58 -> 139447.67
B62: AMBITIONS REALIZED | J62: Less: Cash | L62: ='BALANCE SHEET'!H15 -> 12358
J63: Add: Debt | L63: ='BALANCE SHEET'!H45+'BALANCE SHEET'!H59 -> 16181
J64: Less: Min. Int | L64: ='BALANCE SHEET'!H75 -> 214
J65: Enterprise Value | L65: =L59+L63-L62-L64 -> 143056.67

Sheet P & L ASSUMPTIONS
B1: WIPRO | D1: INCOME STATEMENT ASSUMPTION | K1: INCOME STATEMENT - FORECAST (BEST CASE) | R1: INCOME STATEMENT - FORECAST (BASE CASE) | Y1: INCOME STATEMENT - FORECAST (WORST CASE)
C3: UNIT | D3: Year 1 | E3: Year 2 | F3: Year 3 | G3: Year 4 | H3: Year 5 | K3: Year 6 | L3: Year 7 | M3: Year 8 | N3: Year 9 | O3: Year 10 | R3: Year 6 | S3: Year 7 | T3: Year 8 | U3: Year 9 | V3: Year 10 | Y3: Year 6 | Z3: Year 7 | AA3: Year 8 | AB3: Year 9 | AC3: Year 10
B4: Particulars | D4: ='PROFIT & LOSS'!D4 -> 44276 | E4: ='PROFIT & LOSS'!E4 -> 44641 | F4: ='PROFIT & LOSS'!F4 -> 45006 | G4: ='PROFIT & LOSS'!G4 -> 45372 | H4: ='PROFIT & LOSS'!H4 -> 45737 | K4: ='PROFIT & LOSS'!K4 -> 46102 | L4: ='PROFIT & LOSS'!L4 -> 46467 | M4: ='PROFIT & LOSS'!M4 -> 46833 | N4: ='PROFIT & LOSS'!N4 -> 47198 | O4: ='PROFIT & LOSS'!O4 -> 47563 | R4: =K$4 -> 46102 | S4: =L$4 -> 46467 | T4: =M$4 -> 46833 | U4: =N$4 -> 47198 | V4: =O$4 -> 47563 | Y4: =R$4 -> 46102 | Z4: =S$4 -> 46467 | AA4: =T$4 -> 46833 | AB4: =U$4 -> 47198 | AC4: =V$4 -> 47563
B6: Total Income | C6: ₹ | D6: ='PROFIT & LOSS'!D10 -> 64625 | E6: ='PROFIT & LOSS'!E10 -> 81590 | F6: ='PROFIT & LOSS'!F10 -> 93201 | G6: ='PROFIT & LOSS'!G10 -> 92425 | H6: ='PROFIT & LOSS'!H10 -> 92972 | K6: =K11+K18+K28 -> 94095.92 | L6: =L11+L18+L28 -> 95242.731 | M6: =M11+M18+M28 -> 97322.148 | N6: =N11+N18+N28 -> 99453.628 | O6: =O11+O18+O28 -> 102584.34 | R6: =R11+R18+R28 -> 92275.32 | S6: =S11+S18+S28 -> 91597.259 | T6: =T11+T18+T28 -> 92684.516 | U6: =U11+U18+U28 -> 93791.21 | V6: =V11+V18+V28 -> 95808.665 | Y6: =Y11+Y18+Y28 -> 91791.04 | Z6: =Z11+Z18+Z28 -> 90636.339 | AA6: =AA11+AA18+AA28 -> 89940.023 | AB6: =AB11+AB18+AB28 -> 89259.071 | AC6: =AC11+AC18+AC28 -> 90287.974
B8: IT SERVICES | K8: IT SERVICES - FORECAST (BEST CASE) | R8: IT SERVICES - FORECAST (BASE CASE) | Y8: IT SERVICES - FORECAST (WORST CASE)
B11: Revenue from IT Services | C11: ₹ | D11: 61830 | E11: 79529 | F11: 90935 | G11: 89382 | H11: 89088 | K11: =K$22*K$13 -> 89708.943 | L11: =L$22*L$13 -> 90606.033 | M11: =M$22*M$13 -> 92418.153 | N11: =N$22*N$13 -> 94266.517 | O11: =O$22*O$13 -> 97094.512 | R11: =R$22*R$13 -> 88020.726 | S11: =S$22*S$13 -> 87140.519 | T11: =T$22*T$13 -> 88011.924 | U11: =U$22*U$13 -> 88892.043 | V11: =V$22*V$13 -> 90669.884 | Y11: =Y$22*Y$13 -> 87663.928 | Z11: =Z$22*Z$13 -> 86348.969 | AA11: =AA$22*AA$13 -> 85485.48 | AB11: =AB$22*AB$13 -> 84630.625 | AC11: =AC$22*AC$13 -> 85476.931
B12: YoY Change | C12: % | D12: N/A | E12: =E11/D11-1 -> 0.28625263 | F12: =F11/E11-1 -> 0.14341938 | G12: =G11/F11-1 -> -0.017078133 | H12: =H11/G11-1 -> -0.0032892529 | K12: =$K$11/$H$11-1 -> 0.00697 | L12: =L11/K11-1 -> 0.01 | M12: =M11/L11-1 -> 0.02 | N12: =N11/M11-1 -> 0.02 | O12: =O11/N11-1 -> 0.03 | R12: =$R$11/$H$11-1 -> -0.01198 | S12: =S11/R11-1 -> -0.01 | T12: =T11/S11-1 -> 0.01 | U12: =U11/T11-1 -> 0.01 | V12: =V11/U11-1 -> 0.02 | Y12: =$Y$11/$H$11-1 -> -0.015985 | Z12: =Z11/Y11-1 -> -0.015 | AA12: =AA11/Z11-1 -> -0.01 | AB12: =AB11/AA11-1 -> -0.01 | AC12: =AC11/AB11-1 -> 0.01
B13: % of Rev | C13: % | D13: =D11/D22 -> 0.99336472 | E13: =E11/E22 -> 1 | F13: =F11/F22 -> 1 | G13: =G11/G22 -> 0.99541172 | H13: =H11/H22 -> 1 | K13: =D$43 -> 0.997 | L13: =E$43 -> 0.997 | M13: =F$43 -> 0.997 | N13: =G$43 -> 0.997 | O13: =H$43 -> 0.997 | R13: =D$44 -> 0.998 | S13: =E$44 -> 0.998 | T13: =F$44 -> 0.998 | U13: =G$44 -> 0.998 | V13: =H$44 -> 0.998 | Y13: =D$45 -> 0.999 | Z13: =E$45 -> 0.999 | AA13: =F$45 -> 0.999 | AB13: =G$45 -> 0.999 | AC13: =H$45 -> 0.999
B15: IT PRODUCTS | K15: IT PRODUCTS - FORECAST (BEST CASE) | R15: IT PRODUCTS - FORECAST (BASE CASE) | Y15: IT PRODUCTS - FORECAST (WORST CASE)
B18: Revenue from IT Products | C18: ₹ | D18: =D6-(D11+D28) -> 413 | E18: =E6-(E11+E28) -> 0 | F18: =F6-(F11+F28) -> 0 | G18: =G6-(G11+G28) -> 412 | H18: =H6-(H11+H28) -> 0 | K18: =K$22*K$20 -> 269.93664 | L18: =L$22*L$20 -> 272.63601 | M18: =M$22*M$20 -> 278.08873 | N18: =N$22*N$20 -> 283.6505 | O18: =O$22*O$20 -> 292.16002 | R18: =R$22*R$20 -> 176.39424 | S18: =S$22*S$20 -> 174.6303 | T18: =T$22*T$20 -> 176.3766 | U18: =U$22*U$20 -> 178.14037 | V18: =V$22*V$20 -> 181.70317 | Y18: =Y22*Y20 -> 87.75168 | Z18: =Z22*Z20 -> 86.435405 | AA18: =AA22*AA20 -> 85.571051 | AB18: =AB22*AB20 -> 84.71534 | AC18: =AC22*AC20 -> 85.562494
B19: YoY Change | C19: % | D19: =D12 -> N/A | E19: =E18/D18-1 -> -1 | F19: N/A | G19: N/A | H19: =H18/G18-1 -> -1 | K19: N/A | L19: =L$18/K$18-1 -> 0.01 | M19: =M$18/L$18-1 -> 0.02 | N19: =N$18/M$18-1 -> 0.02 | O19: =O$18/N$18-1 -> 0.03 | R19: N/A | S19: =S$18/R$18-1 -> -0.01 | T19: =T$18/S$18-1 -> 0.01 | U19: =U$18/T$18-1 -> 0.01 | V19: =V$18/U$18-1 -> 0.02 | Y19: N/A | Z19: =Z18/Y18-1 -> -0.015 | AA19: =AA18/Z18-1 -> -0.01 | AB19: =AB18/AA18-1 -> -0.01 | AC19: =AC18/AB18-1 -> 0.01
B20: % of Rev | C20: % | D20: =D18/D22 -> 0.0066352843 | E20: =E18/E22 -> 0 | F20: =F18/F22 -> 0 | G20: =G18/G22 -> 0.0045882798 | H20: =H18/H22 -> 0 | K20: =100%-K13 -> 0.003 | L20: =100%-L13 -> 0.003 | M20: =100%-M13 -> 0.003 | N20: =100%-N13 -> 0.003 | O20: =100%-O13 -> 0.003 | R20: =100%-R13 -> 0.002 | S20: =100%-S13 -> 0.002 | T20: =100%-T13 -> 0.002 | U20: =100%-U13 -> 0.002 | V20: =100%-V13 -> 0.002 | Y20: =100%-Y13 -> 0.001 | Z20: =100%-Z13 -> 0.001 | AA20: =100%-AA13 -> 0.001 | AB20: =100%-AB13 -> 0.001 | AC20: =100%-AC13 -> 0.001
B22: Rev from Operations | C22: ₹ | D22: =D11+D18 -> 62243 | E22: =E11+E18 -> 79529 | F22: =F11+F18 -> 90935 | G22: =G11+G18 -> 89794 | H22: =H11+H18 -> 89088 | K22: =$H$22+($H$22*$D$37) -> 89978.88 | L22: =K$22+(K$22*E$37) -> 90878.669 | M22: =L$22+(L$22*F$37) -> 92696.242 | N22: =M$22+(M$22*G$37) -> 94550.167 | O22: =N$22+(N$22*H$37) -> 97386.672 | R22: =$H$22+($H$22*$D$38) -> 88197.12 | S22: =R$22+(R$22*E$38) -> 87315.149 | T22: =S$22+(S$22*F$38) -> 88188.3 | U22: =T$22+(T$22*G$38) -> 89070.183 | V22: =U$22+(U$22*H$38) -> 90851.587 | Y22: =$H$22+($H$22*$D$39) -> 87751.68 | Z22: =Y$22+(Y$22*E$39) -> 86435.405 | AA22: =Z$22+(Z$22*F$39) -> 85571.051 | AB22: =AA$22+(AA$22*G$39) -> 84715.34 | AC22: =AB$22+(AB$22*H$39) -> 85562.494
B23: % of Total Income | C23: % | D23: =D22/D6 -> 0.9631412 | E23: =E22/E6 -> 0.97473955 | F23: =F22/F6 -> 0.97568696 | G23: =G22/G6 -> 0.97153368 | H23: =H22/H6 -> 0.95822398 | K23: =K22/K6 -> 0.95624635 | L23: =L22/L6 -> 0.95417958 | M23: =M22/M6 -> 0.9524681 | N23: =N22/N6 -> 0.95069601 | O23: =O22/O6 -> 0.94933273 | R23: =R22/R6 -> 0.955804 | S23: =S22/S6 -> 0.95325068 | T23: =T22/T6 -> 0.95148903 | U23: =U22/U6 -> 0.94966451 | V23: =V22/V6 -> 0.94826065 | Y23: =Y22/Y6 -> 0.95599396 | Z23: =Z22/Z6 -> 0.95365066 | AA23: =AA22/AA6 -> 0.9514235 | AB23: =AB22/AB6 -> 0.94909503 | AC23: =AC22/AC6 -> 0.94766213
B25: OTHER INCOME | K25: OTHER INCOME - FORECAST (BEST CASE) | R25: OTHER INCOME - FORECAST (BASE CASE) | Y25: OTHER INCOME - FORECAST (WORST CASE)
B28: Other Income | C28: ₹ | D28: ='PROFIT & LOSS'!D8 -> 2382 | E28: ='PROFIT & LOSS'!E8 -> 2061 | F28: ='PROFIT & LOSS'!F8 -> 2266 | G28: ='PROFIT & LOSS'!G8 -> 2631 | H28: ='PROFIT & LOSS'!H8 -> 3884 | K28: =$H$28+($H$28*K29) -> 4117.04 | L28: =K$28+(K$28*L$29) -> 4364.0624 | M28: =L$28+(L$28*M$29) -> 4625.9061 | N28: =M$28+(M$28*N$29) -> 4903.4605 | O28: =N$28+(N$28*O$29) -> 5197.6681 | R28: =$H$28+($H$28*$R$29) -> 4078.2 | S28: =R$28+(R$28*S$29) -> 4282.11 | T28: =S$28+(S$28*T$29) -> 4496.2155 | U28: =T$28+(T$28*U$29) -> 4721.0263 | V28: =U$28+(U$28*V$29) -> 4957.0776 | Y28: =$H$28+($H$28*$Y$29) -> 4039.36 | Z28: =Y$28+(Y$28*Z$29) -> 4200.9344 | AA28: =Z$28+(Z$28*AA$29) -> 4368.9718 | AB28: =AA$28+(AA$28*AB$29) -> 4543.7306 | AC28: =AB$28+(AB$28*AC$29) -> 4725.4799
B29: YoY change | C29: % | D29: N/A | E29: =E28/D28-1 -> -0.13476071 | F29: =F28/E28-1 -> 0.099466279 | G29: =G28/F28-1 -> 0.16107679 | H29: =H28/G28-1 -> 0.47624477 | K29: =D$49 -> 0.06 | L29: =E$49 -> 0.06 | M29: =F$49 -> 0.06 | N29: =G$49 -> 0.06 | O29: =H$49 -> 0.06 | R29: =D$50 -> 0.05 | S29: =E$50 -> 0.05 | T29: =F$50 -> 0.05 | U29: =G$50 -> 0.05 | V29: =H$50 -> 0.05 | Y29: =D$51 -> 0.04 | Z29: =E$51 -> 0.04 | AA29: =F$51 -> 0.04 | AB29: =G$51 -> 0.04 | AC29: =H$51 -> 0.04
B30: % of Total Income | C30: % | D30: =D28/D6 -> 0.036858801 | E30: =E28/E6 -> 0.025260449 | F30: =F28/F6 -> 0.024313044 | G30: =G28/G6 -> 0.028466324 | H30: =H28/H6 -> 0.041776019 | K30: =K28/K6 -> 0.043753651 | L30: =L28/L6 -> 0.045820425 | M30: =M28/M6 -> 0.047531895 | N30: =N28/N6 -> 0.049303989 | O30: =O28/O6 -> 0.050667267 | R30: =R28/R6 -> 0.044196 | S30: =S28/S6 -> 0.046749325 | T30: =T28/T6 -> 0.048510967 | U30: =U28/U6 -> 0.050335488 | V30: =V28/V6 -> 0.051739345 | Y30: =Y28/Y6 -> 0.044006038 | Z30: =Z28/Z6 -> 0.046349339 | AA30: =AA28/AA6 -> 0.048576503 | AB30: =AB28/AB6 -> 0.050904974 | AC30: =AC28/AC6 -> 0.052337866
D31: Revenue Assumption | K31: COGS & OpEx Assumption & Interest | R31: Depreciation Assumption & Interest | Y31: Tax Assumption
B32: ASSUMPTIONS
D33: Year 1 | E33: Year 2 | F33: Year 3 | G33: Year 4 | H33: Year 5 | K33: Year 1 | L33: Year 2 | M33: Year 3 | N33: Year 4 | O33: Year 5 | R33: Year 1 | S33: Year 2 | T33: Year 3 | U33: Year 4 | V33: Year 5 | Y33: Year 1 | Z33: Year 2 | AA33: Year 3 | AB33: Year 4 | AC33: Year 5
B35: Revenue from Operations CAGR | K35: Cogs % of Rev | R35: Dep. % of PPE | Y35: Tax % of EBT
B37: Best Case | C37: % | D37: 0.01 | E37: 0.01 | F37: 0.02 | G37: 0.02 | H37: 0.03 | K37: 0.71 | L37: 0.71 | M37: 0.71 | N37: 0.71 | O37: 0.71 | R37: 0.15 | S37: 0.151 | T37: 0.152 | U37: 0.153 | V37: 0.154 | Y37: 0.23 | Z37: 0.23 | AA37: 0.23 | AB37: 0.23 | AC37: 0.23
B38: Base Case | C38: % | D38: -0.01 | E38: -0.01 | F38: 0.01 | G38: 0.01 | H38: 0.02 | K38: 0.72 | L38: 0.72 | M38: 0.72 | N38: 0.72 | O38: 0.72 | R38: 0.145 | S38: 0.146 | T38: 0.147 | U38: 0.148 | V38: 0.149 | Y38: 0.24 | Z38: 0.24 | AA38: 0.24 | AB38: 0.24 | AC38: 0.24
B39: Worst Case | C39: % | D39: -0.015 | E39: -0.015 | F39: -0.01 | G39: -0.01 | H39: 0.01 | K39: 0.73 | L39: 0.73 | M39: 0.73 | N39: 0.73 | O39: 0.73 | R39: 0.13 | S39: 0.131 | T39: 0.132 | U39: 0.133 | V39: 0.134 | Y39: 0.25 | Z39: 0.25 | AA39: 0.25 | AB39: 0.25 | AC39: 0.25
B41: IT Services % of Rev from Operations | K41: Opex % of TI | R41: Ac. D % of TI | Y41: Dividend %
B43: Best Case | C43: % | D43: 0.997 | E43: 0.997 | F43: 0.997 | G43: 0.997 | H43: 0.997 | K43: 0.06 | L43: 0.06 | M43: 0.06 | N43: 0.06 | O43: 0.06 | R43: N/A | S43: 0.149 | T43: 0.148 | U43: 0.147 | V43: 0.146 | Y43: 0.15 | Z43: 0.2 | AA43: 0.25 | AB43: 0.25 | AC43: 0.25
B44: Base Case | C44: % | D44: 0.998 | E44: 0.998 | F44: 0.998 | G44: 0.998 | H44: 0.998 | K44: 0.063 | L44: 0.063 | M44: 0.063 | N44: 0.063 | O44: 0.063 | R44: N/A | S44: 0.153 | T44: 0.152 | U44: 0.151 | V44: 0.15 | Y44: 0.2 | Z44: 0.25 | AA44: 0.3 | AB44: 0.3 | AC44: 0.3
B45: Worst Case | C45: % | D45: 0.999 | E45: 0.999 | F45: 0.999 | G45: 0.999 | H45: 0.999 | K45: 0.066 | L45: 0.066 | M45: 0.066 | N45: 0.066 | O45: 0.066 | R45: N/A | S45: 0.159 | T45: 0.159 | U45: 0.159 | V45: 0.159 | Y45: 0.3 | Z45: 0.35 | AA45: 0.4 | AB45: 0.45 | AC45: 0.5
B47: Other Income YoY Change % | K47: Std % of Debt | R47: Ltd % of Debt | Y47: Weighted O.S
B49: Best Case | C49: % | D49: 0.06 | E49: 0.06 | F49: 0.06 | G49: 0.06 | H49: 0.06 | K49: 0.54 | L49: 0.52 | M49: 0.5 | N49: 0.48 | O49: 0.46 | R49: =100%-K49 -> 0.46 | S49: =100%-L49 -> 0.48 | T49: =100%-M49 -> 0.5 | U49: =100%-N49 -> 0.52 | V49: =100%-O49 -> 0.54 | Y49: -0.003 | Z49: -0.003 | AA49: -0.003 | AB49: -0.003 | AC49: -0.003
B50: Base Case | C50: % | D50: 0.05 | E50: 0.05 | F50: 0.05 | G50: 0.05 | H50: 0.05 | K50: 0.58 | L50: 0.56 | M50: 0.54 | N50: 0.52 | O50: 0.5 | R50: =100%-K50 -> 0.42 | S50: =100%-L50 -> 0.44 | T50: =100%-M50 -> 0.46 | U50: =100%-N50 -> 0.48 | V50: =100%-O50 -> 0.5 | Y50: 0.03 | Z50: 0.03 | AA50: 0.03 | AB50: 0.03 | AC50: 0.03
B51: Worst Case | C51: % | D51: 0.04 | E51: 0.04 | F51: 0.04 | G51: 0.04 | H51: 0.04 | K51: 0.59 | L51: 0.6 | M51: 0.6 | N51: 0.6 | O51: 0.6 | R51: =100%-K51 -> 0.41 | S51: =100%-L51 -> 0.4 | T51: =100%-M51 -> 0.4 | U51: =100%-N51 -> 0.4 | V51: =100%-O51 -> 0.4 | Y51: 0.05 | Z51: 0.05 | AA51: 0.05 | AB51: 0.05 | AC51: 0.05
B53: COGS & OPEX | K53: COGS & OPEX - FORECAST (BEST CASE) | R53: COGS & OPEX - FORECAST (BASE CASE) | Y53: COGS & OPEX - FORECAST (WORST CASE)
B56: COGS | C56: ₹ | D56: ='PROFIT & LOSS'!D$12 -> 44351 | E56: ='PROFIT & LOSS'!E$12 -> 59072 | F56: ='PROFIT & LOSS'!F$12 -> 67302 | G56: ='PROFIT & LOSS'!G$12 -> 67100 | H56: ='PROFIT & LOSS'!H$12 -> 65287 | K56: =K58*K22 -> 63885.005 | L56: =L58*L22 -> 64523.855 | M56: =M58*M22 -> 65814.332 | N56: =N58*N22 -> 67130.619 | O56: =O58*O22 -> 69144.537 | R56: =R58*R22 -> 63501.926 | S56: =S58*S22 -> 62866.907 | T56: =T58*T22 -> 63495.576 | U56: =U58*U22 -> 64130.532 | V56: =V58*V22 -> 65413.143 | Y56: =Y58*Y22 -> 64058.726 | Z56: =Z58*Z22 -> 63097.846 | AA56: =AA58*AA22 -> 62466.867 | AB56: =AB58*AB22 -> 61842.198 | AC56: =AC58*AC22 -> 62460.62
B57: YoY change | C57: % | D57: N/A | E57: =E56/D56-1 -> 0.33192036 | F57: =F56/E56-1 -> 0.13932151 | G57: =G56/F56-1 -> -0.0030013967 | H57: =H56/G56-1 -> -0.027019374 | K57: =$K$56/$H$56-1 -> -0.021474339 | L57: =L56/K56-1 -> 0.01 | M57: =M56/L56-1 -> 0.02 | N57: =N56/M56-1 -> 0.02 | O57: =O56/N56-1 -> 0.03 | R57: =$R$56/$H$56-1 -> -0.027341946 | S57: =S56/R56-1 -> -0.01 | T57: =T56/S56-1 -> 0.01 | U57: =U56/T56-1 -> 0.01 | V57: =V56/U56-1 -> 0.02 | Y57: =$Y$56/$H$56-1 -> -0.018813448 | Z57: =Z56/Y56-1 -> -0.015 | AA57: =AA56/Z56-1 -> -0.01 | AB57: =AB56/AA56-1 -> -0.01 | AC57: =AC56/AB56-1 -> 0.01
B58: % of Rev | C58: % | D58: =D56/D22 -> 0.71254599 | E58: =E56/E22 -> 0.74277308 | F58: =F56/F22 -> 0.74011107 | G58: =G56/G22 -> 0.74726596 | H58: =H56/H22 -> 0.73283719 | K58: =K$37 -> 0.71 | L58: =L$37 -> 0.71 | M58: =M$37 -> 0.71 | N58: =N$37 -> 0.71 | O58: =O$37 -> 0.71 | R58: =K$38 -> 0.72 | S58: =L$38 -> 0.72 | T58: =M$38 -> 0.72 | U58: =N$38 -> 0.72 | V58: =O$38 -> 0.72 | Y58: =K$39 -> 0.73 | Z58: =L$39 -> 0.73 | AA58: =M$39 -> 0.73 | AB58: =N$39 -> 0.73 | AC58: =O$39 -> 0.73
B60: OPEX | C60: ₹ | D60: ='PROFIT & LOSS'!D$18 -> 2812 | E60: ='PROFIT & LOSS'!E$18 -> 4924 | F60: ='PROFIT & LOSS'!F$18 -> 6279 | G60: ='PROFIT & LOSS'!G$18 -> 5886 | H60: ='PROFIT & LOSS'!H$18 -> 5781 | K60: =K62*K6 -> 5645.7552 | L60: =L62*L6 -> 5714.5639 | M60: =M62*M6 -> 5839.3289 | N60: =N62*N6 -> 5967.2177 | O60: =O62*O6 -> 6155.0604 | R60: =R62*R6 -> 5813.3452 | S60: =S62*S6 -> 5770.6273 | T60: =T62*T6 -> 5839.1245 | U60: =U62*U6 -> 5908.8462 | V60: =V62*V6 -> 6035.9459 | Y60: =Y62*Y6 -> 6058.2086 | Z60: =Z62*Z6 -> 5981.9984 | AA60: =AA62*AA6 -> 5936.0415 | AB60: =AB62*AB6 -> 5891.0987 | AC60: =AC62*AC6 -> 5959.0063
B61: YoY change | C61: % | D61: N/A | E61: =E60/D60-1 -> 0.75106686 | F61: =F60/E60-1 -> 0.27518278 | G61: =G60/F60-1 -> -0.062589584 | H61: =H60/G60-1 -> -0.01783894 | K61: =$K$60/$H$60-1 -> -0.023394707 | L61: =L60/K60-1 -> 0.012187683 | M61: =M60/L60-1 -> 0.021832817 | N61: =N60/M60-1 -> 0.021901276 | O61: =O60/N60-1 -> 0.03147912 | R61: =$R$60/$H$60-1 -> 0.0055950804 | S61: =S60/R60-1 -> -0.00734824 | T61: =T60/S60-1 -> 0.011869973 | U61: =U60/T60-1 -> 0.011940439 | V61: =V60/U60-1 -> 0.021510065 | Y61: =$Y$60/$H$60-1 -> 0.047951676 | Z61: =Z60/Y60-1 -> -0.012579668 | AA61: =AA60/Z60-1 -> -0.0076825331 | AB61: =AB60/AA60-1 -> -0.0075711748 | AC61: =AC60/AB60-1 -> 0.011527149
B62: % of Total Income | C62: % | D62: =D60/D6 -> 0.043512573 | E62: =E60/E6 -> 0.060350533 | F62: =F60/F6 -> 0.067370522 | G62: =G60/G6 -> 0.063684068 | H62: =H60/H6 -> 0.062180011 | K62: =K$43 -> 0.06 | L62: =L$43 -> 0.06 | M62: =M$43 -> 0.06 | N62: =N$43 -> 0.06 | O62: =O$43 -> 0.06 | R62: =K$44 -> 0.063 | S62: =L$44 -> 0.063 | T62: =M$44 -> 0.063 | U62: =N$44 -> 0.063 | V62: =O$44 -> 0.063 | Y62: =K$45 -> 0.066 | Z62: =L$45 -> 0.066 | AA62: =M$45 -> 0.066 | AB62: =N$45 -> 0.066 | AC62: =O$45 -> 0.066
B64: DEPRECIATION | K64: DEPRECIATION - FORECAST (BEST CASE) | R64: DEPRECIATION - FORECAST (BASE CASE) | Y64: DEPRECIATION - FORECAST (WORST CASE)
B67: Opening Accumulated Depreciation | C67: ₹ | D67: ='DATA SHEET'!I$57 -> 12942 | E67: ='DATA SHEET'!J$57 -> 13327 | F67: ='DATA SHEET'!K$57 -> 14000 | G67: ='DATA SHEET'!L$57 -> 14631 | H67: ='DATA SHEET'!M$57 -> 14339 | K67: =$H$75 -> 14676 | L67: =L$6*L$68 -> 14191.167 | M67: =M$6*M$68 -> 14403.678 | N67: =N$6*N$68 -> 14619.683 | O67: =O$6*O$68 -> 14977.314 | R67: =$H$75 -> 14676 | S67: =S$6*S$68 -> 14014.381 | T67: =T$6*T$68 -> 14088.046 | U67: =U$6*U$68 -> 14162.473 | V67: =V$6*V$68 -> 14371.3 | Y67: =$H$75 -> 14676 | Z67: =Z$6*Z$68 -> 14411.178 | AA67: =AA$6*AA$68 -> 14300.464 | AB67: =AB$6*AB$68 -> 14192.192 | AC67: =AC$6*AC$68 -> 14355.788
B68: % of Total Income | C68: % | D68: =D67/D6 -> 0.20026306 | E68: =E67/E6 -> 0.1633411 | F68: =F67/F6 -> 0.15021298 | G68: =G67/G6 -> 0.15830133 | H68: =H67/H6 -> 0.15422923 | K68: =$K$67/$K$6 -> 0.15596851 | L68: =S$43 -> 0.149 | M68: =T$43 -> 0.148 | N68: =U$43 -> 0.147 | O68: =V$43 -> 0.146 | R68: =$R$67/$R$6 -> 0.15904578 | S68: =S$44 -> 0.153 | T68: =T$44 -> 0.152 | U68: =U$44 -> 0.151 | V68: =V$44 -> 0.15 | Y68: =$Y$67/$Y$6 -> 0.15988489 | Z68: =S$45 -> 0.159 | AA68: =T$45 -> 0.159 | AB68: =U$45 -> 0.159 | AC68: =V$45 -> 0.159
B70: Depreciation Expense | C70: ₹ | D70: ='PROFIT & LOSS'!D24 -> 2763 | E70: ='PROFIT & LOSS'!E24 -> 3078 | F70: ='PROFIT & LOSS'!F24 -> 3340 | G70: ='PROFIT & LOSS'!G24 -> 3407 | H70: ='PROFIT & LOSS'!H24 -> 2958 | K70: =K71*'BALANCE SHEET ASSUMPTION'!K9 -> 3378.45 | L70: =L71*'BALANCE SHEET ASSUMPTION'!L9 -> 3485.3995 | M70: =M71*'BALANCE SHEET ASSUMPTION'!M9 -> 3588.4807 | N70: =N71*'BALANCE SHEET ASSUMPTION'!N9 -> 3693.0873 | O70: =O71*'BALANCE SHEET ASSUMPTION'!O9 -> 3799.3696 | R70: =R71*'BALANCE SHEET ASSUMPTION'!R9 -> 3265.835 | S70: =S71*'BALANCE SHEET ASSUMPTION'!S9 -> 3323.8395 | T70: =T71*'BALANCE SHEET ASSUMPTION'!T9 -> 3373.7128 | U70: =U71*'BALANCE SHEET ASSUMPTION'!U9 -> 3424.996 | V70: =V71*'BALANCE SHEET ASSUMPTION'!V9 -> 3477.628 | Y70: =Y71*'BALANCE SHEET ASSUMPTION'!Y9 -> 2927.99 | Z70: =Z71*'BALANCE SHEET ASSUMPTION'!Z9 -> 2949.5539 | AA70: =AA71*'BALANCE SHEET ASSUMPTION'!AA9 -> 2965.664 | AB70: =AB71*'BALANCE SHEET ASSUMPTION'!AB9 -> 2978.8052 | AC70: =AC71*'BALANCE SHEET ASSUMPTION'!AC9 -> 2989.3113
B71: % of Gross PPE | C71: % | D71: =D70/'BALANCE SHEET ASSUMPTION'!D9 -> 0.15020386 | E71: =E70/'BALANCE SHEET ASSUMPTION'!E9 -> 0.15465782 | F71: =F70/'BALANCE SHEET ASSUMPTION'!F9 -> 0.15563114 | G71: =G70/'BALANCE SHEET ASSUMPTION'!G9 -> 0.14900503 | H71: =H70/'BALANCE SHEET ASSUMPTION'!H9 -> 0.1359875 | K71: =R$37 -> 0.15 | L71: =S$37 -> 0.151 | M71: =T$37 -> 0.152 | N71: =U$37 -> 0.153 | O71: =V$37 -> 0.154 | R71: =R$38 -> 0.145 | S71: =S$38 -> 0.146 | T71: =T$38 -> 0.147 | U71: =U$38 -> 0.148 | V71: =V$38 -> 0.149 | Y71: =R$39 -> 0.13 | Z71: =S$39 -> 0.131 | AA71: =T$39 -> 0.132 | AB71: =U$39 -> 0.133 | AC71: =V$39 -> 0.134
B73: Dep on Disposals | C73: ₹ | D73: =(D67+D70-E67)*-1 -> -2378 | E73: =(E67+E70-F67)*-1 -> -2405 | F73: =(F67+F70-G67)*-1 -> -2709 | G73: =(G67+G70-H67)*-1 -> -3699 | H73: =(H67+H70-H75)*-1 -> -2621 | K73: -2762 | L73: -2762 | M73: -2762 | N73: -2762 | O73: -2762 | R73: -2762 | S73: -2762 | T73: -2762 | U73: -2762 | V73: -2762 | Y73: -2762 | Z73: -2762 | AA73: -2762 | AB73: -2762 | AC73: -2762
B75: Closing Accumulated Depreciation | C75: ₹ | D75: =SUM(D67,D70,D73) -> 13327 | E75: =SUM(E67,E70,E73) -> 14000 | F75: =SUM(F67,F70,F73) -> 14631 | G75: =SUM(G67,G70,G73) -> 14339 | H75: ='DATA SHEET'!$N$57 -> 14676 | K75: =K67+K70+K73 -> 15292.45 | L75: =L67+L70+L73 -> 14914.566 | M75: =M67+M70+M73 -> 15230.159 | N75: =N67+N70+N73 -> 15550.771 | O75: =O67+O70+O73 -> 16014.683 | R75: =R67+R70+R73 -> 15179.835 | S75: =S67+S70+S73 -> 14576.22 | T75: =T67+T70+T73 -> 14699.759 | U75: =U67+U70+U73 -> 14825.469 | V75: =V67+V70+V73 -> 15086.928 | Y75: =Y67+Y70+Y73 -> 14841.99 | Z75: =Z67+Z70+Z73 -> 14598.732 | AA75: =AA67+AA70+AA73 -> 14504.128 | AB75: =AB67+AB70+AB73 -> 14408.997 | AC75: =AC67+AC70+AC73 -> 14583.099
B77: INTEREST | K77: INTEREST - FORECAST (BEST CASE) | R77: INTEREST - FORECAST (BASE CASE) | Y77: INTEREST - FORECAST (WORST CASE)
B80: Opening Total Debt | C80: ₹ | D80: N/A | E80: =D$86 -> 8333 | F80: =E$86 -> 15169 | G80: =F$86 -> 15009 | H80: =G$86 -> 14147 | K80: =$H$86 -> 16181 | L80: =K$86 -> 15981 | M80: =L$86 -> 15781 | N80: =M$86 -> 15581 | O80: =N$86 -> 15481 | R80: =$H$86 -> 16181 | S80: =R$86 -> 16281 | T80: =S$86 -> 16401 | U80: =T$86 -> 16541 | V80: =U$86 -> 16701 | Y80: =$H$86 -> 16181 | Z80: =Y86 -> 16381 | AA80: =Z86 -> 16681 | AB80: =AA86 -> 17081 | AC80: =AB86 -> 17581
B81: Interest Rate | C81: % | D81: N/A | E81: =E82/((E80+E86)/2) -> 0.04552804 | F81: =F82/((F80+F86)/2) -> 0.071376499 | G81: =G82/((G80+G86)/2) -> 0.086088627 | H81: =H82/((H80+H86)/2) -> 0.097401741 | K81: 0.107 | L81: 0.107 | M81: 0.107 | N81: 0.107 | O81: 0.107 | R81: 0.117 | S81: 0.117 | T81: 0.117 | U81: 0.117 | V81: 0.117 | Y81: 0.127 | Z81: 0.127 | AA81: 0.127 | AB81: 0.127 | AC81: 0.127
B82: Interest Expense | C82: ₹ | D82: ='PROFIT & LOSS'!D30 -> 509 | E82: ='PROFIT & LOSS'!E30 -> 535 | F82: ='PROFIT & LOSS'!F30 -> 1077 | G82: ='PROFIT & LOSS'!G30 -> 1255 | H82: ='PROFIT & LOSS'!H30 -> 1477 | K82: =K80*K81 -> 1731.367 | L82: =L80*L81 -> 1709.967 | M82: =M80*M81 -> 1688.567 | N82: =N80*N81 -> 1667.167 | O82: =O80*O81 -> 1656.467 | R82: =R80*R81 -> 1893.177 | S82: =S80*S81 -> 1904.877 | T82: =T80*T81 -> 1918.917 | U82: =U80*U81 -> 1935.297 | V82: =V80*V81 -> 1954.017 | Y82: =Y80*Y81 -> 2054.987 | Z82: =Z80*Z81 -> 2080.387 | AA82: =AA80*AA81 -> 2118.487 | AB82: =AB80*AB81 -> 2169.287 | AC82: =AC80*AC81 -> 2232.787
B83: Debt Repayed | C83: ₹ | D83: 0 | E83: 0 | F83: =F86-F80 -> -160 | G83: =G86-G80 -> -862 | H83: 0 | K83: 0 | L83: 0 | M83: 0 | N83: 0 | O83: 0 | R83: 0 | S83: 0 | T83: 0 | U83: 0 | V83: 0 | Y83: 0 | Z83: 0 | AA83: 0 | AB83: 0 | AC83: 0
B84: New Borrowing | C84: ₹ | D84: =('DATA SHEET'!J36+'DATA SHEET'!J37)-('DATA SHEET'!I36+'DATA SHEET'!I37) -> 896 | E84: =E86-E80 -> 6836 | F84: 0 | G84: 0 | H84: =H86-H80 -> 2034 | K84: -200 | L84: -200 | M84: -200 | N84: -100 | O84: -100 | R84: 100 | S84: 120 | T84: 140 | U84: 160 | V84: 180 | Y84: 200 | Z84: 300 | AA84: 400 | AB84: 500 | AC84: 500
B86: Closing Debt | C86: ₹ | D86: ='BALANCE SHEET'!D45+'BALANCE SHEET'!D59 -> 8333 | E86: ='BALANCE SHEET'!E45+'BALANCE SHEET'!E59 -> 15169 | F86: ='BALANCE SHEET'!F45+'BALANCE SHEET'!F59 -> 15009 | G86: ='BALANCE SHEET'!G45+'BALANCE SHEET'!G59 -> 14147 | H86: ='BALANCE SHEET'!H45+'BALANCE SHEET'!H59 -> 16181 | K86: =K80+K84 -> 15981 | L86: =L80+L84 -> 15781 | M86: =M80+M84 -> 15581 | N86: =N80+N84 -> 15481 | O86: =O80+O84 -> 15381 | R86: =R80+R84 -> 16281 | S86: =S80+S84 -> 16401 | T86: =T80+T84 -> 16541 | U86: =U80+U84 -> 16701 | V86: =V80+V84 -> 16881 | Y86: =Y80+Y84 -> 16381 | Z86: =Z80+Z84 -> 16681 | AA86: =AA80+AA84 -> 17081 | AB86: =AB80+AB84 -> 17581 | AC86: =AC80+AC84 -> 18081
B88: Short Term Debt | C88: ₹ | D88: =STATEMENTS!C45 -> 7587 | E88: =STATEMENTS!D45 -> 9523 | F88: =STATEMENTS!E45 -> 8882 | G88: =STATEMENTS!F45 -> 7917 | H88: =STATEMENTS!G45 -> 9786 | K88: =K$86*K89 -> 8629.74 | L88: =L$86*L89 -> 8206.12 | M88: =M$86*M89 -> 7790.5 | N88: =N$86*N89 -> 7430.88 | O88: =O$86*O89 -> 7075.26 | R88: =R$86*R89 -> 9442.98 | S88: =S$86*S89 -> 9184.56 | T88: =T$86*T89 -> 8932.14 | U88: =U$86*U89 -> 8684.52 | V88: =V$86*V89 -> 8440.5 | Y88: =Y$86*Y89 -> 9664.79 | Z88: =Z$86*Z89 -> 10008.6 | AA88: =AA$86*AA89 -> 10248.6 | AB88: =AB$86*AB89 -> 10548.6 | AC88: =AC$86*AC89 -> 10848.6
B89: % of Total Debt | C89: % | D89: =D88/D86 -> 0.91047642 | E89: =E88/E86 -> 0.62779353 | F89: =F88/F86 -> 0.59177827 | G89: =G88/G86 -> 0.55962395 | H89: =H88/H86 -> 0.60478339 | K89: =K$49 -> 0.54 | L89: =L$49 -> 0.52 | M89: =M$49 -> 0.5 | N89: =N$49 -> 0.48 | O89: =O$49 -> 0.46 | R89: =K$50 -> 0.58 | S89: =L$50 -> 0.56 | T89: =M$50 -> 0.54 | U89: =N$50 -> 0.52 | V89: =O$50 -> 0.5 | Y89: =K$51 -> 0.59 | Z89: =L$51 -> 0.6 | AA89: =M$51 -> 0.6 | AB89: =N$51 -> 0.6 | AC89: =O$51 -> 0.6
B90: Long Term Debt | C90: ₹ | D90: =STATEMENTS!C37 -> 746 | E90: =STATEMENTS!D37 -> 5646 | F90: =STATEMENTS!E37 -> 6127 | G90: =STATEMENTS!F37 -> 6230 | H90: =STATEMENTS!G37 -> 6395 | K90: =K$86*K91 -> 7351.26 | L90: =L$86*L91 -> 7574.88 | M90: =M$86*M91 -> 7790.5 | N90: =N$86*N91 -> 8050.12 | O90: =O$86*O91 -> 8305.74 | R90: =R$86*R91 -> 6838.02 | S90: =S$86*S91 -> 7216.44 | T90: =T$86*T91 -> 7608.86 | U90: =U$86*U91 -> 8016.48 | V90: =V$86*V91 -> 8440.5 | Y90: =Y$86*Y91 -> 6716.21 | Z90: =Z$86*Z91 -> 6672.4 | AA90: =AA$86*AA91 -> 6832.4 | AB90: =AB$86*AB91 -> 7032.4 | AC90: =AC$86*AC91 -> 7232.4
B91: % of Total Debt | C91: % | D91: =D90/D86 -> 0.089523581 | E91: =E90/E86 -> 0.37220647 | F91: =F90/F86 -> 0.40822173 | G91: =G90/G86 -> 0.44037605 | H91: =H90/H86 -> 0.39521661 | K91: =R$49 -> 0.46 | L91: =S$49 -> 0.48 | M91: =T$49 -> 0.5 | N91: =U$49 -> 0.52 | O91: =V$49 -> 0.54 | R91: =R$50 -> 0.42 | S91: =S$50 -> 0.44 | T91: =T$50 -> 0.46 | U91: =U$50 -> 0.48 | V91: =V$50 -> 0.5 | Y91: =R$51 -> 0.41 | Z91: =S$51 -> 0.4 | AA91: =T$51 -> 0.4 | AB91: =U$51 -> 0.4 | AC91: =V$51 -> 0.4
B93: TAX | K93: TAX - FORECAST (BEST CASE) | R93: TAX - FORECAST (BASE CASE) | Y93: TAX - FORECAST (WORST CASE)
B96: EBT | C96: ₹ | D96: ='PROFIT & LOSS'!D32 -> 14190 | E96: ='PROFIT & LOSS'!E32 -> 13981 | F96: ='PROFIT & LOSS'!F32 -> 15203 | G96: ='PROFIT & LOSS'!G32 -> 14777 | H96: ='PROFIT & LOSS'!H32 -> 17469 | K96: =K6-K56-K60-K70-K82 -> 19455.343 | L96: =L6-L56-L60-L70-L82 -> 19808.946 | M96: =M6-M56-M60-M70-M82 -> 20391.44 | N96: =N6-N56-N60-N70-N82 -> 20995.537 | O96: =O6-O56-O60-O70-O82 -> 21828.906 | R96: =R6-R56-R60-R70-R82 -> 17801.036 | S96: =S6-S56-S60-S70-S82 -> 17731.008 | T96: =T6-T56-T60-T70-T82 -> 18057.185 | U96: =U6-U56-U60-U70-U82 -> 18391.538 | V96: =V6-V56-V60-V70-V82 -> 18927.931 | Y96: =Y6-Y56-Y60-Y70-Y82 -> 16691.128 | Z96: =Z6-Z56-Z60-Z70-Z82 -> 16526.554 | AA96: =AA6-AA56-AA60-AA70-AA82 -> 16452.963 | AB96: =AB6-AB56-AB60-AB70-AB82 -> 16377.682 | AC96: =AC6-AC56-AC60-AC70-AC82 -> 16646.249
B97: Tax Rate | C97: % | D97: =D99/D96 -> 0.21388302 | E97: =E99/E96 -> 0.20720978 | F97: =F99/F96 -> 0.22357429 | G97: =G99/G96 -> 0.2442309 | H97: =H99/H96 -> 0.24489095 | K97: =Y$37 -> 0.23 | L97: =Z$37 -> 0.23 | M97: =AA$37 -> 0.23 | N97: =AB$37 -> 0.23 | O97: =AC$37 -> 0.23 | R97: =Y$38 -> 0.24 | S97: =Z$38 -> 0.24 | T97: =AA$38 -> 0.24 | U97: =AB$38 -> 0.24 | V97: =AC$38 -> 0.24 | Y97: =Y$39 -> 0.25 | Z97: =Z$39 -> 0.25 | AA97: =AA$39 -> 0.25 | AB97: =AB$39 -> 0.25 | AC97: =AC$39 -> 0.25
B99: Tax Expense | C99: ₹ | D99: ='PROFIT & LOSS'!D35 -> 3035 | E99: ='PROFIT & LOSS'!E35 -> 2897 | F99: ='PROFIT & LOSS'!F35 -> 3399 | G99: ='PROFIT & LOSS'!G35 -> 3609 | H99: ='PROFIT & LOSS'!H35 -> 4278 | K99: =K96*K97 -> 4474.7289 | L99: =L96*L97 -> 4556.0576 | M99: =M96*M97 -> 4690.0311 | N99: =N96*N97 -> 4828.9735 | O99: =O96*O97 -> 5020.6484 | R99: =R96*R97 -> 4272.2487 | S99: =S96*S97 -> 4255.4419 | T99: =T96*T97 -> 4333.7245 | U99: =U96*U97 -> 4413.9692 | V99: =V96*V97 -> 4542.7035 | Y99: =Y96*Y97 -> 4172.782 | Z99: =Z96*Z97 -> 4131.6386 | AA99: =AA96*AA97 -> 4113.2407 | AB99: =AB96*AB97 -> 4094.4204 | AC99: =AC96*AC97 -> 4161.5621
B101: Net Profit | C101: ₹ | D101: =D96-D99 -> 11155 | E101: =E96-E99 -> 11084 | F101: =F96-F99 -> 11804 | G101: =G96-G99 -> 11168 | H101: =H96-H99 -> 13191 | K101: =K96-K99 -> 14980.614 | L101: =L96-L99 -> 15252.888 | M101: =M96-M99 -> 15701.409 | N101: =N96-N99 -> 16166.563 | O101: =O96-O99 -> 16808.258 | R101: =R96-R99 -> 13528.788 | S101: =S96-S99 -> 13475.566 | T101: =T96-T99 -> 13723.461 | U101: =U96-U99 -> 13977.569 | V101: =V96-V99 -> 14385.228 | Y101: =Y96-Y99 -> 12518.346 | Z101: =Z96-Z99 -> 12394.916 | AA101: =AA96-AA99 -> 12339.722 | AB101: =AB96-AB99 -> 12283.261 | AC101: =AC96-AC99 -> 12484.686
B103: Dividends | C103: ₹ | D103: ='PROFIT & LOSS'!D44 -> 546 | E103: ='PROFIT & LOSS'!E44 -> 547 | F103: ='PROFIT & LOSS'!F44 -> 3281 | G103: ='PROFIT & LOSS'!G44 -> 522 | H103: ='PROFIT & LOSS'!H44 -> 6275 | K103: =K101*Y43 -> 2247.0921 | L103: =L101*Z43 -> 3050.5777 | M103: =M101*AA43 -> 3925.3522 | N103: =N101*AB43 -> 4041.6409 | O103: =O101*AC43 -> 4202.0644 | R103: =R101*Y44 -> 2705.7575 | S103: =S101*Z44 -> 3368.8915 | T103: =T101*AA44 -> 4117.0383 | U103: =U101*AB44 -> 4193.2708 | V103: =V101*AC44 -> 4315.5683 | Y103: =Y101*Y45 -> 3755.5038 | Z103: =Z101*Z45 -> 4338.2205 | AA103: =AA101*AA45 -> 4935.8889 | AB103: =AB101*AB45 -> 5527.4676 | AC103: =AC101*AC45 -> 6242.3432
B104: Retained Earnings | C104: ₹ | D104: ='PROFIT & LOSS'!D47 -> 10609 | E104: ='PROFIT & LOSS'!E47 -> 10537 | F104: ='PROFIT & LOSS'!F47 -> 8523 | G104: ='PROFIT & LOSS'!G47 -> 10646 | H104: ='PROFIT & LOSS'!H47 -> 6916 | K104: =K101-K103 -> 12733.522 | L104: =L101-L103 -> 12202.311 | M104: =M101-M103 -> 11776.056 | N104: =N101-N103 -> 12124.923 | O104: =O101-O103 -> 12606.193 | R104: =R101-R103 -> 10823.03 | S104: =S101-S103 -> 10106.674 | T104: =T101-T103 -> 9606.4226 | U104: =U101-U103 -> 9784.2984 | V104: =V101-V103 -> 10069.659 | Y104: =Y101-Y103 -> 8762.8422 | Z104: =Z101-Z103 -> 8056.6953 | AA104: =AA101-AA103 -> 7403.8333 | AB104: =AB101-AB103 -> 6755.7937 | AC104: =AC101-AC103 -> 6242.3432

Sheet PROFIT & LOSS
B1: WIPRO | D1: INCOME STATEMENT | I1: 2 | K1: INCOME STATEMENT - FORECAST
C3: UNIT | D3: Year 1 | E3: Year 2 | F3: Year 3 | G3: Year 4 | H3: Year 5 | K3: Year 6 | L3: Year 7 | M3: Year 8 | N3: Year 9 | O3: Year 10
B4: Particulars (In Crores) | D4: 44276 | E4: =EDATE(D4,12) -> 44641 | F4: =EDATE(E4,12) -> 45006 | G4: =EDATE(F4,12) -> 45372 | H4: =EDATE(G4,12) -> 45737 | K4: =EDATE(H4,12) -> 46102 | L4: =EDATE(K4,12) -> 46467 | M4: =EDATE(L4,12) -> 46833 | N4: =EDATE(M4,12) -> 47198 | O4: =EDATE(N4,12) -> 47563
B6: Revenue from Operations | C6: ₹ | D6: =STATEMENTS!C63 -> 62243 | E6: =STATEMENTS!D63 -> 79529 | F6: =STATEMENTS!E63 -> 90935 | G6: =STATEMENTS!F63 -> 89794 | H6: =STATEMENTS!G63 -> 89088 | K6: =CHOOSE($I$1,'P & L ASSUMPTIONS'!K$22,'P & L ASSUMPTIONS'!R$22,'P & L ASSUMPTIONS'!Y$22) -> 88197.12 | L6: =CHOOSE($I$1,'P & L ASSUMPTIONS'!L$22,'P & L ASSUMPTIONS'!S$22,'P & L ASSUMPTIONS'!Z$22) -> 87315.149 | M6: =CHOOSE($I$1,'P & L ASSUMPTIONS'!M$22,'P & L ASSUMPTIONS'!T$22,'P & L ASSUMPTIONS'!AA$22) -> 88188.3 | N6: =CHOOSE($I$1,'P & L ASSUMPTIONS'!N$22,'P & L ASSUMPTIONS'!U$22,'P & L ASSUMPTIONS'!AB$22) -> 89070.183 | O6: =CHOOSE($I$1,'P & L ASSUMPTIONS'!O$22,'P & L ASSUMPTIONS'!V$22,'P & L ASSUMPTIONS'!AC$22) -> 90851.587
B8: Other Income | C8: ₹ | D8: =STATEMENTS!C64 -> 2382 | E8: =STATEMENTS!D64 -> 2061 | F8: =STATEMENTS!E64 -> 2266 | G8: =STATEMENTS!F64 -> 2631 | H8: =STATEMENTS!G64 -> 3884 | K8: =CHOOSE($I$1,'P & L ASSUMPTIONS'!K$28,'P & L ASSUMPTIONS'!R$28,'P & L ASSUMPTIONS'!Y$28) -> 4078.2 | L8: =CHOOSE($I$1,'P & L ASSUMPTIONS'!L$28,'P & L ASSUMPTIONS'!S$28,'P & L ASSUMPTIONS'!Z$28) -> 4282.11 | M8: =CHOOSE($I$1,'P & L ASSUMPTIONS'!M$28,'P & L ASSUMPTIONS'!T$28,'P & L ASSUMPTIONS'!AA$28) -> 4496.2155 | N8: =CHOOSE($I$1,'P & L ASSUMPTIONS'!N$28,'P & L ASSUMPTIONS'!U$28,'P & L ASSUMPTIONS'!AB$28) -> 4721.0263 | O8: =CHOOSE($I$1,'P & L ASSUMPTIONS'!O$28,'P & L ASSUMPTIONS'!V$28,'P & L ASSUMPTIONS'!AC$28) -> 4957.0776
B10: Total Income | C10: ₹ | D10: =D6+D8 -> 64625 | E10: =E6+E8 -> 81590 | F10: =F6+F8 -> 93201 | G10: =G6+G8 -> 92425 | H10: =H6+H8 -> 92972 | K10: =K6+K8 -> 92275.32 | L10: =L6+L8 -> 91597.259 | M10: =M6+M8 -> 92684.516 | N10: =N6+N8 -> 93791.21 | O10: =O6+O8 -> 95808.665
B12: COGS | C12: ₹ | D12: =STATEMENTS!C67+STATEMENTS!C68+STATEMENTS!C72+STATEMENTS!C73+STATEMENTS!C69 -> 44351 | E12: =STATEMENTS!D67+STATEMENTS!D68+STATEMENTS!D72+STATEMENTS!D73+STATEMENTS!D69 -> 59072 | F12: =STATEMENTS!E67+STATEMENTS!E68+STATEMENTS!E72+STATEMENTS!E73+STATEMENTS!E69 -> 67302 | G12: =STATEMENTS!F67+STATEMENTS!F68+STATEMENTS!F72+STATEMENTS!F73+STATEMENTS!F69 -> 67100 | H12: =STATEMENTS!G67+STATEMENTS!G68+STATEMENTS!G72+STATEMENTS!G73+STATEMENTS!G69 -> 65287 | K12: =CHOOSE($I$1,'P & L ASSUMPTIONS'!K56,'P & L ASSUMPTIONS'!R56,'P & L ASSUMPTIONS'!Y56) -> 63501.926 | L12: =CHOOSE($I$1,'P & L ASSUMPTIONS'!L56,'P & L ASSUMPTIONS'!S56,'P & L ASSUMPTIONS'!Z56) -> 62866.907 | M12: =CHOOSE($I$1,'P & L ASSUMPTIONS'!M56,'P & L ASSUMPTIONS'!T56,'P & L ASSUMPTIONS'!AA56) -> 63495.576 | N12: =CHOOSE($I$1,'P & L ASSUMPTIONS'!N56,'P & L ASSUMPTIONS'!U56,'P & L ASSUMPTIONS'!AB56) -> 64130.532 | O12: =CHOOSE($I$1,'P & L ASSUMPTIONS'!O56,'P & L ASSUMPTIONS'!V56,'P & L ASSUMPTIONS'!AC56) -> 65413.143
B13: % of Rev | C13: % | D13: =D12/D6 -> 0.71254599 | E13: =E12/E6 -> 0.74277308 | F13: =F12/F6 -> 0.74011107 | G13: =G12/G6 -> 0.74726596 | H13: =H12/H6 -> 0.73283719 | K13: =K12/K6 -> 0.72 | L13: =L12/L6 -> 0.72 | M13: =M12/M6 -> 0.72 | N13: =N12/N6 -> 0.72 | O13: =O12/O6 -> 0.72
B15: Gross Profit | C15: ₹ | D15: =D10-D12 -> 20274 | E15: =E10-E12 -> 22518 | F15: =F10-F12 -> 25899 | G15: =G10-G12 -> 25325 | H15: =H10-H12 -> 27685 | K15: =K10-K12 -> 28773.394 | L15: =L10-L12 -> 28730.352 | M15: =M10-M12 -> 29188.94 | N15: =N10-N12 -> 29660.678 | O15: =O10-O12 -> 30395.522
B16: % of Rev | C16: % | D16: =D15/D6 -> 0.32572337 | E16: =E15/E6 -> 0.283142 | F16: =F15/F6 -> 0.28480783 | G16: =G15/G6 -> 0.28203443 | H16: =H15/H6 -> 0.31076015 | K16: =K15/K6 -> 0.32623961 | L16: =L15/L6 -> 0.32904201 | M16: =M15/M6 -> 0.33098426 | N16: =N15/N6 -> 0.33300344 | O16: =O15/O6 -> 0.33456237
B18: Other Expenses | C18: ₹ | D18: =SUM(STATEMENTS!C74:C80) -> 2812 | E18: =SUM(STATEMENTS!D74:D80) -> 4924 | F18: =SUM(STATEMENTS!E74:E80) -> 6279 | G18: =SUM(STATEMENTS!F74:F80) -> 5886 | H18: =SUM(STATEMENTS!G74:G80) -> 5781 | K18: =CHOOSE($I$1,'P & L ASSUMPTIONS'!K60,'P & L ASSUMPTIONS'!R60,'P & L ASSUMPTIONS'!Y60) -> 5813.3452 | L18: =CHOOSE($I$1,'P & L ASSUMPTIONS'!L60,'P & L ASSUMPTIONS'!S60,'P & L ASSUMPTIONS'!Z60) -> 5770.6273 | M18: =CHOOSE($I$1,'P & L ASSUMPTIONS'!M60,'P & L ASSUMPTIONS'!T60,'P & L ASSUMPTIONS'!AA60) -> 5839.1245 | N18: =CHOOSE($I$1,'P & L ASSUMPTIONS'!N60,'P & L ASSUMPTIONS'!U60,'P & L ASSUMPTIONS'!AB60) -> 5908.8462 | O18: =CHOOSE($I$1,'P & L ASSUMPTIONS'!O60,'P & L ASSUMPTIONS'!V60,'P & L ASSUMPTIONS'!AC60) -> 6035.9459
B19: % of Total Income | C19: % | D19: =D18/D10 -> 0.043512573 | E19: =E18/E10 -> 0.060350533 | F19: =F18/F10 -> 0.067370522 | G19: =G18/G10 -> 0.063684068 | H19: =H18/H10 -> 0.062180011 | K19: =K18/K10 -> 0.063 | L19: =L18/L10 -> 0.063 | M19: =M18/M10 -> 0.063 | N19: =N18/N10 -> 0.063 | O19: =O18/O10 -> 0.063
B21: EBITDA | C21: ₹ | D21: =D15-D18 -> 17462 | E21: =E15-E18 -> 17594 | F21: =F15-F18 -> 19620 | G21: =G15-G18 -> 19439 | H21: =H15-H18 -> 21904 | K21: =K15-K18 -> 22960.048 | L21: =L15-L18 -> 22959.724 | M21: =M15-M18 -> 23349.815 | N21: =N15-N18 -> 23751.831 | O21: =O15-O18 -> 24359.576
B22: % of Total Income | C22: % | D22: =D21/D10 -> 0.27020503 | E22: =E21/E10 -> 0.21563917 | F22: =F21/F10 -> 0.21051276 | G22: =G21/G10 -> 0.21032188 | H22: =H21/H10 -> 0.23559781 | K22: =K21/K10 -> 0.24882112 | L22: =L21/L10 -> 0.25065951 | M22: =M21/M10 -> 0.2519279 | N22: =N21/N10 -> 0.25324155 | O22: =O21/O10 -> 0.25425233
B24: D & A | C24: ₹ | D24: =STATEMENTS!C71 -> 2763 | E24: =STATEMENTS!D71 -> 3078 | F24: =STATEMENTS!E71 -> 3340 | G24: =STATEMENTS!F71 -> 3407 | H24: =STATEMENTS!G71 -> 2958 | K24: =CHOOSE($I$1,'P & L ASSUMPTIONS'!K70,'P & L ASSUMPTIONS'!R70,'P & L ASSUMPTIONS'!Y70) -> 3265.835 | L24: =CHOOSE($I$1,'P & L ASSUMPTIONS'!L70,'P & L ASSUMPTIONS'!S70,'P & L ASSUMPTIONS'!Z70) -> 3323.8395 | M24: =CHOOSE($I$1,'P & L ASSUMPTIONS'!M70,'P & L ASSUMPTIONS'!T70,'P & L ASSUMPTIONS'!AA70) -> 3373.7128 | N24: =CHOOSE($I$1,'P & L ASSUMPTIONS'!N70,'P & L ASSUMPTIONS'!U70,'P & L ASSUMPTIONS'!AB70) -> 3424.996 | O24: =CHOOSE($I$1,'P & L ASSUMPTIONS'!O70,'P & L ASSUMPTIONS'!V70,'P & L ASSUMPTIONS'!AC70) -> 3477.628
B25: % of Total Income | C25: % | D25: =D24/D10 -> 0.042754352 | E25: =E24/E10 -> 0.037725211 | F25: =F24/F10 -> 0.035836525 | G25: =G24/G10 -> 0.036862321 | H25: =H24/H10 -> 0.031816031 | K25: =K24/K10 -> 0.035392291 | L25: =L24/L10 -> 0.036287543 | M25: =M24/M10 -> 0.036399961 | N25: =N24/N10 -> 0.036517239 | O25: =O24/O10 -> 0.036297636
B27: EBIT | C27: ₹ | D27: =D21-D24 -> 14699 | E27: =E21-E24 -> 14516 | F27: =F21-F24 -> 16280 | G27: =G21-G24 -> 16032 | H27: =H21-H24 -> 18946 | K27: =K21-K24 -> 19694.213 | L27: =L21-L24 -> 19635.885 | M27: =M21-M24 -> 19976.102 | N27: =N21-N24 -> 20326.835 | O27: =O21-O24 -> 20881.948
B28: % of Total Income | C28: % | D28: =D27/D10 -> 0.22745068 | E28: =E27/E10 -> 0.17791396 | F28: =F27/F10 -> 0.17467624 | G28: =G27/G10 -> 0.17345956 | H28: =H27/H10 -> 0.20378178 | K28: =K27/K10 -> 0.21342883 | L28: =L27/L10 -> 0.21437197 | M28: =M27/M10 -> 0.21552794 | N28: =N27/N10 -> 0.21672431 | O28: =O27/O10 -> 0.21795469
B30: Interest | C30: ₹ | D30: =STATEMENTS!C70 -> 509 | E30: =STATEMENTS!D70 -> 535 | F30: =STATEMENTS!E70 -> 1077 | G30: =STATEMENTS!F70 -> 1255 | H30: =STATEMENTS!G70 -> 1477 | K30: =CHOOSE($I$1,'P & L ASSUMPTIONS'!K82,'P & L ASSUMPTIONS'!R82,'P & L ASSUMPTIONS'!Y82) -> 1893.177 | L30: =CHOOSE($I$1,'P & L ASSUMPTIONS'!L82,'P & L ASSUMPTIONS'!S82,'P & L ASSUMPTIONS'!Z82) -> 1904.877 | M30: =CHOOSE($I$1,'P & L ASSUMPTIONS'!M82,'P & L ASSUMPTIONS'!T82,'P & L ASSUMPTIONS'!AA82) -> 1918.917 | N30: =CHOOSE($I$1,'P & L ASSUMPTIONS'!N82,'P & L ASSUMPTIONS'!U82,'P & L ASSUMPTIONS'!AB82) -> 1935.297 | O30: =CHOOSE($I$1,'P & L ASSUMPTIONS'!O82,'P & L ASSUMPTIONS'!V82,'P & L ASSUMPTIONS'!AC82) -> 1954.017
B32: EBT | C32: ₹ | D32: =D27-D30 -> 14190 | E32: =E27-E30 -> 13981 | F32: =F27-F30 -> 15203 | G32: =G27-G30 -> 14777 | H32: =H27-H30 -> 17469 | K32: =K27-K30 -> 17801.036 | L32: =L27-L30 -> 17731.008 | M32: =M27-M30 -> 18057.185 | N32: =N27-N30 -> 18391.538 | O32: =O27-O30 -> 18927.931
B33: % of Total Income | C33: % | D33: =D32/D10 -> 0.21957447 | E33: =E32/E10 -> 0.17135678 | F33: =F32/F10 -> 0.16312057 | G33: =G32/G10 -> 0.15988098 | H33: =H32/H10 -> 0.18789528 | K33: =K32/K10 -> 0.19291222 | L33: =L32/L10 -> 0.19357575 | M33: =M32/M10 -> 0.19482419 | N33: =N32/N10 -> 0.19609021 | O33: =O32/O10 -> 0.1975597
B35: Tax | C35: ₹ | D35: =STATEMENTS!C85 -> 3035 | E35: =STATEMENTS!D85 -> 2897 | F35: =STATEMENTS!E85 -> 3399 | G35: =STATEMENTS!F85 -> 3609 | H35: =STATEMENTS!G85 -> 4278 | K35: =CHOOSE($I$1,'P & L ASSUMPTIONS'!K99,'P & L ASSUMPTIONS'!R99,'P & L ASSUMPTIONS'!Y99) -> 4272.2487 | L35: =CHOOSE($I$1,'P & L ASSUMPTIONS'!L99,'P & L ASSUMPTIONS'!S99,'P & L ASSUMPTIONS'!Z99) -> 4255.4419 | M35: =CHOOSE($I$1,'P & L ASSUMPTIONS'!M99,'P & L ASSUMPTIONS'!T99,'P & L ASSUMPTIONS'!AA99) -> 4333.7245 | N35: =CHOOSE($I$1,'P & L ASSUMPTIONS'!N99,'P & L ASSUMPTIONS'!U99,'P & L ASSUMPTIONS'!AB99) -> 4413.9692 | O35: =CHOOSE($I$1,'P & L ASSUMPTIONS'!O99,'P & L ASSUMPTIONS'!V99,'P & L ASSUMPTIONS'!AC99) -> 4542.7035
B36: Effective Tax Rate | C36: % | D36: =D35/D32 -> 0.21388302 | E36: =E35/E32 -> 0.20720978 | F36: =F35/F32 -> 0.22357429 | G36: =G35/G32 -> 0.2442309 | H36: =H35/H32 -> 0.24489095 | K36: =K35/K32 -> 0.24 | L36: =L35/L32 -> 0.24 | M36: =M35/M32 -> 0.24 | N36: =N35/N32 -> 0.24 | O36: =O35/O32 -> 0.24
B38: Net Profit | C38: ₹ | D38: =D32-D35 -> 11155 | E38: =E32-E35 -> 11084 | F38: =F32-F35 -> 11804 | G38: =G32-G35 -> 11168 | H38: =H32-H35 -> 13191 | K38: =K32-K35 -> 13528.788 | L38: =L32-L35 -> 13475.566 | M38: =M32-M35 -> 13723.461 | N38: =N32-N35 -> 13977.569 | O38: =O32-O35 -> 14385.228
B39: % of Total Income | C39: % | D39: =D38/D10 -> 0.17261122 | E39: =E38/E10 -> 0.13584998 | F39: =F38/F10 -> 0.126651 | G39: =G38/G10 -> 0.12083311 | H39: =H38/H10 -> 0.14188143 | K39: =K38/K10 -> 0.14661328 | L39: =L38/L10 -> 0.14711757 | M39: =M38/M10 -> 0.14806638 | N39: =N38/N10 -> 0.14902856 | O39: =O38/O10 -> 0.15014537
B41: Weighted Avg. Outstanding Shares | C41: ₹ | D41: 1048.89 | E41: 1061.14 | F41: 548.9 | G41: 548.21 | H41: 566.17 | K41: =CHOOSE($I$1,'PROFIT & LOSS'!$H$41+$H$41*'P & L ASSUMPTIONS'!Y$49,'PROFIT & LOSS'!$H$41+'PROFIT & LOSS'!$H$41*'P & L ASSUMPTIONS'!Y$50,'PROFIT & LOSS'!$H$41+'PROFIT & LOSS'!$H$41*'P & L ASSUMPTIONS'!Y$51) -> 583.1551 | L41: =CHOOSE($I$1,K$41+K$41*'P & L ASSUMPTIONS'!Z$49,'PROFIT & LOSS'!K$41+'PROFIT & LOSS'!K$41*'P & L ASSUMPTIONS'!Z$50,'PROFIT & LOSS'!K$41+'PROFIT & LOSS'!K$41*'P & L ASSUMPTIONS'!Z$51) -> 600.64975 | M41: =CHOOSE($I$1,L$41+L$41*'P & L ASSUMPTIONS'!AA$49,'PROFIT & LOSS'!L$41+'PROFIT & LOSS'!L$41*'P & L ASSUMPTIONS'!AA$50,'PROFIT & LOSS'!L$41+'PROFIT & LOSS'!L$41*'P & L ASSUMPTIONS'!AA$51) -> 618.66925 | N41: =CHOOSE($I$1,M$41+M$41*'P & L ASSUMPTIONS'!AB$49,'PROFIT & LOSS'!M$41+'PROFIT & LOSS'!M$41*'P & L ASSUMPTIONS'!AB$50,'PROFIT & LOSS'!M$41+'PROFIT & LOSS'!M$41*'P & L ASSUMPTIONS'!AB$51) -> 637.22932 | O41: =CHOOSE($I$1,N$41+N$41*'P & L ASSUMPTIONS'!AC$49,'PROFIT & LOSS'!N$41+'PROFIT & LOSS'!N$41*'P & L ASSUMPTIONS'!AC$50,'PROFIT & LOSS'!N$41+'PROFIT & LOSS'!N$41*'P & L ASSUMPTIONS'!AC$51) -> 656.3462
B42: EPS | C42: ₹ | D42: =STATEMENTS!C90 -> 19.07 | E42: =STATEMENTS!D90 -> 22.31 | F42: =STATEMENTS!E90 -> 20.68 | G42: =STATEMENTS!F90 -> 10.41 | H42: =STATEMENTS!G90 -> 12.52 | K42: =K38/K41 -> 23.199296 | L42: =L38/L41 -> 22.434981 | M42: =M38/M41 -> 22.182226 | N42: =N38/N41 -> 21.934912 | O42: =O38/O41 -> 21.917134
B44: Dividend Paid | C44: ₹ | D44: =-STATEMENTS!C119 -> 546 | E44: =-STATEMENTS!D119 -> 547 | F44: =-STATEMENTS!E119 -> 3281 | G44: =-STATEMENTS!F119 -> 522 | H44: =-STATEMENTS!G119 -> 6275 | K44: =K38*K45 -> 2705.7575 | L44: =L38*L45 -> 3368.8915 | M44: =M38*M45 -> 4117.0383 | N44: =N38*N45 -> 4193.2708 | O44: =O38*O45 -> 4315.5683
B45: Dividend Payout Ratio | C45: % | D45: =D44/D38 -> 0.048946661 | E45: =E44/E38 -> 0.049350415 | F45: =F44/F38 -> 0.27795662 | G45: =G44/G38 -> 0.046740688 | H45: =H44/H38 -> 0.47570313 | K45: =CHOOSE($I$1,'P & L ASSUMPTIONS'!Y$43,'P & L ASSUMPTIONS'!Y$44,'P & L ASSUMPTIONS'!Y$45) -> 0.2 | L45: =CHOOSE($I$1,'P & L ASSUMPTIONS'!Z$43,'P & L ASSUMPTIONS'!Z$44,'P & L ASSUMPTIONS'!Z$45) -> 0.25 | M45: =CHOOSE($I$1,'P & L ASSUMPTIONS'!AA$43,'P & L ASSUMPTIONS'!AA$44,'P & L ASSUMPTIONS'!AA$45) -> 0.3 | N45: =CHOOSE($I$1,'P & L ASSUMPTIONS'!AB$43,'P & L ASSUMPTIONS'!AB$44,'P & L ASSUMPTIONS'!AB$45) -> 0.3 | O45: =CHOOSE($I$1,'P & L ASSUMPTIONS'!AC$43,'P & L ASSUMPTIONS'!AC$44,'P & L ASSUMPTIONS'!AC$45) -> 0.3
B47: Retained Earnings | C47: ₹ | D47: =D38-D44 -> 10609 | E47: =E38-E44 -> 10537 | F47: =F38-F44 -> 8523 | G47: =G38-G44 -> 10646 | H47: =H38-H44 -> 6916 | K47: =K38-K44 -> 10823.03 | L47: =L38-L44 -> 10106.674 | M47: =M38-M44 -> 9606.4226 | N47: =N38-N44 -> 9784.2984 | O47: =O38-O44 -> 10069.659
B48: % of Net Profit | C48: % | D48: =D47/D38 -> 0.95105334 | E48: =E47/E38 -> 0.95064958 | F48: =F47/F38 -> 0.72204338 | G48: =G47/G38 -> 0.95325931 | H48: =H47/H38 -> 0.52429687 | K48: =K47/K38 -> 0.8 | L48: =L47/L38 -> 0.75 | M48: =M47/M38 -> 0.7 | N48: =N47/N38 -> 0.7 | O48: =O47/O38 -> 0.7

Sheet BALANCE SHEET ASSUMPTION
B1: WIPRO | D1: BALANCE SHEET SCHEDULE | K1: BALANCE SHEET - FORECAST (BEST CASE) | R1: BALANCE SHEET - FORECAST (BASE CASE) | Y1: BALANCE SHEET - FORECAST (WORST CASE)
C3: UNIT | D3: Year 1 | E3: Year 2 | F3: Year 3 | G3: Year 4 | H3: Year 5 | K3: Year 6 | L3: Year 7 | M3: Year 8 | N3: Year 9 | O3: Year 10 | R3: Year 6 | S3: Year 7 | T3: Year 8 | U3: Year 9 | V3: Year 10 | Y3: Year 6 | Z3: Year 7 | AA3: Year 8 | AB3: Year 9 | AC3: Year 10
B4: Particulars | D4: ='PROFIT & LOSS'!D4 -> 44276 | E4: ='PROFIT & LOSS'!E4 -> 44641 | F4: ='PROFIT & LOSS'!F4 -> 45006 | G4: ='PROFIT & LOSS'!G4 -> 45372 | H4: ='PROFIT & LOSS'!H4 -> 45737 | K4: ='PROFIT & LOSS'!K4 -> 46102 | L4: ='PROFIT & LOSS'!L4 -> 46467 | M4: ='PROFIT & LOSS'!M4 -> 46833 | N4: ='PROFIT & LOSS'!N4 -> 47198 | O4: ='PROFIT & LOSS'!O4 -> 47563 | R4: =K$4 -> 46102 | S4: =L$4 -> 46467 | T4: =M$4 -> 46833 | U4: =N$4 -> 47198 | V4: =O$4 -> 47563 | Y4: =R$4 -> 46102 | Z4: =S$4 -> 46467 | AA4: =T$4 -> 46833 | AB4: =U$4 -> 47198 | AC4: =V$4 -> 47563
B6: PPE | K6: PPE - FORECAST (BEST CASE) | R6: PPE - FORECAST (BASE CASE) | Y6: PPE - FORECAST (WORST CASE)
B9: Opening Gross PPE | C9: ₹ | D9: =SUM('DATA SHEET'!I47:I53) -> 18395 | E9: =D15 -> 19902 | F9: =E15 -> 21461 | G9: =F15 -> 22865 | H9: =G15 -> 21752 | K9: =$H$15 -> 22523 | L9: =K$15 -> 23082.116 | M9: =L$15 -> 23608.426 | N9: =M$15 -> 24137.825 | O9: =N$15 -> 24671.231 | R9: =$K$9 -> 22523 | S9: =R15 -> 22766.024 | T9: =S15 -> 22950.427 | U9: =T15 -> 23141.865 | V9: =U15 -> 23339.785 | Y9: =$R$9 -> 22523 | Z9: =Y15 -> 22515.679 | AA9: =Z15 -> 22467.152 | AB9: =AA15 -> 22397.032 | AC9: =AB15 -> 22308.293
B10: Addition (CapEx) | C10: ₹ | D10: 3277 | E10: =('BALANCE SHEET'!E25-'BALANCE SHEET'!D25)+'PROFIT & LOSS'!E24 -> 3964 | F10: =('BALANCE SHEET'!F25-'BALANCE SHEET'!E25)+'PROFIT & LOSS'!F24 -> 4113 | G10: =('BALANCE SHEET'!G25-'BALANCE SHEET'!F25)+'PROFIT & LOSS'!G24 -> 2586 | H10: =('BALANCE SHEET'!H25-'BALANCE SHEET'!G25)+'PROFIT & LOSS'!H24 -> 3392 | K10: ='P & L ASSUMPTIONS'!K22*'BALANCE SHEET ASSUMPTION'!K11 -> 3149.2608 | L10: ='P & L ASSUMPTIONS'!L22*'BALANCE SHEET ASSUMPTION'!L11 -> 3180.7534 | M10: ='P & L ASSUMPTIONS'!M22*'BALANCE SHEET ASSUMPTION'!M11 -> 3244.3685 | N10: ='P & L ASSUMPTIONS'!N22*'BALANCE SHEET ASSUMPTION'!N11 -> 3309.2558 | O10: ='P & L ASSUMPTIONS'!O22*'BALANCE SHEET ASSUMPTION'!O11 -> 3408.5335 | R10: ='P & L ASSUMPTIONS'!R22*'BALANCE SHEET ASSUMPTION'!R11 -> 2945.7838 | S10: ='P & L ASSUMPTIONS'!S22*'BALANCE SHEET ASSUMPTION'!S11 -> 2916.326 | T10: ='P & L ASSUMPTIONS'!T22*'BALANCE SHEET ASSUMPTION'!T11 -> 2945.4892 | U10: ='P & L ASSUMPTIONS'!U22*'BALANCE SHEET ASSUMPTION'!U11 -> 2974.9441 | V10: ='P & L ASSUMPTIONS'!V22*'BALANCE SHEET ASSUMPTION'!V11 -> 3034.443 | Y10: ='P & L ASSUMPTIONS'!Y22*'BALANCE SHEET ASSUMPTION'!Y11 -> 2808.0538 | Z10: ='P & L ASSUMPTIONS'!Z22*'BALANCE SHEET ASSUMPTION'!Z11 -> 2765.933 | AA10: ='P & L ASSUMPTIONS'!AA22*'BALANCE SHEET ASSUMPTION'!AA11 -> 2738.2736 | AB10: ='P & L ASSUMPTIONS'!AB22*'BALANCE SHEET ASSUMPTION'!AB11 -> 2710.8909 | AC10: ='P & L ASSUMPTIONS'!AC22*'BALANCE SHEET ASSUMPTION'!AC11 -> 2737.9998
B11: % of Rev from OP | C11: % | D11: =D10/'PROFIT & LOSS'!D6 -> 0.052648491 | E11: =E10/'PROFIT & LOSS'!E6 -> 0.049843453 | F11: =F10/'PROFIT & LOSS'!F6 -> 0.045230109 | G11: =G10/'PROFIT & LOSS'!G6 -> 0.028799252 | H11: =H10/'PROFIT & LOSS'!H6 -> 0.038074713 | K11: =D72 -> 0.035 | L11: =E72 -> 0.035 | M11: =F72 -> 0.035 | N11: =G72 -> 0.035 | O11: =H72 -> 0.035 | R11: =D73 -> 0.0334 | S11: =E73 -> 0.0334 | T11: =F73 -> 0.0334 | U11: =G73 -> 0.0334 | V11: =H73 -> 0.0334 | Y11: =D74 -> 0.032 | Z11: =E74 -> 0.032 | AA11: =F74 -> 0.032 | AB11: =G74 -> 0.032 | AC11: =H74 -> 0.032
B12: Disposals | C12: ₹ | D12: =SUM(D9:D10)-D15 -> 1770 | E12: =SUM(E9:E10)-E15 -> 2405 | F12: =SUM(F9:F10)-F15 -> 2709 | G12: =SUM(G9:G10)-G15 -> 3699 | H12: =SUM(H9:H10)-H15 -> 2621 | K12: =K9*K13 -> 2590.145 | L12: =L9*L13 -> 2654.4433 | M12: =M9*M13 -> 2714.969 | N12: =N9*N13 -> 2775.8499 | O12: =O9*O13 -> 2837.1916 | R12: =R9*R13 -> 2702.76 | S12: =S9*S13 -> 2731.9229 | T12: =T9*T13 -> 2754.0512 | U12: =U9*U13 -> 2777.0238 | V12: =V9*V13 -> 2800.7742 | Y12: =Y9*Y13 -> 2815.375 | Z12: =Z9*Z13 -> 2814.4598 | AA12: =AA9*AA13 -> 2808.394 | AB12: =AB9*AB13 -> 2799.6289 | AC12: =AC9*AC13 -> 2788.5367
B13: % of Gross PPE | C13: % | D13: =D12/D9 -> 0.096221799 | E13: =E12/E9 -> 0.12084213 | F13: =F12/F9 -> 0.12622897 | G13: =G12/G9 -> 0.16177564 | H13: =H12/H9 -> 0.12049467 | K13: =K72 -> 0.115 | L13: =L72 -> 0.115 | M13: =M72 -> 0.115 | N13: =N72 -> 0.115 | O13: =O72 -> 0.115 | R13: =K73 -> 0.12 | S13: =L73 -> 0.12 | T13: =M73 -> 0.12 | U13: =N73 -> 0.12 | V13: =O73 -> 0.12 | Y13: =K74 -> 0.125 | Z13: =L74 -> 0.125 | AA13: =M74 -> 0.125 | AB13: =N74 -> 0.125 | AC13: =O74 -> 0.125
B15: Closing Gross PPE | C15: ₹ | D15: =D16+D18 -> 19902 | E15: =E16+E18 -> 21461 | F15: =F16+F18 -> 22865 | G15: =G16+G18 -> 21752 | H15: =H16+H18 -> 22523 | K15: =K9+K10-K12 -> 23082.116 | L15: =L9+L10-L12 -> 23608.426 | M15: =M9+M10-M12 -> 24137.825 | N15: =N9+N10-N12 -> 24671.231 | O15: =O9+O10-O12 -> 25242.573 | R15: =R9+R10-R12 -> 22766.024 | S15: =S9+S10-S12 -> 22950.427 | T15: =T9+T10-T12 -> 23141.865 | U15: =U9+U10-U12 -> 23339.785 | V15: =V9+V10-V12 -> 23573.454 | Y15: =Y9+Y10-Y12 -> 22515.679 | Z15: =Z9+Z10-Z12 -> 22467.152 | AA15: =AA9+AA10-AA12 -> 22397.032 | AB15: =AB9+AB10-AB12 -> 22308.293 | AC15: =AC9+AC10-AC12 -> 22257.757
B16: Closing Accumulated Depreciation | C16: ₹ | D16: ='P & L ASSUMPTIONS'!D$75 -> 13327 | E16: ='P & L ASSUMPTIONS'!E$75 -> 14000 | F16: ='P & L ASSUMPTIONS'!F$75 -> 14631 | G16: ='P & L ASSUMPTIONS'!G$75 -> 14339 | H16: ='P & L ASSUMPTIONS'!H$75 -> 14676 | K16: ='P & L ASSUMPTIONS'!K75 -> 15292.45 | L16: ='P & L ASSUMPTIONS'!L75 -> 14914.566 | M16: ='P & L ASSUMPTIONS'!M75 -> 15230.159 | N16: ='P & L ASSUMPTIONS'!N75 -> 15550.771 | O16: ='P & L ASSUMPTIONS'!O75 -> 16014.683 | R16: ='P & L ASSUMPTIONS'!R75 -> 15179.835 | S16: ='P & L ASSUMPTIONS'!S75 -> 14576.22 | T16: ='P & L ASSUMPTIONS'!T75 -> 14699.759 | U16: ='P & L ASSUMPTIONS'!U75 -> 14825.469 | V16: ='P & L ASSUMPTIONS'!V75 -> 15086.928 | Y16: ='P & L ASSUMPTIONS'!Y75 -> 14841.99 | Z16: ='P & L ASSUMPTIONS'!Z75 -> 14598.732 | AA16: ='P & L ASSUMPTIONS'!AA75 -> 14504.128 | AB16: ='P & L ASSUMPTIONS'!AB75 -> 14408.997 | AC16: ='P & L ASSUMPTIONS'!AC75 -> 14583.099
B18: Net PPE | C18: ₹ | D18: ='BALANCE SHEET'!D25 -> 6575 | E18: ='BALANCE SHEET'!E25 -> 7461 | F18: ='BALANCE SHEET'!F25 -> 8234 | G18: ='BALANCE SHEET'!G25 -> 7413 | H18: ='BALANCE SHEET'!H25 -> 7847 | K18: =K15-K16 -> 7789.6658 | L18: =L15-L16 -> 8693.8595 | M18: =M15-M16 -> 8907.6667 | N18: =N15-N16 -> 9120.4608 | O18: =O15-O16 -> 9227.8899 | R18: =R15-R16 -> 7586.1888 | S18: =S15-S16 -> 8374.2068 | T18: =T15-T16 -> 8442.1058 | U18: =U15-U16 -> 8514.3166 | V18: =V15-V16 -> 8486.5263 | Y18: =Y15-Y16 -> 7673.6888 | Z18: =Z15-Z16 -> 7868.42 | AA18: =AA15-AA16 -> 7892.9039 | AB18: =AB15-AB16 -> 7899.296 | AC18: =AC15-AC16 -> 7674.6575
B20: OTHER ASSETS | K20: OTHER ASSETS - FORECAST (BEST CASE) | R20: OTHER ASSETS - FORECAST (BASE CASE) | Y20: OTHER ASSETS - FORECAST (WORST CASE)
B23: Unbilled Receivables | C23: ₹ | D23: ='BALANCE SHEET'!D14 -> 2712 | E23: ='BALANCE SHEET'!E14 -> 6081 | F23: ='BALANCE SHEET'!F14 -> 6052 | G23: ='BALANCE SHEET'!G14 -> 5835 | H23: ='BALANCE SHEET'!H14 -> 6428 | K23: ='P & L ASSUMPTIONS'!K22*'BALANCE SHEET ASSUMPTION'!K24 -> 5398.7328 | L23: ='P & L ASSUMPTIONS'!L22*'BALANCE SHEET ASSUMPTION'!L24 -> 5452.7201 | M23: ='P & L ASSUMPTIONS'!M22*'BALANCE SHEET ASSUMPTION'!M24 -> 5561.7745 | N23: ='P & L ASSUMPTIONS'!N22*'BALANCE SHEET ASSUMPTION'!N24 -> 5673.01 | O23: ='P & L ASSUMPTIONS'!O22*'BALANCE SHEET ASSUMPTION'!O24 -> 5843.2003 | R23: ='P & L ASSUMPTIONS'!R22*'BALANCE SHEET ASSUMPTION'!R24 -> 5706.3537 | S23: ='P & L ASSUMPTIONS'!S22*'BALANCE SHEET ASSUMPTION'!S24 -> 5649.2901 | T23: ='P & L ASSUMPTIONS'!T22*'BALANCE SHEET ASSUMPTION'!T24 -> 5705.783 | U23: ='P & L ASSUMPTIONS'!U22*'BALANCE SHEET ASSUMPTION'!U24 -> 5762.8409 | V23: ='P & L ASSUMPTIONS'!V22*'BALANCE SHEET ASSUMPTION'!V24 -> 5878.0977 | Y23: ='P & L ASSUMPTIONS'!Y22*'BALANCE SHEET ASSUMPTION'!Y24 -> 6230.3693 | Z23: ='P & L ASSUMPTIONS'!Z22*'BALANCE SHEET ASSUMPTION'!Z24 -> 6136.9137 | AA23: ='P & L ASSUMPTIONS'!AA22*'BALANCE SHEET ASSUMPTION'!AA24 -> 6075.5446 | AB23: ='P & L ASSUMPTIONS'!AB22*'BALANCE SHEET ASSUMPTION'!AB24 -> 6014.7892 | AC23: ='P & L ASSUMPTIONS'!AC22*'BALANCE SHEET ASSUMPTION'!AC24 -> 6074.937
B24: % of Rev from OP | C24: % | D24: =D23/'PROFIT & LOSS'!D6 -> 0.043571165 | E24: =E23/'PROFIT & LOSS'!E6 -> 0.076462674 | F24: =F23/'PROFIT & LOSS'!F6 -> 0.066553032 | G24: =G23/'PROFIT & LOSS'!G6 -> 0.06498207 | H24: =H23/'PROFIT & LOSS'!H6 -> 0.072153376 | K24: 0.06 | L24: 0.06 | M24: 0.06 | N24: 0.06 | O24: 0.06 | R24: 0.0647 | S24: 0.0647 | T24: 0.0647 | U24: 0.0647 | V24: 0.0647 | Y24: 0.071 | Z24: 0.071 | AA24: 0.071 | AB24: 0.071 | AC24: 0.071
B26: Other Financial Assets | C26: ₹ | D26: ='BALANCE SHEET'!D16+'BALANCE SHEET'!D32 -> 1354 | E26: ='BALANCE SHEET'!E16+'BALANCE SHEET'!E32 -> 4899 | F26: ='BALANCE SHEET'!F16+'BALANCE SHEET'!F32 -> 1543 | G26: ='BALANCE SHEET'!G16+'BALANCE SHEET'!G32 -> 1609 | H26: ='BALANCE SHEET'!H16+'BALANCE SHEET'!H32 -> 1311 | K26: =K41*K27 -> 1881.9184 | L26: =L41*L27 -> 1904.8546 | M26: =M41*M27 -> 1946.443 | N26: =N41*N27 -> 1989.0726 | O26: =O41*O27 -> 2051.6868 | R26: =R41*R27 -> 1522.5428 | S26: =S41*S27 -> 1511.3548 | T26: =T41*T27 -> 1529.2945 | U26: =U41*U27 -> 1547.555 | V26: =V41*V27 -> 1580.843 | Y26: =Y41*Y27 -> 1285.0746 | Z26: =Z41*Z27 -> 1268.9087 | AA26: =AA41*AA27 -> 1259.1603 | AB26: =AB41*AB27 -> 1249.627 | AC26: =AC41*AC27 -> 1264.0316
B27: % of TI | C27: % | D27: =D26/D41 -> 0.020951644 | E27: =E26/E41 -> 0.060044123 | F27: =F26/F41 -> 0.016555616 | G27: =G26/G41 -> 0.01740871 | H27: =H26/H41 -> 0.01410102 | K27: =Y72 -> 0.02 | L27: =Z72 -> 0.02 | M27: =AA72 -> 0.02 | N27: =AB72 -> 0.02 | O27: =AC72 -> 0.02 | R27: =Y73 -> 0.0165 | S27: =Z73 -> 0.0165 | T27: =AA73 -> 0.0165 | U27: =AB73 -> 0.0165 | V27: =AC73 -> 0.0165 | Y27: =Y74 -> 0.014 | Z27: =Z74 -> 0.014 | AA27: =AA74 -> 0.014 | AB27: =AB74 -> 0.014 | AC27: =AC74 -> 0.014
B28: Current Financial Assets | C28: ₹ | D28: ='BALANCE SHEET'!D16 -> 745 | E28: ='BALANCE SHEET'!E16 -> 4291 | F28: ='BALANCE SHEET'!F16 -> 910 | G28: ='BALANCE SHEET'!G16 -> 1054 | H28: ='BALANCE SHEET'!H16 -> 845 | K28: =K26*K29 -> 1129.151 | L28: =L26*L29 -> 1142.9128 | M28: =M26*M29 -> 1167.8658 | N28: =N26*N29 -> 1193.4435 | O28: =O26*O29 -> 1231.0121 | R28: =R26*R29 -> 989.65281 | S28: =S26*S29 -> 982.3806 | T28: =T26*T29 -> 994.04143 | U28: =U26*U29 -> 1005.9107 | V28: =V26*V29 -> 1027.5479 | Y28: =Y26*Y29 -> 899.55219 | Z28: =Z26*Z29 -> 888.23612 | AA28: =AA26*AA29 -> 881.41222 | AB28: =AB26*AB29 -> 874.73889 | AC28: =AC26*AC29 -> 884.82214
B29: % of Total Financial Assets | C29: % | D29: =D28/D26 -> 0.55022157 | E29: =E28/E26 -> 0.87589304 | F29: =F28/F26 -> 0.58976021 | G29: =G28/G26 -> 0.65506526 | H29: =H28/H26 -> 0.64454615 | K29: =100%-K31 -> 0.6 | L29: =100%-L31 -> 0.6 | M29: =100%-M31 -> 0.6 | N29: =100%-N31 -> 0.6 | O29: =100%-O31 -> 0.6 | R29: =100%-R31 -> 0.65 | S29: =100%-S31 -> 0.65 | T29: =100%-T31 -> 0.65 | U29: =100%-U31 -> 0.65 | V29: =100%-V31 -> 0.65 | Y29: =100%-Y31 -> 0.7 | Z29: =100%-Z31 -> 0.7 | AA29: =100%-AA31 -> 0.7 | AB29: =100%-AB31 -> 0.7 | AC29: =100%-AC31 -> 0.7
B30: Non Current Financial Assets | C30: ₹ | D30: ='BALANCE SHEET'!D32 -> 609 | E30: ='BALANCE SHEET'!E32 -> 608 | F30: ='BALANCE SHEET'!F32 -> 633 | G30: ='BALANCE SHEET'!G32 -> 555 | H30: ='BALANCE SHEET'!H32 -> 466 | K30: =K26*K31 -> 752.76736 | L30: =L26*L31 -> 761.94185 | M30: =M26*M31 -> 778.57719 | N30: =N26*N31 -> 795.62902 | O30: =O26*O31 -> 820.67472 | R30: =R26*R31 -> 532.88997 | S30: =S26*S31 -> 528.97417 | T30: =T26*T31 -> 535.25308 | U30: =U26*U31 -> 541.64424 | V30: =V26*V31 -> 553.29504 | Y30: =Y26*Y31 -> 385.52237 | Z30: =Z26*Z31 -> 380.67262 | AA30: =AA26*AA31 -> 377.74809 | AB30: =AB26*AB31 -> 374.8881 | AC30: =AC26*AC31 -> 379.20949
B31: % of Total Financial Assets | C31: % | D31: =D30/D26 -> 0.44977843 | E31: =E30/E26 -> 0.12410696 | F31: =F30/F26 -> 0.41023979 | G31: =G30/G26 -> 0.34493474 | H31: =H30/H26 -> 0.35545385 | K31: 0.4 | L31: 0.4 | M31: 0.4 | N31: 0.4 | O31: 0.4 | R31: 0.35 | S31: 0.35 | T31: 0.35 | U31: 0.35 | V31: 0.35 | Y31: 0.3 | Z31: 0.3 | AA31: 0.3 | AB31: 0.3 | AC31: 0.3
B33: Current Tax Assets | C33: ₹ | D33: ='BALANCE SHEET'!D17 -> 246 | E33: ='BALANCE SHEET'!E17 -> 237 | F33: ='BALANCE SHEET'!F17 -> 509 | G33: ='BALANCE SHEET'!G17 -> 648 | H33: ='BALANCE SHEET'!H17 -> 642 | K33: =R$33+50 -> 650 | L33: =S$33+50 -> 680 | M33: =T$33+50 -> 710 | N33: =U$33+50 -> 740 | O33: =V$33+50 -> 770 | R33: 600 | S33: =R33+30 -> 630 | T33: =S33+30 -> 660 | U33: =T33+30 -> 690 | V33: =U33+30 -> 720 | Y33: =R33+10 -> 610 | Z33: =Y33+10 -> 620 | AA33: =Z33+10 -> 630 | AB33: =AA33+10 -> 640 | AC33: =AB33+10 -> 650
B35: Contract Assets | C35: ₹ | D35: ='BALANCE SHEET'!D18 -> 1651 | E35: ='BALANCE SHEET'!E18 -> 2065 | F35: ='BALANCE SHEET'!F18 -> 2300 | G35: ='BALANCE SHEET'!G18 -> 1985 | H35: ='BALANCE SHEET'!H18 -> 1580 | K35: ='P & L ASSUMPTIONS'!K22*'BALANCE SHEET ASSUMPTION'!K36 -> 1801.821 | L35: ='P & L ASSUMPTIONS'!L22*'BALANCE SHEET ASSUMPTION'!L36 -> 1819.8392 | M35: ='P & L ASSUMPTIONS'!M22*'BALANCE SHEET ASSUMPTION'!M36 -> 1856.236 | N35: ='P & L ASSUMPTIONS'!N22*'BALANCE SHEET ASSUMPTION'!N36 -> 1893.3607 | O35: ='P & L ASSUMPTIONS'!O22*'BALANCE SHEET ASSUMPTION'!O36 -> 1950.1615 | R35: ='P & L ASSUMPTIONS'!R22*'BALANCE SHEET ASSUMPTION'!R36 -> 2074.8313 | S35: ='P & L ASSUMPTIONS'!S22*'BALANCE SHEET ASSUMPTION'!S36 -> 2054.083 | T35: ='P & L ASSUMPTIONS'!T22*'BALANCE SHEET ASSUMPTION'!T36 -> 2074.6238 | U35: ='P & L ASSUMPTIONS'!U22*'BALANCE SHEET ASSUMPTION'!U36 -> 2095.37 | V35: ='P & L ASSUMPTIONS'!V22*'BALANCE SHEET ASSUMPTION'!V36 -> 2137.2774 | Y35: ='P & L ASSUMPTIONS'!Y22*'BALANCE SHEET ASSUMPTION'!Y36 -> 2371.4832 | Z35: ='P & L ASSUMPTIONS'!Z22*'BALANCE SHEET ASSUMPTION'!Z36 -> 2335.911 | AA35: ='P & L ASSUMPTIONS'!AA22*'BALANCE SHEET ASSUMPTION'!AA36 -> 2312.5518 | AB35: ='P & L ASSUMPTIONS'!AB22*'BALANCE SHEET ASSUMPTION'!AB36 -> 2289.4263 | AC35: ='P & L ASSUMPTIONS'!AC22*'BALANCE SHEET ASSUMPTION'!AC36 -> 2312.3206
B36: % of Rev from OP | C36: % | D36: =D35/'PROFIT & LOSS'!D6 -> 0.026525071 | E36: =E35/'PROFIT & LOSS'!E6 -> 0.025965371 | F36: =F35/'PROFIT & LOSS'!F6 -> 0.025292792 | G36: =G35/'PROFIT & LOSS'!G6 -> 0.022106154 | H36: =H35/'PROFIT & LOSS'!H6 -> 0.017735273 | K36: =R$36-0.35% -> 0.020024932 | L36: =S$36-0.35% -> 0.020024932 | M36: =T$36-0.35% -> 0.020024932 | N36: =U$36-0.35% -> 0.020024932 | O36: =V$36-0.35% -> 0.020024932 | R36: =AVERAGE(D36:H36) -> 0.023524932 | S36: =$R$36 -> 0.023524932 | T36: =$R$36 -> 0.023524932 | U36: =$R$36 -> 0.023524932 | V36: =$R$36 -> 0.023524932 | Y36: =R$36+0.35% -> 0.027024932 | Z36: =S$36+0.35% -> 0.027024932 | AA36: =T$36+0.35% -> 0.027024932 | AB36: =U$36+0.35% -> 0.027024932 | AC36: =V$36+0.35% -> 0.027024932
B38: CWIP & INVESTMENT | K38: CWIP & INVESTMENT - FORECAST (BEST CASE) | R38: CWIP & INVESTMENT - FORECAST (BASE CASE) | Y38: CWIP & INVESTMENT - FORECAST (WORST CASE)
B41: Total Income | C41: ₹ | D41: ='PROFIT & LOSS'!D10 -> 64625 | E41: ='PROFIT & LOSS'!E10 -> 81590 | F41: ='PROFIT & LOSS'!F10 -> 93201 | G41: ='PROFIT & LOSS'!G10 -> 92425 | H41: ='PROFIT & LOSS'!H10 -> 92972 | K41: ='P & L ASSUMPTIONS'!K6 -> 94095.92 | L41: ='P & L ASSUMPTIONS'!L6 -> 95242.731 | M41: ='P & L ASSUMPTIONS'!M6 -> 97322.148 | N41: ='P & L ASSUMPTIONS'!N6 -> 99453.628 | O41: ='P & L ASSUMPTIONS'!O6 -> 102584.34 | R41: ='P & L ASSUMPTIONS'!R6 -> 92275.32 | S41: ='P & L ASSUMPTIONS'!S6 -> 91597.259 | T41: ='P & L ASSUMPTIONS'!T6 -> 92684.516 | U41: ='P & L ASSUMPTIONS'!U6 -> 93791.21 | V41: ='P & L ASSUMPTIONS'!V6 -> 95808.665 | Y41: ='P & L ASSUMPTIONS'!Y6 -> 91791.04 | Z41: ='P & L ASSUMPTIONS'!Z6 -> 90636.339 | AA41: ='P & L ASSUMPTIONS'!AA6 -> 89940.023 | AB41: ='P & L ASSUMPTIONS'!AB6 -> 89259.071 | AC41: ='P & L ASSUMPTIONS'!AC6 -> 90287.974
B43: CWIP | C43: ₹ | D43: ='BALANCE SHEET'!D27 -> 1853 | E43: ='BALANCE SHEET'!E27 -> 1602 | F43: ='BALANCE SHEET'!F27 -> 617 | G43: ='BALANCE SHEET'!G27 -> 723 | H43: ='BALANCE SHEET'!H27 -> 196 | K43: =K10*K44 -> 629.85216 | L43: =L10*L44 -> 477.11301 | M43: =M10*M44 -> 324.43685 | N43: =N10*N44 -> 165.46279 | O43: =O10*O44 -> 170.42668 | R43: =R10*R44 -> 736.44595 | S43: =S10*S44 -> 874.89779 | T43: =T10*T44 -> 736.37231 | U43: =U10*U44 -> 446.24162 | V43: =V10*V44 -> 303.4443 | Y43: =Y10*Y44 -> 842.41613 | Z43: =Z10*Z44 -> 1106.3732 | AA43: =AA10*AA44 -> 958.39577 | AB43: =AB10*AB44 -> 677.72272 | AC43: =AC10*AC44 -> 410.69997
B44: % of CapEx | C44: % | D44: =D43/D10 -> 0.56545621 | E44: =E43/E10 -> 0.40413724 | F44: =F43/F10 -> 0.15001216 | G44: =G43/G10 -> 0.27958237 | H44: =H43/H10 -> 0.057783019 | K44: =R72 -> 0.2 | L44: =S72 -> 0.15 | M44: =T72 -> 0.1 | N44: =U72 -> 0.05 | O44: =V72 -> 0.05 | R44: =R73 -> 0.25 | S44: =S73 -> 0.3 | T44: =T73 -> 0.25 | U44: =U73 -> 0.15 | V44: =V73 -> 0.1 | Y44: =R74 -> 0.3 | Z44: =S74 -> 0.4 | AA44: =T74 -> 0.35 | AB44: =U74 -> 0.25 | AC44: =V74 -> 0.15
B46: ROU Assets | C46: ₹ | D46: ='BALANCE SHEET'!D26 -> 1642 | E46: ='BALANCE SHEET'!E26 -> 1887 | F46: ='BALANCE SHEET'!F26 -> 1870 | G46: ='BALANCE SHEET'!G26 -> 1796 | H46: ='BALANCE SHEET'!H26 -> 2560 | K46: =K41*K47 -> 2352.398 | L46: =L41*L47 -> 2476.311 | M46: =M41*M47 -> 2627.698 | N46: =N41*N47 -> 2585.7943 | O46: =O41*O47 -> 2667.1928 | R46: =R41*R47 -> 2122.3324 | S46: =S41*S47 -> 2198.3342 | T46: =T41*T47 -> 2131.7439 | U46: =U41*U47 -> 2250.989 | V46: =V41*V47 -> 2203.5993 | Y46: =Y41*Y47 -> 1927.6118 | Z46: =Z41*Z47 -> 1903.3631 | AA46: =AA41*AA47 -> 1978.6805 | AB46: =AB41*AB47 -> 1963.6996 | AC46: =AC41*AC47 -> 1986.3354
B47: % of TI | C47: % | D47: =D46/D41 -> 0.025408124 | E47: =E46/E41 -> 0.023127834 | F47: =F46/F41 -> 0.020064162 | G47: =G46/G41 -> 0.019431972 | H47: =H46/H41 -> 0.027535172 | K47: =K78 -> 0.025 | L47: =L78 -> 0.026 | M47: =M78 -> 0.027 | N47: =N78 -> 0.026 | O47: =O78 -> 0.026 | R47: =K79 -> 0.023 | S47: =L79 -> 0.024 | T47: =M79 -> 0.023 | U47: =N79 -> 0.024 | V47: =O79 -> 0.023 | Y47: =K80 -> 0.021 | Z47: =L80 -> 0.021 | AA47: =M80 -> 0.022 | AB47: =N80 -> 0.022 | AC47: =O80 -> 0.022
B49: Goodwill | C49: ₹ | D49: ='BALANCE SHEET'!D28 -> 13515 | E49: ='BALANCE SHEET'!E28 -> 24286 | F49: ='BALANCE SHEET'!F28 -> 30349 | G49: ='BALANCE SHEET'!G28 -> 31145 | H49: ='BALANCE SHEET'!H28 -> 32035 | K49: =$H$49+($H$49*$K$50) -> 33316.4 | L49: =K$49+(K$49*L$50) -> 34649.056 | M49: =L$49+(L$49*M$50) -> 36035.018 | N49: =M$49+(M$49*N$50) -> 37476.419 | O49: =N$49+(N$49*O$50) -> 38975.476 | R49: =$H$49+($H$49*$R$50) -> 32899.945 | S49: =R$49+(R$49*S$50) -> 33788.244 | T49: =S$49+(S$49*T$50) -> 34700.526 | U49: =T$49+(T$49*U$50) -> 35637.44 | V49: =U$49+(U$49*V$50) -> 36599.651 | Y49: =$H$49+($H$49*$Y$50) -> 32515.525 | Z49: =Y$49+(Y$49*Z$50) -> 33003.258 | AA49: =Z$49+(Z$49*AA$50) -> 33498.307 | AB49: =AA$49+(AA$49*AB$50) -> 34000.781 | AC49: =AB$49+(AB$49*AC$50) -> 34510.793
B50: YoY Growth | C50: % | D50: N/A | E50: =E49/D49-1 -> 0.79696633 | F50: =F49/E49-1 -> 0.24965 | G50: =G49/F49-1 -> 0.026228212 | H50: =H49/G49-1 -> 0.028576015 | K50: =K90 -> 0.04 | L50: =L90 -> 0.04 | M50: =M90 -> 0.04 | N50: =N90 -> 0.04 | O50: =O90 -> 0.04 | R50: =K91 -> 0.027 | S50: =L91 -> 0.027 | T50: =M91 -> 0.027 | U50: =N91 -> 0.027 | V50: =O91 -> 0.027 | Y50: =K92 -> 0.015 | Z50: =L92 -> 0.015 | AA50: =M92 -> 0.015 | AB50: =N92 -> 0.015 | AC50: =O92 -> 0.015
B52: Current Investments | C52: ₹ | D52: ='BALANCE SHEET'!D11 -> 17571 | E52: ='BALANCE SHEET'!E11 -> 24166 | F52: ='BALANCE SHEET'!F11 -> 30923 | G52: ='BALANCE SHEET'!G11 -> 31117 | H52: ='BALANCE SHEET'!H11 -> 41147 | K52: 48000 | L52: 53000 | M52: 60000 | N52: 67000 | O52: 74000 | R52: 48000 | S52: 53000 | T52: 59000 | U52: 66000 | V52: 73000 | Y52: 46000 | Z52: 51000 | AA52: 56000 | AB52: 62000 | AC52: 68000
B53: YoY Change | C53: % | D53: N/A | E53: =E52/D52-1 -> 0.37533436 | F53: =F52/E52-1 -> 0.27960771 | G53: =G52/F52-1 -> 0.0062736474 | H53: =H52/G52-1 -> 0.32233184 | K53: =K52/H52-1 -> 0.1665492 | L53: =L52/K52-1 -> 0.10416667 | M53: =M52/L52-1 -> 0.13207547 | N53: =N52/M52-1 -> 0.11666667 | O53: =O52/N52-1 -> 0.10447761 | R53: =R52/H52-1 -> 0.1665492 | S53: =S52/R52-1 -> 0.10416667 | T53: =T52/S52-1 -> 0.11320755 | U53: =U52/T52-1 -> 0.11864407 | V53: =V52/U52-1 -> 0.10606061 | Y53: =Y52/H52-1 -> 0.11794298 | Z53: =Z52/Y52-1 -> 0.10869565 | AA53: =AA52/Z52-1 -> 0.098039216 | AB53: =AB52/AA52-1 -> 0.10714286 | AC53: =AC52/AB52-1 -> 0.096774194
B55: Intangiable Assets | C55: ₹ | D55: ='BALANCE SHEET'!D29 -> 1309 | E55: ='BALANCE SHEET'!E29 -> 4356 | F55: ='BALANCE SHEET'!F29 -> 4305 | G55: ='BALANCE SHEET'!G29 -> 3275 | H55: ='BALANCE SHEET'!H29 -> 2745 | K55: =K41*K56 -> 3011.0694 | L55: =L41*L56 -> 3238.2529 | M55: =M41*M56 -> 3503.5973 | N55: =N41*N56 -> 3779.2378 | O55: =O41*O56 -> 4103.3736 | R55: =R41*R56 -> 2768.2596 | S55: =S41*S56 -> 2747.9178 | T55: =T41*T56 -> 2780.5355 | U55: =U41*U56 -> 3001.3187 | V55: =V41*V56 -> 3065.8773 | Y55: =Y41*Y56 -> 2570.1491 | Z55: =Z41*Z56 -> 2537.8175 | AA55: =AA41*AA56 -> 2518.3206 | AB55: =AB41*AB56 -> 2677.7721 | AC55: =AC41*AC56 -> 2708.6392
B56: % of TI | C56: % | D56: =D55/D41 -> 0.020255319 | E56: =E55/E41 -> 0.053388896 | F56: =F55/F41 -> 0.046190492 | G56: =G55/G41 -> 0.035434136 | H56: =H55/H41 -> 0.029525018 | K56: =D84 -> 0.032 | L56: =E84 -> 0.034 | M56: =F84 -> 0.036 | N56: =G84 -> 0.038 | O56: =H84 -> 0.04 | R56: =D85 -> 0.03 | S56: =E85 -> 0.03 | T56: =F85 -> 0.03 | U56: =G85 -> 0.032 | V56: =H85 -> 0.032 | Y56: =D86 -> 0.028 | Z56: =E86 -> 0.028 | AA56: =F86 -> 0.028 | AB56: =G86 -> 0.03 | AC56: =H86 -> 0.03
B58: Non Current Investments | C58: ₹ | D58: ='BALANCE SHEET'!D30 -> 1058 | E58: ='BALANCE SHEET'!E30 -> 1911 | F58: ='BALANCE SHEET'!F30 -> 2072 | G58: ='BALANCE SHEET'!G30 -> 2163 | H58: ='BALANCE SHEET'!H30 -> 2646 | K58: =H58+120 -> 2766 | L58: =K58+120 -> 2886 | M58: =L58+120 -> 3006 | N58: =M58+120 -> 3126 | O58: =N58+120 -> 3246 | R58: =H58+100 -> 2746 | S58: =R58+100 -> 2846 | T58: =S58+100 -> 2946 | U58: =T58+100 -> 3046 | V58: =U58+100 -> 3146 | Y58: =H58+50 -> 2696 | Z58: =Y58+50 -> 2746 | AA58: =Z58+50 -> 2796 | AB58: =AA58+50 -> 2846 | AC58: =AB58+50 -> 2896
B59: YoY Change | C59: % | D59: N/A | E59: =E58/D58-1 -> 0.80623819 | F59: =F58/E58-1 -> 0.084249084 | G59: =G58/F58-1 -> 0.043918919 | H59: =H58/G58-1 -> 0.22330097 | K59: =K58/H58-1 -> 0.045351474 | L59: =L58/K58-1 -> 0.043383948 | M59: =M58/L58-1 -> 0.041580042 | N59: =N58/M58-1 -> 0.03992016 | O59: =O58/N58-1 -> 0.038387716 | R59: =R58/H58-1 -> 0.037792895 | S59: =S58/R58-1 -> 0.036416606 | T59: =T58/S58-1 -> 0.035137034 | U59: =U58/T58-1 -> 0.033944331 | V59: =V58/U58-1 -> 0.032829941 | Y59: =Y58/H58-1 -> 0.018896447 | Z59: =Z58/Y58-1 -> 0.018545994 | AA59: =AA58/Z58-1 -> 0.018208303 | AB59: =AB58/AA58-1 -> 0.01788269 | AC59: =AC58/AB58-1 -> 0.017568517
B61: Non Current Tax Assets | C61: ₹ | D61: ='BALANCE SHEET'!D34 -> 1432 | E61: ='BALANCE SHEET'!E34 -> 1026 | F61: ='BALANCE SHEET'!F34 -> 1192 | G61: ='BALANCE SHEET'!G34 -> 904 | H61: ='BALANCE SHEET'!H34 -> 723 | K61: ='P & L ASSUMPTIONS'!K99*'BALANCE SHEET ASSUMPTION'!K62 -> 581.71476 | L61: ='P & L ASSUMPTIONS'!L99*'BALANCE SHEET ASSUMPTION'!L62 -> 455.60576 | M61: ='P & L ASSUMPTIONS'!M99*'BALANCE SHEET ASSUMPTION'!M62 -> 422.1028 | N61: ='P & L ASSUMPTIONS'!N99*'BALANCE SHEET ASSUMPTION'!N62 -> 386.31788 | O61: ='P & L ASSUMPTIONS'!O99*'BALANCE SHEET ASSUMPTION'!O62 -> 351.44539 | R61: ='P & L ASSUMPTIONS'!R99*'BALANCE SHEET ASSUMPTION'!R62 -> 598.11482 | S61: ='P & L ASSUMPTIONS'!S99*'BALANCE SHEET ASSUMPTION'!S62 -> 510.65303 | T61: ='P & L ASSUMPTIONS'!T99*'BALANCE SHEET ASSUMPTION'!T62 -> 433.37245 | U61: ='P & L ASSUMPTIONS'!U99*'BALANCE SHEET ASSUMPTION'!U62 -> 397.25723 | V61: ='P & L ASSUMPTIONS'!V99*'BALANCE SHEET ASSUMPTION'!V62 -> 363.41628 | Y61: ='P & L ASSUMPTIONS'!Y99*'BALANCE SHEET ASSUMPTION'!Y62 -> 792.82858 | Z61: ='P & L ASSUMPTIONS'!Z99*'BALANCE SHEET ASSUMPTION'!Z62 -> 785.01133 | AA61: ='P & L ASSUMPTIONS'!AA99*'BALANCE SHEET ASSUMPTION'!AA62 -> 781.51574 | AB61: ='P & L ASSUMPTIONS'!AB99*'BALANCE SHEET ASSUMPTION'!AB62 -> 777.93988 | AC61: ='P & L ASSUMPTIONS'!AC99*'BALANCE SHEET ASSUMPTION'!AC62 -> 790.69681
B62: % of Tax Expense | C62: % | D62: =D61/'PROFIT & LOSS'!D35 -> 0.47182867 | E62: =E61/'PROFIT & LOSS'!E35 -> 0.35415948 | F62: =F61/'PROFIT & LOSS'!F35 -> 0.35069138 | G62: =G61/'PROFIT & LOSS'!G35 -> 0.2504849 | H62: =H61/'PROFIT & LOSS'!H35 -> 0.16900421 | K62: =Y84 -> 0.13 | L62: =Z84 -> 0.1 | M62: =AA84 -> 0.09 | N62: =AB84 -> 0.08 | O62: =AC84 -> 0.07 | R62: =Y85 -> 0.14 | S62: =Z85 -> 0.12 | T62: =AA85 -> 0.1 | U62: =AB85 -> 0.09 | V62: =AC85 -> 0.08 | Y62: =Y86 -> 0.19 | Z62: =Z86 -> 0.19 | AA62: =AA86 -> 0.19 | AB62: =AB86 -> 0.19 | AC62: =AC86 -> 0.19
B64: Other Fixed Assets | C64: ₹ | D64: ='BALANCE SHEET'!D35 -> 1671 | E64: ='BALANCE SHEET'!E35 -> 1510 | F64: ='BALANCE SHEET'!F35 -> 1376 | G64: ='BALANCE SHEET'!G35 -> 1058 | H64: ='BALANCE SHEET'!H35 -> 771 | K64: =K18*K65 -> 778.96658 | L64: =L18*L65 -> 869.38595 | M64: =M18*M65 -> 890.76667 | N64: =N18*N65 -> 912.04608 | O64: =O18*O65 -> 922.78899 | R64: =R18*R65 -> 682.75699 | S64: =S18*S65 -> 753.67862 | T64: =T18*T65 -> 759.78952 | U64: =U18*U65 -> 766.28849 | V64: =V18*V65 -> 763.78737 | Y64: =Y18*Y65 -> 613.8951 | Z64: =Z18*Z65 -> 629.4736 | AA64: =AA18*AA65 -> 631.43231 | AB64: =AB18*AB65 -> 631.94368 | AC64: =AC18*AC65 -> 613.9726
B65: % of Net PPE | C65: % | D65: =D64/D18 -> 0.25414449 | E65: =E64/E18 -> 0.20238574 | F65: =F64/F18 -> 0.16711197 | G65: =G64/G18 -> 0.14272224 | H65: =H64/H18 -> 0.09825411 | K65: =D78 -> 0.1 | L65: =E78 -> 0.1 | M65: =F78 -> 0.1 | N65: =G78 -> 0.1 | O65: =H78 -> 0.1 | R65: =D79 -> 0.09 | S65: =E79 -> 0.09 | T65: =F79 -> 0.09 | U65: =G79 -> 0.09 | V65: =H79 -> 0.09 | Y65: =D80 -> 0.08 | Z65: =E80 -> 0.08 | AA65: =F80 -> 0.08 | AB65: =G80 -> 0.08 | AC65: =H80 -> 0.08
D66: Capex Assumption & Other Fixed ; Intangiable Assets, Ac. Receivables | K66: Disposal Assumption , ROU, Lease L., Goodwill | R66: CWIP Assumption, AR Days (Non Current), Other Current Assets, Inventory | Y66: Other Financial Assets, Provisions, Tax, AP Days
B67: ASSUMPTIONS
D68: Year 1 | E68: Year 2 | F68: Year 3 | G68: Year 4 | H68: Year 5 | K68: Year 1 | L68: Year 2 | M68: Year 3 | N68: Year 4 | O68: Year 5 | R68: Year 1 | S68: Year 2 | T68: Year 3 | U68: Year 4 | V68: Year 5 | Y68: Year 1 | Z68: Year 2 | AA68: Year 3 | AB68: Year 4 | AC68: Year 5
B70: Capex % of Revenue | K70: Disposal | R70: CWIP % of Cex | Y70: OFA % of TI
B72: Best Case | C72: % | D72: 0.035 | E72: 0.035 | F72: 0.035 | G72: 0.035 | H72: 0.035 | K72: 0.115 | L72: 0.115 | M72: 0.115 | N72: 0.115 | O72: 0.115 | R72: 0.2 | S72: 0.15 | T72: 0.1 | U72: 0.05 | V72: 0.05 | Y72: 0.02 | Z72: 0.02 | AA72: 0.02 | AB72: 0.02 | AC72: 0.02
B73: Base Case | C73: % | D73: 0.0334 | E73: 0.0334 | F73: 0.0334 | G73: 0.0334 | H73: 0.0334 | K73: 0.12 | L73: 0.12 | M73: 0.12 | N73: 0.12 | O73: 0.12 | R73: 0.25 | S73: 0.3 | T73: 0.25 | U73: 0.15 | V73: 0.1 | Y73: 0.0165 | Z73: 0.0165 | AA73: 0.0165 | AB73: 0.0165 | AC73: 0.0165
B74: Worst Case | C74: % | D74: 0.032 | E74: 0.032 | F74: 0.032 | G74: 0.032 | H74: 0.032 | K74: 0.125 | L74: 0.125 | M74: 0.125 | N74: 0.125 | O74: 0.125 | R74: 0.3 | S74: 0.4 | T74: 0.35 | U74: 0.25 | V74: 0.15 | Y74: 0.014 | Z74: 0.014 | AA74: 0.014 | AB74: 0.014 | AC74: 0.014
B76: Other Fixed Assets % of Net PPE | K76: ROU % of TI | R76: AR Days (Non) | Y76: Pro. % of TI
B78: Best Case | C78: % | D78: 0.1 | E78: 0.1 | F78: 0.1 | G78: 0.1 | H78: 0.1 | K78: 0.025 | L78: 0.026 | M78: 0.027 | N78: 0.026 | O78: 0.026 | R78: 0.0005 | S78: 0.001 | T78: 0.0015 | U78: 0.002 | V78: 0.0025 | Y78: 0.024 | Z78: 0.024 | AA78: 0.024 | AB78: 0.024 | AC78: 0.024
B79: Base Case | C79: % | D79: 0.09 | E79: 0.09 | F79: 0.09 | G79: 0.09 | H79: 0.09 | K79: 0.023 | L79: 0.024 | M79: 0.023 | N79: 0.024 | O79: 0.023 | R79: 0.001 | S79: 0.0015 | T79: 0.002 | U79: 0.0025 | V79: 0.003 | Y79: 0.0249 | Z79: 0.0249 | AA79: 0.0249 | AB79: 0.0249 | AC79: 0.0249
B80: Worst Case | C80: % | D80: 0.08 | E80: 0.08 | F80: 0.08 | G80: 0.08 | H80: 0.08 | K80: 0.021 | L80: 0.021 | M80: 0.022 | N80: 0.022 | O80: 0.022 | R80: 0.0015 | S80: 0.002 | T80: 0.0025 | U80: 0.0035 | V80: 0.004 | Y80: 0.026 | Z80: 0.026 | AA80: 0.026 | AB80: 0.026 | AC80: 0.026
B82: Intangiable Assets % of TI | K82: Lea. % of TI | R82: OCA % of TI | Y82: Tax Ass. % Ex.
B84: Best Case | C84: % | D84: 0.032 | E84: 0.034 | F84: 0.036 | G84: 0.038 | H84: 0.04 | K84: 0.032 | L84: 0.033 | M84: 0.034 | N84: 0.035 | O84: 0.037 | R84: 0.03 | S84: 0.03 | T84: 0.03 | U84: 0.03 | V84: 0.03 | Y84: 0.13 | Z84: 0.1 | AA84: 0.09 | AB84: 0.08 | AC84: 0.07
B85: Base Case | C85: % | D85: 0.03 | E85: 0.03 | F85: 0.03 | G85: 0.032 | H85: 0.032 | K85: 0.03 | L85: 0.031 | M85: 0.032 | N85: 0.033 | O85: 0.035 | R85: 0.0346 | S85: 0.0346 | T85: 0.0346 | U85: 0.0346 | V85: 0.0346 | Y85: 0.14 | Z85: 0.12 | AA85: 0.1 | AB85: 0.09 | AC85: 0.08
B86: Worst Case | C86: % | D86: 0.028 | E86: 0.028 | F86: 0.028 | G86: 0.03 | H86: 0.03 | K86: 0.028 | L86: 0.028 | M86: 0.03 | N86: 0.03 | O86: 0.032 | R86: 0.04 | S86: 0.04 | T86: 0.04 | U86: 0.04 | V86: 0.04 | Y86: 0.19 | Z86: 0.19 | AA86: 0.19 | AB86: 0.19 | AC86: 0.19
B88: Accounts Receivable Days (Current) | K88: Goodwill YoY | R88: Inventory Days | Y88: AP Days
B90: Best Case | C90: D / % | D90: 43 | E90: 42 | F90: 40 | G90: 39 | H90: 37 | K90: 0.04 | L90: 0.04 | M90: 0.04 | N90: 0.04 | O90: 0.04 | R90: 1 | S90: 1 | T90: 1 | U90: 1 | V90: 1 | Y90: 35 | Z90: 35 | AA90: 35 | AB90: 35 | AC90: 35
B91: Base Case | C91: D / % | D91: 45 | E91: 44 | F91: 42 | G91: 41 | H91: 40 | K91: 0.027 | L91: 0.027 | M91: 0.027 | N91: 0.027 | O91: 0.027 | R91: 1 | S91: 1 | T91: 1 | U91: 1 | V91: 1 | Y91: 33 | Z91: 33 | AA91: 33 | AB91: 33 | AC91: 33
B92: Worst Case | C92: D / % | D92: 46 | E92: 47 | F92: 48 | G92: 49 | H92: 50 | K92: 0.015 | L92: 0.015 | M92: 0.015 | N92: 0.015 | O92: 0.015 | R92: 1 | S92: 1 | T92: 1 | U92: 1 | V92: 1 | Y92: 31 | Z92: 31 | AA92: 31 | AB92: 31 | AC92: 31
B94: TRADE WORKING CAPITAL | K94: TRADE WORKING CAPITAL - FORECAST (BEST CASE) | R94: TRADE WORKING CAPITAL - FORECAST (BASE CASE) | Y94: TRADE WORKING CAPITAL - FORECAST (WORST CASE)
B97: COGS | C97: ₹ | D97: ='P & L ASSUMPTIONS'!D56 -> 44351 | E97: ='P & L ASSUMPTIONS'!E56 -> 59072 | F97: ='P & L ASSUMPTIONS'!F56 -> 67302 | G97: ='P & L ASSUMPTIONS'!G56 -> 67100 | H97: ='P & L ASSUMPTIONS'!H56 -> 65287 | K97: ='P & L ASSUMPTIONS'!K56 -> 63885.005 | L97: ='P & L ASSUMPTIONS'!L56 -> 64523.855 | M97: ='P & L ASSUMPTIONS'!M56 -> 65814.332 | N97: ='P & L ASSUMPTIONS'!N56 -> 67130.619 | O97: ='P & L ASSUMPTIONS'!O56 -> 69144.537 | R97: ='P & L ASSUMPTIONS'!R56 -> 63501.926 | S97: ='P & L ASSUMPTIONS'!S56 -> 62866.907 | T97: ='P & L ASSUMPTIONS'!T56 -> 63495.576 | U97: ='P & L ASSUMPTIONS'!U56 -> 64130.532 | V97: ='P & L ASSUMPTIONS'!V56 -> 65413.143 | Y97: ='P & L ASSUMPTIONS'!Y56 -> 64058.726 | Z97: ='P & L ASSUMPTIONS'!Z56 -> 63097.846 | AA97: ='P & L ASSUMPTIONS'!AA56 -> 62466.867 | AB97: ='P & L ASSUMPTIONS'!AB56 -> 61842.198 | AC97: ='P & L ASSUMPTIONS'!AC56 -> 62460.62
B99: Accounts Receivable (Current) | C99: ₹ | D99: ='BALANCE SHEET'!D13 -> 9430 | E99: ='BALANCE SHEET'!E13 -> 11522 | F99: ='BALANCE SHEET'!F13 -> 12635 | G99: ='BALANCE SHEET'!G13 -> 11548 | H99: ='BALANCE SHEET'!H13 -> 11745 | K99: =(D$90*K$41)/365 -> 11085.273 | L99: =(E$90*L$41)/365 -> 10959.438 | M99: =(F$90*M$41)/365 -> 10665.441 | N99: =(G$90*N$41)/365 -> 10626.552 | O99: =(H$90*O$41)/365 -> 10398.961 | R99: =(D$91*R$41)/365 -> 11376.409 | S99: =(E$91*S$41)/365 -> 11041.861 | T99: =(F$91*T$41)/365 -> 10665.068 | U99: =(G$91*U$41)/365 -> 10535.451 | V99: =(H$91*V$41)/365 -> 10499.58 | Y99: =(D$92*Y$41)/365 -> 11568.186 | Z99: =(E$92*Z$41)/365 -> 11670.981 | AA99: =(F$92*AA$41)/365 -> 11827.729 | AB99: =(G$92*AB$41)/365 -> 11982.725 | AC99: =(H$92*AC$41)/365 -> 12368.216
B100: AR Days | C100: D | D100: N/A | E100: ='RATIO ANALYSIS'!D30 -> 61.43245 | F100: ='RATIO ANALYSIS'!E30 -> 55.434527 | G100: ='RATIO ANALYSIS'!F30 -> 48.53354 | H100: ='RATIO ANALYSIS'!G30 -> 47.341387 | K100: =D90 -> 43 | L100: =E90 -> 42 | M100: =F90 -> 40 | N100: =G90 -> 39 | O100: =H90 -> 37 | R100: =D91 -> 45 | S100: =E91 -> 44 | T100: =F91 -> 42 | U100: =G91 -> 41 | V100: =H91 -> 40 | Y100: =D92 -> 46 | Z100: =E92 -> 47 | AA100: =F92 -> 48 | AB100: =G92 -> 49 | AC100: =H92 -> 50
B102: Accounts Receivable (Non Current) | C102: ₹ | D102: ='BALANCE SHEET'!D31 -> 436 | E102: ='BALANCE SHEET'!E31 -> 476 | F102: ='BALANCE SHEET'!F31 -> 86 | G102: ='BALANCE SHEET'!G31 -> 405 | H102: ='BALANCE SHEET'!H31 -> 30 | K102: =K41*K103 -> 47.04796 | L102: =L41*L103 -> 95.242731 | M102: =M41*M103 -> 145.98322 | N102: =N41*N103 -> 198.90726 | O102: =O41*O103 -> 256.46085 | R102: =R41*R103 -> 92.27532 | S102: =S41*S103 -> 137.39589 | T102: =T41*T103 -> 185.36903 | U102: =U41*U103 -> 234.47802 | V102: =V41*V103 -> 287.42599 | Y102: =Y41*Y103 -> 137.68656 | Z102: =Z41*Z103 -> 181.27268 | AA102: =AA41*AA103 -> 224.85006 | AB102: =AB41*AB103 -> 312.40675 | AC102: =AC41*AC103 -> 361.15189
B103: % of TI | C103: % | D103: =D102/D41 -> 0.0067466151 | E103: =E102/E41 -> 0.0058340483 | F103: =F102/F41 -> 0.00092273688 | G103: =G102/G41 -> 0.0043819313 | H103: =H102/H41 -> 0.0003226778 | K103: =R78 -> 0.0005 | L103: =S78 -> 0.001 | M103: =T78 -> 0.0015 | N103: =U78 -> 0.002 | O103: =V78 -> 0.0025 | R103: =R79 -> 0.001 | S103: =S79 -> 0.0015 | T103: =T79 -> 0.002 | U103: =U79 -> 0.0025 | V103: =V79 -> 0.003 | Y103: =R80 -> 0.0015 | Z103: =S80 -> 0.002 | AA103: =T80 -> 0.0025 | AB103: =U80 -> 0.0035 | AC103: =V80 -> 0.004
B105: Inventory | C105: ₹ | D105: ='BALANCE SHEET'!D10 -> 106 | E105: ='BALANCE SHEET'!E10 -> 133 | F105: ='BALANCE SHEET'!F10 -> 119 | G105: ='BALANCE SHEET'!G10 -> 91 | H105: ='BALANCE SHEET'!H10 -> 69 | K105: =(K$97*R$90)/365 -> 175.02741 | L105: =(L$97*S$90)/365 -> 176.77768 | M105: =(M$97*T$90)/365 -> 180.31324 | N105: =(N$97*U$90)/365 -> 183.9195 | O105: =(O$97*V$90)/365 -> 189.43709 | R105: =(R$97*R$91)/365 -> 173.97788 | S105: =(S$97*S$91)/365 -> 172.2381 | T105: =(T$97*T$91)/365 -> 173.96048 | U105: =(U$97*U$91)/365 -> 175.70009 | V105: =(V$97*V$91)/365 -> 179.21409 | Y105: =(Y$97*R$92)/365 -> 175.50336 | Z105: =(Z$97*S$92)/365 -> 172.87081 | AA105: =(AA$97*T$92)/365 -> 171.1421 | AB105: =(AB$97*U$92)/365 -> 169.43068 | AC105: =(AC$97*V$92)/365 -> 171.12499
B106: Inventory Days | C106: D | D106: N/A | E106: ='RATIO ANALYSIS'!D28 -> 0.73837859 | F106: ='RATIO ANALYSIS'!E28 -> 0.68333779 | G106: ='RATIO ANALYSIS'!F28 -> 0.57116244 | H106: ='RATIO ANALYSIS'!G28 -> 0.44725596 | K106: =R90 -> 1 | L106: =S90 -> 1 | M106: =T90 -> 1 | N106: =U90 -> 1 | O106: =V90 -> 1 | R106: =R91 -> 1 | S106: =S91 -> 1 | T106: =T91 -> 1 | U106: =U91 -> 1 | V106: =V91 -> 1 | Y106: =R92 -> 1 | Z106: =S92 -> 1 | AA106: =T92 -> 1 | AB106: =U92 -> 1 | AC106: =V92 -> 1
B108: Accounts Payable | C108: ₹ | D108: ='BALANCE SHEET'!D48 -> 5182 | E108: ='BALANCE SHEET'!E48 -> 6252 | F108: ='BALANCE SHEET'!F48 -> 5972 | G108: ='BALANCE SHEET'!G48 -> 5766 | H108: ='BALANCE SHEET'!H48 -> 5867 | K108: =(K$97*Y$90)/365 -> 6125.9594 | L108: =(L$97*Z$90)/365 -> 6187.219 | M108: =(M$97*AA$90)/365 -> 6310.9633 | N108: =(N$97*AB$90)/365 -> 6437.1826 | O108: =(O$97*AC$90)/365 -> 6630.2981 | R108: =(R$97*Y$91)/365 -> 5741.2701 | S108: =(S$97*Z$91)/365 -> 5683.8574 | T108: =(T$97*AA$91)/365 -> 5740.6959 | U108: =(U$97*AB$91)/365 -> 5798.1029 | V108: =(V$97*AC$91)/365 -> 5914.0649 | Y108: =(Y$97*Y$92)/365 -> 5440.6042 | Z108: =(Z$97*Z$92)/365 -> 5358.9951 | AA108: =(AA$97*AA$92)/365 -> 5305.4051 | AB108: =(AB$97*AB$92)/365 -> 5252.3511 | AC108: =(AC$97*AC$92)/365 -> 5304.8746
B109: AP Days | C109: D | D109: N/A | E109: ='RATIO ANALYSIS'!D32 -> 35.324773 | F109: ='RATIO ANALYSIS'!E32 -> 33.147306 | G109: ='RATIO ANALYSIS'!F32 -> 31.925261 | H109: ='RATIO ANALYSIS'!G32 -> 32.518304 | K109: =Y90 -> 35 | L109: =Z90 -> 35 | M109: =AA90 -> 35 | N109: =AB90 -> 35 | O109: =AC90 -> 35 | R109: =Y91 -> 33 | S109: =Z91 -> 33 | T109: =AA91 -> 33 | U109: =AB91 -> 33 | V109: =AC91 -> 33 | Y109: =Y92 -> 31 | Z109: =Z92 -> 31 | AA109: =AA92 -> 31 | AB109: =AB92 -> 31 | AC109: =AC92 -> 31
B111: EQUITY & RESERVES | K111: EQUITY & RESERVES - FORECAST (BEST CASE) | R111: EQUITY & RESERVES - FORECAST (BASE CASE) | Y111: EQUITY & RESERVES - FORECAST (WORST CASE)
B114: Opening Equity | C114: ₹ | D114: N/A | E114: =D$118 -> 1096 | F114: =E$118 -> 1096 | G114: =F$118 -> 1098 | H114: =G$118 -> 1045 | K114: =$H$118 -> 2094 | L114: =K$118 -> 1994 | M114: =L$118 -> 1894 | N114: =M$118 -> 1794 | O114: =N$118 -> 1694 | R114: =$H$118 -> 2094 | S114: =R$118 -> 2344 | T114: =S$118 -> 2594 | U114: =T$118 -> 2844 | V114: =U$118 -> 3094 | Y114: =$H$118 -> 2094 | Z114: =Y$118 -> 2494 | AA114: =Z$118 -> 2894 | AB114: =AA$118 -> 3294 | AC114: =AB$118 -> 3694
B115: New Shares Issued | C115: ₹ | D115: N/A | E115: =E118-E114 -> 0 | F115: =F118-F114 -> 2 | G115: =G118-G114 -> -53 | H115: =H118-H114 -> 1049 | K115: 0 | L115: 0 | M115: 0 | N115: 0 | O115: 0 | R115: 250 | S115: 250 | T115: 250 | U115: 250 | V115: 250 | Y115: 400 | Z115: 400 | AA115: 400 | AB115: 400 | AC115: 400
B116: Buyback | C116: ₹ | D116: N/A | E116: =E114-E118 -> 0 | F116: =IF(F114>F118,F114-F118,0) -> 0 | G116: =IF(G114>G118,G114-G118,0) -> 53 | H116: =IF(H114>H118,H114-H118,0) -> 0 | K116: 100 | L116: 100 | M116: 100 | N116: 100 | O116: 100 | R116: 0 | S116: 0 | T116: 0 | U116: 0 | V116: 0 | Y116: 0 | Z116: 0 | AA116: 0 | AB116: 0 | AC116: 0
B118: Closing Equity | C118: ₹ | D118: ='BALANCE SHEET'!D$73 -> 1096 | E118: ='BALANCE SHEET'!E$73 -> 1096 | F118: ='BALANCE SHEET'!F$73 -> 1098 | G118: ='BALANCE SHEET'!G$73 -> 1045 | H118: ='BALANCE SHEET'!H$73 -> 2094 | K118: =K114+K115-K116 -> 1994 | L118: =L114+L115-L116 -> 1894 | M118: =M114+M115-M116 -> 1794 | N118: =N114+N115-N116 -> 1694 | O118: =O114+O115-O116 -> 1594 | R118: =R114+R115-R116 -> 2344 | S118: =S114+S115-S116 -> 2594 | T118: =T114+T115-T116 -> 2844 | U118: =U114+U115-U116 -> 3094 | V118: =V114+V115-V116 -> 3344 | Y118: =SUM(Y114:Y115)-Y116 -> 2494 | Z118: =SUM(Z114:Z115)-Z116 -> 2894 | AA118: =SUM(AA114:AA115)-AA116 -> 3294 | AB118: =SUM(AB114:AB115)-AB116 -> 3694 | AC118: =SUM(AC114:AC115)-AC116 -> 4094
B120: Reserves | C120: ₹ | D120: ='BALANCE SHEET'!D$74 -> 53805 | E120: ='BALANCE SHEET'!E$74 -> 64307 | F120: ='BALANCE SHEET'!F$74 -> 76570 | G120: ='BALANCE SHEET'!G$74 -> 73488 | H120: ='BALANCE SHEET'!H$74 -> 80270 | K120: =$H$120+($H$120*$K$121) -> 85888.9 | L120: =K$120+(K$120*L$121) -> 91901.123 | M120: =L$120+(L$120*M$121) -> 98334.202 | N120: =M$120+(M$120*N$121) -> 105217.6 | O120: =N$120+(N$120*O$121) -> 112582.83 | R120: =$H$120+($H$120*$R$121) -> 85086.2 | S120: =R$120+(R$120*S$121) -> 90191.372 | T120: =S$120+(S$120*T$121) -> 95602.854 | U120: =T$120+(T$120*U$121) -> 101339.03 | V120: =U$120+(U$120*V$121) -> 107419.37 | Y120: =$H$120+($H$120*$Y$121) -> 84283.5 | Z120: =Y$120+(Y$120*Z$121) -> 88497.675 | AA120: =Z$120+(Z$120*AA$121) -> 92922.559 | AB120: =AA$120+(AA$120*AB$121) -> 97568.687 | AC120: =AB$120+(AB$120*AC$121) -> 102447.12
B121: YoY Growth | C121: % | D121: N/A | E121: =E120/D120-1 -> 0.19518632 | F121: =F120/E120-1 -> 0.19069464 | G121: =G120/F120-1 -> -0.040250751 | H121: =H120/G120-1 -> 0.092287176 | K121: 0.07 | L121: 0.07 | M121: 0.07 | N121: 0.07 | O121: 0.07 | R121: 0.06 | S121: 0.06 | T121: 0.06 | U121: 0.06 | V121: 0.06 | Y121: 0.05 | Z121: 0.05 | AA121: 0.05 | AB121: 0.05 | AC121: 0.05
B123: OTHER CURRENT ASSETS & LIABILITIES | K123: ASSETS ; LIABILITIES - FORECAST (BEST CASE) | R123: ASSETS ; LIABILITIES - FORECAST (BASE CASE) | Y123: ASSETS ; LIABILITIES - FORECAST (WORST CASE)
B126: Other Current Assets | C126: ₹ | D126: ='BALANCE SHEET'!D19 -> 2492 | E126: ='BALANCE SHEET'!E19 -> 2893 | F126: ='BALANCE SHEET'!F19 -> 3290 | G126: ='BALANCE SHEET'!G19 -> 2960 | H126: ='BALANCE SHEET'!H19 -> 2913 | K126: =K127*K41 -> 2822.8776 | L126: =L127*L41 -> 2857.2819 | M126: =M127*M41 -> 2919.6644 | N126: =N127*N41 -> 2983.6088 | O126: =O127*O41 -> 3077.5302 | R126: =R127*R41 -> 3192.7261 | S126: =S127*S41 -> 3169.2652 | T126: =T127*T41 -> 3206.8842 | U126: =U127*U41 -> 3245.1759 | V126: =V127*V41 -> 3314.9798 | Y126: =Y127*Y41 -> 3671.6416 | Z126: =Z127*Z41 -> 3625.4536 | AA126: =AA127*AA41 -> 3597.6009 | AB126: =AB127*AB41 -> 3570.3628 | AC126: =AC127*AC41 -> 3611.5189
B127: % of TI | C127: % | D127: =D126/D41 -> 0.038560928 | E127: =E126/E41 -> 0.035457777 | F127: =F126/F41 -> 0.03530005 | G127: =G126/G41 -> 0.032025967 | H127: =H126/H41 -> 0.031332014 | K127: =R84 -> 0.03 | L127: =S84 -> 0.03 | M127: =T84 -> 0.03 | N127: =U84 -> 0.03 | O127: =V84 -> 0.03 | R127: =R85 -> 0.0346 | S127: =S85 -> 0.0346 | T127: =T85 -> 0.0346 | U127: =U85 -> 0.0346 | V127: =V85 -> 0.0346 | Y127: =R86 -> 0.04 | Z127: =S86 -> 0.04 | AA127: =T86 -> 0.04 | AB127: =U86 -> 0.04 | AC127: =V86 -> 0.04
B129: Total Lease Liabilities | C129: ₹ | D129: ='BALANCE SHEET'!D60+'BALANCE SHEET'!D46 -> 2118 | E129: ='BALANCE SHEET'!E60+'BALANCE SHEET'!E46 -> 2424 | F129: ='BALANCE SHEET'!F60+'BALANCE SHEET'!F46 -> 2457 | G129: ='BALANCE SHEET'!G60+'BALANCE SHEET'!G46 -> 2318 | H129: ='BALANCE SHEET'!H60+'BALANCE SHEET'!H46 -> 3022 | K129: =K41*K130 -> 3011.0694 | L129: =L41*L130 -> 3143.0101 | M129: =M41*M130 -> 3308.953 | N129: =N41*N130 -> 3480.877 | O129: =O41*O130 -> 3795.6206 | R129: =R41*R130 -> 2768.2596 | S129: =S41*S130 -> 2839.515 | T129: =T41*T130 -> 2965.9045 | U129: =U41*U130 -> 3095.1099 | V129: =V41*V130 -> 3353.3033 | Y129: =Y41*Y130 -> 2570.1491 | Z129: =Z41*Z130 -> 2537.8175 | AA129: =AA41*AA130 -> 2698.2007 | AB129: =AB41*AB130 -> 2677.7721 | AC129: =AC41*AC130 -> 2889.2152
B130: % of TI | C130: % | D130: =D129/D41 -> 0.032773694 | E130: =E129/E41 -> 0.029709523 | F130: =F129/F41 -> 0.026362378 | G130: =G129/G41 -> 0.025079794 | H130: =H129/H41 -> 0.03250441 | K130: =K84 -> 0.032 | L130: =L84 -> 0.033 | M130: =M84 -> 0.034 | N130: =N84 -> 0.035 | O130: =O84 -> 0.037 | R130: =K85 -> 0.03 | S130: =L85 -> 0.031 | T130: =M85 -> 0.032 | U130: =N85 -> 0.033 | V130: =O85 -> 0.035 | Y130: =K86 -> 0.028 | Z130: =L86 -> 0.028 | AA130: =M86 -> 0.03 | AB130: =N86 -> 0.03 | AC130: =O86 -> 0.032
B131: Current Lease | C131: ₹ | D131: ='BALANCE SHEET'!D46 -> 767 | E131: ='BALANCE SHEET'!E46 -> 906 | F131: ='BALANCE SHEET'!F46 -> 862 | G131: ='BALANCE SHEET'!G46 -> 922 | H131: ='BALANCE SHEET'!H46 -> 803 | K131: =K129*K132 -> 963.54222 | L131: =L129*L132 -> 1005.7632 | M131: =M129*M132 -> 1058.865 | N131: =N129*N132 -> 1113.8806 | O131: =O129*O132 -> 1214.5986 | R131: =R129*R132 -> 968.89086 | S131: =S129*S132 -> 993.83026 | T131: =T129*T132 -> 1038.0666 | U131: =U129*U132 -> 1083.2885 | V131: =V129*V132 -> 1173.6561 | Y131: =Y129*Y132 -> 976.65667 | Z131: =Z129*Z132 -> 964.37065 | AA131: =AA129*AA132 -> 1025.3163 | AB131: =AB129*AB132 -> 1017.5534 | AC131: =AC129*AC132 -> 1097.9018
B132: % of Total Lease | C132: % | D132: =D131/D129 -> 0.36213409 | E132: =E131/E129 -> 0.37376238 | F132: =F131/F129 -> 0.35083435 | G132: =G131/G129 -> 0.39775669 | H132: =H131/H129 -> 0.26571807 | K132: 0.32 | L132: 0.32 | M132: 0.32 | N132: 0.32 | O132: 0.32 | R132: 0.35 | S132: 0.35 | T132: 0.35 | U132: 0.35 | V132: 0.35 | Y132: 0.38 | Z132: 0.38 | AA132: 0.38 | AB132: 0.38 | AC132: 0.38
B133: Non Current Lease | C133: ₹ | D133: ='BALANCE SHEET'!D60 -> 1351 | E133: ='BALANCE SHEET'!E60 -> 1518 | F133: ='BALANCE SHEET'!F60 -> 1595 | G133: ='BALANCE SHEET'!G60 -> 1396 | H133: ='BALANCE SHEET'!H60 -> 2219 | K133: =K129*K134 -> 2047.5272 | L133: =L129*L134 -> 2137.2469 | M133: =M129*M134 -> 2250.0881 | N133: =N129*N134 -> 2366.9963 | O133: =O129*O134 -> 2581.022 | R133: =R129*R134 -> 1799.3687 | S133: =S129*S134 -> 1845.6848 | T133: =T129*T134 -> 1927.8379 | U133: =U129*U134 -> 2011.8214 | V133: =V129*V134 -> 2179.6471 | Y133: =Y129*Y134 -> 1593.4925 | Z133: =Z129*Z134 -> 1573.4468 | AA133: =AA129*AA134 -> 1672.8844 | AB133: =AB129*AB134 -> 1660.2187 | AC133: =AC129*AC134 -> 1791.3134
B134: % of Total Lease | C134: % | D134: =D133/D129 -> 0.63786591 | E134: =E133/E129 -> 0.62623762 | F134: =F133/F129 -> 0.64916565 | G134: =G133/G129 -> 0.60224331 | H134: =H133/H129 -> 0.73428193 | K134: =100%-K132 -> 0.68 | L134: =100%-L132 -> 0.68 | M134: =100%-M132 -> 0.68 | N134: =100%-N132 -> 0.68 | O134: =100%-O132 -> 0.68 | R134: =100%-R132 -> 0.65 | S134: =100%-S132 -> 0.65 | T134: =100%-T132 -> 0.65 | U134: =100%-U132 -> 0.65 | V134: =100%-V132 -> 0.65 | Y134: =100%-Y132 -> 0.62 | Z134: =100%-Z132 -> 0.62 | AA134: =100%-AA132 -> 0.62 | AB134: =100%-AB132 -> 0.62 | AC134: =100%-AC132 -> 0.62
B136: Other Non Current Liabilities | C136: ₹ | D136: ='BALANCE SHEET'!D65 -> 478 | E136: ='BALANCE SHEET'!E65 -> 485 | F136: ='BALANCE SHEET'!F65 -> 639 | G136: ='BALANCE SHEET'!G65 -> 875 | H136: ='BALANCE SHEET'!H65 -> 1276 | K136: =K41*K137 -> 1599.6306 | L136: =L41*L137 -> 1714.3692 | M136: =M41*M137 -> 1751.7987 | N136: =N41*N137 -> 1889.6189 | O136: =O41*O137 -> 2051.6868 | R136: =R41*R137 -> 1476.4051 | S136: =S41*S137 -> 1557.1534 | T136: =T41*T137 -> 1668.3213 | U136: =U41*U137 -> 1782.033 | V136: =V41*V137 -> 1916.1733 | Y136: =Y41*Y137 -> 1376.8656 | Z136: =Z41*Z137 -> 1450.1814 | AA136: =AA41*AA137 -> 1528.9804 | AB136: =AB41*AB137 -> 1606.6633 | AC136: =AC41*AC137 -> 1715.4715
B137: % of TI | C137: % | D137: =D136/D41 -> 0.0073965184 | E137: =E136/E41 -> 0.0059443559 | F137: =F136/F41 -> 0.0068561496 | G137: =G136/G41 -> 0.0094671355 | H137: =H136/H41 -> 0.013724562 | K137: 0.017 | L137: 0.018 | M137: 0.018 | N137: 0.019 | O137: 0.02 | R137: 0.016 | S137: 0.017 | T137: 0.018 | U137: 0.019 | V137: 0.02 | Y137: 0.015 | Z137: 0.016 | AA137: 0.017 | AB137: 0.018 | AC137: 0.019
B139: Other Financial Liabilities | C139: ₹ | D139: ='BALANCE SHEET'!D49+'BALANCE SHEET'!D61 -> 2846 | E139: ='BALANCE SHEET'!E49+'BALANCE SHEET'!E61 -> 6803 | F139: ='BALANCE SHEET'!F49+'BALANCE SHEET'!F61 -> 3612 | G139: ='BALANCE SHEET'!G49+'BALANCE SHEET'!G61 -> 3817 | H139: ='BALANCE SHEET'!H49+'BALANCE SHEET'!H61 -> 4125 | K139: =K41*K140 -> 4121.4013 | L139: =L41*L140 -> 4171.6316 | M139: =M41*M140 -> 4262.7101 | N139: =N41*N140 -> 4356.0689 | O139: =O41*O140 -> 4493.1941 | R139: =R41*R140 -> 3949.3837 | S139: =S41*S140 -> 3920.3627 | T139: =T41*T140 -> 3966.8973 | U139: =U41*U140 -> 4014.2638 | V139: =V41*V140 -> 4100.6108 | Y139: =Y41*Y140 -> 3836.8655 | Z139: =Z41*Z140 -> 3788.599 | AA139: =AA41*AA140 -> 3759.4929 | AB139: =AB41*AB140 -> 3731.0292 | AC139: =AC41*AC140 -> 3774.0373
B140: % of TI | C140: % | D140: =D139/D41 -> 0.044038685 | E140: =E139/E41 -> 0.083380316 | F140: =F139/F41 -> 0.038754949 | G140: =G139/G41 -> 0.04129835 | H140: =H139/H41 -> 0.044368197 | K140: 0.0438 | L140: 0.0438 | M140: 0.0438 | N140: 0.0438 | O140: 0.0438 | R140: 0.0428 | S140: 0.0428 | T140: 0.0428 | U140: 0.0428 | V140: 0.0428 | Y140: 0.0418 | Z140: 0.0418 | AA140: 0.0418 | AB140: 0.0418 | AC140: 0.0418
B141: Current Financial Liabilities | C141: ₹ | D141: ='BALANCE SHEET'!D49 -> 2617 | E141: ='BALANCE SHEET'!E49 -> 6507 | F141: ='BALANCE SHEET'!F49 -> 3347 | G141: ='BALANCE SHEET'!G49 -> 3318 | H141: ='BALANCE SHEET'!H49 -> 3346 | K141: =K139*K142 -> 3255.907 | L141: =L139*L142 -> 3128.7237 | M141: =M139*M142 -> 3069.1513 | N141: =N139*N142 -> 3049.2482 | O141: =O139*O142 -> 3055.372 | R141: =R139*R142 -> 3120.0131 | S141: =S139*S142 -> 3018.6793 | T141: =T139*T142 -> 2975.173 | U141: =U139*U142 -> 2930.4126 | V141: =V139*V142 -> 2911.4337 | Y141: =Y139*Y142 -> 3069.4924 | Z141: =Z139*Z142 -> 2955.1072 | AA141: =AA139*AA142 -> 2894.8096 | AB141: =AB139*AB142 -> 2798.2719 | AC141: =AC139*AC142 -> 2755.0472
B142: % of Total F.L | C142: % | D142: =D141/D139 -> 0.91953619 | E142: =E141/E139 -> 0.95648978 | F142: =F141/F139 -> 0.92663344 | G142: =G141/G139 -> 0.86926906 | H142: =H141/H139 -> 0.81115152 | K142: 0.79 | L142: 0.75 | M142: 0.72 | N142: 0.7 | O142: 0.68 | R142: 0.79 | S142: 0.77 | T142: 0.75 | U142: 0.73 | V142: 0.71 | Y142: 0.8 | Z142: 0.78 | AA142: 0.77 | AB142: 0.75 | AC142: 0.73
B143: Non Current Financial Liabilities | C143: ₹ | D143: ='BALANCE SHEET'!D61 -> 229 | E143: ='BALANCE SHEET'!E61 -> 296 | F143: ='BALANCE SHEET'!F61 -> 265 | G143: ='BALANCE SHEET'!G61 -> 499 | H143: ='BALANCE SHEET'!H61 -> 779 | K143: =K139*K144 -> 865.49427 | L143: =L139*L144 -> 1042.9079 | M143: =M139*M144 -> 1193.5588 | N143: =N139*N144 -> 1306.8207 | O143: =O139*O144 -> 1437.8221 | R143: =R139*R144 -> 829.37058 | S143: =S139*S144 -> 901.68342 | T143: =T139*T144 -> 991.72432 | U143: =U139*U144 -> 1083.8512 | V143: =V139*V144 -> 1189.1771 | Y143: =Y139*Y144 -> 767.37309 | Z143: =Z139*Z144 -> 833.49178 | AA143: =AA139*AA144 -> 864.68338 | AB143: =AB139*AB144 -> 932.75729 | AC143: =AC139*AC144 -> 1018.9901
B144: % of Total F.L | C144: % | D144: =D143/D139 -> 0.080463809 | E144: =E143/E139 -> 0.043510216 | F144: =F143/F139 -> 0.073366556 | G144: =G143/G139 -> 0.13073094 | H144: =H143/H139 -> 0.18884848 | K144: =100%-K142 -> 0.21 | L144: =100%-L142 -> 0.25 | M144: =100%-M142 -> 0.28 | N144: =100%-N142 -> 0.3 | O144: =100%-O142 -> 0.32 | R144: =100%-R142 -> 0.21 | S144: =100%-S142 -> 0.23 | T144: =100%-T142 -> 0.25 | U144: =100%-U142 -> 0.27 | V144: =100%-V142 -> 0.29 | Y144: =100%-Y142 -> 0.2 | Z144: =100%-Z142 -> 0.22 | AA144: =100%-AA142 -> 0.23 | AB144: =100%-AB142 -> 0.25 | AC144: =100%-AC142 -> 0.27
B146: Other Current Liabilities | C146: ₹ | D146: ='BALANCE SHEET'!D51 -> 975 | E146: ='BALANCE SHEET'!E51 -> 1208 | F146: ='BALANCE SHEET'!F51 -> 1430 | G146: ='BALANCE SHEET'!G51 -> 1524 | H146: ='BALANCE SHEET'!H51 -> 1508 | K146: =(K$41*K$147)/365 -> 1546.7822 | L146: =(L$41*L$147)/365 -> 1565.6339 | M146: =(M$41*M$147)/365 -> 1599.8161 | N146: =(N$41*N$147)/365 -> 1634.8542 | O146: =(O$41*O$147)/365 -> 1686.3179 | R146: =(R$41*R$147)/365 -> 1516.8546 | S146: =(S$41*S$147)/365 -> 1505.7084 | T146: =(T$41*T$147)/365 -> 1523.5811 | U146: =(U$41*U$147)/365 -> 1541.7733 | V146: =(V$41*V$147)/365 -> 1574.937 | Y146: =(Y$41*Y$147)/365 -> 1508.8938 | Z146: =(Z$41*Z$147)/365 -> 1489.9124 | AA146: =(AA$41*AA$147)/365 -> 1478.4661 | AB146: =(AB$41*AB$147)/365 -> 1467.2724 | AC146: =(AC$41*AC$147)/365 -> 1484.1859
B147: Other C.L Days | C147: D | D147: =(D146/D$41)*365 -> 5.5067698 | E147: =(E146/E$41)*365 -> 5.4040936 | F147: =(F146/F$41)*365 -> 5.6002618 | G147: =(G146/G$41)*365 -> 6.0185015 | H147: =(H146/H$41)*365 -> 5.9202771 | K147: 6 | L147: 6 | M147: 6 | N147: 6 | O147: 6 | R147: 6 | S147: 6 | T147: 6 | U147: 6 | V147: 6 | Y147: 6 | Z147: 6 | AA147: 6 | AB147: 6 | AC147: 6
B149: PROVISIONS & LIABILITIES | K149: PROVISION - FORECAST (BEST CASE) | R149: PROVISION - FORECAST (BASE CASE) | Y149: PROVISION - FORECAST (WORST CASE)
B152: Total Provisions | C152: ₹ | D152: ='BALANCE SHEET'!D62+'BALANCE SHEET'!D52 -> 2090 | E152: ='BALANCE SHEET'!E62+'BALANCE SHEET'!E52 -> 2080 | F152: ='BALANCE SHEET'!F62+'BALANCE SHEET'!F52 -> 2138 | G152: ='BALANCE SHEET'!G62+'BALANCE SHEET'!G52 -> 2225 | H152: ='BALANCE SHEET'!H62+'BALANCE SHEET'!H52 -> 2230 | K152: =K41*K153 -> 2117.1582 | L152: =L41*L153 -> 2142.9615 | M152: =M41*M153 -> 2189.7483 | N152: =N41*N153 -> 2237.7066 | O152: =O41*O153 -> 2308.1477 | R152: =R41*R153 -> 2260.7453 | S152: =S41*S153 -> 2244.1328 | T152: =T41*T153 -> 2270.7706 | U152: =U41*U153 -> 2297.8846 | V152: =V41*V153 -> 2347.3123 | Y152: =Y41*Y153 -> 2432.4626 | Z152: =Z41*Z153 -> 2401.863 | AA152: =AA41*AA153 -> 2383.4106 | AB152: =AB41*AB153 -> 2365.3654 | AC152: =AC41*AC153 -> 2392.6313
B153: % of TI | C153: % | D153: =D152/D41 -> 0.032340426 | E153: =E152/E41 -> 0.02549332 | F153: =F152/F41 -> 0.022939668 | G153: =G152/G41 -> 0.024073573 | H153: =H152/H41 -> 0.023985716 | K153: 0.0225 | L153: 0.0225 | M153: 0.0225 | N153: 0.0225 | O153: 0.0225 | R153: 0.0245 | S153: 0.0245 | T153: 0.0245 | U153: 0.0245 | V153: 0.0245 | Y153: 0.0265 | Z153: 0.0265 | AA153: 0.0265 | AB153: 0.0265 | AC153: 0.0265
...

Sheet BALANCE SHEET
B1: WIPRO | D1: BALANCE SHEET | I1: 2 | K1: BALANCE SHEET - FORECAST
C3: UNIT | D3: Year 1 | E3: Year 2 | F3: Year 3 | G3: Year 4 | H3: Year 5 | K3: Year 6 | L3: Year 7 | M3: Year 8 | N3: Year 9 | O3: Year 10
B4: Particulars (In Crores) | D4: 44276 | E4: =EDATE(D4,12) -> 44641 | F4: =EDATE(E4,12) -> 45006 | G4: =EDATE(F4,12) -> 45372 | H4: =EDATE(G4,12) -> 45737 | K4: =EDATE(H4,12) -> 46102 | L4: =EDATE(K4,12) -> 46467 | M4: =EDATE(L4,12) -> 46833 | N4: =EDATE(M4,12) -> 47198 | O4: =EDATE(N4,12) -> 47563
B6: ASSETS | K6: =K79-K39 -> 0 | L6: =L79-L39 -> 0 | M6: =M79-M39 -> 0 | N6: =N79-N39 -> 0 | O6: =O79-O39 -> 0
B8: Current Assets
B10: Inventories | C10: ₹ | D10: =STATEMENTS!C19 -> 106 | E10: =STATEMENTS!D19 -> 133 | F10: =STATEMENTS!E19 -> 119 | G10: =STATEMENTS!F19 -> 91 | H10: =STATEMENTS!G19 -> 69 | K10: =CHOOSE($I$1,'BALANCE SHEET ASSUMPTION'!K$105,'BALANCE SHEET ASSUMPTION'!R$105,'BALANCE SHEET ASSUMPTION'!Y$105) -> 173.97788 | L10: =CHOOSE($I$1,'BALANCE SHEET ASSUMPTION'!L$105,'BALANCE SHEET ASSUMPTION'!S$105,'BALANCE SHEET ASSUMPTION'!Z$105) -> 172.2381 | M10: =CHOOSE($I$1,'BALANCE SHEET ASSUMPTION'!M$105,'BALANCE SHEET ASSUMPTION'!T$105,'BALANCE SHEET ASSUMPTION'!AA$105) -> 173.96048 | N10: =CHOOSE($I$1,'BALANCE SHEET ASSUMPTION'!N$105,'BALANCE SHEET ASSUMPTION'!U$105,'BALANCE SHEET ASSUMPTION'!AB$105) -> 175.70009 | O10: =CHOOSE($I$1,'BALANCE SHEET ASSUMPTION'!O$105,'BALANCE SHEET ASSUMPTION'!V$105,'BALANCE SHEET ASSUMPTION'!AC$105) -> 179.21409
B11: Investments | C11: ₹ | D11: =STATEMENTS!C20 -> 17571 | E11: =STATEMENTS!D20 -> 24166 | F11: =STATEMENTS!E20 -> 30923 | G11: =STATEMENTS!F20 -> 31117 | H11: =STATEMENTS!G20 -> 41147 | K11: =CHOOSE($I$1,'BALANCE SHEET ASSUMPTION'!K$52,'BALANCE SHEET ASSUMPTION'!R$52,'BALANCE SHEET ASSUMPTION'!Y$52) -> 48000 | L11: =CHOOSE($I$1,'BALANCE SHEET ASSUMPTION'!L$52,'BALANCE SHEET ASSUMPTION'!S$52,'BALANCE SHEET ASSUMPTION'!Z$52) -> 53000 | M11: =CHOOSE($I$1,'BALANCE SHEET ASSUMPTION'!M$52,'BALANCE SHEET ASSUMPTION'!T$52,'BALANCE SHEET ASSUMPTION'!AA$52) -> 59000 | N11: =CHOOSE($I$1,'BALANCE SHEET ASSUMPTION'!N$52,'BALANCE SHEET ASSUMPTION'!U$52,'BALANCE SHEET ASSUMPTION'!AB$52) -> 66000 | O11: =CHOOSE($I$1,'BALANCE SHEET ASSUMPTION'!O$52,'BALANCE SHEET ASSUMPTION'!V$52,'BALANCE SHEET ASSUMPTION'!AC$52) -> 73000
B12: Derivative Assets | C12: ₹ | D12: =STATEMENTS!C21 -> 41 | E12: =STATEMENTS!D21 -> 303 | F12: =STATEMENTS!E21 -> 184 | G12: =STATEMENTS!F21 -> 133 | H12: =STATEMENTS!G21 -> 182 | K12: =AVERAGE(D12:H12) -> 168.6 | L12: =$K$12 -> 168.6 | M12: =$K$12 -> 168.6 | N12: =$K$12 -> 168.6 | O12: =$K$12 -> 168.6
B13: Trade Receivables | C13: ₹ | D13: =STATEMENTS!C22 -> 9430 | E13: =STATEMENTS!D22 -> 11522 | F13: =STATEMENTS!E22 -> 12635 | G13: =STATEMENTS!F22 -> 11548 | H13: =STATEMENTS!G22 -> 11745 | K13: =CHOOSE($I$1,'BALANCE SHEET ASSUMPTION'!K$99,'BALANCE SHEET ASSUMPTION'!R$99,'BALANCE SHEET ASSUMPTION'!Y$99) -> 11376.409 | L13: =CHOOSE($I$1,'BALANCE SHEET ASSUMPTION'!L$99,'BALANCE SHEET ASSUMPTION'!S$99,'BALANCE SHEET ASSUMPTION'!Z$99) -> 11041.861 | M13: =CHOOSE($I$1,'BALANCE SHEET ASSUMPTION'!M$99,'BALANCE SHEET ASSUMPTION'!T$99,'BALANCE SHEET ASSUMPTION'!AA$99) -> 10665.068 | N13: =CHOOSE($I$1,'BALANCE SHEET ASSUMPTION'!N$99,'BALANCE SHEET ASSUMPTION'!U$99,'BALANCE SHEET ASSUMPTION'!AB$99) -> 10535.451 | O13: =CHOOSE($I$1,'BALANCE SHEET ASSUMPTION'!O$99,'BALANCE SHEET ASSUMPTION'!V$99,'BALANCE SHEET ASSUMPTION'!AC$99) -> 10499.58
B14: Unbilled Receivables | C14: ₹ | D14: =STATEMENTS!C23 -> 2712 | E14: =STATEMENTS!D23 -> 6081 | F14: =STATEMENTS!E23 -> 6052 | G14: =STATEMENTS!F23 -> 5835 | H14: =STATEMENTS!G23 -> 6428 | K14: =CHOOSE($I$1,'BALANCE SHEET ASSUMPTION'!K$23,'BALANCE SHEET ASSUMPTION'!R$23,'BALANCE SHEET ASSUMPTION'!Y$23) -> 5706.3537 | L14: =CHOOSE($I$1,'BALANCE SHEET ASSUMPTION'!L$23,'BALANCE SHEET ASSUMPTION'!S$23,'BALANCE SHEET ASSUMPTION'!Z$23) -> 5649.2901 | M14: =CHOOSE($I$1,'BALANCE SHEET ASSUMPTION'!M$23,'BALANCE SHEET ASSUMPTION'!T$23,'BALANCE SHEET ASSUMPTION'!AA$23) -> 5705.783 | N14: =CHOOSE($I$1,'BALANCE SHEET ASSUMPTION'!N$23,'BALANCE SHEET ASSUMPTION'!U$23,'BALANCE SHEET ASSUMPTION'!AB$23) -> 5762.8409 | O14: =CHOOSE($I$1,'BALANCE SHEET ASSUMPTION'!O$23,'BALANCE SHEET ASSUMPTION'!V$23,'BALANCE SHEET ASSUMPTION'!AC$23) -> 5878.0977
B15: Cash Equivalents | C15: ₹ | D15: =STATEMENTS!C24 -> 17473 | E15: =STATEMENTS!D24 -> 10002 | F15: =STATEMENTS!E24 -> 9247 | G15: =STATEMENTS!F24 -> 9802 | H15: =STATEMENTS!G24 -> 12358 | K15: =CHOOSE($I$1,'CASH FLOW ASSUMPTION'!D62,'CASH FLOW ASSUMPTION'!K62,'CASH FLOW ASSUMPTION'!R62) -> 10833.768 | L15: =CHOOSE($I$1,'CASH FLOW ASSUMPTION'!E62,'CASH FLOW ASSUMPTION'!L62,'CASH FLOW ASSUMPTION'!S62) -> 10683.265 | M15: =CHOOSE($I$1,'CASH FLOW ASSUMPTION'!F62,'CASH FLOW ASSUMPTION'!M62,'CASH FLOW ASSUMPTION'!T62) -> 11140.238 | N15: =CHOOSE($I$1,'CASH FLOW ASSUMPTION'!G62,'CASH FLOW ASSUMPTION'!N62,'CASH FLOW ASSUMPTION'!U62) -> 10616.362 | O15: =CHOOSE($I$1,'CASH FLOW ASSUMPTION'!H62,'CASH FLOW ASSUMPTION'!O62,'CASH FLOW ASSUMPTION'!V62) -> 10863.195
B16: Other Financial Assets | C16: ₹ | D16: =STATEMENTS!C25 -> 745 | E16: =STATEMENTS!D25 -> 4291 | F16: =STATEMENTS!E25 -> 910 | G16: =STATEMENTS!F25 -> 1054 | H16: =STATEMENTS!G25 -> 845 | K16: =CHOOSE($I$1,'BALANCE SHEET ASSUMPTION'!K28,'BALANCE SHEET ASSUMPTION'!R28,'BALANCE SHEET ASSUMPTION'!Y28) -> 989.65281 | L16: =CHOOSE($I$1,'BALANCE SHEET ASSUMPTION'!L28,'BALANCE SHEET ASSUMPTION'!S28,'BALANCE SHEET ASSUMPTION'!Z28) -> 982.3806 | M16: =CHOOSE($I$1,'BALANCE SHEET ASSUMPTION'!M28,'BALANCE SHEET ASSUMPTION'!T28,'BALANCE SHEET ASSUMPTION'!AA28) -> 994.04143 | N16: =CHOOSE($I$1,'BALANCE SHEET ASSUMPTION'!N28,'BALANCE SHEET ASSUMPTION'!U28,'BALANCE SHEET ASSUMPTION'!AB28) -> 1005.9107 | O16: =CHOOSE($I$1,'BALANCE SHEET ASSUMPTION'!O28,'BALANCE SHEET ASSUMPTION'!V28,'BALANCE SHEET ASSUMPTION'!AC28) -> 1027.5479
B17: Current Tax Assets | C17: ₹ | D17: =STATEMENTS!C26 -> 246 | E17: =STATEMENTS!D26 -> 237 | F17: =STATEMENTS!E26 -> 509 | G17: =STATEMENTS!F26 -> 648 | H17: =STATEMENTS!G26 -> 642 | K17: =CHOOSE($I$1,'BALANCE SHEET ASSUMPTION'!K$33,'BALANCE SHEET ASSUMPTION'!R$33,'BALANCE SHEET ASSUMPTION'!Y$33) -> 600 | L17: =CHOOSE($I$1,'BALANCE SHEET ASSUMPTION'!L$33,'BALANCE SHEET ASSUMPTION'!S$33,'BALANCE SHEET ASSUMPTION'!Z$33) -> 630 | M17: =CHOOSE($I$1,'BALANCE SHEET ASSUMPTION'!M$33,'BALANCE SHEET ASSUMPTION'!T$33,'BALANCE SHEET ASSUMPTION'!AA$33) -> 660 | N17: =CHOOSE($I$1,'BALANCE SHEET ASSUMPTION'!N$33,'BALANCE SHEET ASSUMPTION'!U$33,'BALANCE SHEET ASSUMPTION'!AB$33) -> 690 | O17: =CHOOSE($I$1,'BALANCE SHEET ASSUMPTION'!O$33,'BALANCE SHEET ASSUMPTION'!V$33,'BALANCE SHEET ASSUMPTION'!AC$33) -> 720
B18: Contract Assets | C18: ₹ | D18: =STATEMENTS!C27 -> 1651 | E18: =STATEMENTS!D27 -> 2065 | F18: =STATEMENTS!E27 -> 2300 | G18: =STATEMENTS!F27 -> 1985 | H18: =STATEMENTS!G27 -> 1580 | K18: =CHOOSE($I$1,'BALANCE SHEET ASSUMPTION'!K$35,'BALANCE SHEET ASSUMPTION'!R$35,'BALANCE SHEET ASSUMPTION'!Y$35) -> 2074.8313 | L18: =CHOOSE($I$1,'BALANCE SHEET ASSUMPTION'!L$35,'BALANCE SHEET ASSUMPTION'!S$35,'BALANCE SHEET ASSUMPTION'!Z$35) -> 2054.083 | M18: =CHOOSE($I$1,'BALANCE SHEET ASSUMPTION'!M$35,'BALANCE SHEET ASSUMPTION'!T$35,'BALANCE SHEET ASSUMPTION'!AA$35) -> 2074.6238 | N18: =CHOOSE($I$1,'BALANCE SHEET ASSUMPTION'!N$35,'BALANCE SHEET ASSUMPTION'!U$35,'BALANCE SHEET ASSUMPTION'!AB$35) -> 2095.37 | O18: =CHOOSE($I$1,'BALANCE SHEET ASSUMPTION'!O$35,'BALANCE SHEET ASSUMPTION'!V$35,'BALANCE SHEET ASSUMPTION'!AC$35) -> 2137.2774
B19: Other Current Assets | C19: ₹ | D19: =STATEMENTS!C28 -> 2492 | E19: =STATEMENTS!D28 -> 2893 | F19: =STATEMENTS!E28 -> 3290 | G19: =STATEMENTS!F28 -> 2960 | H19: =STATEMENTS!G28 -> 2913 | K19: =CHOOSE($I$1,'BALANCE SHEET ASSUMPTION'!K$126,'BALANCE SHEET ASSUMPTION'!R$126,'BALANCE SHEET ASSUMPTION'!Y$126) -> 3192.7261 | L19: =CHOOSE($I$1,'BALANCE SHEET ASSUMPTION'!L$126,'BALANCE SHEET ASSUMPTION'!S$126,'BALANCE SHEET ASSUMPTION'!Z$126) -> 3169.2652 | M19: =CHOOSE($I$1,'BALANCE SHEET ASSUMPTION'!M$126,'BALANCE SHEET ASSUMPTION'!T$126,'BALANCE SHEET ASSUMPTION'!AA$126) -> 3206.8842 | N19: =CHOOSE($I$1,'BALANCE SHEET ASSUMPTION'!N$126,'BALANCE SHEET ASSUMPTION'!U$126,'BALANCE SHEET ASSUMPTION'!AB$126) -> 3245.1759 | O19: =CHOOSE($I$1,'BALANCE SHEET ASSUMPTION'!O$126,'BALANCE SHEET ASSUMPTION'!V$126,'BALANCE SHEET ASSUMPTION'!AC$126) -> 3314.9798
B21: Total Current Assets | C21: ₹ | D21: =SUM(D10:D19) -> 52467 | E21: =SUM(E10:E19) -> 61693 | F21: =SUM(F10:F19) -> 66169 | G21: =SUM(G10:G19) -> 65173 | H21: =SUM(H10:H19) -> 77909 | K21: =SUM(K10:K19) -> 83116.319 | L21: =SUM(L10:L19) -> 87550.983 | M21: =SUM(M10:M19) -> 93789.198 | N21: =SUM(N10:N19) -> 100295.41 | O21: =SUM(O10:O19) -> 107788.49
D22: =P21-T21 -> 0
B23: Fixed Assets
B25: PPE | C25: ₹ | D25: =STATEMENTS!C7 -> 6575 | E25: =STATEMENTS!D7 -> 7461 | F25: =STATEMENTS!E7 -> 8234 | G25: =STATEMENTS!F7 -> 7413 | H25: =STATEMENTS!G7 -> 7847 | K25: =CHOOSE($I$1,'BALANCE SHEET ASSUMPTION'!K$18,'BALANCE SHEET ASSUMPTION'!R$18,'BALANCE SHEET ASSUMPTION'!Y$18) -> 7586.1888 | L25: =CHOOSE($I$1,'BALANCE SHEET ASSUMPTION'!L$18,'BALANCE SHEET ASSUMPTION'!S$18,'BALANCE SHEET ASSUMPTION'!Z$18) -> 8374.2068 | M25: =CHOOSE($I$1,'BALANCE SHEET ASSUMPTION'!M$18,'BALANCE SHEET ASSUMPTION'!T$18,'BALANCE SHEET ASSUMPTION'!AA$18) -> 8442.1058 | N25: =CHOOSE($I$1,'BALANCE SHEET ASSUMPTION'!N$18,'BALANCE SHEET ASSUMPTION'!U$18,'BALANCE SHEET ASSUMPTION'!AB$18) -> 8514.3166 | O25: =CHOOSE($I$1,'BALANCE SHEET ASSUMPTION'!O$18,'BALANCE SHEET ASSUMPTION'!V$18,'BALANCE SHEET ASSUMPTION'!AC$18) -> 8486.5263
B26: Right of Use Assets | C26: ₹ | D26: =STATEMENTS!C8 -> 1642 | E26: =STATEMENTS!D8 -> 1887 | F26: =STATEMENTS!E8 -> 1870 | G26: =STATEMENTS!F8 -> 1796 | H26: =STATEMENTS!G8 -> 2560 | K26: =CHOOSE($I$1,'BALANCE SHEET ASSUMPTION'!K$46,'BALANCE SHEET ASSUMPTION'!R$46,'BALANCE SHEET ASSUMPTION'!Y$46) -> 2122.3324 | L26: =CHOOSE($I$1,'BALANCE SHEET ASSUMPTION'!L$46,'BALANCE SHEET ASSUMPTION'!S$46,'BALANCE SHEET ASSUMPTION'!Z$46) -> 2198.3342 | M26: =CHOOSE($I$1,'BALANCE SHEET ASSUMPTION'!M$46,'BALANCE SHEET ASSUMPTION'!T$46,'BALANCE SHEET ASSUMPTION'!AA$46) -> 2131.7439 | N26: =CHOOSE($I$1,'BALANCE SHEET ASSUMPTION'!N$46,'BALANCE SHEET ASSUMPTION'!U$46,'BALANCE SHEET ASSUMPTION'!AB$46) -> 2250.989 | O26: =CHOOSE($I$1,'BALANCE SHEET ASSUMPTION'!O$46,'BALANCE SHEET ASSUMPTION'!V$46,'BALANCE SHEET ASSUMPTION'!AC$46) -> 2203.5993
B27: CWIP | C27: ₹ | D27: =STATEMENTS!C9 -> 1853 | E27: =STATEMENTS!D9 -> 1602 | F27: =STATEMENTS!E9 -> 617 | G27: =STATEMENTS!F9 -> 723 | H27: =STATEMENTS!G9 -> 196 | K27: =CHOOSE($I$1,'BALANCE SHEET ASSUMPTION'!K$43,'BALANCE SHEET ASSUMPTION'!R$43,'BALANCE SHEET ASSUMPTION'!Y$43) -> 736.44595 | L27: =CHOOSE($I$1,'BALANCE SHEET ASSUMPTION'!L$43,'BALANCE SHEET ASSUMPTION'!S$43,'BALANCE SHEET ASSUMPTION'!Z$43) -> 874.89779 | M27: =CHOOSE($I$1,'BALANCE SHEET ASSUMPTION'!M$43,'BALANCE SHEET ASSUMPTION'!T$43,'BALANCE SHEET ASSUMPTION'!AA$43) -> 736.37231 | N27: =CHOOSE($I$1,'BALANCE SHEET ASSUMPTION'!N$43,'BALANCE SHEET ASSUMPTION'!U$43,'BALANCE SHEET ASSUMPTION'!AB$43) -> 446.24162 | O27: =CHOOSE($I$1,'BALANCE SHEET ASSUMPTION'!O$43,'BALANCE SHEET ASSUMPTION'!V$43,'BALANCE SHEET ASSUMPTION'!AC$43) -> 303.4443
B28: Goodwill | C28: ₹ | D28: =STATEMENTS!C10 -> 13515 | E28: =STATEMENTS!D10 -> 24286 | F28: =STATEMENTS!E10 -> 30349 | G28: =STATEMENTS!F10 -> 31145 | H28: =STATEMENTS!G10 -> 32035 | K28: =CHOOSE($I$1,'BALANCE SHEET ASSUMPTION'!K$49,'BALANCE SHEET ASSUMPTION'!R$49,'BALANCE SHEET ASSUMPTION'!Y$49) -> 32899.945 | L28: =CHOOSE($I$1,'BALANCE SHEET ASSUMPTION'!L$49,'BALANCE SHEET ASSUMPTION'!S$49,'BALANCE SHEET ASSUMPTION'!Z$49) -> 33788.244 | M28: =CHOOSE($I$1,'BALANCE SHEET ASSUMPTION'!M$49,'BALANCE SHEET ASSUMPTION'!T$49,'BALANCE SHEET ASSUMPTION'!AA$49) -> 34700.526 | N28: =CHOOSE($I$1,'BALANCE SHEET ASSUMPTION'!N$49,'BALANCE SHEET ASSUMPTION'!U$49,'BALANCE SHEET ASSUMPTION'!AB$49) -> 35637.44 | O28: =CHOOSE($I$1,'BALANCE SHEET ASSUMPTION'!O$49,'BALANCE SHEET ASSUMPTION'!V$49,'BALANCE SHEET ASSUMPTION'!AC$49) -> 36599.651
B29: Other Intangiable Assets | C29: ₹ | D29: =STATEMENTS!C11 -> 1309 | E29: =STATEMENTS!D11 -> 4356 | F29: =STATEMENTS!E11 -> 4305 | G29: =STATEMENTS!F11 -> 3275 | H29: =STATEMENTS!G11 -> 2745 | K29: =CHOOSE($I$1,'BALANCE SHEET ASSUMPTION'!K$55,'BALANCE SHEET ASSUMPTION'!R$55,'BALANCE SHEET ASSUMPTION'!Y$55) -> 2768.2596 | L29: =CHOOSE($I$1,'BALANCE SHEET ASSUMPTION'!L$55,'BALANCE SHEET ASSUMPTION'!S$55,'BALANCE SHEET ASSUMPTION'!Z$55) -> 2747.9178 | M29: =CHOOSE($I$1,'BALANCE SHEET ASSUMPTION'!M$55,'BALANCE SHEET ASSUMPTION'!T$55,'BALANCE SHEET ASSUMPTION'!AA$55) -> 2780.5355 | N29: =CHOOSE($I$1,'BALANCE SHEET ASSUMPTION'!N$55,'BALANCE SHEET ASSUMPTION'!U$55,'BALANCE SHEET ASSUMPTION'!AB$55) -> 3001.3187 | O29: =CHOOSE($I$1,'BALANCE SHEET ASSUMPTION'!O$55,'BALANCE SHEET ASSUMPTION'!V$55,'BALANCE SHEET ASSUMPTION'!AC$55) -> 3065.8773
B30: Investments | C30: ₹ | D30: =STATEMENTS!C12 -> 1058 | E30: =STATEMENTS!D12 -> 1911 | F30: =STATEMENTS!E12 -> 2072 | G30: =STATEMENTS!F12 -> 2163 | H30: =STATEMENTS!G12 -> 2646 | K30: =CHOOSE($I$1,'BALANCE SHEET ASSUMPTION'!K$58,'BALANCE SHEET ASSUMPTION'!R$58,'BALANCE SHEET ASSUMPTION'!Y$58) -> 2746 | L30: =CHOOSE($I$1,'BALANCE SHEET ASSUMPTION'!L$58,'BALANCE SHEET ASSUMPTION'!S$58,'BALANCE SHEET ASSUMPTION'!Z$58) -> 2846 | M30: =CHOOSE($I$1,'BALANCE SHEET ASSUMPTION'!M$58,'BALANCE SHEET ASSUMPTION'!T$58,'BALANCE SHEET ASSUMPTION'!AA$58) -> 2946 | N30: =CHOOSE($I$1,'BALANCE SHEET ASSUMPTION'!N$58,'BALANCE SHEET ASSUMPTION'!U$58,'BALANCE SHEET ASSUMPTION'!AB$58) -> 3046 | O30: =CHOOSE($I$1,'BALANCE SHEET ASSUMPTION'!O$58,'BALANCE SHEET ASSUMPTION'!V$58,'BALANCE SHEET ASSUMPTION'!AC$58) -> 3146
B31: Trade Receivables | C31: ₹ | D31: =STATEMENTS!C13 -> 436 | E31: =STATEMENTS!D13 -> 476 | F31: =STATEMENTS!E13 -> 86 | G31: =STATEMENTS!F13 -> 405 | H31: =STATEMENTS!G13 -> 30 | K31: =CHOOSE($I$1,'BALANCE SHEET ASSUMPTION'!K$102,'BALANCE SHEET ASSUMPTION'!R102,'BALANCE SHEET ASSUMPTION'!Y102) -> 92.27532 | L31: =CHOOSE($I$1,'BALANCE SHEET ASSUMPTION'!L$102,'BALANCE SHEET ASSUMPTION'!S102,'BALANCE SHEET ASSUMPTION'!Z102) -> 137.39589 | M31: =CHOOSE($I$1,'BALANCE SHEET ASSUMPTION'!M$102,'BALANCE SHEET ASSUMPTION'!T102,'BALANCE SHEET ASSUMPTION'!AA102) -> 185.36903 | N31: =CHOOSE($I$1,'BALANCE SHEET ASSUMPTION'!N$102,'BALANCE SHEET ASSUMPTION'!U102,'BALANCE SHEET ASSUMPTION'!AB102) -> 234.47802 | O31: =CHOOSE($I$1,'BALANCE SHEET ASSUMPTION'!O$102,'BALANCE SHEET ASSUMPTION'!V102,'BALANCE SHEET ASSUMPTION'!AC102) -> 287.42599
B32: Other Financial Assets | C32: ₹ | D32: =STATEMENTS!C14 -> 609 | E32: =STATEMENTS!D14 -> 608 | F32: =STATEMENTS!E14 -> 633 | G32: =STATEMENTS!F14 -> 555 | H32: =STATEMENTS!G14 -> 466 | K32: =CHOOSE($I$1,'BALANCE SHEET ASSUMPTION'!K30,'BALANCE SHEET ASSUMPTION'!R30,'BALANCE SHEET ASSUMPTION'!Y30) -> 532.88997 | L32: =CHOOSE($I$1,'BALANCE SHEET ASSUMPTION'!L30,'BALANCE SHEET ASSUMPTION'!S30,'BALANCE SHEET ASSUMPTION'!Z30) -> 528.97417 | M32: =CHOOSE($I$1,'BALANCE SHEET ASSUMPTION'!M30,'BALANCE SHEET ASSUMPTION'!T30,'BALANCE SHEET ASSUMPTION'!AA30) -> 535.25308 | N32: =CHOOSE($I$1,'BALANCE SHEET ASSUMPTION'!N30,'BALANCE SHEET ASSUMPTION'!U30,'BALANCE SHEET ASSUMPTION'!AB30) -> 541.64424 | O32: =CHOOSE($I$1,'BALANCE SHEET ASSUMPTION'!O30,'BALANCE SHEET ASSUMPTION'!V30,'BALANCE SHEET ASSUMPTION'!AC30) -> 553.29504
B33: Deferred Tax Assets | C33: ₹ | D33: =STATEMENTS!C15 -> 166 | E33: =STATEMENTS!D15 -> 230 | F33: =STATEMENTS!E15 -> 210 | G33: =STATEMENTS!F15 -> 182 | H33: =STATEMENTS!G15 -> 256 | K33: =AVERAGE(D33:H33) -> 208.8 | L33: =AVERAGE(E33:I33) -> 219.5 | M33: =AVERAGE(F33:J33) -> 216 | N33: =AVERAGE(G33:K33) -> 215.6 | O33: =AVERAGE(H33:L33) -> 228.1
B34: Non Current Tax Assets | C34: ₹ | D34: =STATEMENTS!C16 -> 1432 | E34: =STATEMENTS!D16 -> 1026 | F34: =STATEMENTS!E16 -> 1192 | G34: =STATEMENTS!F16 -> 904 | H34: =STATEMENTS!G16 -> 723 | K34: =CHOOSE($I$1,'BALANCE SHEET ASSUMPTION'!K$61,'BALANCE SHEET ASSUMPTION'!R$61,'BALANCE SHEET ASSUMPTION'!Y$61) -> 598.11482 | L34: =CHOOSE($I$1,'BALANCE SHEET ASSUMPTION'!L$61,'BALANCE SHEET ASSUMPTION'!S$61,'BALANCE SHEET ASSUMPTION'!Z$61) -> 510.65303 | M34: =CHOOSE($I$1,'BALANCE SHEET ASSUMPTION'!M$61,'BALANCE SHEET ASSUMPTION'!T$61,'BALANCE SHEET ASSUMPTION'!AA$61) -> 433.37245 | N34: =CHOOSE($I$1,'BALANCE SHEET ASSUMPTION'!N$61,'BALANCE SHEET ASSUMPTION'!U$61,'BALANCE SHEET ASSUMPTION'!AB$61) -> 397.25723 | O34: =CHOOSE($I$1,'BALANCE SHEET ASSUMPTION'!O$61,'BALANCE SHEET ASSUMPTION'!V$61,'BALANCE SHEET ASSUMPTION'!AC$61) -> 363.41628
B35: Other Fixed Assets | C35: ₹ | D35: =STATEMENTS!C17 -> 1671 | E35: =STATEMENTS!D17 -> 1510 | F35: =STATEMENTS!E17 -> 1376 | G35: =STATEMENTS!F17 -> 1058 | H35: =STATEMENTS!G17 -> 771 | K35: =CHOOSE($I$1,'BALANCE SHEET ASSUMPTION'!K64,'BALANCE SHEET ASSUMPTION'!R64,'BALANCE SHEET ASSUMPTION'!Y64) -> 682.75699 | L35: =CHOOSE($I$1,'BALANCE SHEET ASSUMPTION'!L64,'BALANCE SHEET ASSUMPTION'!S64,'BALANCE SHEET ASSUMPTION'!Z64) -> 753.67862 | M35: =CHOOSE($I$1,'BALANCE SHEET ASSUMPTION'!M64,'BALANCE SHEET ASSUMPTION'!T64,'BALANCE SHEET ASSUMPTION'!AA64) -> 759.78952 | N35: =CHOOSE($I$1,'BALANCE SHEET ASSUMPTION'!N64,'BALANCE SHEET ASSUMPTION'!U64,'BALANCE SHEET ASSUMPTION'!AB64) -> 766.28849 | O35: =CHOOSE($I$1,'BALANCE SHEET ASSUMPTION'!O64,'BALANCE SHEET ASSUMPTION'!V64,'BALANCE SHEET ASSUMPTION'!AC64) -> 763.78737
B37: Total Fixed Assets | C37: ₹ | D37: =SUM(D25:D35) -> 30266 | E37: =SUM(E25:E35) -> 45353 | F37: =SUM(F25:F35) -> 50944 | G37: =SUM(G25:G35) -> 49619 | H37: =SUM(H25:H35) -> 50275 | K37: =SUM(K25:K35) -> 50974.009 | L37: =SUM(L25:L35) -> 52979.802 | M37: =SUM(M25:M35) -> 53867.068 | N37: =SUM(N25:N35) -> 55051.574 | O37: =SUM(O25:O35) -> 56001.123
B39: Total Assets | C39: ₹ | D39: =D21+D37 -> 82733 | E39: =E21+E37 -> 107046 | F39: =F21+F37 -> 117113 | G39: =G21+G37 -> 114792 | H39: =H21+H37 -> 128184 | K39: =K21+K37 -> 134090.33 | L39: =L21+L37 -> 140530.79 | M39: =M21+M37 -> 147656.27 | N39: =N21+N37 -> 155346.98 | O39: =O21+O37 -> 163789.61 | P39: =K79-K39 -> 0 | Q39: =L79-L39 -> 0 | R39: =M79-M39 -> 0 | S39: =N79-N39 -> 0 | T39: =O79-O39 -> 0
B41: LIABILITIES
B43: Current Liabilities
B45: Short Term Borrowings | C45: ₹ | D45: =STATEMENTS!C45 -> 7587 | E45: =STATEMENTS!D45 -> 9523 | F45: =STATEMENTS!E45 -> 8882 | G45: =STATEMENTS!F45 -> 7917 | H45: =STATEMENTS!G45 -> 9786 | K45: =CHOOSE($I$1,'P & L ASSUMPTIONS'!K88,'P & L ASSUMPTIONS'!R88,'P & L ASSUMPTIONS'!Y88) -> 9442.98 | L45: =CHOOSE($I$1,'P & L ASSUMPTIONS'!L88,'P & L ASSUMPTIONS'!S88,'P & L ASSUMPTIONS'!Z88) -> 9184.56 | M45: =CHOOSE($I$1,'P & L ASSUMPTIONS'!M88,'P & L ASSUMPTIONS'!T88,'P & L ASSUMPTIONS'!AA88) -> 8932.14 | N45: =CHOOSE($I$1,'P & L ASSUMPTIONS'!N88,'P & L ASSUMPTIONS'!U88,'P & L ASSUMPTIONS'!AB88) -> 8684.52 | O45: =CHOOSE($I$1,'P & L ASSUMPTIONS'!O88,'P & L ASSUMPTIONS'!V88,'P & L ASSUMPTIONS'!AC88) -> 8440.5
B46: Lease Liabilities | C46: ₹ | D46: =STATEMENTS!C46 -> 767 | E46: =STATEMENTS!D46 -> 906 | F46: =STATEMENTS!E46 -> 862 | G46: =STATEMENTS!F46 -> 922 | H46: =STATEMENTS!G46 -> 803 | K46: =CHOOSE($I$1,'BALANCE SHEET ASSUMPTION'!K131,'BALANCE SHEET ASSUMPTION'!R131,'BALANCE SHEET ASSUMPTION'!Y131) -> 968.89086 | L46: =CHOOSE($I$1,'BALANCE SHEET ASSUMPTION'!L131,'BALANCE SHEET ASSUMPTION'!S131,'BALANCE SHEET ASSUMPTION'!Z131) -> 993.83026 | M46: =CHOOSE($I$1,'BALANCE SHEET ASSUMPTION'!M131,'BALANCE SHEET ASSUMPTION'!T131,'BALANCE SHEET ASSUMPTION'!AA131) -> 1038.0666 | N46: =CHOOSE($I$1,'BALANCE SHEET ASSUMPTION'!N131,'BALANCE SHEET ASSUMPTION'!U131,'BALANCE SHEET ASSUMPTION'!AB131) -> 1083.2885 | O46: =CHOOSE($I$1,'BALANCE SHEET ASSUMPTION'!O131,'BALANCE SHEET ASSUMPTION'!V131,'BALANCE SHEET ASSUMPTION'!AC131) -> 1173.6561
B47: Derivative Liabilities | C47: ₹ | D47: =STATEMENTS!C47 -> 107 | E47: =STATEMENTS!D47 -> 59 | F47: =STATEMENTS!E47 -> 283 | G47: =STATEMENTS!F47 -> 56 | H47: =STATEMENTS!G47 -> 97 | K47: =AVERAGE(D47:H47) -> 120.4 | L47: =K47 -> 120.4 | M47: =L47 -> 120.4 | N47: =M47 -> 120.4 | O47: =N47 -> 120.4
B48: Trade Payables | C48: ₹ | D48: =STATEMENTS!C48 -> 5182 | E48: =STATEMENTS!D48 -> 6252 | F48: =STATEMENTS!E48 -> 5972 | G48: =STATEMENTS!F48 -> 5766 | H48: =STATEMENTS!G48 -> 5867 | K48: =CHOOSE($I$1,'BALANCE SHEET ASSUMPTION'!K$108,'BALANCE SHEET ASSUMPTION'!R$108,'BALANCE SHEET ASSUMPTION'!Y$108) -> 5741.2701 | L48: =CHOOSE($I$1,'BALANCE SHEET ASSUMPTION'!L$108,'BALANCE SHEET ASSUMPTION'!S$108,'BALANCE SHEET ASSUMPTION'!Z$108) -> 5683.8574 | M48: =CHOOSE($I$1,'BALANCE SHEET ASSUMPTION'!M$108,'BALANCE SHEET ASSUMPTION'!T$108,'BALANCE SHEET ASSUMPTION'!AA$108) -> 5740.6959 | N48: =CHOOSE($I$1,'BALANCE SHEET ASSUMPTION'!N$108,'BALANCE SHEET ASSUMPTION'!U$108,'BALANCE SHEET ASSUMPTION'!AB$108) -> 5798.1029 | O48: =CHOOSE($I$1,'BALANCE SHEET ASSUMPTION'!O$108,'BALANCE SHEET ASSUMPTION'!V$108,'BALANCE SHEET ASSUMPTION'!AC$108) -> 5914.0649
B49: Other Financial Liabilities | C49: ₹ | D49: =STATEMENTS!C49 -> 2617 | E49: =STATEMENTS!D49 -> 6507 | F49: =STATEMENTS!E49 -> 3347 | G49: =STATEMENTS!F49 -> 3318 | H49: =STATEMENTS!G49 -> 3346 | K49: =CHOOSE($I$1,'BALANCE SHEET ASSUMPTION'!K141,'BALANCE SHEET ASSUMPTION'!R141,'BALANCE SHEET ASSUMPTION'!Y141) -> 3120.0131 | L49: =CHOOSE($I$1,'BALANCE SHEET ASSUMPTION'!L141,'BALANCE SHEET ASSUMPTION'!S141,'BALANCE SHEET ASSUMPTION'!Z141) -> 3018.6793 | M49: =CHOOSE($I$1,'BALANCE SHEET ASSUMPTION'!M141,'BALANCE SHEET ASSUMPTION'!T141,'BALANCE SHEET ASSUMPTION'!AA141) -> 2975.173 | N49: =CHOOSE($I$1,'BALANCE SHEET ASSUMPTION'!N141,'BALANCE SHEET ASSUMPTION'!U141,'BALANCE SHEET ASSUMPTION'!AB141) -> 2930.4126 | O49: =CHOOSE($I$1,'BALANCE SHEET ASSUMPTION'!O141,'BALANCE SHEET ASSUMPTION'!V141,'BALANCE SHEET ASSUMPTION'!AC141) -> 2911.4337
B50: Contract Liabilities | C50: ₹ | D50: =STATEMENTS!C50 -> 2253 | E50: =STATEMENTS!D50 -> 2792 | F50: =STATEMENTS!E50 -> 2268 | G50: =STATEMENTS!F50 -> 1765 | H50: =STATEMENTS!G50 -> 2006 | K50: =CHOOSE($I$1,'BALANCE SHEET ASSUMPTION'!K168,'BALANCE SHEET ASSUMPTION'!R168,'BALANCE SHEET ASSUMPTION'!Y168) -> 2443.0602 | L50: =CHOOSE($I$1,'BALANCE SHEET ASSUMPTION'!L168,'BALANCE SHEET ASSUMPTION'!S168,'BALANCE SHEET ASSUMPTION'!Z168) -> 2418.6296 | M50: =CHOOSE($I$1,'BALANCE SHEET ASSUMPTION'!M168,'BALANCE SHEET ASSUMPTION'!T168,'BALANCE SHEET ASSUMPTION'!AA168) -> 2442.8159 | N50: =CHOOSE($I$1,'BALANCE SHEET ASSUMPTION'!N168,'BALANCE SHEET ASSUMPTION'!U168,'BALANCE SHEET ASSUMPTION'!AB168) -> 2467.2441 | O50: =CHOOSE($I$1,'BALANCE SHEET ASSUMPTION'!O168,'BALANCE SHEET ASSUMPTION'!V168,'BALANCE SHEET ASSUMPTION'!AC168) -> 2516.589
B51: Other Current Liabilities | C51: ₹ | D51: =STATEMENTS!C51 -> 975 | E51: =STATEMENTS!D51 -> 1208 | F51: =STATEMENTS!E51 -> 1430 | G51: =STATEMENTS!F51 -> 1524 | H51: =STATEMENTS!G51 -> 1508 | K51: =CHOOSE($I$1,'BALANCE SHEET ASSUMPTION'!K146,'BALANCE SHEET ASSUMPTION'!R146,'BALANCE SHEET ASSUMPTION'!Y146) -> 1516.8546 | L51: =CHOOSE($I$1,'BALANCE SHEET ASSUMPTION'!L146,'BALANCE SHEET ASSUMPTION'!S146,'BALANCE SHEET ASSUMPTION'!Z146) -> 1505.7084 | M51: =CHOOSE($I$1,'BALANCE SHEET ASSUMPTION'!M146,'BALANCE SHEET ASSUMPTION'!T146,'BALANCE SHEET ASSUMPTION'!AA146) -> 1523.5811 | N51: =CHOOSE($I$1,'BALANCE SHEET ASSUMPTION'!N146,'BALANCE SHEET ASSUMPTION'!U146,'BALANCE SHEET ASSUMPTION'!AB146) -> 1541.7733 | O51: =CHOOSE($I$1,'BALANCE SHEET ASSUMPTION'!O146,'BALANCE SHEET ASSUMPTION'!V146,'BALANCE SHEET ASSUMPTION'!AC146) -> 1574.937
B52: Provisions | C52: ₹ | D52: =STATEMENTS!C52 -> 1784 | E52: =STATEMENTS!D52 -> 1808 | F52: =STATEMENTS!E52 -> 1843 | G52: =STATEMENTS!F52 -> 1803 | H52: =STATEMENTS!G52 -> 1764 | K52: =CHOOSE($I$1,'BALANCE SHEET ASSUMPTION'!K154,'BALANCE SHEET ASSUMPTION'!R154,'BALANCE SHEET ASSUMPTION'!Y154) -> 1785.9888 | L52: =CHOOSE($I$1,'BALANCE SHEET ASSUMPTION'!L154,'BALANCE SHEET ASSUMPTION'!S154,'BALANCE SHEET ASSUMPTION'!Z154) -> 1750.4236 | M52: =CHOOSE($I$1,'BALANCE SHEET ASSUMPTION'!M154,'BALANCE SHEET ASSUMPTION'!T154,'BALANCE SHEET ASSUMPTION'!AA154) -> 1748.4934 | N52: =CHOOSE($I$1,'BALANCE SHEET ASSUMPTION'!N154,'BALANCE SHEET ASSUMPTION'!U154,'BALANCE SHEET ASSUMPTION'!AB154) -> 1746.3923 | O52: =CHOOSE($I$1,'BALANCE SHEET ASSUMPTION'!O154,'BALANCE SHEET ASSUMPTION'!V154,'BALANCE SHEET ASSUMPTION'!AC154) -> 1737.0111
B53: Tax Liabilities | C53: ₹ | D53: =STATEMENTS!C53 -> 1732 | E53: =STATEMENTS!D53 -> 1323 | F53: =STATEMENTS!E53 -> 1885 | G53: =STATEMENTS!F53 -> 2176 | H53: =STATEMENTS!G53 -> 3448 | K53: =CHOOSE($I$1,'BALANCE SHEET ASSUMPTION'!K160,'BALANCE SHEET ASSUMPTION'!R160,'BALANCE SHEET ASSUMPTION'!Y160) -> 3631.4114 | L53: =CHOOSE($I$1,'BALANCE SHEET ASSUMPTION'!L160,'BALANCE SHEET ASSUMPTION'!S160,'BALANCE SHEET ASSUMPTION'!Z160) -> 3617.1256 | M53: =CHOOSE($I$1,'BALANCE SHEET ASSUMPTION'!M160,'BALANCE SHEET ASSUMPTION'!T160,'BALANCE SHEET ASSUMPTION'!AA160) -> 3683.6658 | N53: =CHOOSE($I$1,'BALANCE SHEET ASSUMPTION'!N160,'BALANCE SHEET ASSUMPTION'!U160,'BALANCE SHEET ASSUMPTION'!AB160) -> 3751.8738 | O53: =CHOOSE($I$1,'BALANCE SHEET ASSUMPTION'!O160,'BALANCE SHEET ASSUMPTION'!V160,'BALANCE SHEET ASSUMPTION'!AC160) -> 3861.2979
B55: Total Current Liabilities | C55: ₹ | D55: =SUM(D45:D53) -> 23004 | E55: =SUM(E45:E53) -> 30378 | F55: =SUM(F45:F53) -> 26772 | G55: =SUM(G45:G53) -> 25247 | H55: =SUM(H45:H53) -> 28625 | K55: =SUM(K45:K53) -> 28770.869 | L55: =SUM(L45:L53) -> 28293.214 | M55: =SUM(M45:M53) -> 28205.032 | N55: =SUM(N45:N53) -> 28124.007 | O55: =SUM(O45:O53) -> 28249.89
B57: Non Current Liabilities
B59: Long Term Borrowings | C59: ₹ | D59: =STATEMENTS!C37 -> 746 | E59: =STATEMENTS!D37 -> 5646 | F59: =STATEMENTS!E37 -> 6127 | G59: =STATEMENTS!F37 -> 6230 | H59: =STATEMENTS!G37 -> 6395 | K59: =CHOOSE($I$1,'P & L ASSUMPTIONS'!K90,'P & L ASSUMPTIONS'!R90,'P & L ASSUMPTIONS'!Y90) -> 6838.02 | L59: =CHOOSE($I$1,'P & L ASSUMPTIONS'!L90,'P & L ASSUMPTIONS'!S90,'P & L ASSUMPTIONS'!Z90) -> 7216.44 | M59: =CHOOSE($I$1,'P & L ASSUMPTIONS'!M90,'P & L ASSUMPTIONS'!T90,'P & L ASSUMPTIONS'!AA90) -> 7608.86 | N59: =CHOOSE($I$1,'P & L ASSUMPTIONS'!N90,'P & L ASSUMPTIONS'!U90,'P & L ASSUMPTIONS'!AB90) -> 8016.48 | O59: =CHOOSE($I$1,'P & L ASSUMPTIONS'!O90,'P & L ASSUMPTIONS'!V90,'P & L ASSUMPTIONS'!AC90) -> 8440.5
B60: Lease Liabilities | C60: ₹ | D60: =STATEMENTS!C38 -> 1351 | E60: =STATEMENTS!D38 -> 1518 | F60: =STATEMENTS!E38 -> 1595 | G60: =STATEMENTS!F38 -> 1396 | H60: =STATEMENTS!G38 -> 2219 | K60: =CHOOSE($I$1,'BALANCE SHEET ASSUMPTION'!K133,'BALANCE SHEET ASSUMPTION'!R133,'BALANCE SHEET ASSUMPTION'!Y133) -> 1799.3687 | L60: =CHOOSE($I$1,'BALANCE SHEET ASSUMPTION'!L133,'BALANCE SHEET ASSUMPTION'!S133,'BALANCE SHEET ASSUMPTION'!Z133) -> 1845.6848 | M60: =CHOOSE($I$1,'BALANCE SHEET ASSUMPTION'!M133,'BALANCE SHEET ASSUMPTION'!T133,'BALANCE SHEET ASSUMPTION'!AA133) -> 1927.8379 | N60: =CHOOSE($I$1,'BALANCE SHEET ASSUMPTION'!N133,'BALANCE SHEET ASSUMPTION'!U133,'BALANCE SHEET ASSUMPTION'!AB133) -> 2011.8214 | O60: =CHOOSE($I$1,'BALANCE SHEET ASSUMPTION'!O133,'BALANCE SHEET ASSUMPTION'!V133,'BALANCE SHEET ASSUMPTION'!AC133) -> 2179.6471
B61: Other Financial Liabilities | C61: ₹ | D61: =STATEMENTS!C39 -> 229 | E61: =STATEMENTS!D39 -> 296 | F61: =STATEMENTS!E39 -> 265 | G61: =STATEMENTS!F39 -> 499 | H61: =STATEMENTS!G39 -> 779 | K61: =CHOOSE($I$1,'BALANCE SHEET ASSUMPTION'!K143,'BALANCE SHEET ASSUMPTION'!R143,'BALANCE SHEET ASSUMPTION'!Y143) -> 829.37058 | L61: =CHOOSE($I$1,'BALANCE SHEET ASSUMPTION'!L143,'BALANCE SHEET ASSUMPTION'!S143,'BALANCE SHEET ASSUMPTION'!Z143) -> 901.68342 | M61: =CHOOSE($I$1,'BALANCE SHEET ASSUMPTION'!M143,'BALANCE SHEET ASSUMPTION'!T143,'BALANCE SHEET ASSUMPTION'!AA143) -> 991.72432 | N61: =CHOOSE($I$1,'BALANCE SHEET ASSUMPTION'!N143,'BALANCE SHEET ASSUMPTION'!U143,'BALANCE SHEET ASSUMPTION'!AB143) -> 1083.8512 | O61: =CHOOSE($I$1,'BALANCE SHEET ASSUMPTION'!O143,'BALANCE SHEET ASSUMPTION'!V143,'BALANCE SHEET ASSUMPTION'!AC143) -> 1189.1771
B62: Provisions | C62: ₹ | D62: =STATEMENTS!C40 -> 306 | E62: =STATEMENTS!D40 -> 272 | F62: =STATEMENTS!E40 -> 295 | G62: =STATEMENTS!F40 -> 422 | H62: =STATEMENTS!G40 -> 466 | K62: =CHOOSE($I$1,'BALANCE SHEET ASSUMPTION'!K156,'BALANCE SHEET ASSUMPTION'!R156,'BALANCE SHEET ASSUMPTION'!Y156) -> 474.75652 | L62: =CHOOSE($I$1,'BALANCE SHEET ASSUMPTION'!L156,'BALANCE SHEET ASSUMPTION'!S156,'BALANCE SHEET ASSUMPTION'!Z156) -> 493.70922 | M62: =CHOOSE($I$1,'BALANCE SHEET ASSUMPTION'!M156,'BALANCE SHEET ASSUMPTION'!T156,'BALANCE SHEET ASSUMPTION'!AA156) -> 522.27725 | N62: =CHOOSE($I$1,'BALANCE SHEET ASSUMPTION'!N156,'BALANCE SHEET ASSUMPTION'!U156,'BALANCE SHEET ASSUMPTION'!AB156) -> 551.49231 | O62: =CHOOSE($I$1,'BALANCE SHEET ASSUMPTION'!O156,'BALANCE SHEET ASSUMPTION'!V156,'BALANCE SHEET ASSUMPTION'!AC156) -> 610.30119
B63: Deferred Tax Liabilities | C63: ₹ | D63: =STATEMENTS!C41 -> 461 | E63: =STATEMENTS!D41 -> 1214 | F63: =STATEMENTS!E41 -> 1515 | G63: =STATEMENTS!F41 -> 1747 | H63: =STATEMENTS!G41 -> 1644 | K63: =CHOOSE($I$1,'BALANCE SHEET ASSUMPTION'!K165,'BALANCE SHEET ASSUMPTION'!R165,'BALANCE SHEET ASSUMPTION'!Y165) -> 1517.2378 | L63: =CHOOSE($I$1,'BALANCE SHEET ASSUMPTION'!L165,'BALANCE SHEET ASSUMPTION'!S165,'BALANCE SHEET ASSUMPTION'!Z165) -> 1758.5834 | M63: =CHOOSE($I$1,'BALANCE SHEET ASSUMPTION'!M165,'BALANCE SHEET ASSUMPTION'!T165,'BALANCE SHEET ASSUMPTION'!AA165) -> 1772.8422 | N63: =CHOOSE($I$1,'BALANCE SHEET ASSUMPTION'!N165,'BALANCE SHEET ASSUMPTION'!U165,'BALANCE SHEET ASSUMPTION'!AB165) -> 1873.1497 | O63: =CHOOSE($I$1,'BALANCE SHEET ASSUMPTION'!O165,'BALANCE SHEET ASSUMPTION'!V165,'BALANCE SHEET ASSUMPTION'!AC165) -> 1867.0358
B64: Tax Liabilities | C64: ₹ | D64: =STATEMENTS!C42 -> 1107 | E64: =STATEMENTS!D42 -> 1782 | F64: =STATEMENTS!E42 -> 2178 | G64: =STATEMENTS!F42 -> 3709 | H64: =STATEMENTS!G42 -> 4202 | K64: =CHOOSE($I$1,'BALANCE SHEET ASSUMPTION'!K162,'BALANCE SHEET ASSUMPTION'!R162,'BALANCE SHEET ASSUMPTION'!Y162) -> 4832.3 | L64: =CHOOSE($I$1,'BALANCE SHEET ASSUMPTION'!L162,'BALANCE SHEET ASSUMPTION'!S162,'BALANCE SHEET ASSUMPTION'!Z162) -> 5557.145 | M64: =CHOOSE($I$1,'BALANCE SHEET ASSUMPTION'!M162,'BALANCE SHEET ASSUMPTION'!T162,'BALANCE SHEET ASSUMPTION'!AA162) -> 6390.7168 | N64: =CHOOSE($I$1,'BALANCE SHEET ASSUMPTION'!N162,'BALANCE SHEET ASSUMPTION'!U162,'BALANCE SHEET ASSUMPTION'!AB162) -> 7349.3243 | O64: =CHOOSE($I$1,'BALANCE SHEET ASSUMPTION'!O162,'BALANCE SHEET ASSUMPTION'!V162,'BALANCE SHEET ASSUMPTION'!AC162) -> 8451.7229
B65: Other Non Current Liabilities | C65: ₹ | D65: =STATEMENTS!C43 -> 478 | E65: =STATEMENTS!D43 -> 485 | F65: =STATEMENTS!E43 -> 639 | G65: =STATEMENTS!F43 -> 875 | H65: =STATEMENTS!G43 -> 1276 | K65: =CHOOSE($I$1,'BALANCE SHEET ASSUMPTION'!K136,'BALANCE SHEET ASSUMPTION'!R136,'BALANCE SHEET ASSUMPTION'!Y136) -> 1476.4051 | L65: =CHOOSE($I$1,'BALANCE SHEET ASSUMPTION'!L136,'BALANCE SHEET ASSUMPTION'!S136,'BALANCE SHEET ASSUMPTION'!Z136) -> 1557.1534 | M65: =CHOOSE($I$1,'BALANCE SHEET ASSUMPTION'!M136,'BALANCE SHEET ASSUMPTION'!T136,'BALANCE SHEET ASSUMPTION'!AA136) -> 1668.3213 | N65: =CHOOSE($I$1,'BALANCE SHEET ASSUMPTION'!N136,'BALANCE SHEET ASSUMPTION'!U136,'BALANCE SHEET ASSUMPTION'!AB136) -> 1782.033 | O65: =CHOOSE($I$1,'BALANCE SHEET ASSUMPTION'!O136,'BALANCE SHEET ASSUMPTION'!V136,'BALANCE SHEET ASSUMPTION'!AC136) -> 1916.1733
B67: Total Non Current Liabilities | C67: ₹ | D67: =SUM(D59:D65) -> 4678 | E67: =SUM(E59:E65) -> 11213 | F67: =SUM(F59:F65) -> 12614 | G67: =SUM(G59:G65) -> 14878 | H67: =SUM(H59:H65) -> 16981 | K67: =SUM(K59:K65) -> 17767.459 | L67: =SUM(L59:L65) -> 19330.399 | M67: =SUM(M59:M65) -> 20882.58 | N67: =SUM(N59:N65) -> 22668.152 | O67: =SUM(O59:O65) -> 24654.557
B69: Total Liabilities | C69: ₹ | D69: =SUM(D67,D55) -> 27682 | E69: =SUM(E67,E55) -> 41591 | F69: =SUM(F67,F55) -> 39386 | G69: =SUM(G67,G55) -> 40125 | H69: =SUM(H67,H55) -> 45606 | K69: =SUM(K67,K55) -> 46538.328 | L69: =SUM(L67,L55) -> 47623.613 | M69: =SUM(M67,M55) -> 49087.611 | N69: =SUM(N67,N55) -> 50792.159 | O69: =SUM(O67,O55) -> 52904.447
B71: EQUITY
B73: Share Capital | C73: ₹ | D73: =STATEMENTS!C32 -> 1096 | E73: =STATEMENTS!D32 -> 1096 | F73: =STATEMENTS!E32 -> 1098 | G73: =STATEMENTS!F32 -> 1045 | H73: =STATEMENTS!G32 -> 2094 | K73: =CHOOSE($I$1,'BALANCE SHEET ASSUMPTION'!K$118,'BALANCE SHEET ASSUMPTION'!R$118,'BALANCE SHEET ASSUMPTION'!Y$118) -> 2344 | L73: =CHOOSE($I$1,'BALANCE SHEET ASSUMPTION'!L$118,'BALANCE SHEET ASSUMPTION'!S$118,'BALANCE SHEET ASSUMPTION'!Z$118) -> 2594 | M73: =CHOOSE($I$1,'BALANCE SHEET ASSUMPTION'!M$118,'BALANCE SHEET ASSUMPTION'!T$118,'BALANCE SHEET ASSUMPTION'!AA$118) -> 2844 | N73: =CHOOSE($I$1,'BALANCE SHEET ASSUMPTION'!N$118,'BALANCE SHEET ASSUMPTION'!U$118,'BALANCE SHEET ASSUMPTION'!AB$118) -> 3094 | O73: =CHOOSE($I$1,'BALANCE SHEET ASSUMPTION'!O$118,'BALANCE SHEET ASSUMPTION'!V$118,'BALANCE SHEET ASSUMPTION'!AC$118) -> 3344
B74: Other Equity | C74: ₹ | D74: =STATEMENTS!C33 -> 53805 | E74: =STATEMENTS!D33 -> 64307 | F74: =STATEMENTS!E33 -> 76570 | G74: =STATEMENTS!F33 -> 73488 | H74: =STATEMENTS!G33 -> 80270 | K74: =CHOOSE($I$1,'BALANCE SHEET ASSUMPTION'!K$120,'BALANCE SHEET ASSUMPTION'!R$120,'BALANCE SHEET ASSUMPTION'!Y$120) -> 85086.2 | L74: =CHOOSE($I$1,'BALANCE SHEET ASSUMPTION'!L$120,'BALANCE SHEET ASSUMPTION'!S$120,'BALANCE SHEET ASSUMPTION'!Z$120) -> 90191.372 | M74: =CHOOSE($I$1,'BALANCE SHEET ASSUMPTION'!M$120,'BALANCE SHEET ASSUMPTION'!T$120,'BALANCE SHEET ASSUMPTION'!AA$120) -> 95602.854 | N74: =CHOOSE($I$1,'BALANCE SHEET ASSUMPTION'!N$120,'BALANCE SHEET ASSUMPTION'!U$120,'BALANCE SHEET ASSUMPTION'!AB$120) -> 101339.03 | O74: =CHOOSE($I$1,'BALANCE SHEET ASSUMPTION'!O$120,'BALANCE SHEET ASSUMPTION'!V$120,'BALANCE SHEET ASSUMPTION'!AC$120) -> 107419.37
B75: Non Controlling Interest | C75: ₹ | D75: =STATEMENTS!C35 -> 150 | E75: =STATEMENTS!D35 -> 52 | F75: =STATEMENTS!E35 -> 59 | G75: =STATEMENTS!F35 -> 134 | H75: =STATEMENTS!G35 -> 214 | K75: =AVERAGE(D75:H75) -> 121.8 | L75: =$K$75 -> 121.8 | M75: =$K$75 -> 121.8 | N75: =$K$75 -> 121.8 | O75: =$K$75 -> 121.8
B77: Total Equity | C77: ₹ | D77: =SUM(D73:D75) -> 55051 | E77: =SUM(E73:E75) -> 65455 | F77: =SUM(F73:F75) -> 77727 | G77: =SUM(G73:G75) -> 74667 | H77: =SUM(H73:H75) -> 82578 | K77: =SUM(K73:K75) -> 87552 | L77: =SUM(L73:L75) -> 92907.172 | M77: =SUM(M73:M75) -> 98568.654 | N77: =SUM(N73:N75) -> 104554.83 | O77: =SUM(O73:O75) -> 110885.17
B79: Total Equity + Total Liabilities | C79: ₹ | D79: =SUM(D77,D69) -> 82733 | E79: =SUM(E77,E69) -> 107046 | F79: =SUM(F77,F69) -> 117113 | G79: =SUM(G77,G69) -> 114792 | H79: =SUM(H77,H69) -> 128184 | K79: =SUM(K77,K69) -> 134090.33 | L79: =SUM(L77,L69) -> 140530.79 | M79: =SUM(M77,M69) -> 147656.27 | N79: =SUM(N77,N69) -> 155346.98 | O79: =SUM(O77,O69) -> 163789.61
B81: Check | D81: =IF(D79=D39,"--","Nope") -> -- | E81: =IF(E79=E39,"--","Nope") -> -- | F81: =IF(F79=F39,"--","Nope") -> -- | G81: =IF(G79=G39,"--","Nope") -> -- | H81: =IF(H79=H39,"--","Nope") -> -- | K81: =IF(K79=K39,"--","Nope") -> -- | L81: =IF(L79=L39,"--","Nope") -> -- | M81: =IF(M79=M39,"--","Nope") -> -- | N81: =IF(N79=N39,"--","Nope") -> -- | O81: =IF(O79=O39,"--","Nope") -> --

Sheet CASH FLOW ASSUMPTION
B1: WIPRO | D1: BALANCE SHEET - FORECAST (BEST CASE) | K1: BALANCE SHEET - FORECAST (BASE CASE) | R1: BALANCE SHEET - FORECAST (WORST CASE)
C3: UNIT | D3: Year 6 | E3: Year 7 | F3: Year 8 | G3: Year 9 | H3: Year 10 | K3: Year 6 | L3: Year 7 | M3: Year 8 | N3: Year 9 | O3: Year 10 | R3: Year 6 | S3: Year 7 | T3: Year 8 | U3: Year 9 | V3: Year 10
B4: Particulars (In Crores) | D4: ='PROFIT & LOSS'!K4 -> 46102 | E4: ='PROFIT & LOSS'!L4 -> 46467 | F4: ='PROFIT & LOSS'!M4 -> 46833 | G4: ='PROFIT & LOSS'!N4 -> 47198 | H4: ='PROFIT & LOSS'!O4 -> 47563 | K4: =D$4 -> 46102 | L4: =E$4 -> 46467 | M4: =F$4 -> 46833 | N4: =G$4 -> 47198 | O4: =H$4 -> 47563 | R4: =K$4 -> 46102 | S4: =L$4 -> 46467 | T4: =M$4 -> 46833 | U4: =N$4 -> 47198 | V4: =O$4 -> 47563
B6: OPERATING ACTIVITIES
B8: Net Profit | C8: ₹ | D8: ='P & L ASSUMPTIONS'!K96-'P & L ASSUMPTIONS'!K99 -> 14980.614 | E8: ='P & L ASSUMPTIONS'!L96-'P & L ASSUMPTIONS'!L99 -> 15252.888 | F8: ='P & L ASSUMPTIONS'!M96-'P & L ASSUMPTIONS'!M99 -> 15701.409 | G8: ='P & L ASSUMPTIONS'!N96-'P & L ASSUMPTIONS'!N99 -> 16166.563 | H8: ='P & L ASSUMPTIONS'!O96-'P & L ASSUMPTIONS'!O99 -> 16808.258 | K8: ='P & L ASSUMPTIONS'!R96-'P & L ASSUMPTIONS'!R99 -> 13528.788 | L8: ='P & L ASSUMPTIONS'!S96-'P & L ASSUMPTIONS'!S99 -> 13475.566 | M8: ='P & L ASSUMPTIONS'!T96-'P & L ASSUMPTIONS'!T99 -> 13723.461 | N8: ='P & L ASSUMPTIONS'!U96-'P & L ASSUMPTIONS'!U99 -> 13977.569 | O8: ='P & L ASSUMPTIONS'!V96-'P & L ASSUMPTIONS'!V99 -> 14385.228 | R8: ='P & L ASSUMPTIONS'!Y96-'P & L ASSUMPTIONS'!Y99 -> 12518.346 | S8: ='P & L ASSUMPTIONS'!Z96-'P & L ASSUMPTIONS'!Z99 -> 12394.916 | T8: ='P & L ASSUMPTIONS'!AA96-'P & L ASSUMPTIONS'!AA99 -> 12339.722 | U8: ='P & L ASSUMPTIONS'!AB96-'P & L ASSUMPTIONS'!AB99 -> 12283.261 | V8: ='P & L ASSUMPTIONS'!AC96-'P & L ASSUMPTIONS'!AC99 -> 12484.686
B9: Depreciation & Amortization | C9: ₹ | D9: ='P & L ASSUMPTIONS'!K70 -> 3378.45 | E9: ='P & L ASSUMPTIONS'!L70 -> 3485.3995 | F9: ='P & L ASSUMPTIONS'!M70 -> 3588.4807 | G9: ='P & L ASSUMPTIONS'!N70 -> 3693.0873 | H9: ='P & L ASSUMPTIONS'!O70 -> 3799.3696 | K9: ='P & L ASSUMPTIONS'!R70 -> 3265.835 | L9: ='P & L ASSUMPTIONS'!S70 -> 3323.8395 | M9: ='P & L ASSUMPTIONS'!T70 -> 3373.7128 | N9: ='P & L ASSUMPTIONS'!U70 -> 3424.996 | O9: ='P & L ASSUMPTIONS'!V70 -> 3477.628 | R9: ='P & L ASSUMPTIONS'!Y70 -> 2927.99 | S9: ='P & L ASSUMPTIONS'!Z70 -> 2949.5539 | T9: ='P & L ASSUMPTIONS'!AA70 -> 2965.664 | U9: ='P & L ASSUMPTIONS'!AB70 -> 2978.8052 | V9: ='P & L ASSUMPTIONS'!AC70 -> 2989.3113
B11: Change in Networking Capital
B13: Current Assets
B15: Inventories | C15: ₹ | D15: =('BALANCE SHEET ASSUMPTION'!K105-'BALANCE SHEET ASSUMPTION'!H105)*-1 -> -106.02741 | E15: =('BALANCE SHEET ASSUMPTION'!L105-'BALANCE SHEET ASSUMPTION'!K105)*-1 -> -1.7502741 | F15: =('BALANCE SHEET ASSUMPTION'!M105-'BALANCE SHEET ASSUMPTION'!L105)*-1 -> -3.5355537 | G15: =('BALANCE SHEET ASSUMPTION'!N105-'BALANCE SHEET ASSUMPTION'!M105)*-1 -> -3.6062648 | H15: =('BALANCE SHEET ASSUMPTION'!O105-'BALANCE SHEET ASSUMPTION'!N105)*-1 -> -5.5175851 | K15: =('BALANCE SHEET ASSUMPTION'!R105-'BALANCE SHEET ASSUMPTION'!H105)*-1 -> -104.97788 | L15: =('BALANCE SHEET ASSUMPTION'!S105-'BALANCE SHEET ASSUMPTION'!R105)*-1 -> 1.7397788 | M15: =('BALANCE SHEET ASSUMPTION'!T105-'BALANCE SHEET ASSUMPTION'!S105)*-1 -> -1.722381 | N15: =('BALANCE SHEET ASSUMPTION'!U105-'BALANCE SHEET ASSUMPTION'!T105)*-1 -> -1.7396048 | O15: =('BALANCE SHEET ASSUMPTION'!V105-'BALANCE SHEET ASSUMPTION'!U105)*-1 -> -3.5140018 | R15: =('BALANCE SHEET ASSUMPTION'!Y105-'BALANCE SHEET ASSUMPTION'!H105)*-1 -> -106.50336 | S15: =('BALANCE SHEET ASSUMPTION'!Z105-'BALANCE SHEET ASSUMPTION'!Y105)*-1 -> 2.6325504 | T15: =('BALANCE SHEET ASSUMPTION'!AA105-'BALANCE SHEET ASSUMPTION'!Z105)*-1 -> 1.7287081 | U15: =('BALANCE SHEET ASSUMPTION'!AB105-'BALANCE SHEET ASSUMPTION'!AA105)*-1 -> 1.711421 | V15: =('BALANCE SHEET ASSUMPTION'!AC105-'BALANCE SHEET ASSUMPTION'!AB105)*-1 -> -1.6943068
B16: Trade Receivables | C16: ₹ | D16: =('BALANCE SHEET ASSUMPTION'!K99-'BALANCE SHEET ASSUMPTION'!H99)*-1 -> 659.72723 | E16: =('BALANCE SHEET ASSUMPTION'!L99-'BALANCE SHEET ASSUMPTION'!K99)*-1 -> 125.8352 | F16: =('BALANCE SHEET ASSUMPTION'!M99-'BALANCE SHEET ASSUMPTION'!L99)*-1 -> 293.99665 | G16: =('BALANCE SHEET ASSUMPTION'!N99-'BALANCE SHEET ASSUMPTION'!M99)*-1 -> 38.888929 | H16: =('BALANCE SHEET ASSUMPTION'!O99-'BALANCE SHEET ASSUMPTION'!N99)*-1 -> 227.59147 | K16: =('BALANCE SHEET ASSUMPTION'!R99-'BALANCE SHEET ASSUMPTION'!H99)*-1 -> 368.59068 | L16: =('BALANCE SHEET ASSUMPTION'!S99-'BALANCE SHEET ASSUMPTION'!R99)*-1 -> 334.54798 | M16: =('BALANCE SHEET ASSUMPTION'!T99-'BALANCE SHEET ASSUMPTION'!S99)*-1 -> 376.79376 | N16: =('BALANCE SHEET ASSUMPTION'!U99-'BALANCE SHEET ASSUMPTION'!T99)*-1 -> 129.61663 | O16: =('BALANCE SHEET ASSUMPTION'!V99-'BALANCE SHEET ASSUMPTION'!U99)*-1 -> 35.871261 | R16: =('BALANCE SHEET ASSUMPTION'!Y99-'BALANCE SHEET ASSUMPTION'!H99)*-1 -> 176.81414 | S16: =('BALANCE SHEET ASSUMPTION'!Z99-'BALANCE SHEET ASSUMPTION'!Y99)*-1 -> -102.7948 | T16: =('BALANCE SHEET ASSUMPTION'!AA99-'BALANCE SHEET ASSUMPTION'!Z99)*-1 -> -156.74833 | U16: =('BALANCE SHEET ASSUMPTION'!AB99-'BALANCE SHEET ASSUMPTION'!AA99)*-1 -> -154.9956 | V16: =('BALANCE SHEET ASSUMPTION'!AC99-'BALANCE SHEET ASSUMPTION'!AB99)*-1 -> -385.49097
B17: Unbilled Receivables | C17: ₹ | D17: =('BALANCE SHEET ASSUMPTION'!K23-'BALANCE SHEET ASSUMPTION'!H23)*-1 -> 1029.2672 | E17: =('BALANCE SHEET ASSUMPTION'!L23-'BALANCE SHEET ASSUMPTION'!K23)*-1 -> -53.987328 | F17: =('BALANCE SHEET ASSUMPTION'!M23-'BALANCE SHEET ASSUMPTION'!L23)*-1 -> -109.0544 | G17: =('BALANCE SHEET ASSUMPTION'!N23-'BALANCE SHEET ASSUMPTION'!M23)*-1 -> -111.23549 | H17: =('BALANCE SHEET ASSUMPTION'!O23-'BALANCE SHEET ASSUMPTION'!N23)*-1 -> -170.1903 | K17: =('BALANCE SHEET ASSUMPTION'!R23-'BALANCE SHEET ASSUMPTION'!H23)*-1 -> 721.64634 | L17: =('BALANCE SHEET ASSUMPTION'!S23-'BALANCE SHEET ASSUMPTION'!R23)*-1 -> 57.063537 | M17: =('BALANCE SHEET ASSUMPTION'!T23-'BALANCE SHEET ASSUMPTION'!S23)*-1 -> -56.492901 | N17: =('BALANCE SHEET ASSUMPTION'!U23-'BALANCE SHEET ASSUMPTION'!T23)*-1 -> -57.05783 | O17: =('BALANCE SHEET ASSUMPTION'!V23-'BALANCE SHEET ASSUMPTION'!U23)*-1 -> -115.25682 | R17: =('BALANCE SHEET ASSUMPTION'!Y23-'BALANCE SHEET ASSUMPTION'!H23)*-1 -> 197.63072 | S17: =('BALANCE SHEET ASSUMPTION'!Z23-'BALANCE SHEET ASSUMPTION'!Y23)*-1 -> 93.455539 | T17: =('BALANCE SHEET ASSUMPTION'!AA23-'BALANCE SHEET ASSUMPTION'!Z23)*-1 -> 61.369137 | U17: =('BALANCE SHEET ASSUMPTION'!AB23-'BALANCE SHEET ASSUMPTION'!AA23)*-1 -> 60.755446 | V17: =('BALANCE SHEET ASSUMPTION'!AC23-'BALANCE SHEET ASSUMPTION'!AB23)*-1 -> -60.147892
B18: Other Financial Assets | C18: ₹ | D18: =('BALANCE SHEET ASSUMPTION'!K139-'BALANCE SHEET ASSUMPTION'!H139)*-1 -> 3.598704 | E18: =('BALANCE SHEET ASSUMPTION'!L139-'BALANCE SHEET ASSUMPTION'!K139)*-1 -> -50.230331 | F18: =('BALANCE SHEET ASSUMPTION'!M139-'BALANCE SHEET ASSUMPTION'!L139)*-1 -> -91.07847 | G18: =('BALANCE SHEET ASSUMPTION'!N139-'BALANCE SHEET ASSUMPTION'!M139)*-1 -> -93.358789 | H18: =('BALANCE SHEET ASSUMPTION'!O139-'BALANCE SHEET ASSUMPTION'!N139)*-1 -> -137.12521 | K18: =('BALANCE SHEET ASSUMPTION'!R139-'BALANCE SHEET ASSUMPTION'!H139)*-1 -> 175.6163 | L18: =('BALANCE SHEET ASSUMPTION'!S139-'BALANCE SHEET ASSUMPTION'!R139)*-1 -> 29.021019 | M18: =('BALANCE SHEET ASSUMPTION'!T139-'BALANCE SHEET ASSUMPTION'!S139)*-1 -> -46.534599 | N18: =('BALANCE SHEET ASSUMPTION'!U139-'BALANCE SHEET ASSUMPTION'!T139)*-1 -> -47.366494 | O18: =('BALANCE SHEET ASSUMPTION'!V139-'BALANCE SHEET ASSUMPTION'!U139)*-1 -> -86.347073 | R18: =('BALANCE SHEET ASSUMPTION'!Y139-'BALANCE SHEET ASSUMPTION'!H139)*-1 -> 288.13453 | S18: =('BALANCE SHEET ASSUMPTION'!Z139-'BALANCE SHEET ASSUMPTION'!Y139)*-1 -> 48.266493 | T18: =('BALANCE SHEET ASSUMPTION'!AA139-'BALANCE SHEET ASSUMPTION'!Z139)*-1 -> 29.106037 | U18: =('BALANCE SHEET ASSUMPTION'!AB139-'BALANCE SHEET ASSUMPTION'!AA139)*-1 -> 28.463778 | V18: =('BALANCE SHEET ASSUMPTION'!AC139-'BALANCE SHEET ASSUMPTION'!AB139)*-1 -> -43.00813
B19: Current Tax Assets | C19: ₹ | D19: =('BALANCE SHEET ASSUMPTION'!K33-'BALANCE SHEET ASSUMPTION'!H33)*-1 -> -8 | E19: =('BALANCE SHEET ASSUMPTION'!L33-'BALANCE SHEET ASSUMPTION'!K33)*-1 -> -30 | F19: =('BALANCE SHEET ASSUMPTION'!M33-'BALANCE SHEET ASSUMPTION'!L33)*-1 -> -30 | G19: =('BALANCE SHEET ASSUMPTION'!N33-'BALANCE SHEET ASSUMPTION'!M33)*-1 -> -30 | H19: =('BALANCE SHEET ASSUMPTION'!O33-'BALANCE SHEET ASSUMPTION'!N33)*-1 -> -30 | K19: =('BALANCE SHEET ASSUMPTION'!R33-'BALANCE SHEET ASSUMPTION'!H33)*-1 -> 42 | L19: =('BALANCE SHEET ASSUMPTION'!S33-'BALANCE SHEET ASSUMPTION'!R33)*-1 -> -30 | M19: =('BALANCE SHEET ASSUMPTION'!T33-'BALANCE SHEET ASSUMPTION'!S33)*-1 -> -30 | N19: =('BALANCE SHEET ASSUMPTION'!U33-'BALANCE SHEET ASSUMPTION'!T33)*-1 -> -30 | O19: =('BALANCE SHEET ASSUMPTION'!V33-'BALANCE SHEET ASSUMPTION'!U33)*-1 -> -30 | R19: =('BALANCE SHEET ASSUMPTION'!Y33-'BALANCE SHEET ASSUMPTION'!H33)*-1 -> 32 | S19: =('BALANCE SHEET ASSUMPTION'!Z33-'BALANCE SHEET ASSUMPTION'!Y33)*-1 -> -10 | T19: =('BALANCE SHEET ASSUMPTION'!AA33-'BALANCE SHEET ASSUMPTION'!Z33)*-1 -> -10 | U19: =('BALANCE SHEET ASSUMPTION'!AB33-'BALANCE SHEET ASSUMPTION'!AA33)*-1 -> -10 | V19: =('BALANCE SHEET ASSUMPTION'!AC33-'BALANCE SHEET ASSUMPTION'!AB33)*-1 -> -10
B20: Contract Assets | C20: ₹ | D20: =('BALANCE SHEET ASSUMPTION'!K35-'BALANCE SHEET ASSUMPTION'!H35)*-1 -> -221.82097 | E20: =('BALANCE SHEET ASSUMPTION'!L35-'BALANCE SHEET ASSUMPTION'!K35)*-1 -> -18.01821 | F20: =('BALANCE SHEET ASSUMPTION'!M35-'BALANCE SHEET ASSUMPTION'!L35)*-1 -> -36.396784 | G20: =('BALANCE SHEET ASSUMPTION'!N35-'BALANCE SHEET ASSUMPTION'!M35)*-1 -> -37.124719 | H20: =('BALANCE SHEET ASSUMPTION'!O35-'BALANCE SHEET ASSUMPTION'!N35)*-1 -> -56.80082 | K20: =('BALANCE SHEET ASSUMPTION'!R35-'BALANCE SHEET ASSUMPTION'!H35)*-1 -> -494.83127 | L20: =('BALANCE SHEET ASSUMPTION'!S35-'BALANCE SHEET ASSUMPTION'!R35)*-1 -> 20.748313 | M20: =('BALANCE SHEET ASSUMPTION'!T35-'BALANCE SHEET ASSUMPTION'!S35)*-1 -> -20.54083 | N20: =('BALANCE SHEET ASSUMPTION'!U35-'BALANCE SHEET ASSUMPTION'!T35)*-1 -> -20.746238 | O20: =('BALANCE SHEET ASSUMPTION'!V35-'BALANCE SHEET ASSUMPTION'!U35)*-1 -> -41.9074 | R20: =('BALANCE SHEET ASSUMPTION'!Y35-'BALANCE SHEET ASSUMPTION'!H35)*-1 -> -791.4832 | S20: =('BALANCE SHEET ASSUMPTION'!Z35-'BALANCE SHEET ASSUMPTION'!Y35)*-1 -> 35.572248 | T20: =('BALANCE SHEET ASSUMPTION'!AA35-'BALANCE SHEET ASSUMPTION'!Z35)*-1 -> 23.35911 | U20: =('BALANCE SHEET ASSUMPTION'!AB35-'BALANCE SHEET ASSUMPTION'!AA35)*-1 -> 23.125518 | V20: =('BALANCE SHEET ASSUMPTION'!AC35-'BALANCE SHEET ASSUMPTION'!AB35)*-1 -> -22.894263
B21: Other Current Assets | C21: ₹ | D21: =('BALANCE SHEET ASSUMPTION'!K126-'BALANCE SHEET ASSUMPTION'!H126)*-1 -> 90.1224 | E21: =('BALANCE SHEET ASSUMPTION'!L126-'BALANCE SHEET ASSUMPTION'!K126)*-1 -> -34.404336 | F21: =('BALANCE SHEET ASSUMPTION'!M126-'BALANCE SHEET ASSUMPTION'!L126)*-1 -> -62.382514 | G21: =('BALANCE SHEET ASSUMPTION'!N126-'BALANCE SHEET ASSUMPTION'!M126)*-1 -> -63.944376 | H21: =('BALANCE SHEET ASSUMPTION'!O126-'BALANCE SHEET ASSUMPTION'!N126)*-1 -> -93.921379 | K21: =('BALANCE SHEET ASSUMPTION'!R126-'BALANCE SHEET ASSUMPTION'!H126)*-1 -> -279.72607 | L21: =('BALANCE SHEET ASSUMPTION'!S126-'BALANCE SHEET ASSUMPTION'!R126)*-1 -> 23.460918 | M21: =('BALANCE SHEET ASSUMPTION'!T126-'BALANCE SHEET ASSUMPTION'!S126)*-1 -> -37.619092 | N21: =('BALANCE SHEET ASSUMPTION'!U126-'BALANCE SHEET ASSUMPTION'!T126)*-1 -> -38.291605 | O21: =('BALANCE SHEET ASSUMPTION'!V126-'BALANCE SHEET ASSUMPTION'!U126)*-1 -> -69.803942 | R21: =('BALANCE SHEET ASSUMPTION'!Y126-'BALANCE SHEET ASSUMPTION'!H126)*-1 -> -758.6416 | S21: =('BALANCE SHEET ASSUMPTION'!Z126-'BALANCE SHEET ASSUMPTION'!Y126)*-1 -> 46.188032 | T21: =('BALANCE SHEET ASSUMPTION'!AA126-'BALANCE SHEET ASSUMPTION'!Z126)*-1 -> 27.852667 | U21: =('BALANCE SHEET ASSUMPTION'!AB126-'BALANCE SHEET ASSUMPTION'!AA126)*-1 -> 27.238065 | V21: =('BALANCE SHEET ASSUMPTION'!AC126-'BALANCE SHEET ASSUMPTION'!AB126)*-1 -> -41.156105
B23: Total Current Assets | C23: ₹ | D23: =SUM(D15:D21) -> 1446.8672 | E23: =SUM(E15:E21) -> -62.555274 | F23: =SUM(F15:F21) -> -38.451072 | G23: =SUM(G15:G21) -> -300.38071 | H23: =SUM(H15:H21) -> -265.96383 | K23: =SUM(K15:K21) -> 428.31811 | L23: =SUM(L15:L21) -> 436.58155 | M23: =SUM(M15:M21) -> 183.88396 | N23: =SUM(N15:N21) -> -65.585139 | O23: =SUM(O15:O21) -> -310.95797 | R23: =SUM(R15:R21) -> -962.04877 | S23: =SUM(S15:S21) -> 113.32006 | T23: =SUM(T15:T21) -> -23.332667 | U23: =SUM(U15:U21) -> -23.701366 | V23: =SUM(V15:V21) -> -564.39166
B25: Non Current Assets
B27: Trade Payables | C27: ₹ | D27: ='BALANCE SHEET ASSUMPTION'!K108-'BALANCE SHEET ASSUMPTION'!H108 -> 258.95936 | E27: ='BALANCE SHEET ASSUMPTION'!L108-'BALANCE SHEET ASSUMPTION'!K108 -> 61.259594 | F27: ='BALANCE SHEET ASSUMPTION'!M108-'BALANCE SHEET ASSUMPTION'!L108 -> 123.74438 | G27: ='BALANCE SHEET ASSUMPTION'!N108-'BALANCE SHEET ASSUMPTION'!M108 -> 126.21927 | H27: ='BALANCE SHEET ASSUMPTION'!O108-'BALANCE SHEET ASSUMPTION'!N108 -> 193.11548 | K27: =('BALANCE SHEET ASSUMPTION'!R108-'BALANCE SHEET ASSUMPTION'!H108) -> -125.72994 | L27: =('BALANCE SHEET ASSUMPTION'!S108-'BALANCE SHEET ASSUMPTION'!R108) -> -57.412701 | M27: =('BALANCE SHEET ASSUMPTION'!T108-'BALANCE SHEET ASSUMPTION'!S108) -> 56.838574 | N27: =('BALANCE SHEET ASSUMPTION'!U108-'BALANCE SHEET ASSUMPTION'!T108) -> 57.406959 | O27: =('BALANCE SHEET ASSUMPTION'!V108-'BALANCE SHEET ASSUMPTION'!U108) -> 115.96206 | R27: =('BALANCE SHEET ASSUMPTION'!Y108-'BALANCE SHEET ASSUMPTION'!H108) -> -426.39584 | S27: =('BALANCE SHEET ASSUMPTION'!Z108-'BALANCE SHEET ASSUMPTION'!Y108) -> -81.609062 | T27: =('BALANCE SHEET ASSUMPTION'!AA108-'BALANCE SHEET ASSUMPTION'!Z108) -> -53.589951 | U27: =('BALANCE SHEET ASSUMPTION'!AB108-'BALANCE SHEET ASSUMPTION'!AA108) -> -53.054051 | V27: =('BALANCE SHEET ASSUMPTION'!AC108-'BALANCE SHEET ASSUMPTION'!AB108) -> 52.523511
B28: Other Financial Liabilities | C28: ₹ | D28: ='BALANCE SHEET ASSUMPTION'!K139-'BALANCE SHEET ASSUMPTION'!H139 -> -3.598704 | E28: ='BALANCE SHEET ASSUMPTION'!L139-'BALANCE SHEET ASSUMPTION'!K139 -> 50.230331 | F28: ='BALANCE SHEET ASSUMPTION'!M139-'BALANCE SHEET ASSUMPTION'!L139 -> 91.07847 | G28: ='BALANCE SHEET ASSUMPTION'!N139-'BALANCE SHEET ASSUMPTION'!M139 -> 93.358789 | H28: ='BALANCE SHEET ASSUMPTION'!O139-'BALANCE SHEET ASSUMPTION'!N139 -> 137.12521 | K28: ='BALANCE SHEET ASSUMPTION'!R139-'BALANCE SHEET ASSUMPTION'!H139 -> -175.6163 | L28: ='BALANCE SHEET ASSUMPTION'!S139-'BALANCE SHEET ASSUMPTION'!R139 -> -29.021019 | M28: ='BALANCE SHEET ASSUMPTION'!T139-'BALANCE SHEET ASSUMPTION'!S139 -> 46.534599 | N28: ='BALANCE SHEET ASSUMPTION'!U139-'BALANCE SHEET ASSUMPTION'!T139 -> 47.366494 | O28: ='BALANCE SHEET ASSUMPTION'!V139-'BALANCE SHEET ASSUMPTION'!U139 -> 86.347073 | R28: ='BALANCE SHEET ASSUMPTION'!Y139-'BALANCE SHEET ASSUMPTION'!H139 -> -288.13453 | S28: ='BALANCE SHEET ASSUMPTION'!Z139-'BALANCE SHEET ASSUMPTION'!Y139 -> -48.266493 | T28: ='BALANCE SHEET ASSUMPTION'!AA139-'BALANCE SHEET ASSUMPTION'!Z139 -> -29.106037 | U28: ='BALANCE SHEET ASSUMPTION'!AB139-'BALANCE SHEET ASSUMPTION'!AA139 -> -28.463778 | V28: ='BALANCE SHEET ASSUMPTION'!AC139-'BALANCE SHEET ASSUMPTION'!AB139 -> 43.00813
B29: Contract Liabilities | C29: ₹ | D29: ='BALANCE SHEET ASSUMPTION'!K168-'BALANCE SHEET ASSUMPTION'!H168 -> 693.3664 | E29: ='BALANCE SHEET ASSUMPTION'!L168-'BALANCE SHEET ASSUMPTION'!K168 -> 26.993664 | F29: ='BALANCE SHEET ASSUMPTION'!M168-'BALANCE SHEET ASSUMPTION'!L168 -> 54.527201 | G29: ='BALANCE SHEET ASSUMPTION'!N168-'BALANCE SHEET ASSUMPTION'!M168 -> 55.617745 | H29: ='BALANCE SHEET ASSUMPTION'!O168-'BALANCE SHEET ASSUMPTION'!N168 -> 85.09515 | K29: ='BALANCE SHEET ASSUMPTION'!R168-'BALANCE SHEET ASSUMPTION'!H168 -> 437.06022 | L29: ='BALANCE SHEET ASSUMPTION'!S168-'BALANCE SHEET ASSUMPTION'!R168 -> -24.430602 | M29: ='BALANCE SHEET ASSUMPTION'!T168-'BALANCE SHEET ASSUMPTION'!S168 -> 24.186296 | N29: ='BALANCE SHEET ASSUMPTION'!U168-'BALANCE SHEET ASSUMPTION'!T168 -> 24.428159 | O29: ='BALANCE SHEET ASSUMPTION'!V168-'BALANCE SHEET ASSUMPTION'!U168 -> 49.344882 | R29: ='BALANCE SHEET ASSUMPTION'!Y168-'BALANCE SHEET ASSUMPTION'!H168 -> 100.04032 | S29: ='BALANCE SHEET ASSUMPTION'!Z168-'BALANCE SHEET ASSUMPTION'!Y168 -> -31.590605 | T29: ='BALANCE SHEET ASSUMPTION'!AA168-'BALANCE SHEET ASSUMPTION'!Z168 -> -20.744497 | U29: ='BALANCE SHEET ASSUMPTION'!AB168-'BALANCE SHEET ASSUMPTION'!AA168 -> -20.537052 | V29: ='BALANCE SHEET ASSUMPTION'!AC168-'BALANCE SHEET ASSUMPTION'!AB168 -> 20.331682
B30: Other Current Liabilities | C30: ₹ | D30: ='BALANCE SHEET ASSUMPTION'!K146-'BALANCE SHEET ASSUMPTION'!H146 -> 38.782247 | E30: ='BALANCE SHEET ASSUMPTION'!L146-'BALANCE SHEET ASSUMPTION'!K146 -> 18.851691 | F30: ='BALANCE SHEET ASSUMPTION'!M146-'BALANCE SHEET ASSUMPTION'!L146 -> 34.182199 | G30: ='BALANCE SHEET ASSUMPTION'!N146-'BALANCE SHEET ASSUMPTION'!M146 -> 35.038014 | H30: ='BALANCE SHEET ASSUMPTION'!O146-'BALANCE SHEET ASSUMPTION'!N146 -> 51.463769 | K30: ='BALANCE SHEET ASSUMPTION'!R146-'BALANCE SHEET ASSUMPTION'!H146 -> 8.8545753 | L30: ='BALANCE SHEET ASSUMPTION'!S146-'BALANCE SHEET ASSUMPTION'!I146 -> 1505.7084 | M30: ='BALANCE SHEET ASSUMPTION'!T146-'BALANCE SHEET ASSUMPTION'!J146 -> 1523.5811 | N30: ='BALANCE SHEET ASSUMPTION'!U146-'BALANCE SHEET ASSUMPTION'!K146 -> -5.0089386 | O30: ='BALANCE SHEET ASSUMPTION'!V146-'BALANCE SHEET ASSUMPTION'!L146 -> 9.3030139 | R30: ='BALANCE SHEET ASSUMPTION'!Y146-'BALANCE SHEET ASSUMPTION'!H146 -> 0.89380822 | S30: ='BALANCE SHEET ASSUMPTION'!Z146-'BALANCE SHEET ASSUMPTION'!Y146 -> -18.981383 | T30: ='BALANCE SHEET ASSUMPTION'!AA146-'BALANCE SHEET ASSUMPTION'!Z146 -> -11.446301 | U30: ='BALANCE SHEET ASSUMPTION'!AB146-'BALANCE SHEET ASSUMPTION'!AA146 -> -11.193726 | V30: ='BALANCE SHEET ASSUMPTION'!AC146-'BALANCE SHEET ASSUMPTION'!AB146 -> 16.913468
B31: Provisions | C31: ₹ | D31: ='BALANCE SHEET ASSUMPTION'!K152-'BALANCE SHEET ASSUMPTION'!H152 -> -112.8418 | E31: ='BALANCE SHEET ASSUMPTION'!L152-'BALANCE SHEET ASSUMPTION'!K152 -> 25.803252 | F31: ='BALANCE SHEET ASSUMPTION'!M152-'BALANCE SHEET ASSUMPTION'!L152 -> 46.786885 | G31: ='BALANCE SHEET ASSUMPTION'!N152-'BALANCE SHEET ASSUMPTION'!M152 -> 47.958282 | H31: ='BALANCE SHEET ASSUMPTION'!O152-'BALANCE SHEET ASSUMPTION'!N152 -> 70.441034 | K31: ='BALANCE SHEET ASSUMPTION'!R152-'BALANCE SHEET ASSUMPTION'!H152 -> 30.74534 | L31: ='BALANCE SHEET ASSUMPTION'!S152-'BALANCE SHEET ASSUMPTION'!R152 -> -16.612499 | M31: ='BALANCE SHEET ASSUMPTION'!T152-'BALANCE SHEET ASSUMPTION'!S152 -> 26.637796 | N31: ='BALANCE SHEET ASSUMPTION'!U152-'BALANCE SHEET ASSUMPTION'!T152 -> 27.113998 | O31: ='BALANCE SHEET ASSUMPTION'!V152-'BALANCE SHEET ASSUMPTION'!U152 -> 49.427647 | R31: ='BALANCE SHEET ASSUMPTION'!Y152-'BALANCE SHEET ASSUMPTION'!H152 -> 202.46256 | S31: ='BALANCE SHEET ASSUMPTION'!Z152-'BALANCE SHEET ASSUMPTION'!Y152 -> -30.599571 | T31: ='BALANCE SHEET ASSUMPTION'!AA152-'BALANCE SHEET ASSUMPTION'!Z152 -> -18.452392 | U31: ='BALANCE SHEET ASSUMPTION'!AB152-'BALANCE SHEET ASSUMPTION'!AA152 -> -18.045218 | V31: ='BALANCE SHEET ASSUMPTION'!AC152-'BALANCE SHEET ASSUMPTION'!AB152 -> 27.26592
B32: Tax Liabilities | C32: ₹ | D32: ='BALANCE SHEET ASSUMPTION'!K159-'BALANCE SHEET ASSUMPTION'!H159 -> 972.18311 | E32: ='BALANCE SHEET ASSUMPTION'!L159-'BALANCE SHEET ASSUMPTION'!K159 -> 1073.543 | F32: ='BALANCE SHEET ASSUMPTION'!M159-'BALANCE SHEET ASSUMPTION'!L159 -> 1317.3548 | G32: ='BALANCE SHEET ASSUMPTION'!N159-'BALANCE SHEET ASSUMPTION'!M159 -> 1563.3651 | H32: ='BALANCE SHEET ASSUMPTION'!O159-'BALANCE SHEET ASSUMPTION'!N159 -> 1895.9933 | K32: ='BALANCE SHEET ASSUMPTION'!R159-'BALANCE SHEET ASSUMPTION'!H159 -> 813.71143 | L32: ='BALANCE SHEET ASSUMPTION'!S159-'BALANCE SHEET ASSUMPTION'!R159 -> 710.55917 | M32: ='BALANCE SHEET ASSUMPTION'!T159-'BALANCE SHEET ASSUMPTION'!S159 -> 900.11195 | N32: ='BALANCE SHEET ASSUMPTION'!U159-'BALANCE SHEET ASSUMPTION'!T159 -> 1026.8155 | O32: ='BALANCE SHEET ASSUMPTION'!V159-'BALANCE SHEET ASSUMPTION'!U159 -> 1211.8227 | R32: ='BALANCE SHEET ASSUMPTION'!Y159-'BALANCE SHEET ASSUMPTION'!H159 -> 727.70379 | S32: ='BALANCE SHEET ASSUMPTION'!Z159-'BALANCE SHEET ASSUMPTION'!Y159 -> 425.19095 | T32: ='BALANCE SHEET ASSUMPTION'!AA159-'BALANCE SHEET ASSUMPTION'!Z159 -> 491.88392 | U32: ='BALANCE SHEET ASSUMPTION'!AB159-'BALANCE SHEET ASSUMPTION'!AA159 -> 542.34791 | V32: ='BALANCE SHEET ASSUMPTION'!AC159-'BALANCE SHEET ASSUMPTION'!AB159 -> 675.64238
B34: Total Non Current Assets | C34: ₹ | D34: =SUM(D27:D32) -> 1846.8506 | E34: =SUM(E27:E32) -> 1256.6815 | F34: =SUM(F27:F32) -> 1667.674 | G34: =SUM(G27:G32) -> 1921.5572 | H34: =SUM(H27:H32) -> 2433.234 | K34: =SUM(K27:K32) -> 989.02533 | L34: =SUM(L27:L32) -> 2088.7907 | M34: =SUM(M27:M32) -> 2577.8903 | N34: =SUM(N27:N32) -> 1178.1222 | O34: =SUM(O27:O32) -> 1522.2074 | R34: =SUM(R27:R32) -> 316.57011 | S34: =SUM(S27:S32) -> 214.14383 | T34: =SUM(T27:T32) -> 358.54475 | U34: =SUM(U27:U32) -> 411.05408 | V34: =SUM(V27:V32) -> 835.68509
B36: Networking Capital Change | C36: ₹ | D36: =-D23+D34 -> 399.98346 | E36: =-E23+E34 -> 1319.2368 | F36: =-F23+F34 -> 1706.1251 | G36: =-G23+G34 -> 2221.9379 | H36: =-H23+H34 -> 2699.1978 | K36: =-K23+K34 -> 560.70722 | L36: =-L23+L34 -> 1652.2092 | M36: =-M23+M34 -> 2394.0063 | N36: =-N23+N34 -> 1243.7073 | O36: =-O23+O34 -> 1833.1654 | R36: =-R23+R34 -> 1278.6189 | S36: =-S23+S34 -> 100.82377 | T36: =-T23+T34 -> 381.87741 | U36: =-U23+U34 -> 434.75545 | V36: =-V23+V34 -> 1400.0768
B38: Cash from Operating Act. | C38: ₹ | D38: =D36+D9+D8 -> 18759.048 | E38: =E36+E9+E8 -> 20057.525 | F38: =F36+F9+F8 -> 20996.014 | G38: =G36+G9+G8 -> 22081.589 | H38: =H36+H9+H8 -> 23306.825 | K38: =K36+K9+K8 -> 17355.33 | L38: =L36+L9+L8 -> 18451.615 | M38: =M36+M9+M8 -> 19491.18 | N38: =N36+N9+N8 -> 18646.273 | O38: =O36+O9+O8 -> 19696.021 | R38: =R36+R9+R8 -> 16724.955 | S38: =S36+S9+S8 -> 15445.293 | T38: =T36+T9+T8 -> 15687.264 | U38: =U36+U9+U8 -> 15696.822 | V38: =V36+V9+V8 -> 16874.075
B40: INVESTING ACTIVITIES
B42: Purchase of PPE | C42: ₹ | D42: =('BALANCE SHEET ASSUMPTION'!K10)*-1 -> -3149.2608 | E42: =('BALANCE SHEET ASSUMPTION'!L10)*-1 -> -3180.7534 | F42: =('BALANCE SHEET ASSUMPTION'!M10)*-1 -> -3244.3685 | G42: =('BALANCE SHEET ASSUMPTION'!N10)*-1 -> -3309.2558 | H42: =('BALANCE SHEET ASSUMPTION'!O10)*-1 -> -3408.5335 | K42: =('BALANCE SHEET ASSUMPTION'!R10)*-1 -> -2945.7838 | L42: =('BALANCE SHEET ASSUMPTION'!S10)*-1 -> -2916.326 | M42: =('BALANCE SHEET ASSUMPTION'!T10)*-1 -> -2945.4892 | N42: =('BALANCE SHEET ASSUMPTION'!U10)*-1 -> -2974.9441 | O42: =('BALANCE SHEET ASSUMPTION'!V10)*-1 -> -3034.443 | R42: =('BALANCE SHEET ASSUMPTION'!Y10)*-1 -> -2808.0538 | S42: =('BALANCE SHEET ASSUMPTION'!Z10)*-1 -> -2765.933 | T42: =('BALANCE SHEET ASSUMPTION'!AA10)*-1 -> -2738.2736 | U42: =('BALANCE SHEET ASSUMPTION'!AB10)*-1 -> -2710.8909 | V42: =('BALANCE SHEET ASSUMPTION'!AC10)*-1 -> -2737.9998
B43: Sale of PPE | C43: ₹ | D43: ='BALANCE SHEET ASSUMPTION'!K12 -> 2590.145 | E43: ='BALANCE SHEET ASSUMPTION'!L12 -> 2654.4433 | F43: ='BALANCE SHEET ASSUMPTION'!M12 -> 2714.969 | G43: ='BALANCE SHEET ASSUMPTION'!N12 -> 2775.8499 | H43: ='BALANCE SHEET ASSUMPTION'!O12 -> 2837.1916 | K43: ='BALANCE SHEET ASSUMPTION'!R12 -> 2702.76 | L43: ='BALANCE SHEET ASSUMPTION'!S12 -> 2731.9229 | M43: ='BALANCE SHEET ASSUMPTION'!T12 -> 2754.0512 | N43: ='BALANCE SHEET ASSUMPTION'!U12 -> 2777.0238 | O43: ='BALANCE SHEET ASSUMPTION'!V12 -> 2800.7742 | R43: ='BALANCE SHEET ASSUMPTION'!Y12 -> 2815.375 | S43: ='BALANCE SHEET ASSUMPTION'!Z12 -> 2814.4598 | T43: ='BALANCE SHEET ASSUMPTION'!AA12 -> 2808.394 | U43: ='BALANCE SHEET ASSUMPTION'!AB12 -> 2799.6289 | V43: ='BALANCE SHEET ASSUMPTION'!AC12 -> 2788.5367
